Workbook

Sheet 개요
A1: 독도 코리아 스쿨 1.1 | B1: 실제 반영 내용
A2: 문항 수 | B2: =COUNTA(문항_KO!A2:A241) -> 240
A3: 개념 묶음 | B3: 60
A4: 단원 수 | B4: =COUNTA(단원!A2:A13) -> 12
A5: L1 알아보기 | B5: =COUNTIF(문항_KO!D2:D241,1) -> 60
A6: L2 이어보기 | B6: =COUNTIF(문항_KO!D2:D241,2) -> 60
A7: L3 자료읽기 | B7: =COUNTIF(문항_KO!D2:D241,3) -> 60
A8: L4 따져보기 | B8: =COUNTIF(문항_KO!D2:D241,4) -> 60
A9: 원본 엑셀 대조 | B9: 질문 1,513개가 원본 questions.json과 일치, 변경된 질문 0개. 진단표이지 수정 문항집은 아닙니다.
A10: 이번 파일의 범위 | B10: 새 240문항(한국어·영어 쌍)을 실제 앱에 연결. 같은 사실을 네 사고 단계로 묻는 60개 묶음입니다. 원본 1,513문항 전부를 고쳤다는 뜻이 아닙니다.
A11: 기록 보호 | B11: 새 문항 ID 910001~910240. 이전 1,513문항과 48문항의 학습 기록은 보존하며 새 출제에서는 제외합니다.
A12: 자료와 검수 | B12: 출처를 연결한 자체 검토본입니다. 독립 교사 검수·국가 교육과정 인증·실기기 검증 완료를 주장하지 않습니다.
A13: 엑셀 편집과 배포 | B13: 이 파일은 검토·편집용입니다. 엑셀을 고쳐도 웹앱이 자동 변경되지는 않습니다. tools/content의 작성 원본을 수정하고 npm run content:build 및 테스트를 실행하세요.
A14: 지도 범위 | B14: 지도 보기에는 동도의 낮고 넓은 상부를 설명하는 형상 비교도를 추가했습니다. 감상용 홈 이미지는 생성 일러스트로 유지하며, 실측 3D 지형이나 시설 위치를 재현했다고 표시하지 않습니다.

Sheet 문항_KO
A1: 문항 ID | B1: 단원 | C1: 개념 묶음 | D1: 인지단계 | E1: 질문 | F1: 보기 1 | G1: 보기 2 | H1: 보기 3 | I1: 정답 번호 | J1: 사실·해설 | K1: 오답 해설 1 | L1: 오답 해설 2 | M1: 오답 해설 3 | N1: 판단 자료 | O1: 출처 URL | P1: 질문+최장보기 글자수 | Q1: 검토 상태
A2: 910001 | B2: 1 | C2: dk-composition | D2: 1 | E2: 독도의 두 큰 섬은? | F2: 제주도와 서도 | G2: 동도와 서도 | H2: 울릉도와 동도 | I2: 2 | J2: 독도는 동도와 서도, 그리고 주변의 작은 바위섬들로 이루어져 있어요. | K2: 고른 보기 ‘제주도와 서도’와 달라요. 이 문항의 정답은 ‘동도와 서도’입니다. 독도는 동도와 서도, 그리고 주변의 작은 바위섬들로 이루어져 있어요. | L2: 독도는 동도와 서도, 그리고 주변의 작은 바위섬들로 이루어져 있어요. | M2: 고른 보기 ‘울릉도와 동도’와 달라요. 이 문항의 정답은 ‘동도와 서도’입니다. 독도는 동도와 서도, 그리고 주변의 작은 바위섬들로 이루어져 있어요. | O2: https://dokdo.mofa.go.kr/kor/introduce/location.jsp | P2: =LEN(E2)+MAX(LEN(F2),LEN(G2),LEN(H2)) -> 18 | Q2: 출처 기반 자체 검토 / 독립 승인 전
A3: 910002 | B3: 1 | C3: dk-composition | D3: 2 | E3: 동도·서도만 그리면 빠지는 것은? | F3: 주변의 작은 바위섬 | G3: 두 큰 섬의 위치 | H3: 서도라는 섬 | I3: 1 | J3: 독도는 동도와 서도, 그리고 주변의 작은 바위섬들로 이루어져 있어요. | K3: 독도는 동도와 서도, 그리고 주변의 작은 바위섬들로 이루어져 있어요. | L3: 고른 보기 ‘두 큰 섬의 위치’와 달라요. 이 문항의 정답은 ‘주변의 작은 바위섬’입니다. 독도는 동도와 서도, 그리고 주변의 작은 바위섬들로 이루어져 있어요. | M3: 고른 보기 ‘서도라는 섬’와 달라요. 이 문항의 정답은 ‘주변의 작은 바위섬’입니다. 독도는 동도와 서도, 그리고 주변의 작은 바위섬들로 이루어져 있어요. | O3: https://dokdo.mofa.go.kr/kor/introduce/location.jsp | P3: =LEN(E3)+MAX(LEN(F3),LEN(G3),LEN(H3)) -> 28 | Q3: 출처 기반 자체 검토 / 독립 승인 전
A4: 910003 | B4: 1 | C4: dk-composition | D4: 3 | E4: 자료의 89개는 무엇을 센 수일까요? | F4: 동도와 서도를 포함한 모든 섬 | G4: 동도 안에 있는 봉우리 | H4: 두 큰 섬과 별도로 센 부속 도서 | I4: 3 | J4: 독도는 동도와 서도, 그리고 주변의 작은 바위섬들로 이루어져 있어요. | K4: 고른 보기 ‘동도와 서도를 포함한 모든 섬’와 달라요. 이 문항의 정답은 ‘두 큰 섬과 별도로 센 부속 도서’입니다. 독도는 동도와 서도, 그리고 주변의 작은 바위섬들로 이루어져 있어요. | L4: 고른 보기 ‘동도 안에 있는 봉우리’와 달라요. 이 문항의 정답은 ‘두 큰 섬과 별도로 센 부속 도서’입니다. 독도는 동도와 서도, 그리고 주변의 작은 바위섬들로 이루어져 있어요. | M4: 독도는 동도와 서도, 그리고 주변의 작은 바위섬들로 이루어져 있어요. | N4: 외교부 자료: 두 큰 섬 동도·서도와 부속 도서 89개로 독도를 설명합니다. | O4: https://dokdo.mofa.go.kr/kor/introduce/location.jsp | P4: =LEN(E4)+MAX(LEN(F4),LEN(G4),LEN(H4)) -> 38 | Q4: 출처 기반 자체 검토 / 독립 승인 전
A5: 910004 | B5: 1 | C5: dk-composition | D5: 4 | E5: 독도를 ‘섬 두 개뿐’이라 소개한 글의 수정은? | F5: 89개가 모두 큰 섬이라고 고친다 | G5: 두 큰 섬과 부속 도서를 구분해 쓴다 | H5: 작은 바위섬은 모두 독도에서 뺀다 | I5: 2 | J5: 독도는 동도와 서도, 그리고 주변의 작은 바위섬들로 이루어져 있어요. 대표적인 두 섬과 독도의 전체 구성은 구분해야 합니다. | K5: 고른 보기 ‘89개가 모두 큰 섬이라고 고친다’와 달라요. 이 문항의 정답은 ‘두 큰 섬과 부속 도서를 구분해 쓴다’입니다. 독도는 동도와 서도, 그리고 주변의 작은 바위섬들로 이루어져 있어요. 대표적인 두 섬과 독도의 전체 구성은 구분해야 합니다. | L5: 독도는 동도와 서도, 그리고 주변의 작은 바위섬들로 이루어져 있어요. 대표적인 두 섬과 독도의 전체 구성은 구분해야 합니다. | M5: 고른 보기 ‘작은 바위섬은 모두 독도에서 뺀다’와 달라요. 이 문항의 정답은 ‘두 큰 섬과 부속 도서를 구분해 쓴다’입니다. 독도는 동도와 서도, 그리고 주변의 작은 바위섬들로 이루어져 있어요. 대표적인 두 섬과 독도의 전체 구성은 구분해야 합니다. | N5: 외교부 자료: 두 큰 섬 동도·서도와 부속 도서 89개로 독도를 설명합니다. | O5: https://dokdo.mofa.go.kr/kor/introduce/location.jsp | P5: =LEN(E5)+MAX(LEN(F5),LEN(G5),LEN(H5)) -> 46 | Q5: 출처 기반 자체 검토 / 독립 승인 전
A6: 910005 | B6: 1 | C6: dk-relative-location | D6: 1 | E6: 울릉도에서 독도는 어느 방향일까요? | F6: 동남쪽 | G6: 서북쪽 | H6: 남서쪽 | I6: 1 | J6: 독도는 울릉도에서 동남쪽으로 약 87.4km 떨어져 있어요. | K6: 독도는 울릉도에서 동남쪽으로 약 87.4km 떨어져 있어요. | L6: 고른 보기 ‘서북쪽’와 달라요. 이 문항의 정답은 ‘동남쪽’입니다. 독도는 울릉도에서 동남쪽으로 약 87.4km 떨어져 있어요. | M6: 고른 보기 ‘남서쪽’와 달라요. 이 문항의 정답은 ‘동남쪽’입니다. 독도는 울릉도에서 동남쪽으로 약 87.4km 떨어져 있어요. | O6: https://dokdo.mofa.go.kr/kor/introduce/location.jsp | P6: =LEN(E6)+MAX(LEN(F6),LEN(G6),LEN(H6)) -> 22 | Q6: 출처 기반 자체 검토 / 독립 승인 전
A7: 910006 | B7: 1 | C7: dk-relative-location | D7: 2 | E7: 울릉도와 독도의 관계는? | F7: 한 섬의 동쪽과 서쪽 이름 | G7: 두 섬 모두 동도 안에 있음 | H7: 바다를 사이에 둔 서로 다른 섬 | I7: 3 | J7: 독도는 울릉도에서 동남쪽으로 약 87.4km 떨어져 있어요. | K7: 고른 보기 ‘한 섬의 동쪽과 서쪽 이름’와 달라요. 이 문항의 정답은 ‘바다를 사이에 둔 서로 다른 섬’입니다. 독도는 울릉도에서 동남쪽으로 약 87.4km 떨어져 있어요. | L7: 고른 보기 ‘두 섬 모두 동도 안에 있음’와 달라요. 이 문항의 정답은 ‘바다를 사이에 둔 서로 다른 섬’입니다. 독도는 울릉도에서 동남쪽으로 약 87.4km 떨어져 있어요. | M7: 독도는 울릉도에서 동남쪽으로 약 87.4km 떨어져 있어요. | O7: https://dokdo.mofa.go.kr/kor/introduce/location.jsp | P7: =LEN(E7)+MAX(LEN(F7),LEN(G7),LEN(H7)) -> 30 | Q7: 출처 기반 자체 검토 / 독립 승인 전
A8: 910007 | B8: 1 | C8: dk-relative-location | D8: 3 | E8: 주어진 거리에서 독도에 더 가까운 곳은? | F8: 두 곳의 거리가 같음 | G8: 울릉도 | H8: 오키섬 | I8: 2 | J8: 독도는 울릉도에서 동남쪽으로 약 87.4km 떨어져 있어요. 87.4km가 157.5km보다 짧습니다. | K8: 고른 보기 ‘두 곳의 거리가 같음’와 달라요. 이 문항의 정답은 ‘울릉도’입니다. 독도는 울릉도에서 동남쪽으로 약 87.4km 떨어져 있어요. 87.4km가 157.5km보다 짧습니다. | L8: 독도는 울릉도에서 동남쪽으로 약 87.4km 떨어져 있어요. 87.4km가 157.5km보다 짧습니다. | M8: 고른 보기 ‘오키섬’와 달라요. 이 문항의 정답은 ‘울릉도’입니다. 독도는 울릉도에서 동남쪽으로 약 87.4km 떨어져 있어요. 87.4km가 157.5km보다 짧습니다. | N8: 독도 기준 거리: 울릉도 87.4km, 일본 오키섬 157.5km. 두 거리의 출발점은 모두 독도입니다. | O8: https://dokdo.mofa.go.kr/kor/introduce/location.jsp | P8: =LEN(E8)+MAX(LEN(F8),LEN(G8),LEN(H8)) -> 33 | Q8: 출처 기반 자체 검토 / 독립 승인 전
A9: 910008 | B9: 1 | C9: dk-relative-location | D9: 4 | E9: 이 거리 표만으로 뒷받침되는 말은? | F9: 울릉도가 오키섬보다 독도에 가깝다 | G9: 거리만으로 영토의 모든 역사가 결정된다 | H9: 울릉도와 독도가 육지로 이어진다 | I9: 1 | J9: 독도는 울릉도에서 동남쪽으로 약 87.4km 떨어져 있어요. 거리 비교와 역사·법적 근거의 판단은 구분합니다. | K9: 독도는 울릉도에서 동남쪽으로 약 87.4km 떨어져 있어요. 거리 비교와 역사·법적 근거의 판단은 구분합니다. | L9: 고른 보기 ‘거리만으로 영토의 모든 역사가 결정된다’와 달라요. 이 문항의 정답은 ‘울릉도가 오키섬보다 독도에 가깝다’입니다. 독도는 울릉도에서 동남쪽으로 약 87.4km 떨어져 있어요. 거리 비교와 역사·법적 근거의 판단은 구분합니다. | M9: 고른 보기 ‘울릉도와 독도가 육지로 이어진다’와 달라요. 이 문항의 정답은 ‘울릉도가 오키섬보다 독도에 가깝다’입니다. 독도는 울릉도에서 동남쪽으로 약 87.4km 떨어져 있어요. 거리 비교와 역사·법적 근거의 판단은 구분합니다. | N9: 독도 기준 거리: 울릉도 87.4km, 일본 오키섬 157.5km. 두 거리의 출발점은 모두 독도입니다. | O9: https://dokdo.mofa.go.kr/kor/introduce/location.jsp | P9: =LEN(E9)+MAX(LEN(F9),LEN(G9),LEN(H9)) -> 40 | Q9: 출처 기반 자체 검토 / 독립 승인 전
A10: 910009 | B10: 1 | C10: dk-orientation | D10: 1 | E10: 독도의 동쪽 큰 섬 이름은? | F10: 서도 | G10: 울릉도 | H10: 동도 | I10: 3 | J10: 서도는 서쪽, 동도는 동쪽의 큰 섬이에요. 지도를 돌려도 실제 동쪽과 서쪽은 바뀌지 않아요. | K10: 고른 보기 ‘서도’와 달라요. 이 문항의 정답은 ‘동도’입니다. 서도는 서쪽, 동도는 동쪽의 큰 섬이에요. 지도를 돌려도 실제 동쪽과 서쪽은 바뀌지 않아요. | L10: 고른 보기 ‘울릉도’와 달라요. 이 문항의 정답은 ‘동도’입니다. 서도는 서쪽, 동도는 동쪽의 큰 섬이에요. 지도를 돌려도 실제 동쪽과 서쪽은 바뀌지 않아요. | M10: 서도는 서쪽, 동도는 동쪽의 큰 섬이에요. 지도를 돌려도 실제 동쪽과 서쪽은 바뀌지 않아요. | O10: https://dokdo.mofa.go.kr/kor/introduce/location.jsp | P10: =LEN(E10)+MAX(LEN(F10),LEN(G10),LEN(H10)) -> 18 | Q10: 출처 기반 자체 검토 / 독립 승인 전
A11: 910010 | B11: 1 | C11: dk-orientation | D11: 2 | E11: 서도 이름의 ‘서’와 연결되는 방향은? | F11: 북쪽 | G11: 서쪽 | H11: 동쪽 | I11: 2 | J11: 서도는 서쪽, 동도는 동쪽의 큰 섬이에요. 지도를 돌려도 실제 동쪽과 서쪽은 바뀌지 않아요. | K11: 고른 보기 ‘북쪽’와 달라요. 이 문항의 정답은 ‘서쪽’입니다. 서도는 서쪽, 동도는 동쪽의 큰 섬이에요. 지도를 돌려도 실제 동쪽과 서쪽은 바뀌지 않아요. | L11: 서도는 서쪽, 동도는 동쪽의 큰 섬이에요. 지도를 돌려도 실제 동쪽과 서쪽은 바뀌지 않아요. | M11: 고른 보기 ‘동쪽’와 달라요. 이 문항의 정답은 ‘서쪽’입니다. 서도는 서쪽, 동도는 동쪽의 큰 섬이에요. 지도를 돌려도 실제 동쪽과 서쪽은 바뀌지 않아요. | O11: https://dokdo.mofa.go.kr/kor/introduce/location.jsp | P11: =LEN(E11)+MAX(LEN(F11),LEN(G11),LEN(H11)) -> 23 | Q11: 출처 기반 자체 검토 / 독립 승인 전
A12: 910011 | B12: 1 | C12: dk-orientation | D12: 3 | E12: 주어진 방향도에서 동도는 서도의 어느 쪽인가요? | F12: 오른쪽 | G12: 왼쪽 | H12: 같은 지점 | I12: 1 | J12: 서도는 서쪽, 동도는 동쪽의 큰 섬이에요. 지도를 돌려도 실제 동쪽과 서쪽은 바뀌지 않아요. | K12: 서도는 서쪽, 동도는 동쪽의 큰 섬이에요. 지도를 돌려도 실제 동쪽과 서쪽은 바뀌지 않아요. | L12: 고른 보기 ‘왼쪽’와 달라요. 이 문항의 정답은 ‘오른쪽’입니다. 서도는 서쪽, 동도는 동쪽의 큰 섬이에요. 지도를 돌려도 실제 동쪽과 서쪽은 바뀌지 않아요. | M12: 고른 보기 ‘같은 지점’와 달라요. 이 문항의 정답은 ‘오른쪽’입니다. 서도는 서쪽, 동도는 동쪽의 큰 섬이에요. 지도를 돌려도 실제 동쪽과 서쪽은 바뀌지 않아요. | N12: 방향을 익히는 개략도: 북쪽 ↑, 서쪽 ←, 동쪽 →. 서도가 왼쪽, 동도가 오른쪽에 있습니다. 두 섬의 해안선이나 정확한 거리를 나타내는 도면은 아닙니다. | O12: https://dokdo.mofa.go.kr/kor/introduce/location.jsp | P12: =LEN(E12)+MAX(LEN(F12),LEN(G12),LEN(H12)) -> 31 | Q12: 출처 기반 자체 검토 / 독립 승인 전
A13: 910012 | B13: 1 | C13: dk-orientation | D13: 4 | E13: 지도를 돌려 동도가 왼쪽에 보이면? | F13: 동도의 이름을 서도로 바꾼다 | G13: 섬이 실제로 이동했다고 판단한다 | H13: 방향표로 실제 동서 관계를 확인한다 | I13: 3 | J13: 서도는 서쪽, 동도는 동쪽의 큰 섬이에요. 지도를 돌려도 실제 동쪽과 서쪽은 바뀌지 않아요. 화면의 좌우와 지리적 동서는 다를 수 있습니다. | K13: 고른 보기 ‘동도의 이름을 서도로 바꾼다’와 달라요. 이 문항의 정답은 ‘방향표로 실제 동서 관계를 확인한다’입니다. 서도는 서쪽, 동도는 동쪽의 큰 섬이에요. 지도를 돌려도 실제 동쪽과 서쪽은 바뀌지 않아요. 화면의 좌우와 지리적 동서는 다를 수 있습니다. | L13: 고른 보기 ‘섬이 실제로 이동했다고 판단한다’와 달라요. 이 문항의 정답은 ‘방향표로 실제 동서 관계를 확인한다’입니다. 서도는 서쪽, 동도는 동쪽의 큰 섬이에요. 지도를 돌려도 실제 동쪽과 서쪽은 바뀌지 않아요. 화면의 좌우와 지리적 동서는 다를 수 있습니다. | M13: 서도는 서쪽, 동도는 동쪽의 큰 섬이에요. 지도를 돌려도 실제 동쪽과 서쪽은 바뀌지 않아요. 화면의 좌우와 지리적 동서는 다를 수 있습니다. | N13: 방향을 익히는 개략도: 북쪽 ↑, 서쪽 ←, 동쪽 →. 서도가 왼쪽, 동도가 오른쪽에 있습니다. 두 섬의 해안선이나 정확한 거리를 나타내는 도면은 아닙니다. | O13: https://dokdo.mofa.go.kr/kor/introduce/location.jsp | P13: =LEN(E13)+MAX(LEN(F13),LEN(G13),LEN(H13)) -> 38 | Q13: 출처 기반 자체 검토 / 독립 승인 전
A14: 910013 | B14: 1 | C14: dk-visibility | D14: 1 | E14: 울릉도에서 독도를 보기 좋은 날씨는? | F14: 시야를 가리는 비 | G14: 맑은 날 | H14: 짙은 안개 | I14: 2 | J14: 울릉도에서는 맑은 날 독도를 볼 수 있어요. 안개나 비가 시야를 가리면 보이지 않을 수도 있어요. | K14: 고른 보기 ‘시야를 가리는 비’와 달라요. 이 문항의 정답은 ‘맑은 날’입니다. 울릉도에서는 맑은 날 독도를 볼 수 있어요. 안개나 비가 시야를 가리면 보이지 않을 수도 있어요. | L14: 울릉도에서는 맑은 날 독도를 볼 수 있어요. 안개나 비가 시야를 가리면 보이지 않을 수도 있어요. | M14: 고른 보기 ‘짙은 안개’와 달라요. 이 문항의 정답은 ‘맑은 날’입니다. 울릉도에서는 맑은 날 독도를 볼 수 있어요. 안개나 비가 시야를 가리면 보이지 않을 수도 있어요. | O14: https://dokdo.mofa.go.kr/kor/introduce/location.jsp https://dokdo.mofa.go.kr/kor/pds/part06_view02.jsp | P14: =LEN(E14)+MAX(LEN(F14),LEN(G14),LEN(H14)) -> 29 | Q14: 출처 기반 자체 검토 / 독립 승인 전
A15: 910014 | B15: 1 | C15: dk-visibility | D15: 2 | E15: 오늘 독도가 안 보이면 먼저 살필 것은? | F15: 안개 같은 날씨 조건 | G15: 섬 이름의 변경 | H15: 서도의 면적 증가 | I15: 1 | J15: 울릉도에서는 맑은 날 독도를 볼 수 있어요. 안개나 비가 시야를 가리면 보이지 않을 수도 있어요. | K15: 울릉도에서는 맑은 날 독도를 볼 수 있어요. 안개나 비가 시야를 가리면 보이지 않을 수도 있어요. | L15: 고른 보기 ‘섬 이름의 변경’와 달라요. 이 문항의 정답은 ‘안개 같은 날씨 조건’입니다. 울릉도에서는 맑은 날 독도를 볼 수 있어요. 안개나 비가 시야를 가리면 보이지 않을 수도 있어요. | M15: 고른 보기 ‘서도의 면적 증가’와 달라요. 이 문항의 정답은 ‘안개 같은 날씨 조건’입니다. 울릉도에서는 맑은 날 독도를 볼 수 있어요. 안개나 비가 시야를 가리면 보이지 않을 수도 있어요. | O15: https://dokdo.mofa.go.kr/kor/introduce/location.jsp https://dokdo.mofa.go.kr/kor/pds/part06_view02.jsp | P15: =LEN(E15)+MAX(LEN(F15),LEN(G15),LEN(H15)) -> 33 | Q15: 출처 기반 자체 검토 / 독립 승인 전
A16: 910015 | B16: 1 | C16: dk-visibility | D16: 3 | E16: 옛 기록이 가시성에 붙인 조건은? | F16: 모든 날씨에 항상 | G16: 겨울에만 | H16: 날씨가 맑을 때 | I16: 3 | J16: 울릉도에서는 맑은 날 독도를 볼 수 있어요. 안개나 비가 시야를 가리면 보이지 않을 수도 있어요. | K16: 고른 보기 ‘모든 날씨에 항상’와 달라요. 이 문항의 정답은 ‘날씨가 맑을 때’입니다. 울릉도에서는 맑은 날 독도를 볼 수 있어요. 안개나 비가 시야를 가리면 보이지 않을 수도 있어요. | L16: 고른 보기 ‘겨울에만’와 달라요. 이 문항의 정답은 ‘날씨가 맑을 때’입니다. 울릉도에서는 맑은 날 독도를 볼 수 있어요. 안개나 비가 시야를 가리면 보이지 않을 수도 있어요. | M16: 울릉도에서는 맑은 날 독도를 볼 수 있어요. 안개나 비가 시야를 가리면 보이지 않을 수도 있어요. | N16: 외교부가 소개한 『세종실록』 지리지는 우산·무릉 두 섬이 서로 멀지 않아 날씨가 맑으면 바라볼 수 있다고 설명합니다. | O16: https://dokdo.mofa.go.kr/kor/introduce/location.jsp https://dokdo.mofa.go.kr/kor/pds/part06_view02.jsp | P16: =LEN(E16)+MAX(LEN(F16),LEN(G16),LEN(H16)) -> 27 | Q16: 출처 기반 자체 검토 / 독립 승인 전
A17: 910016 | B17: 1 | C17: dk-visibility | D17: 4 | E17: ‘울릉도에서 독도는 항상 보인다’는 요약은? | F17: 가까운 섬에는 날씨가 영향을 주지 않는다 | G17: 맑은 날이라는 조건이 빠져 부정확하다 | H17: 섬 이름이 맞으므로 충분히 정확하다 | I17: 2 | J17: 울릉도에서는 맑은 날 독도를 볼 수 있어요. 안개나 비가 시야를 가리면 보이지 않을 수도 있어요. | K17: 고른 보기 ‘가까운 섬에는 날씨가 영향을 주지 않는다’와 달라요. 이 문항의 정답은 ‘맑은 날이라는 조건이 빠져 부정확하다’입니다. 울릉도에서는 맑은 날 독도를 볼 수 있어요. 안개나 비가 시야를 가리면 보이지 않을 수도 있어요. | L17: 울릉도에서는 맑은 날 독도를 볼 수 있어요. 안개나 비가 시야를 가리면 보이지 않을 수도 있어요. | M17: 고른 보기 ‘섬 이름이 맞으므로 충분히 정확하다’와 달라요. 이 문항의 정답은 ‘맑은 날이라는 조건이 빠져 부정확하다’입니다. 울릉도에서는 맑은 날 독도를 볼 수 있어요. 안개나 비가 시야를 가리면 보이지 않을 수도 있어요. | N17: 외교부가 소개한 『세종실록』 지리지는 우산·무릉 두 섬이 서로 멀지 않아 날씨가 맑으면 바라볼 수 있다고 설명합니다. | O17: https://dokdo.mofa.go.kr/kor/introduce/location.jsp https://dokdo.mofa.go.kr/kor/pds/part06_view02.jsp | P17: =LEN(E17)+MAX(LEN(F17),LEN(G17),LEN(H17)) -> 46 | Q17: 출처 기반 자체 검토 / 독립 승인 전
A18: 910017 | B18: 1 | C18: dk-islet-count | D18: 1 | E18: 작은 바위섬도 독도의 일부일까요? | F18: 네, 독도의 일부예요 | G18: 아니요, 큰 섬만 독도예요 | H18: 모두 울릉도의 일부예요 | I18: 1 | J18: 독도 전체 면적에는 동도·서도뿐 아니라 부속 도서의 땅도 포함돼요. | K18: 독도 전체 면적에는 동도·서도뿐 아니라 부속 도서의 땅도 포함돼요. | L18: 고른 보기 ‘아니요, 큰 섬만 독도예요’와 달라요. 이 문항의 정답은 ‘네, 독도의 일부예요’입니다. 독도 전체 면적에는 동도·서도뿐 아니라 부속 도서의 땅도 포함돼요. | M18: 고른 보기 ‘모두 울릉도의 일부예요’와 달라요. 이 문항의 정답은 ‘네, 독도의 일부예요’입니다. 독도 전체 면적에는 동도·서도뿐 아니라 부속 도서의 땅도 포함돼요. | O18: https://dokdo.mofa.go.kr/kor/introduce/location.jsp | P18: =LEN(E18)+MAX(LEN(F18),LEN(G18),LEN(H18)) -> 32 | Q18: 출처 기반 자체 검토 / 독립 승인 전
A19: 910018 | B19: 1 | C19: dk-islet-count | D19: 2 | E19: 독도 전체 넓이를 구할 때 더할 것은? | F19: 두 큰 섬의 높이 | G19: 울릉도 전체 넓이 | H19: 두 큰 섬과 부속 도서의 넓이 | I19: 3 | J19: 독도 전체 면적에는 동도·서도뿐 아니라 부속 도서의 땅도 포함돼요. | K19: 고른 보기 ‘두 큰 섬의 높이’와 달라요. 이 문항의 정답은 ‘두 큰 섬과 부속 도서의 넓이’입니다. 독도 전체 면적에는 동도·서도뿐 아니라 부속 도서의 땅도 포함돼요. | L19: 고른 보기 ‘울릉도 전체 넓이’와 달라요. 이 문항의 정답은 ‘두 큰 섬과 부속 도서의 넓이’입니다. 독도 전체 면적에는 동도·서도뿐 아니라 부속 도서의 땅도 포함돼요. | M19: 독도 전체 면적에는 동도·서도뿐 아니라 부속 도서의 땅도 포함돼요. | O19: https://dokdo.mofa.go.kr/kor/introduce/location.jsp | P19: =LEN(E19)+MAX(LEN(F19),LEN(G19),LEN(H19)) -> 37 | Q19: 출처 기반 자체 검토 / 독립 승인 전
A20: 910019 | B20: 1 | C20: dk-islet-count | D20: 3 | E20: 두 큰 섬의 면적 합이 전체보다 작은 까닭은? | F20: 섬의 높이가 면적에서 빠졌기 때문 | G20: 부속 도서 면적이 따로 있기 때문 | H20: 바다 넓이를 두 배로 계산했기 때문 | I20: 2 | J20: 독도 전체 면적에는 동도·서도뿐 아니라 부속 도서의 땅도 포함돼요. | K20: 고른 보기 ‘섬의 높이가 면적에서 빠졌기 때문’와 달라요. 이 문항의 정답은 ‘부속 도서 면적이 따로 있기 때문’입니다. 독도 전체 면적에는 동도·서도뿐 아니라 부속 도서의 땅도 포함돼요. | L20: 독도 전체 면적에는 동도·서도뿐 아니라 부속 도서의 땅도 포함돼요. | M20: 고른 보기 ‘바다 넓이를 두 배로 계산했기 때문’와 달라요. 이 문항의 정답은 ‘부속 도서 면적이 따로 있기 때문’입니다. 독도 전체 면적에는 동도·서도뿐 아니라 부속 도서의 땅도 포함돼요. | N20: 면적 자료: 동도 73,297㎡, 서도 88,740㎡, 독도 전체 187,554㎡. 전체에는 부속 도서가 포함됩니다. | O20: https://dokdo.mofa.go.kr/kor/introduce/location.jsp | P20: =LEN(E20)+MAX(LEN(F20),LEN(G20),LEN(H20)) -> 44 | Q20: 출처 기반 자체 검토 / 독립 승인 전
A21: 910020 | B21: 1 | C21: dk-islet-count | D21: 4 | E21: 사진 한 장에 보이는 바위 수를 전체 수라 한다면? | F21: 사진 밖의 부속 도서를 빠뜨릴 수 있다 | G21: 사진의 바위는 모두 독도가 아니다 | H21: 사진이면 반드시 전체를 보여준다 | I21: 1 | J21: 독도 전체 면적에는 동도·서도뿐 아니라 부속 도서의 땅도 포함돼요. | K21: 독도 전체 면적에는 동도·서도뿐 아니라 부속 도서의 땅도 포함돼요. | L21: 고른 보기 ‘사진의 바위는 모두 독도가 아니다’와 달라요. 이 문항의 정답은 ‘사진 밖의 부속 도서를 빠뜨릴 수 있다’입니다. 독도 전체 면적에는 동도·서도뿐 아니라 부속 도서의 땅도 포함돼요. | M21: 고른 보기 ‘사진이면 반드시 전체를 보여준다’와 달라요. 이 문항의 정답은 ‘사진 밖의 부속 도서를 빠뜨릴 수 있다’입니다. 독도 전체 면적에는 동도·서도뿐 아니라 부속 도서의 땅도 포함돼요. | N21: 면적 자료: 동도 73,297㎡, 서도 88,740㎡, 독도 전체 187,554㎡. 전체에는 부속 도서가 포함됩니다. | O21: https://dokdo.mofa.go.kr/kor/introduce/location.jsp | P21: =LEN(E21)+MAX(LEN(F21),LEN(G21),LEN(H21)) -> 49 | Q21: 출처 기반 자체 검토 / 독립 승인 전
A22: 910021 | B22: 2 | C22: dk-heights | D22: 1 | E22: 두 큰 섬 중 더 높은 섬은? | F22: 동도 | G22: 두 섬이 같아요 | H22: 서도 | I22: 3 | J22: 서도의 최고 높이는 168.5m, 동도는 98.6m예요. 서도가 더 높아요. | K22: 고른 보기 ‘동도’와 달라요. 이 문항의 정답은 ‘서도’입니다. 서도의 최고 높이는 168.5m, 동도는 98.6m예요. 서도가 더 높아요. | L22: 고른 보기 ‘두 섬이 같아요’와 달라요. 이 문항의 정답은 ‘서도’입니다. 서도의 최고 높이는 168.5m, 동도는 98.6m예요. 서도가 더 높아요. | M22: 서도의 최고 높이는 168.5m, 동도는 98.6m예요. 서도가 더 높아요. | O22: https://dokdo.mofa.go.kr/kor/introduce/location.jsp | P22: =LEN(E22)+MAX(LEN(F22),LEN(G22),LEN(H22)) -> 24 | Q22: 출처 기반 자체 검토 / 독립 승인 전
A23: 910022 | B23: 2 | C23: dk-heights | D23: 2 | E23: 높이를 바르게 연결한 것은? | F23: 두 섬 모두 168.5m | G23: 서도 168.5m·동도 98.6m | H23: 서도 98.6m·동도 168.5m | I23: 2 | J23: 서도의 최고 높이는 168.5m, 동도는 98.6m예요. 서도가 더 높아요. | K23: 고른 보기 ‘두 섬 모두 168.5m’와 달라요. 이 문항의 정답은 ‘서도 168.5m·동도 98.6m’입니다. 서도의 최고 높이는 168.5m, 동도는 98.6m예요. 서도가 더 높아요. | L23: 서도의 최고 높이는 168.5m, 동도는 98.6m예요. 서도가 더 높아요. | M23: 고른 보기 ‘서도 98.6m·동도 168.5m’와 달라요. 이 문항의 정답은 ‘서도 168.5m·동도 98.6m’입니다. 서도의 최고 높이는 168.5m, 동도는 98.6m예요. 서도가 더 높아요. | O23: https://dokdo.mofa.go.kr/kor/introduce/location.jsp | P23: =LEN(E23)+MAX(LEN(F23),LEN(G23),LEN(H23)) -> 33 | Q23: 출처 기반 자체 검토 / 독립 승인 전
A24: 910023 | B24: 2 | C24: dk-heights | D24: 3 | E24: 자료에서 최고 높이의 차이는? | F24: 69.9m | G24: 267.1m | H24: 87.4m | I24: 1 | J24: 서도의 최고 높이는 168.5m, 동도는 98.6m예요. 서도가 더 높아요. 168.5−98.6=69.9m입니다. 더하기가 아니라 차이를 구합니다. | K24: 서도의 최고 높이는 168.5m, 동도는 98.6m예요. 서도가 더 높아요. 168.5−98.6=69.9m입니다. 더하기가 아니라 차이를 구합니다. | L24: 고른 보기 ‘267.1m’와 달라요. 이 문항의 정답은 ‘69.9m’입니다. 서도의 최고 높이는 168.5m, 동도는 98.6m예요. 서도가 더 높아요. 168.5−98.6=69.9m입니다. 더하기가 아니라 차이를 구합니다. | M24: 고른 보기 ‘87.4m’와 달라요. 이 문항의 정답은 ‘69.9m’입니다. 서도의 최고 높이는 168.5m, 동도는 98.6m예요. 서도가 더 높아요. 168.5−98.6=69.9m입니다. 더하기가 아니라 차이를 구합니다. | N24: 높이 자료: 서도 168.5m / 동도 98.6m. 두 값 모두 해수면을 기준으로 한 높이입니다. | O24: https://dokdo.mofa.go.kr/kor/introduce/location.jsp | P24: =LEN(E24)+MAX(LEN(F24),LEN(G24),LEN(H24)) -> 22 | Q24: 출처 기반 자체 검토 / 독립 승인 전
A25: 910024 | B25: 2 | C25: dk-heights | D25: 4 | E25: 사진 속 동도가 더 커 보일 때 옳은 판단은? | F25: 사진 크기만으로 동도가 더 높다고 한다 | G25: 사진마다 실제 표고가 달라진다고 한다 | H25: 원근과 실제 높이 자료를 함께 살핀다 | I25: 3 | J25: 서도의 최고 높이는 168.5m, 동도는 98.6m예요. 서도가 더 높아요. | K25: 고른 보기 ‘사진 크기만으로 동도가 더 높다고 한다’와 달라요. 이 문항의 정답은 ‘원근과 실제 높이 자료를 함께 살핀다’입니다. 서도의 최고 높이는 168.5m, 동도는 98.6m예요. 서도가 더 높아요. | L25: 고른 보기 ‘사진마다 실제 표고가 달라진다고 한다’와 달라요. 이 문항의 정답은 ‘원근과 실제 높이 자료를 함께 살핀다’입니다. 서도의 최고 높이는 168.5m, 동도는 98.6m예요. 서도가 더 높아요. | M25: 서도의 최고 높이는 168.5m, 동도는 98.6m예요. 서도가 더 높아요. | N25: 높이 자료: 서도 168.5m / 동도 98.6m. 두 값 모두 해수면을 기준으로 한 높이입니다. | O25: https://dokdo.mofa.go.kr/kor/introduce/location.jsp | P25: =LEN(E25)+MAX(LEN(F25),LEN(G25),LEN(H25)) -> 46 | Q25: 출처 기반 자체 검토 / 독립 승인 전
A26: 910025 | B26: 2 | C26: dk-area | D26: 1 | E26: 땅의 넓이가 더 넓은 큰 섬은? | F26: 두 섬이 같아요 | G26: 서도 | H26: 동도 | I26: 2 | J26: 서도는 동도보다 땅의 넓이도 넓어요. 높이와 면적은 서로 다른 값이에요. | K26: 고른 보기 ‘두 섬이 같아요’와 달라요. 이 문항의 정답은 ‘서도’입니다. 서도는 동도보다 땅의 넓이도 넓어요. 높이와 면적은 서로 다른 값이에요. | L26: 서도는 동도보다 땅의 넓이도 넓어요. 높이와 면적은 서로 다른 값이에요. | M26: 고른 보기 ‘동도’와 달라요. 이 문항의 정답은 ‘서도’입니다. 서도는 동도보다 땅의 넓이도 넓어요. 높이와 면적은 서로 다른 값이에요. | O26: https://dokdo.mofa.go.kr/kor/introduce/location.jsp | P26: =LEN(E26)+MAX(LEN(F26),LEN(G26),LEN(H26)) -> 25 | Q26: 출처 기반 자체 검토 / 독립 승인 전
A27: 910026 | B27: 2 | C27: dk-area | D27: 2 | E27: ‘서도가 더 넓다’는 무엇을 비교한 말인가요? | F27: 땅의 넓이 | G27: 바다의 깊이 | H27: 등대의 높이 | I27: 1 | J27: 서도는 동도보다 땅의 넓이도 넓어요. 높이와 면적은 서로 다른 값이에요. | K27: 서도는 동도보다 땅의 넓이도 넓어요. 높이와 면적은 서로 다른 값이에요. | L27: 고른 보기 ‘바다의 깊이’와 달라요. 이 문항의 정답은 ‘땅의 넓이’입니다. 서도는 동도보다 땅의 넓이도 넓어요. 높이와 면적은 서로 다른 값이에요. | M27: 고른 보기 ‘등대의 높이’와 달라요. 이 문항의 정답은 ‘땅의 넓이’입니다. 서도는 동도보다 땅의 넓이도 넓어요. 높이와 면적은 서로 다른 값이에요. | O27: https://dokdo.mofa.go.kr/kor/introduce/location.jsp | P27: =LEN(E27)+MAX(LEN(F27),LEN(G27),LEN(H27)) -> 31 | Q27: 출처 기반 자체 검토 / 독립 승인 전
A28: 910027 | B28: 2 | C28: dk-area | D28: 3 | E28: 두 섬의 면적을 비교할 때 사용할 값은? | F28: 168.5m와 98.6m | G28: 87.4km와 151m | H28: 88,740㎡와 73,297㎡ | I28: 3 | J28: 서도는 동도보다 땅의 넓이도 넓어요. 높이와 면적은 서로 다른 값이에요. | K28: 고른 보기 ‘168.5m와 98.6m’와 달라요. 이 문항의 정답은 ‘88,740㎡와 73,297㎡’입니다. 서도는 동도보다 땅의 넓이도 넓어요. 높이와 면적은 서로 다른 값이에요. | L28: 고른 보기 ‘87.4km와 151m’와 달라요. 이 문항의 정답은 ‘88,740㎡와 73,297㎡’입니다. 서도는 동도보다 땅의 넓이도 넓어요. 높이와 면적은 서로 다른 값이에요. | M28: 서도는 동도보다 땅의 넓이도 넓어요. 높이와 면적은 서로 다른 값이에요. | N28: 서도 면적 88,740㎡, 동도 면적 73,297㎡. 높이는 m, 면적은 ㎡로 표시합니다. | O28: https://dokdo.mofa.go.kr/kor/introduce/location.jsp | P28: =LEN(E28)+MAX(LEN(F28),LEN(G28),LEN(H28)) -> 38 | Q28: 출처 기반 자체 검토 / 독립 승인 전
A29: 910028 | B29: 2 | C29: dk-area | D29: 4 | E29: ‘서도는 높으니 반드시 넓다’라는 설명은? | F29: 높은 섬은 언제나 면적이 작다 | G29: 면적은 별도의 면적 자료로 확인해야 한다 | H29: 높이를 더하면 면적이 되므로 옳다 | I29: 2 | J29: 서도는 동도보다 땅의 넓이도 넓어요. 높이와 면적은 서로 다른 값이에요. 이번 경우 두 값 모두 서도가 크지만, 높이만으로 면적을 증명할 수는 없습니다. | K29: 고른 보기 ‘높은 섬은 언제나 면적이 작다’와 달라요. 이 문항의 정답은 ‘면적은 별도의 면적 자료로 확인해야 한다’입니다. 서도는 동도보다 땅의 넓이도 넓어요. 높이와 면적은 서로 다른 값이에요. 이번 경우 두 값 모두 서도가 크지만, 높이만으로 면적을 증명할 수는 없습니다. | L29: 서도는 동도보다 땅의 넓이도 넓어요. 높이와 면적은 서로 다른 값이에요. 이번 경우 두 값 모두 서도가 크지만, 높이만으로 면적을 증명할 수는 없습니다. | M29: 고른 보기 ‘높이를 더하면 면적이 되므로 옳다’와 달라요. 이 문항의 정답은 ‘면적은 별도의 면적 자료로 확인해야 한다’입니다. 서도는 동도보다 땅의 넓이도 넓어요. 높이와 면적은 서로 다른 값이에요. 이번 경우 두 값 모두 서도가 크지만, 높이만으로 면적을 증명할 수는 없습니다. | N29: 서도 면적 88,740㎡, 동도 면적 73,297㎡. 높이는 m, 면적은 ㎡로 표시합니다. | O29: https://dokdo.mofa.go.kr/kor/introduce/location.jsp | P29: =LEN(E29)+MAX(LEN(F29),LEN(G29),LEN(H29)) -> 45 | Q29: 출처 기반 자체 검토 / 독립 승인 전
A30: 910029 | B30: 2 | C30: dk-shore-gap | D30: 1 | E30: 동도와 서도 사이를 채우는 것은? | F30: 바닷물 | G30: 두 섬을 잇는 육지 | H30: 울릉도의 산 | I30: 1 | J30: 동도와 서도는 바다로 떨어져 있어요. 가장 가까운 해안 사이 거리는 약 151m예요. | K30: 동도와 서도는 바다로 떨어져 있어요. 가장 가까운 해안 사이 거리는 약 151m예요. | L30: 고른 보기 ‘두 섬을 잇는 육지’와 달라요. 이 문항의 정답은 ‘바닷물’입니다. 동도와 서도는 바다로 떨어져 있어요. 가장 가까운 해안 사이 거리는 약 151m예요. | M30: 고른 보기 ‘울릉도의 산’와 달라요. 이 문항의 정답은 ‘바닷물’입니다. 동도와 서도는 바다로 떨어져 있어요. 가장 가까운 해안 사이 거리는 약 151m예요. | O30: https://www.dokdo.re.kr/home/cms/cmsCont.do?cntnts_sn=66 | P30: =LEN(E30)+MAX(LEN(F30),LEN(G30),LEN(H30)) -> 28 | Q30: 출처 기반 자체 검토 / 독립 승인 전
A31: 910030 | B31: 2 | C31: dk-shore-gap | D31: 2 | E31: 151m와 바르게 연결되는 것은? | F31: 서도의 최고 높이 | G31: 울릉도에서 독도까지 거리 | H31: 가장 가까운 해안 사이 거리 | I31: 3 | J31: 동도와 서도는 바다로 떨어져 있어요. 가장 가까운 해안 사이 거리는 약 151m예요. | K31: 고른 보기 ‘서도의 최고 높이’와 달라요. 이 문항의 정답은 ‘가장 가까운 해안 사이 거리’입니다. 동도와 서도는 바다로 떨어져 있어요. 가장 가까운 해안 사이 거리는 약 151m예요. | L31: 고른 보기 ‘울릉도에서 독도까지 거리’와 달라요. 이 문항의 정답은 ‘가장 가까운 해안 사이 거리’입니다. 동도와 서도는 바다로 떨어져 있어요. 가장 가까운 해안 사이 거리는 약 151m예요. | M31: 동도와 서도는 바다로 떨어져 있어요. 가장 가까운 해안 사이 거리는 약 151m예요. | O31: https://www.dokdo.re.kr/home/cms/cmsCont.do?cntnts_sn=66 | P31: =LEN(E31)+MAX(LEN(F31),LEN(G31),LEN(H31)) -> 33 | Q31: 출처 기반 자체 검토 / 독립 승인 전
A32: 910031 | B32: 2 | C32: dk-shore-gap | D32: 3 | E32: 151m 선을 그릴 때 맞는 두 끝점은? | F32: 울릉도와 서도의 중심 | G32: 두 섬의 가장 가까운 해안 지점 | H32: 동도와 서도의 정상 | I32: 2 | J32: 동도와 서도는 바다로 떨어져 있어요. 가장 가까운 해안 사이 거리는 약 151m예요. | K32: 고른 보기 ‘울릉도와 서도의 중심’와 달라요. 이 문항의 정답은 ‘두 섬의 가장 가까운 해안 지점’입니다. 동도와 서도는 바다로 떨어져 있어요. 가장 가까운 해안 사이 거리는 약 151m예요. | L32: 동도와 서도는 바다로 떨어져 있어요. 가장 가까운 해안 사이 거리는 약 151m예요. | M32: 고른 보기 ‘동도와 서도의 정상’와 달라요. 이 문항의 정답은 ‘두 섬의 가장 가까운 해안 지점’입니다. 동도와 서도는 바다로 떨어져 있어요. 가장 가까운 해안 사이 거리는 약 151m예요. | N32: 지형 자료의 151m는 두 섬 사이 해협의 폭을 뜻합니다. 두 정상이나 두 섬 중심 사이의 거리가 아닙니다. | O32: https://www.dokdo.re.kr/home/cms/cmsCont.do?cntnts_sn=66 | P32: =LEN(E32)+MAX(LEN(F32),LEN(G32),LEN(H32)) -> 39 | Q32: 출처 기반 자체 검토 / 독립 승인 전
A33: 910032 | B33: 2 | C33: dk-shore-gap | D33: 4 | E33: 정상끼리 잇는 선에 151m를 썼다면? | F33: 자료와 측정 끝점이 달라 수정한다 | G33: 같은 두 섬이므로 어디든 괜찮다 | H33: 151m는 면적이므로 선을 지운다 | I33: 1 | J33: 동도와 서도는 바다로 떨어져 있어요. 가장 가까운 해안 사이 거리는 약 151m예요. 숫자뿐 아니라 무엇과 무엇 사이를 재는지도 맞아야 합니다. | K33: 동도와 서도는 바다로 떨어져 있어요. 가장 가까운 해안 사이 거리는 약 151m예요. 숫자뿐 아니라 무엇과 무엇 사이를 재는지도 맞아야 합니다. | L33: 고른 보기 ‘같은 두 섬이므로 어디든 괜찮다’와 달라요. 이 문항의 정답은 ‘자료와 측정 끝점이 달라 수정한다’입니다. 동도와 서도는 바다로 떨어져 있어요. 가장 가까운 해안 사이 거리는 약 151m예요. 숫자뿐 아니라 무엇과 무엇 사이를 재는지도 맞아야 합니다. | M33: 고른 보기 ‘151m는 면적이므로 선을 지운다’와 달라요. 이 문항의 정답은 ‘자료와 측정 끝점이 달라 수정한다’입니다. 동도와 서도는 바다로 떨어져 있어요. 가장 가까운 해안 사이 거리는 약 151m예요. 숫자뿐 아니라 무엇과 무엇 사이를 재는지도 맞아야 합니다. | N33: 지형 자료의 151m는 두 섬 사이 해협의 폭을 뜻합니다. 두 정상이나 두 섬 중심 사이의 거리가 아닙니다. | O33: https://www.dokdo.re.kr/home/cms/cmsCont.do?cntnts_sn=66 | P33: =LEN(E33)+MAX(LEN(F33),LEN(G33),LEN(H33)) -> 39 | Q33: 출처 기반 자체 검토 / 독립 승인 전
A34: 910033 | B34: 2 | C34: dk-terrain-contrast | D34: 1 | E34: 가파르게 솟은 모습이 두드러지는 섬은? | F34: 동도 | G34: 두 섬 모두 평평해요 | H34: 서도 | I34: 3 | J34: 서도는 가파르게 솟은 모습이고, 동도는 정상 부근에 비교적 완만한 공간이 있어요. | K34: 고른 보기 ‘동도’와 달라요. 이 문항의 정답은 ‘서도’입니다. 서도는 가파르게 솟은 모습이고, 동도는 정상 부근에 비교적 완만한 공간이 있어요. | L34: 고른 보기 ‘두 섬 모두 평평해요’와 달라요. 이 문항의 정답은 ‘서도’입니다. 서도는 가파르게 솟은 모습이고, 동도는 정상 부근에 비교적 완만한 공간이 있어요. | M34: 서도는 가파르게 솟은 모습이고, 동도는 정상 부근에 비교적 완만한 공간이 있어요. | O34: https://www.heritage.go.kr/heri/cul/culSelectDetail.do?VdkVgwKey=16%2C03360000%2C37&pageNo=1_1_2_0 https://www.jbe.go.kr/dokdo/assets/sub/picture.html | P34: =LEN(E34)+MAX(LEN(F34),LEN(G34),LEN(H34)) -> 32 | Q34: 출처 기반 자체 검토 / 독립 승인 전
A35: 910034 | B35: 2 | C35: dk-terrain-contrast | D35: 2 | E35: 동도 정상 부근과 연결되는 모습은? | F35: 섬 전체가 모래평지 | G35: 비교적 완만한 공간 | H35: 서도보다 높은 뾰족봉만 | I35: 2 | J35: 서도는 가파르게 솟은 모습이고, 동도는 정상 부근에 비교적 완만한 공간이 있어요. | K35: 고른 보기 ‘섬 전체가 모래평지’와 달라요. 이 문항의 정답은 ‘비교적 완만한 공간’입니다. 서도는 가파르게 솟은 모습이고, 동도는 정상 부근에 비교적 완만한 공간이 있어요. | L35: 서도는 가파르게 솟은 모습이고, 동도는 정상 부근에 비교적 완만한 공간이 있어요. | M35: 고른 보기 ‘서도보다 높은 뾰족봉만’와 달라요. 이 문항의 정답은 ‘비교적 완만한 공간’입니다. 서도는 가파르게 솟은 모습이고, 동도는 정상 부근에 비교적 완만한 공간이 있어요. | O35: https://www.heritage.go.kr/heri/cul/culSelectDetail.do?VdkVgwKey=16%2C03360000%2C37&pageNo=1_1_2_0 https://www.jbe.go.kr/dokdo/assets/sub/picture.html | P35: =LEN(E35)+MAX(LEN(F35),LEN(G35),LEN(H35)) -> 31 | Q35: 출처 기반 자체 검토 / 독립 승인 전
A36: 910035 | B36: 2 | C36: dk-terrain-contrast | D36: 3 | E36: 자료에 맞는 두 섬의 비교는? | F36: 서도는 가파르고 동도 상부는 비교적 완만하다 | G36: 동도는 서도보다 높고 더 뾰족하다 | H36: 두 섬은 같은 형태와 높이를 가진다 | I36: 1 | J36: 서도는 가파르게 솟은 모습이고, 동도는 정상 부근에 비교적 완만한 공간이 있어요. | K36: 서도는 가파르게 솟은 모습이고, 동도는 정상 부근에 비교적 완만한 공간이 있어요. | L36: 고른 보기 ‘동도는 서도보다 높고 더 뾰족하다’와 달라요. 이 문항의 정답은 ‘서도는 가파르고 동도 상부는 비교적 완만하다’입니다. 서도는 가파르게 솟은 모습이고, 동도는 정상 부근에 비교적 완만한 공간이 있어요. | M36: 고른 보기 ‘두 섬은 같은 형태와 높이를 가진다’와 달라요. 이 문항의 정답은 ‘서도는 가파르고 동도 상부는 비교적 완만하다’입니다. 서도는 가파르게 솟은 모습이고, 동도는 정상 부근에 비교적 완만한 공간이 있어요. | N36: 국가유산 설명과 항공사진을 함께 보면 서도의 가파른 형태와 동도의 비교적 평탄한 정상 부근을 구분할 수 있습니다. 동도도 해안 절벽과 능선이 있습니다. | O36: https://www.heritage.go.kr/heri/cul/culSelectDetail.do?VdkVgwKey=16%2C03360000%2C37&pageNo=1_1_2_0 https://www.jbe.go.kr/dokdo/assets/sub/picture.html | P36: =LEN(E36)+MAX(LEN(F36),LEN(G36),LEN(H36)) -> 40 | Q36: 출처 기반 자체 검토 / 독립 승인 전
A37: 910036 | B37: 2 | C37: dk-terrain-contrast | D37: 4 | E37: 동도를 완전히 평평한 판으로 그리면? | F37: 시설이 있으므로 평평한 판이 정확하다 | G37: 서도보다 낮으면 절벽도 없어야 한다 | H37: 상부의 상대적 특징을 섬 전체로 확대했다 | I37: 3 | J37: 서도는 가파르게 솟은 모습이고, 동도는 정상 부근에 비교적 완만한 공간이 있어요. | K37: 고른 보기 ‘시설이 있으므로 평평한 판이 정확하다’와 달라요. 이 문항의 정답은 ‘상부의 상대적 특징을 섬 전체로 확대했다’입니다. 서도는 가파르게 솟은 모습이고, 동도는 정상 부근에 비교적 완만한 공간이 있어요. | L37: 고른 보기 ‘서도보다 낮으면 절벽도 없어야 한다’와 달라요. 이 문항의 정답은 ‘상부의 상대적 특징을 섬 전체로 확대했다’입니다. 서도는 가파르게 솟은 모습이고, 동도는 정상 부근에 비교적 완만한 공간이 있어요. | M37: 서도는 가파르게 솟은 모습이고, 동도는 정상 부근에 비교적 완만한 공간이 있어요. | N37: 국가유산 설명과 항공사진을 함께 보면 서도의 가파른 형태와 동도의 비교적 평탄한 정상 부근을 구분할 수 있습니다. 동도도 해안 절벽과 능선이 있습니다. | O37: https://www.heritage.go.kr/heri/cul/culSelectDetail.do?VdkVgwKey=16%2C03360000%2C37&pageNo=1_1_2_0 https://www.jbe.go.kr/dokdo/assets/sub/picture.html | P37: =LEN(E37)+MAX(LEN(F37),LEN(G37),LEN(H37)) -> 42 | Q37: 출처 기반 자체 검토 / 독립 승인 전
A38: 910037 | B38: 2 | C38: dk-above-below | D38: 1 | E38: 독도의 지형은 바닷속에도 이어질까요? | F38: 배가 받치고 있어요 | G38: 네, 바닷속에도 이어져요 | H38: 아니요, 수면에 떠 있어요 | I38: 2 | J38: 독도는 큰 해저 화산체의 일부가 물 위에 드러난 모습이에요. 바닷속에도 지형이 이어져요. | K38: 고른 보기 ‘배가 받치고 있어요’와 달라요. 이 문항의 정답은 ‘네, 바닷속에도 이어져요’입니다. 독도는 큰 해저 화산체의 일부가 물 위에 드러난 모습이에요. 바닷속에도 지형이 이어져요. | L38: 독도는 큰 해저 화산체의 일부가 물 위에 드러난 모습이에요. 바닷속에도 지형이 이어져요. | M38: 고른 보기 ‘아니요, 수면에 떠 있어요’와 달라요. 이 문항의 정답은 ‘네, 바닷속에도 이어져요’입니다. 독도는 큰 해저 화산체의 일부가 물 위에 드러난 모습이에요. 바닷속에도 지형이 이어져요. | O38: https://www.dokdo.re.kr/home/cms/cmsCont.do?cntnts_sn=66 | P38: =LEN(E38)+MAX(LEN(F38),LEN(G38),LEN(H38)) -> 34 | Q38: 출처 기반 자체 검토 / 독립 승인 전
A39: 910038 | B39: 2 | C39: dk-above-below | D39: 2 | E39: 독도 화산체 전체를 보려면 어디도 살필까요? | F39: 바닷속 부분 | G39: 등대 지붕만 | H39: 동도 건물만 | I39: 1 | J39: 독도는 큰 해저 화산체의 일부가 물 위에 드러난 모습이에요. 바닷속에도 지형이 이어져요. | K39: 독도는 큰 해저 화산체의 일부가 물 위에 드러난 모습이에요. 바닷속에도 지형이 이어져요. | L39: 고른 보기 ‘등대 지붕만’와 달라요. 이 문항의 정답은 ‘바닷속 부분’입니다. 독도는 큰 해저 화산체의 일부가 물 위에 드러난 모습이에요. 바닷속에도 지형이 이어져요. | M39: 고른 보기 ‘동도 건물만’와 달라요. 이 문항의 정답은 ‘바닷속 부분’입니다. 독도는 큰 해저 화산체의 일부가 물 위에 드러난 모습이에요. 바닷속에도 지형이 이어져요. | O39: https://www.dokdo.re.kr/home/cms/cmsCont.do?cntnts_sn=66 | P39: =LEN(E39)+MAX(LEN(F39),LEN(G39),LEN(H39)) -> 30 | Q39: 출처 기반 자체 검토 / 독립 승인 전
A40: 910039 | B40: 2 | C40: dk-above-below | D40: 3 | E40: 168.5m와 약 2,300m가 함께 쓰이는 이유는? | F40: 서도의 높이가 하루마다 크게 달라진다 | G40: 두 수치는 모두 땅의 넓이이다 | H40: 수면과 해저 기저부라는 기준이 다르다 | I40: 3 | J40: 독도는 큰 해저 화산체의 일부가 물 위에 드러난 모습이에요. 바닷속에도 지형이 이어져요. | K40: 고른 보기 ‘서도의 높이가 하루마다 크게 달라진다’와 달라요. 이 문항의 정답은 ‘수면과 해저 기저부라는 기준이 다르다’입니다. 독도는 큰 해저 화산체의 일부가 물 위에 드러난 모습이에요. 바닷속에도 지형이 이어져요. | L40: 고른 보기 ‘두 수치는 모두 땅의 넓이이다’와 달라요. 이 문항의 정답은 ‘수면과 해저 기저부라는 기준이 다르다’입니다. 독도는 큰 해저 화산체의 일부가 물 위에 드러난 모습이에요. 바닷속에도 지형이 이어져요. | M40: 독도는 큰 해저 화산체의 일부가 물 위에 드러난 모습이에요. 바닷속에도 지형이 이어져요. | N40: 수면 위 최고 높이: 서도 168.5m·동도 98.6m. 해저 기저부부터 본 독도 화산체 전체 높이: 약 2,300m. 높이의 기준점이 다릅니다. | O40: https://www.dokdo.re.kr/home/cms/cmsCont.do?cntnts_sn=66 | P40: =LEN(E40)+MAX(LEN(F40),LEN(G40),LEN(H40)) -> 49 | Q40: 출처 기반 자체 검토 / 독립 승인 전
A41: 910040 | B41: 2 | C41: dk-above-below | D41: 4 | E41: ‘독도가 수면 위로 2,300m 솟았다’의 수정은? | F41: 168.5m에 2,300m를 더한다 | G41: 2,300m는 해저 기저부 기준임을 밝힌다 | H41: 동도의 표고를 2,300m로 바꾼다 | I41: 2 | J41: 독도는 큰 해저 화산체의 일부가 물 위에 드러난 모습이에요. 바닷속에도 지형이 이어져요. | K41: 고른 보기 ‘168.5m에 2,300m를 더한다’와 달라요. 이 문항의 정답은 ‘2,300m는 해저 기저부 기준임을 밝힌다’입니다. 독도는 큰 해저 화산체의 일부가 물 위에 드러난 모습이에요. 바닷속에도 지형이 이어져요. | L41: 독도는 큰 해저 화산체의 일부가 물 위에 드러난 모습이에요. 바닷속에도 지형이 이어져요. | M41: 고른 보기 ‘동도의 표고를 2,300m로 바꾼다’와 달라요. 이 문항의 정답은 ‘2,300m는 해저 기저부 기준임을 밝힌다’입니다. 독도는 큰 해저 화산체의 일부가 물 위에 드러난 모습이에요. 바닷속에도 지형이 이어져요. | N41: 수면 위 최고 높이: 서도 168.5m·동도 98.6m. 해저 기저부부터 본 독도 화산체 전체 높이: 약 2,300m. 높이의 기준점이 다릅니다. | O41: https://www.dokdo.re.kr/home/cms/cmsCont.do?cntnts_sn=66 | P41: =LEN(E41)+MAX(LEN(F41),LEN(G41),LEN(H41)) -> 51 | Q41: 출처 기반 자체 검토 / 독립 승인 전
A42: 910041 | B42: 3 | C42: dk-volcano | D42: 1 | E42: 독도 형성과 관련된 활동은? | F42: 바닷속 화산활동 | G42: 강 하구에 모래 쌓임 | H42: 빙하가 바다에 떠다님 | I42: 1 | J42: 독도는 바닷속 화산활동으로 만들어졌어요. 화산에서 나온 물질이 쌓이고 굳어 바위가 되었어요. | K42: 독도는 바닷속 화산활동으로 만들어졌어요. 화산에서 나온 물질이 쌓이고 굳어 바위가 되었어요. | L42: 고른 보기 ‘강 하구에 모래 쌓임’와 달라요. 이 문항의 정답은 ‘바닷속 화산활동’입니다. 독도는 바닷속 화산활동으로 만들어졌어요. 화산에서 나온 물질이 쌓이고 굳어 바위가 되었어요. | M42: 고른 보기 ‘빙하가 바다에 떠다님’와 달라요. 이 문항의 정답은 ‘바닷속 화산활동’입니다. 독도는 바닷속 화산활동으로 만들어졌어요. 화산에서 나온 물질이 쌓이고 굳어 바위가 되었어요. | O42: https://www.dokdo.re.kr/home/cms/cmsCont.do?cntnts_sn=66 | P42: =LEN(E42)+MAX(LEN(F42),LEN(G42),LEN(H42)) -> 26 | Q42: 출처 기반 자체 검토 / 독립 승인 전
A43: 910042 | B43: 3 | C43: dk-volcano | D43: 2 | E43: 화산에서 나온 물질과 독도 바위의 관계는? | F43: 등대가 바위를 만든 재료예요 | G43: 바닷물이 얼어 된 얼음이에요 | H43: 쌓이고 굳어 바위가 되었어요 | I43: 3 | J43: 독도는 바닷속 화산활동으로 만들어졌어요. 화산에서 나온 물질이 쌓이고 굳어 바위가 되었어요. | K43: 고른 보기 ‘등대가 바위를 만든 재료예요’와 달라요. 이 문항의 정답은 ‘쌓이고 굳어 바위가 되었어요’입니다. 독도는 바닷속 화산활동으로 만들어졌어요. 화산에서 나온 물질이 쌓이고 굳어 바위가 되었어요. | L43: 고른 보기 ‘바닷물이 얼어 된 얼음이에요’와 달라요. 이 문항의 정답은 ‘쌓이고 굳어 바위가 되었어요’입니다. 독도는 바닷속 화산활동으로 만들어졌어요. 화산에서 나온 물질이 쌓이고 굳어 바위가 되었어요. | M43: 독도는 바닷속 화산활동으로 만들어졌어요. 화산에서 나온 물질이 쌓이고 굳어 바위가 되었어요. | O43: https://www.dokdo.re.kr/home/cms/cmsCont.do?cntnts_sn=66 | P43: =LEN(E43)+MAX(LEN(F43),LEN(G43),LEN(H43)) -> 38 | Q43: 출처 기반 자체 검토 / 독립 승인 전
A44: 910043 | B44: 3 | C44: dk-volcano | D44: 3 | E44: 자료가 독도를 화산섬이라 설명하는 근거는? | F44: 현재 시설의 이름 | G44: 해저 분출 과정과 화산암 구성 | H44: 선착장의 배 크기 | I44: 2 | J44: 독도는 바닷속 화산활동으로 만들어졌어요. 화산에서 나온 물질이 쌓이고 굳어 바위가 되었어요. | K44: 고른 보기 ‘현재 시설의 이름’와 달라요. 이 문항의 정답은 ‘해저 분출 과정과 화산암 구성’입니다. 독도는 바닷속 화산활동으로 만들어졌어요. 화산에서 나온 물질이 쌓이고 굳어 바위가 되었어요. | L44: 독도는 바닷속 화산활동으로 만들어졌어요. 화산에서 나온 물질이 쌓이고 굳어 바위가 되었어요. | M44: 고른 보기 ‘선착장의 배 크기’와 달라요. 이 문항의 정답은 ‘해저 분출 과정과 화산암 구성’입니다. 독도는 바닷속 화산활동으로 만들어졌어요. 화산에서 나온 물질이 쌓이고 굳어 바위가 되었어요. | N44: 한국해양과학기술원은 독도가 해저에서 분출한 화산체로 형성되었으며 조면안산암·응회암 등 화산암으로 이루어져 있다고 설명합니다. 암석 이름의 암기가 아니라 형성 과정을 살펴봅니다. | O44: https://www.dokdo.re.kr/home/cms/cmsCont.do?cntnts_sn=66 | P44: =LEN(E44)+MAX(LEN(F44),LEN(G44),LEN(H44)) -> 39 | Q44: 출처 기반 자체 검토 / 독립 승인 전
A45: 910044 | B45: 3 | C45: dk-volcano | D45: 4 | E45: 독도의 화산암 이름만 외우면 형성을 설명했을까요? | F45: 분출·퇴적·굳음의 과정도 연결해야 한다 | G45: 이름 수가 많으면 형성 순서도 증명된다 | H45: 시설 설치 순서가 화산 형성 순서다 | I45: 1 | J45: 독도는 바닷속 화산활동으로 만들어졌어요. 화산에서 나온 물질이 쌓이고 굳어 바위가 되었어요. | K45: 독도는 바닷속 화산활동으로 만들어졌어요. 화산에서 나온 물질이 쌓이고 굳어 바위가 되었어요. | L45: 고른 보기 ‘이름 수가 많으면 형성 순서도 증명된다’와 달라요. 이 문항의 정답은 ‘분출·퇴적·굳음의 과정도 연결해야 한다’입니다. 독도는 바닷속 화산활동으로 만들어졌어요. 화산에서 나온 물질이 쌓이고 굳어 바위가 되었어요. | M45: 고른 보기 ‘시설 설치 순서가 화산 형성 순서다’와 달라요. 이 문항의 정답은 ‘분출·퇴적·굳음의 과정도 연결해야 한다’입니다. 독도는 바닷속 화산활동으로 만들어졌어요. 화산에서 나온 물질이 쌓이고 굳어 바위가 되었어요. | N45: 한국해양과학기술원은 독도가 해저에서 분출한 화산체로 형성되었으며 조면안산암·응회암 등 화산암으로 이루어져 있다고 설명합니다. 암석 이름의 암기가 아니라 형성 과정을 살펴봅니다. | O45: https://www.dokdo.re.kr/home/cms/cmsCont.do?cntnts_sn=66 | P45: =LEN(E45)+MAX(LEN(F45),LEN(G45),LEN(H45)) -> 48 | Q45: 출처 기반 자체 검토 / 독립 승인 전
A46: 910045 | B46: 3 | C46: dk-formation-time | D46: 1 | E46: 독도는 어떻게 만들어졌을까요? | F46: 등대를 지은 하루에 | G46: 배가 처음 온 순간에 | H46: 오랜 시간에 걸쳐 | I46: 3 | J46: 독도는 오랜 시간에 걸쳐 만들어지고 변했어요. 바닷속에서 자란 뒤 물 위로 드러났어요. | K46: 고른 보기 ‘등대를 지은 하루에’와 달라요. 이 문항의 정답은 ‘오랜 시간에 걸쳐’입니다. 독도는 오랜 시간에 걸쳐 만들어지고 변했어요. 바닷속에서 자란 뒤 물 위로 드러났어요. | L46: 고른 보기 ‘배가 처음 온 순간에’와 달라요. 이 문항의 정답은 ‘오랜 시간에 걸쳐’입니다. 독도는 오랜 시간에 걸쳐 만들어지고 변했어요. 바닷속에서 자란 뒤 물 위로 드러났어요. | M46: 독도는 오랜 시간에 걸쳐 만들어지고 변했어요. 바닷속에서 자란 뒤 물 위로 드러났어요. | O46: https://www.dokdo.re.kr/home/cms/cmsCont.do?cntnts_sn=66 | P46: =LEN(E46)+MAX(LEN(F46),LEN(G46),LEN(H46)) -> 27 | Q46: 출처 기반 자체 검토 / 독립 승인 전
A47: 910046 | B47: 3 | C47: dk-formation-time | D47: 2 | E47: 독도 형성 순서로 알맞은 것은? | F47: 선착장 공사→바위 생성 시작 | G47: 해저 화산 성장→수면 위 출현 | H47: 등대 설치→해저 화산 시작 | I47: 2 | J47: 독도는 오랜 시간에 걸쳐 만들어지고 변했어요. 바닷속에서 자란 뒤 물 위로 드러났어요. | K47: 고른 보기 ‘선착장 공사→바위 생성 시작’와 달라요. 이 문항의 정답은 ‘해저 화산 성장→수면 위 출현’입니다. 독도는 오랜 시간에 걸쳐 만들어지고 변했어요. 바닷속에서 자란 뒤 물 위로 드러났어요. | L47: 독도는 오랜 시간에 걸쳐 만들어지고 변했어요. 바닷속에서 자란 뒤 물 위로 드러났어요. | M47: 고른 보기 ‘등대 설치→해저 화산 시작’와 달라요. 이 문항의 정답은 ‘해저 화산 성장→수면 위 출현’입니다. 독도는 오랜 시간에 걸쳐 만들어지고 변했어요. 바닷속에서 자란 뒤 물 위로 드러났어요. | O47: https://www.dokdo.re.kr/home/cms/cmsCont.do?cntnts_sn=66 | P47: =LEN(E47)+MAX(LEN(F47),LEN(G47),LEN(H47)) -> 33 | Q47: 출처 기반 자체 검토 / 독립 승인 전
A48: 910047 | B48: 3 | C48: dk-formation-time | D48: 3 | E48: 자료에서 더 먼저 일어난 것은? | F48: 해저 화산활동의 시작 | G48: 수면 위로 드러난 시기 | H48: 오늘날 등대의 설치 | I48: 1 | J48: 독도는 오랜 시간에 걸쳐 만들어지고 변했어요. 바닷속에서 자란 뒤 물 위로 드러났어요. | K48: 독도는 오랜 시간에 걸쳐 만들어지고 변했어요. 바닷속에서 자란 뒤 물 위로 드러났어요. | L48: 고른 보기 ‘수면 위로 드러난 시기’와 달라요. 이 문항의 정답은 ‘해저 화산활동의 시작’입니다. 독도는 오랜 시간에 걸쳐 만들어지고 변했어요. 바닷속에서 자란 뒤 물 위로 드러났어요. | M48: 고른 보기 ‘오늘날 등대의 설치’와 달라요. 이 문항의 정답은 ‘해저 화산활동의 시작’입니다. 독도는 오랜 시간에 걸쳐 만들어지고 변했어요. 바닷속에서 자란 뒤 물 위로 드러났어요. | N48: 자료의 대략적 시점: 약 460만 년 전부터 해저 화산활동, 약 250만 년 전부터 수면 위 출현. 이후에는 침식의 영향이 컸습니다. 정확한 연도를 외우는 대신 순서를 읽으세요. | O48: https://www.dokdo.re.kr/home/cms/cmsCont.do?cntnts_sn=66 | P48: =LEN(E48)+MAX(LEN(F48),LEN(G48),LEN(H48)) -> 29 | Q48: 출처 기반 자체 검토 / 독립 승인 전
A49: 910048 | B49: 3 | C49: dk-formation-time | D49: 4 | E49: ‘460만 년 전 지금 모양으로 완성’이라는 설명은? | F49: 시작 시점과 현재 모양은 항상 같다 | G49: 수면 위 출현 전에는 화산체가 없었다 | H49: 형성 이후 침식과 변화를 빠뜨렸다 | I49: 3 | J49: 독도는 오랜 시간에 걸쳐 만들어지고 변했어요. 바닷속에서 자란 뒤 물 위로 드러났어요. | K49: 고른 보기 ‘시작 시점과 현재 모양은 항상 같다’와 달라요. 이 문항의 정답은 ‘형성 이후 침식과 변화를 빠뜨렸다’입니다. 독도는 오랜 시간에 걸쳐 만들어지고 변했어요. 바닷속에서 자란 뒤 물 위로 드러났어요. | L49: 고른 보기 ‘수면 위 출현 전에는 화산체가 없었다’와 달라요. 이 문항의 정답은 ‘형성 이후 침식과 변화를 빠뜨렸다’입니다. 독도는 오랜 시간에 걸쳐 만들어지고 변했어요. 바닷속에서 자란 뒤 물 위로 드러났어요. | M49: 독도는 오랜 시간에 걸쳐 만들어지고 변했어요. 바닷속에서 자란 뒤 물 위로 드러났어요. | N49: 자료의 대략적 시점: 약 460만 년 전부터 해저 화산활동, 약 250만 년 전부터 수면 위 출현. 이후에는 침식의 영향이 컸습니다. 정확한 연도를 외우는 대신 순서를 읽으세요. | O49: https://www.dokdo.re.kr/home/cms/cmsCont.do?cntnts_sn=66 | P49: =LEN(E49)+MAX(LEN(F49),LEN(G49),LEN(H49)) -> 49 | Q49: 출처 기반 자체 검토 / 독립 승인 전
A50: 910049 | B50: 3 | C50: dk-wave-erosion | D50: 1 | E50: 독도 해안의 바위를 깎는 힘은? | F50: 헬기장의 표시 | G50: 파도 | H50: 등대의 빛 | I50: 2 | J50: 독도 해안의 파도는 바위를 깎아요. 해안 절벽·동굴·바위 아치 같은 지형이 생기는 데 영향을 주었어요. | K50: 고른 보기 ‘헬기장의 표시’와 달라요. 이 문항의 정답은 ‘파도’입니다. 독도 해안의 파도는 바위를 깎아요. 해안 절벽·동굴·바위 아치 같은 지형이 생기는 데 영향을 주었어요. | L50: 독도 해안의 파도는 바위를 깎아요. 해안 절벽·동굴·바위 아치 같은 지형이 생기는 데 영향을 주었어요. | M50: 고른 보기 ‘등대의 빛’와 달라요. 이 문항의 정답은 ‘파도’입니다. 독도 해안의 파도는 바위를 깎아요. 해안 절벽·동굴·바위 아치 같은 지형이 생기는 데 영향을 주었어요. | O50: https://www.dokdo.re.kr/home/cms/cmsCont.do?cntnts_sn=66 https://korean.visitkorea.or.kr/detail/ms_detail.do?cotid=0fe4eeb6-3f6a-48b1-ab75-c8d4ab6b43be | P50: =LEN(E50)+MAX(LEN(F50),LEN(G50),LEN(H50)) -> 24 | Q50: 출처 기반 자체 검토 / 독립 승인 전
A51: 910050 | B51: 3 | C51: dk-wave-erosion | D51: 2 | E51: 해안 동굴과 연결되는 과정은? | F51: 파도가 바위를 깎기 | G51: 바닷물이 얼어 쌓이기 | H51: 등대 불빛이 모이기 | I51: 1 | J51: 독도 해안의 파도는 바위를 깎아요. 해안 절벽·동굴·바위 아치 같은 지형이 생기는 데 영향을 주었어요. | K51: 독도 해안의 파도는 바위를 깎아요. 해안 절벽·동굴·바위 아치 같은 지형이 생기는 데 영향을 주었어요. | L51: 고른 보기 ‘바닷물이 얼어 쌓이기’와 달라요. 이 문항의 정답은 ‘파도가 바위를 깎기’입니다. 독도 해안의 파도는 바위를 깎아요. 해안 절벽·동굴·바위 아치 같은 지형이 생기는 데 영향을 주었어요. | M51: 고른 보기 ‘등대 불빛이 모이기’와 달라요. 이 문항의 정답은 ‘파도가 바위를 깎기’입니다. 독도 해안의 파도는 바위를 깎아요. 해안 절벽·동굴·바위 아치 같은 지형이 생기는 데 영향을 주었어요. | O51: https://www.dokdo.re.kr/home/cms/cmsCont.do?cntnts_sn=66 https://korean.visitkorea.or.kr/detail/ms_detail.do?cotid=0fe4eeb6-3f6a-48b1-ab75-c8d4ab6b43be | P51: =LEN(E51)+MAX(LEN(F51),LEN(G51),LEN(H51)) -> 27 | Q51: 출처 기반 자체 검토 / 독립 승인 전
A52: 910051 | B52: 3 | C52: dk-wave-erosion | D52: 3 | E52: 파도에 깎인 절벽을 가리키는 말은? | F52: 해식동 | G52: 시아치 | H52: 해식애 | I52: 3 | J52: 독도 해안의 파도는 바위를 깎아요. 해안 절벽·동굴·바위 아치 같은 지형이 생기는 데 영향을 주었어요. 세 용어는 모두 해안 지형이지만 모양과 구조가 다릅니다. | K52: 고른 보기 ‘해식동’와 달라요. 이 문항의 정답은 ‘해식애’입니다. 독도 해안의 파도는 바위를 깎아요. 해안 절벽·동굴·바위 아치 같은 지형이 생기는 데 영향을 주었어요. 세 용어는 모두 해안 지형이지만 모양과 구조가 다릅니다. | L52: 고른 보기 ‘시아치’와 달라요. 이 문항의 정답은 ‘해식애’입니다. 독도 해안의 파도는 바위를 깎아요. 해안 절벽·동굴·바위 아치 같은 지형이 생기는 데 영향을 주었어요. 세 용어는 모두 해안 지형이지만 모양과 구조가 다릅니다. | M52: 독도 해안의 파도는 바위를 깎아요. 해안 절벽·동굴·바위 아치 같은 지형이 생기는 데 영향을 주었어요. 세 용어는 모두 해안 지형이지만 모양과 구조가 다릅니다. | N52: 해식애는 파도가 깎은 절벽, 해식동은 해안 동굴, 시아치는 바위 아치입니다. 독도에서는 이런 해안 침식 지형을 볼 수 있습니다. | O52: https://www.dokdo.re.kr/home/cms/cmsCont.do?cntnts_sn=66 https://korean.visitkorea.or.kr/detail/ms_detail.do?cotid=0fe4eeb6-3f6a-48b1-ab75-c8d4ab6b43be | P52: =LEN(E52)+MAX(LEN(F52),LEN(G52),LEN(H52)) -> 22 | Q52: 출처 기반 자체 검토 / 독립 승인 전
A53: 910052 | B53: 3 | C53: dk-wave-erosion | D53: 4 | E53: 바위 아치를 사람이 만든 문이라 해석하면? | F53: 해안에서 침식은 일어나지 않는다 | G53: 닮은 모양과 실제 형성 과정을 혼동한다 | H53: 문처럼 보이면 모두 건축물이다 | I53: 2 | J53: 독도 해안의 파도는 바위를 깎아요. 해안 절벽·동굴·바위 아치 같은 지형이 생기는 데 영향을 주었어요. | K53: 고른 보기 ‘해안에서 침식은 일어나지 않는다’와 달라요. 이 문항의 정답은 ‘닮은 모양과 실제 형성 과정을 혼동한다’입니다. 독도 해안의 파도는 바위를 깎아요. 해안 절벽·동굴·바위 아치 같은 지형이 생기는 데 영향을 주었어요. | L53: 독도 해안의 파도는 바위를 깎아요. 해안 절벽·동굴·바위 아치 같은 지형이 생기는 데 영향을 주었어요. | M53: 고른 보기 ‘문처럼 보이면 모두 건축물이다’와 달라요. 이 문항의 정답은 ‘닮은 모양과 실제 형성 과정을 혼동한다’입니다. 독도 해안의 파도는 바위를 깎아요. 해안 절벽·동굴·바위 아치 같은 지형이 생기는 데 영향을 주었어요. | N53: 해식애는 파도가 깎은 절벽, 해식동은 해안 동굴, 시아치는 바위 아치입니다. 독도에서는 이런 해안 침식 지형을 볼 수 있습니다. | O53: https://www.dokdo.re.kr/home/cms/cmsCont.do?cntnts_sn=66 https://korean.visitkorea.or.kr/detail/ms_detail.do?cotid=0fe4eeb6-3f6a-48b1-ab75-c8d4ab6b43be | P53: =LEN(E53)+MAX(LEN(F53),LEN(G53),LEN(H53)) -> 44 | Q53: 출처 기반 자체 검토 / 독립 승인 전
A54: 910053 | B54: 3 | C54: dk-weathering | D54: 1 | E54: 독도 바위의 모습은 시간이 지나면? | F54: 조금씩 달라질 수 있어요 | G54: 어느 부분도 절대 안 변해요 | H54: 등대 색으로만 결정돼요 | I54: 1 | J54: 독도 바위는 바람과 파도에 노출되어 조금씩 풍화되고 깎여요. 바위와 해안을 계속 살피는 연구가 필요해요. | K54: 독도 바위는 바람과 파도에 노출되어 조금씩 풍화되고 깎여요. 바위와 해안을 계속 살피는 연구가 필요해요. | L54: 고른 보기 ‘어느 부분도 절대 안 변해요’와 달라요. 이 문항의 정답은 ‘조금씩 달라질 수 있어요’입니다. 독도 바위는 바람과 파도에 노출되어 조금씩 풍화되고 깎여요. 바위와 해안을 계속 살피는 연구가 필요해요. | M54: 고른 보기 ‘등대 색으로만 결정돼요’와 달라요. 이 문항의 정답은 ‘조금씩 달라질 수 있어요’입니다. 독도 바위는 바람과 파도에 노출되어 조금씩 풍화되고 깎여요. 바위와 해안을 계속 살피는 연구가 필요해요. | O54: https://www.dokdo.re.kr/home/cms/cmsCont.do?cntnts_sn=66 | P54: =LEN(E54)+MAX(LEN(F54),LEN(G54),LEN(H54)) -> 34 | Q54: 출처 기반 자체 검토 / 독립 승인 전
A55: 910054 | B55: 3 | C55: dk-weathering | D55: 2 | E55: 독도를 여러 해에 걸쳐 재는 까닭은? | F55: 섬 이름을 매년 바꾸려고 | G55: 바위의 수를 무조건 늘리려고 | H55: 해안과 바위의 변화를 보려고 | I55: 3 | J55: 독도 바위는 바람과 파도에 노출되어 조금씩 풍화되고 깎여요. 바위와 해안을 계속 살피는 연구가 필요해요. | K55: 고른 보기 ‘섬 이름을 매년 바꾸려고’와 달라요. 이 문항의 정답은 ‘해안과 바위의 변화를 보려고’입니다. 독도 바위는 바람과 파도에 노출되어 조금씩 풍화되고 깎여요. 바위와 해안을 계속 살피는 연구가 필요해요. | L55: 고른 보기 ‘바위의 수를 무조건 늘리려고’와 달라요. 이 문항의 정답은 ‘해안과 바위의 변화를 보려고’입니다. 독도 바위는 바람과 파도에 노출되어 조금씩 풍화되고 깎여요. 바위와 해안을 계속 살피는 연구가 필요해요. | M55: 독도 바위는 바람과 파도에 노출되어 조금씩 풍화되고 깎여요. 바위와 해안을 계속 살피는 연구가 필요해요. | O55: https://www.dokdo.re.kr/home/cms/cmsCont.do?cntnts_sn=66 | P55: =LEN(E55)+MAX(LEN(F55),LEN(G55),LEN(H55)) -> 35 | Q55: 출처 기반 자체 검토 / 독립 승인 전
A56: 910055 | B56: 3 | C56: dk-weathering | D56: 3 | E56: 독도의 지형 변화를 비교하기 좋은 자료는? | F56: 두 섬의 별명만 적은 표 | G56: 기준을 맞춘 반복 측량 | H56: 촬영 시점 없는 그림 한 장 | I56: 2 | J56: 독도 바위는 바람과 파도에 노출되어 조금씩 풍화되고 깎여요. 바위와 해안을 계속 살피는 연구가 필요해요. | K56: 고른 보기 ‘두 섬의 별명만 적은 표’와 달라요. 이 문항의 정답은 ‘기준을 맞춘 반복 측량’입니다. 독도 바위는 바람과 파도에 노출되어 조금씩 풍화되고 깎여요. 바위와 해안을 계속 살피는 연구가 필요해요. | L56: 독도 바위는 바람과 파도에 노출되어 조금씩 풍화되고 깎여요. 바위와 해안을 계속 살피는 연구가 필요해요. | M56: 고른 보기 ‘촬영 시점 없는 그림 한 장’와 달라요. 이 문항의 정답은 ‘기준을 맞춘 반복 측량’입니다. 독도 바위는 바람과 파도에 노출되어 조금씩 풍화되고 깎여요. 바위와 해안을 계속 살피는 연구가 필요해요. | N56: 독도 지형 연구는 낙석·토층 유실·해안선 변화 등을 관찰합니다. 반복 측량은 같은 기준으로 과거와 현재를 비교할 때 도움이 됩니다. | O56: https://www.dokdo.re.kr/home/cms/cmsCont.do?cntnts_sn=66 | P56: =LEN(E56)+MAX(LEN(F56),LEN(G56),LEN(H56)) -> 38 | Q56: 출처 기반 자체 검토 / 독립 승인 전
A57: 910056 | B57: 3 | C57: dk-weathering | D57: 4 | E57: 사진 두 장의 차이를 모두 낙석이라 해도 될까요? | F57: 촬영 각도·시점부터 대조해야 한다 | G57: 독도 사진이면 각도는 무관하다 | H57: 사진 속 그림자는 모두 낙석이다 | I57: 1 | J57: 독도 바위는 바람과 파도에 노출되어 조금씩 풍화되고 깎여요. 바위와 해안을 계속 살피는 연구가 필요해요. | K57: 독도 바위는 바람과 파도에 노출되어 조금씩 풍화되고 깎여요. 바위와 해안을 계속 살피는 연구가 필요해요. | L57: 고른 보기 ‘독도 사진이면 각도는 무관하다’와 달라요. 이 문항의 정답은 ‘촬영 각도·시점부터 대조해야 한다’입니다. 독도 바위는 바람과 파도에 노출되어 조금씩 풍화되고 깎여요. 바위와 해안을 계속 살피는 연구가 필요해요. | M57: 고른 보기 ‘사진 속 그림자는 모두 낙석이다’와 달라요. 이 문항의 정답은 ‘촬영 각도·시점부터 대조해야 한다’입니다. 독도 바위는 바람과 파도에 노출되어 조금씩 풍화되고 깎여요. 바위와 해안을 계속 살피는 연구가 필요해요. | N57: 독도 지형 연구는 낙석·토층 유실·해안선 변화 등을 관찰합니다. 반복 측량은 같은 기준으로 과거와 현재를 비교할 때 도움이 됩니다. | O57: https://www.dokdo.re.kr/home/cms/cmsCont.do?cntnts_sn=66 | P57: =LEN(E57)+MAX(LEN(F57),LEN(G57),LEN(H57)) -> 45 | Q57: 출처 기반 자체 검토 / 독립 승인 전
A58: 910057 | B58: 3 | C58: dk-mulgol | D58: 1 | E58: 물골이 있는 큰 섬은? | F58: 동도 | G58: 울릉도 | H58: 서도 | I58: 3 | J58: 서도의 물골에는 바위에서 떨어지는 물이 있어요. 담수화 시설이 생기기 전에는 식수원으로 쓰였어요. | K58: 고른 보기 ‘동도’와 달라요. 이 문항의 정답은 ‘서도’입니다. 서도의 물골에는 바위에서 떨어지는 물이 있어요. 담수화 시설이 생기기 전에는 식수원으로 쓰였어요. | L58: 고른 보기 ‘울릉도’와 달라요. 이 문항의 정답은 ‘서도’입니다. 서도의 물골에는 바위에서 떨어지는 물이 있어요. 담수화 시설이 생기기 전에는 식수원으로 쓰였어요. | M58: 서도의 물골에는 바위에서 떨어지는 물이 있어요. 담수화 시설이 생기기 전에는 식수원으로 쓰였어요. | O58: https://www.dokdo.re.kr/home/cms/cmsCont.do?cntnts_sn=66 | P58: =LEN(E58)+MAX(LEN(F58),LEN(G58),LEN(H58)) -> 15 | Q58: 출처 기반 자체 검토 / 독립 승인 전
A59: 910058 | B59: 3 | C59: dk-mulgol | D59: 2 | E59: 물골과 예전 독도 생활의 연결은? | F59: 배에 빛을 보내는 곳 | G59: 물을 얻는 곳 | H59: 헬기가 내리는 곳 | I59: 2 | J59: 서도의 물골에는 바위에서 떨어지는 물이 있어요. 담수화 시설이 생기기 전에는 식수원으로 쓰였어요. | K59: 고른 보기 ‘배에 빛을 보내는 곳’와 달라요. 이 문항의 정답은 ‘물을 얻는 곳’입니다. 서도의 물골에는 바위에서 떨어지는 물이 있어요. 담수화 시설이 생기기 전에는 식수원으로 쓰였어요. | L59: 서도의 물골에는 바위에서 떨어지는 물이 있어요. 담수화 시설이 생기기 전에는 식수원으로 쓰였어요. | M59: 고른 보기 ‘헬기가 내리는 곳’와 달라요. 이 문항의 정답은 ‘물을 얻는 곳’입니다. 서도의 물골에는 바위에서 떨어지는 물이 있어요. 담수화 시설이 생기기 전에는 식수원으로 쓰였어요. | O59: https://www.dokdo.re.kr/home/cms/cmsCont.do?cntnts_sn=66 | P59: =LEN(E59)+MAX(LEN(F59),LEN(G59),LEN(H59)) -> 29 | Q59: 출처 기반 자체 검토 / 독립 승인 전
A60: 910059 | B60: 3 | C60: dk-mulgol | D60: 3 | E60: 자료에서 확인할 수 있는 물골의 역할은? | F60: 담수화 시설 전 식수원 | G60: 현재 모든 물의 유일한 공급원 | H60: 비행장의 연료 저장고 | I60: 1 | J60: 서도의 물골에는 바위에서 떨어지는 물이 있어요. 담수화 시설이 생기기 전에는 식수원으로 쓰였어요. | K60: 서도의 물골에는 바위에서 떨어지는 물이 있어요. 담수화 시설이 생기기 전에는 식수원으로 쓰였어요. | L60: 고른 보기 ‘현재 모든 물의 유일한 공급원’와 달라요. 이 문항의 정답은 ‘담수화 시설 전 식수원’입니다. 서도의 물골에는 바위에서 떨어지는 물이 있어요. 담수화 시설이 생기기 전에는 식수원으로 쓰였어요. | M60: 고른 보기 ‘비행장의 연료 저장고’와 달라요. 이 문항의 정답은 ‘담수화 시설 전 식수원’입니다. 서도의 물골에는 바위에서 떨어지는 물이 있어요. 담수화 시설이 생기기 전에는 식수원으로 쓰였어요. | N60: 한국해양과학기술원은 물골을 서도 북서쪽 해안 동굴로 소개하며, 바위에서 떨어지는 물이 담수화 시설 설치 이전 식수원이었다고 설명합니다. | O60: https://www.dokdo.re.kr/home/cms/cmsCont.do?cntnts_sn=66 | P60: =LEN(E60)+MAX(LEN(F60),LEN(G60),LEN(H60)) -> 38 | Q60: 출처 기반 자체 검토 / 독립 승인 전
A61: 910060 | B61: 3 | C61: dk-mulgol | D61: 4 | E61: 물골이 지금도 유일한 식수원이라는 주장은? | F61: 과거에 썼으므로 현재도 유일함이 증명된다 | G61: 담수화 시설은 식수와 전혀 관계없다 | H61: 과거의 역할을 현재로 확대해 추가 확인이 필요하다 | I61: 3 | J61: 서도의 물골에는 바위에서 떨어지는 물이 있어요. 담수화 시설이 생기기 전에는 식수원으로 쓰였어요. | K61: 고른 보기 ‘과거에 썼으므로 현재도 유일함이 증명된다’와 달라요. 이 문항의 정답은 ‘과거의 역할을 현재로 확대해 추가 확인이 필요하다’입니다. 서도의 물골에는 바위에서 떨어지는 물이 있어요. 담수화 시설이 생기기 전에는 식수원으로 쓰였어요. | L61: 고른 보기 ‘담수화 시설은 식수와 전혀 관계없다’와 달라요. 이 문항의 정답은 ‘과거의 역할을 현재로 확대해 추가 확인이 필요하다’입니다. 서도의 물골에는 바위에서 떨어지는 물이 있어요. 담수화 시설이 생기기 전에는 식수원으로 쓰였어요. | M61: 서도의 물골에는 바위에서 떨어지는 물이 있어요. 담수화 시설이 생기기 전에는 식수원으로 쓰였어요. | N61: 한국해양과학기술원은 물골을 서도 북서쪽 해안 동굴로 소개하며, 바위에서 떨어지는 물이 담수화 시설 설치 이전 식수원이었다고 설명합니다. | O61: https://www.dokdo.re.kr/home/cms/cmsCont.do?cntnts_sn=66 | P61: =LEN(E61)+MAX(LEN(F61),LEN(G61),LEN(H61)) -> 50 | Q61: 출처 기반 자체 검토 / 독립 승인 전
A62: 910061 | B62: 4 | C62: dk-migratory-stopover | D62: 1 | E62: 이동하는 새에게 독도의 역할은? | F62: 민물만 있는 호수 | G62: 중간에 쉬는 곳 | H62: 대륙 안의 논 | I62: 2 | J62: 독도는 먼 길을 이동하는 새들이 쉬어 가는 곳이기도 해요. | K62: 고른 보기 ‘민물만 있는 호수’와 달라요. 이 문항의 정답은 ‘중간에 쉬는 곳’입니다. 독도는 먼 길을 이동하는 새들이 쉬어 가는 곳이기도 해요. | L62: 독도는 먼 길을 이동하는 새들이 쉬어 가는 곳이기도 해요. | M62: 고른 보기 ‘대륙 안의 논’와 달라요. 이 문항의 정답은 ‘중간에 쉬는 곳’입니다. 독도는 먼 길을 이동하는 새들이 쉬어 가는 곳이기도 해요. | O62: https://dokdo.mofa.go.kr/kor/introduce/nature.jsp | P62: =LEN(E62)+MAX(LEN(F62),LEN(G62),LEN(H62)) -> 26 | Q62: 출처 기반 자체 검토 / 독립 승인 전
A63: 910062 | B63: 4 | C63: dk-migratory-stopover | D63: 2 | E63: ‘중간기착지’와 연결되는 독도의 모습은? | F63: 긴 이동 중 잠시 머무는 섬 | G63: 모든 새가 평생 떠나지 않는 섬 | H63: 육지와 도로로 이어진 섬 | I63: 1 | J63: 독도는 먼 길을 이동하는 새들이 쉬어 가는 곳이기도 해요. | K63: 독도는 먼 길을 이동하는 새들이 쉬어 가는 곳이기도 해요. | L63: 고른 보기 ‘모든 새가 평생 떠나지 않는 섬’와 달라요. 이 문항의 정답은 ‘긴 이동 중 잠시 머무는 섬’입니다. 독도는 먼 길을 이동하는 새들이 쉬어 가는 곳이기도 해요. | M63: 고른 보기 ‘육지와 도로로 이어진 섬’와 달라요. 이 문항의 정답은 ‘긴 이동 중 잠시 머무는 섬’입니다. 독도는 먼 길을 이동하는 새들이 쉬어 가는 곳이기도 해요. | O63: https://dokdo.mofa.go.kr/kor/introduce/nature.jsp | P63: =LEN(E63)+MAX(LEN(F63),LEN(G63),LEN(H63)) -> 39 | Q63: 출처 기반 자체 검토 / 독립 승인 전
A64: 910063 | B64: 4 | C64: dk-migratory-stopover | D64: 3 | E64: 자료가 설명하는 독도의 생태적 가치는? | F64: 모든 철새의 최종 목적지다 | G64: 철새는 독도에서만 먹이를 얻는다 | H64: 철새의 이동 과정에서 휴식처가 된다 | I64: 3 | J64: 독도는 먼 길을 이동하는 새들이 쉬어 가는 곳이기도 해요. | K64: 고른 보기 ‘모든 철새의 최종 목적지다’와 달라요. 이 문항의 정답은 ‘철새의 이동 과정에서 휴식처가 된다’입니다. 독도는 먼 길을 이동하는 새들이 쉬어 가는 곳이기도 해요. | L64: 고른 보기 ‘철새는 독도에서만 먹이를 얻는다’와 달라요. 이 문항의 정답은 ‘철새의 이동 과정에서 휴식처가 된다’입니다. 독도는 먼 길을 이동하는 새들이 쉬어 가는 곳이기도 해요. | M64: 독도는 먼 길을 이동하는 새들이 쉬어 가는 곳이기도 해요. | N64: 외교부는 독도를 철새 이동경로의 중간 피난처와 휴식처로 소개합니다. 모든 새가 같은 기간 머문다는 뜻은 아닙니다. | O64: https://dokdo.mofa.go.kr/kor/introduce/nature.jsp | P64: =LEN(E64)+MAX(LEN(F64),LEN(G64),LEN(H64)) -> 40 | Q64: 출처 기반 자체 검토 / 독립 승인 전
A65: 910064 | B65: 4 | C65: dk-migratory-stopover | D65: 4 | E65: ‘독도에 온 새는 모두 그곳에서 번식한다’는 말은? | F65: 잠시 머무는 새는 이동하는 새가 아니다 | G65: 휴식과 번식을 구별한 추가 자료가 필요하다 | H65: 쉼터라는 설명만으로 충분히 증명된다 | I65: 2 | J65: 독도는 먼 길을 이동하는 새들이 쉬어 가는 곳이기도 해요. | K65: 고른 보기 ‘잠시 머무는 새는 이동하는 새가 아니다’와 달라요. 이 문항의 정답은 ‘휴식과 번식을 구별한 추가 자료가 필요하다’입니다. 독도는 먼 길을 이동하는 새들이 쉬어 가는 곳이기도 해요. | L65: 독도는 먼 길을 이동하는 새들이 쉬어 가는 곳이기도 해요. | M65: 고른 보기 ‘쉼터라는 설명만으로 충분히 증명된다’와 달라요. 이 문항의 정답은 ‘휴식과 번식을 구별한 추가 자료가 필요하다’입니다. 독도는 먼 길을 이동하는 새들이 쉬어 가는 곳이기도 해요. | N65: 외교부는 독도를 철새 이동경로의 중간 피난처와 휴식처로 소개합니다. 모든 새가 같은 기간 머문다는 뜻은 아닙니다. | O65: https://dokdo.mofa.go.kr/kor/introduce/nature.jsp | P65: =LEN(E65)+MAX(LEN(F65),LEN(G65),LEN(H65)) -> 51 | Q65: 출처 기반 자체 검토 / 독립 승인 전
A66: 910065 | B66: 4 | C66: dk-breeding-birds | D66: 1 | E66: 독도에서 번식하는 바닷새의 예는? | F66: 괭이갈매기 | G66: 참새만 | H66: 도시비둘기만 | I66: 1 | J66: 독도에서는 괭이갈매기·바다제비·슴새 같은 바닷새가 번식해요. 번식은 새끼를 낳고 기르는 일이에요. | K66: 독도에서는 괭이갈매기·바다제비·슴새 같은 바닷새가 번식해요. 번식은 새끼를 낳고 기르는 일이에요. | L66: 고른 보기 ‘참새만’와 달라요. 이 문항의 정답은 ‘괭이갈매기’입니다. 독도에서는 괭이갈매기·바다제비·슴새 같은 바닷새가 번식해요. 번식은 새끼를 낳고 기르는 일이에요. | M66: 고른 보기 ‘도시비둘기만’와 달라요. 이 문항의 정답은 ‘괭이갈매기’입니다. 독도에서는 괭이갈매기·바다제비·슴새 같은 바닷새가 번식해요. 번식은 새끼를 낳고 기르는 일이에요. | O66: https://www.heritage.go.kr/heri/cul/culSelectDetail.do?VdkVgwKey=16%2C03360000%2C37&pageNo=1_1_2_0 | P66: =LEN(E66)+MAX(LEN(F66),LEN(G66),LEN(H66)) -> 24 | Q66: 출처 기반 자체 검토 / 독립 승인 전
A67: 910066 | B67: 4 | C67: dk-breeding-birds | D67: 2 | E67: 독도가 새의 번식지라는 뜻은? | F67: 새가 잠깐 지나가기만 하는 곳 | G67: 새 이름을 전시하는 건물 | H67: 새끼를 낳고 기르는 곳 | I67: 3 | J67: 독도에서는 괭이갈매기·바다제비·슴새 같은 바닷새가 번식해요. 번식은 새끼를 낳고 기르는 일이에요. | K67: 고른 보기 ‘새가 잠깐 지나가기만 하는 곳’와 달라요. 이 문항의 정답은 ‘새끼를 낳고 기르는 곳’입니다. 독도에서는 괭이갈매기·바다제비·슴새 같은 바닷새가 번식해요. 번식은 새끼를 낳고 기르는 일이에요. | L67: 고른 보기 ‘새 이름을 전시하는 건물’와 달라요. 이 문항의 정답은 ‘새끼를 낳고 기르는 곳’입니다. 독도에서는 괭이갈매기·바다제비·슴새 같은 바닷새가 번식해요. 번식은 새끼를 낳고 기르는 일이에요. | M67: 독도에서는 괭이갈매기·바다제비·슴새 같은 바닷새가 번식해요. 번식은 새끼를 낳고 기르는 일이에요. | O67: https://www.heritage.go.kr/heri/cul/culSelectDetail.do?VdkVgwKey=16%2C03360000%2C37&pageNo=1_1_2_0 | P67: =LEN(E67)+MAX(LEN(F67),LEN(G67),LEN(H67)) -> 32 | Q67: 출처 기반 자체 검토 / 독립 승인 전
A68: 910067 | B68: 4 | C68: dk-breeding-birds | D68: 3 | E68: 번식지를 판단하는 데 더 직접적인 관찰은? | F68: 빈 바위 사진 한 장 | G68: 둥지와 새끼를 기르는 행동 | H68: 하늘을 한 번 지나간 새 | I68: 2 | J68: 독도에서는 괭이갈매기·바다제비·슴새 같은 바닷새가 번식해요. 번식은 새끼를 낳고 기르는 일이에요. | K68: 고른 보기 ‘빈 바위 사진 한 장’와 달라요. 이 문항의 정답은 ‘둥지와 새끼를 기르는 행동’입니다. 독도에서는 괭이갈매기·바다제비·슴새 같은 바닷새가 번식해요. 번식은 새끼를 낳고 기르는 일이에요. | L68: 독도에서는 괭이갈매기·바다제비·슴새 같은 바닷새가 번식해요. 번식은 새끼를 낳고 기르는 일이에요. | M68: 고른 보기 ‘하늘을 한 번 지나간 새’와 달라요. 이 문항의 정답은 ‘둥지와 새끼를 기르는 행동’입니다. 독도에서는 괭이갈매기·바다제비·슴새 같은 바닷새가 번식해요. 번식은 새끼를 낳고 기르는 일이에요. | N68: 국가유산청 설명은 독도를 바다제비·슴새·괭이갈매기의 번식지로 소개합니다. 번식지라는 말은 새를 한 번 보았다는 말보다 구체적인 생태 정보를 담습니다. | O68: https://www.heritage.go.kr/heri/cul/culSelectDetail.do?VdkVgwKey=16%2C03360000%2C37&pageNo=1_1_2_0 | P68: =LEN(E68)+MAX(LEN(F68),LEN(G68),LEN(H68)) -> 37 | Q68: 출처 기반 자체 검토 / 독립 승인 전
A69: 910068 | B69: 4 | C69: dk-breeding-birds | D69: 4 | E69: 새 한 마리의 통과 사진만으로 번식지라 한다면? | F69: 번식 행동이나 둥지 자료가 더 필요하다 | G69: 날개가 보이면 번식이 확인된다 | H69: 자료에 종 이름이 있으면 항상 번식한다 | I69: 1 | J69: 독도에서는 괭이갈매기·바다제비·슴새 같은 바닷새가 번식해요. 번식은 새끼를 낳고 기르는 일이에요. | K69: 독도에서는 괭이갈매기·바다제비·슴새 같은 바닷새가 번식해요. 번식은 새끼를 낳고 기르는 일이에요. | L69: 고른 보기 ‘날개가 보이면 번식이 확인된다’와 달라요. 이 문항의 정답은 ‘번식 행동이나 둥지 자료가 더 필요하다’입니다. 독도에서는 괭이갈매기·바다제비·슴새 같은 바닷새가 번식해요. 번식은 새끼를 낳고 기르는 일이에요. | M69: 고른 보기 ‘자료에 종 이름이 있으면 항상 번식한다’와 달라요. 이 문항의 정답은 ‘번식 행동이나 둥지 자료가 더 필요하다’입니다. 독도에서는 괭이갈매기·바다제비·슴새 같은 바닷새가 번식해요. 번식은 새끼를 낳고 기르는 일이에요. | N69: 국가유산청 설명은 독도를 바다제비·슴새·괭이갈매기의 번식지로 소개합니다. 번식지라는 말은 새를 한 번 보았다는 말보다 구체적인 생태 정보를 담습니다. | O69: https://www.heritage.go.kr/heri/cul/culSelectDetail.do?VdkVgwKey=16%2C03360000%2C37&pageNo=1_1_2_0 | P69: =LEN(E69)+MAX(LEN(F69),LEN(G69),LEN(H69)) -> 47 | Q69: 출처 기반 자체 검토 / 독립 승인 전
A70: 910069 | B70: 4 | C70: dk-birds-and-seaweed | D70: 1 | E70: 미역과 달리 독도의 바닷새인 것은? | F70: 다시마 | G70: 김 | H70: 괭이갈매기 | I70: 3 | J70: 독도에는 바닷새도, 미역 같은 바닷말도 있어요. 비슷하게 들리는 말이라도 가리키는 생물은 다를 수 있어요. | K70: 고른 보기 ‘다시마’와 달라요. 이 문항의 정답은 ‘괭이갈매기’입니다. 독도에는 바닷새도, 미역 같은 바닷말도 있어요. 비슷하게 들리는 말이라도 가리키는 생물은 다를 수 있어요. | L70: 고른 보기 ‘김’와 달라요. 이 문항의 정답은 ‘괭이갈매기’입니다. 독도에는 바닷새도, 미역 같은 바닷말도 있어요. 비슷하게 들리는 말이라도 가리키는 생물은 다를 수 있어요. | M70: 독도에는 바닷새도, 미역 같은 바닷말도 있어요. 비슷하게 들리는 말이라도 가리키는 생물은 다를 수 있어요. | O70: https://www.heritage.go.kr/heri/cul/culSelectDetail.do?VdkVgwKey=16%2C03360000%2C37&pageNo=1_1_2_0 https://dokdo.mofa.go.kr/kor/introduce/nature.jsp | P70: =LEN(E70)+MAX(LEN(F70),LEN(G70),LEN(H70)) -> 24 | Q70: 출처 기반 자체 검토 / 독립 승인 전
A71: 910070 | B71: 4 | C71: dk-birds-and-seaweed | D71: 2 | E71: 괭이갈매기와 미역을 바르게 나누면? | F71: 둘 다 물고기 | G71: 괭이갈매기=새·미역=바닷말 | H71: 괭이갈매기=바닷말·미역=새 | I71: 2 | J71: 독도에는 바닷새도, 미역 같은 바닷말도 있어요. 비슷하게 들리는 말이라도 가리키는 생물은 다를 수 있어요. | K71: 고른 보기 ‘둘 다 물고기’와 달라요. 이 문항의 정답은 ‘괭이갈매기=새·미역=바닷말’입니다. 독도에는 바닷새도, 미역 같은 바닷말도 있어요. 비슷하게 들리는 말이라도 가리키는 생물은 다를 수 있어요. | L71: 독도에는 바닷새도, 미역 같은 바닷말도 있어요. 비슷하게 들리는 말이라도 가리키는 생물은 다를 수 있어요. | M71: 고른 보기 ‘괭이갈매기=바닷말·미역=새’와 달라요. 이 문항의 정답은 ‘괭이갈매기=새·미역=바닷말’입니다. 독도에는 바닷새도, 미역 같은 바닷말도 있어요. 비슷하게 들리는 말이라도 가리키는 생물은 다를 수 있어요. | O71: https://www.heritage.go.kr/heri/cul/culSelectDetail.do?VdkVgwKey=16%2C03360000%2C37&pageNo=1_1_2_0 https://dokdo.mofa.go.kr/kor/introduce/nature.jsp | P71: =LEN(E71)+MAX(LEN(F71),LEN(G71),LEN(H71)) -> 33 | Q71: 출처 기반 자체 검토 / 독립 승인 전
A72: 910071 | B72: 4 | C72: dk-birds-and-seaweed | D72: 3 | E72: 자료의 海鳥類가 가리키는 것은? | F72: 바닷새 | G72: 바닷말 | H72: 해안의 바위 | I72: 1 | J72: 독도에는 바닷새도, 미역 같은 바닷말도 있어요. 비슷하게 들리는 말이라도 가리키는 생물은 다를 수 있어요. | K72: 독도에는 바닷새도, 미역 같은 바닷말도 있어요. 비슷하게 들리는 말이라도 가리키는 생물은 다를 수 있어요. | L72: 고른 보기 ‘바닷말’와 달라요. 이 문항의 정답은 ‘바닷새’입니다. 독도에는 바닷새도, 미역 같은 바닷말도 있어요. 비슷하게 들리는 말이라도 가리키는 생물은 다를 수 있어요. | M72: 고른 보기 ‘해안의 바위’와 달라요. 이 문항의 정답은 ‘바닷새’입니다. 독도에는 바닷새도, 미역 같은 바닷말도 있어요. 비슷하게 들리는 말이라도 가리키는 생물은 다를 수 있어요. | N72: 국가유산 설명의 해조류(海鳥類)는 바닷새입니다. 바닷말을 뜻하는 해조류(海藻類)와 한자가 다릅니다. 괭이갈매기는 새, 미역은 바닷말입니다. | O72: https://www.heritage.go.kr/heri/cul/culSelectDetail.do?VdkVgwKey=16%2C03360000%2C37&pageNo=1_1_2_0 https://dokdo.mofa.go.kr/kor/introduce/nature.jsp | P72: =LEN(E72)+MAX(LEN(F72),LEN(G72),LEN(H72)) -> 23 | Q72: 출처 기반 자체 검토 / 독립 승인 전
A73: 910072 | B73: 4 | C73: dk-birds-and-seaweed | D73: 4 | E73: ‘해조류 번식지’를 미역 번식지로만 읽으면? | F73: 한글 발음이 같으니 생물도 같다 | G73: 미역도 있으니 원문의 뜻은 중요하지 않다 | H73: 한자와 문맥을 확인해 바닷새인지 구분한다 | I73: 3 | J73: 독도에는 바닷새도, 미역 같은 바닷말도 있어요. 비슷하게 들리는 말이라도 가리키는 생물은 다를 수 있어요. | K73: 고른 보기 ‘한글 발음이 같으니 생물도 같다’와 달라요. 이 문항의 정답은 ‘한자와 문맥을 확인해 바닷새인지 구분한다’입니다. 독도에는 바닷새도, 미역 같은 바닷말도 있어요. 비슷하게 들리는 말이라도 가리키는 생물은 다를 수 있어요. | L73: 고른 보기 ‘미역도 있으니 원문의 뜻은 중요하지 않다’와 달라요. 이 문항의 정답은 ‘한자와 문맥을 확인해 바닷새인지 구분한다’입니다. 독도에는 바닷새도, 미역 같은 바닷말도 있어요. 비슷하게 들리는 말이라도 가리키는 생물은 다를 수 있어요. | M73: 독도에는 바닷새도, 미역 같은 바닷말도 있어요. 비슷하게 들리는 말이라도 가리키는 생물은 다를 수 있어요. | N73: 국가유산 설명의 해조류(海鳥類)는 바닷새입니다. 바닷말을 뜻하는 해조류(海藻類)와 한자가 다릅니다. 괭이갈매기는 새, 미역은 바닷말입니다. | O73: https://www.heritage.go.kr/heri/cul/culSelectDetail.do?VdkVgwKey=16%2C03360000%2C37&pageNo=1_1_2_0 https://dokdo.mofa.go.kr/kor/introduce/nature.jsp | P73: =LEN(E73)+MAX(LEN(F73),LEN(G73),LEN(H73)) -> 46 | Q73: 출처 기반 자체 검토 / 독립 승인 전
A74: 910073 | B74: 4 | C74: dk-coastal-plants | D74: 1 | E74: 독도 땅에서 자라는 식물의 예는? | F74: 다시마 | G74: 해국 | H74: 미역 | I74: 2 | J74: 독도 땅에는 해국·섬기린초·땅채송화 같은 식물이 자라요. 바닷속 생물과 땅 위 식물을 함께 살펴보면 독도의 생명이 더 잘 보여요. | K74: 고른 보기 ‘다시마’와 달라요. 이 문항의 정답은 ‘해국’입니다. 독도 땅에는 해국·섬기린초·땅채송화 같은 식물이 자라요. 바닷속 생물과 땅 위 식물을 함께 살펴보면 독도의 생명이 더 잘 보여요. | L74: 독도 땅에는 해국·섬기린초·땅채송화 같은 식물이 자라요. 바닷속 생물과 땅 위 식물을 함께 살펴보면 독도의 생명이 더 잘 보여요. | M74: 고른 보기 ‘미역’와 달라요. 이 문항의 정답은 ‘해국’입니다. 독도 땅에는 해국·섬기린초·땅채송화 같은 식물이 자라요. 바닷속 생물과 땅 위 식물을 함께 살펴보면 독도의 생명이 더 잘 보여요. | O74: https://dokdo.mofa.go.kr/kor/introduce/nature.jsp | P74: =LEN(E74)+MAX(LEN(F74),LEN(G74),LEN(H74)) -> 21 | Q74: 출처 기반 자체 검토 / 독립 승인 전
A75: 910074 | B75: 4 | C75: dk-coastal-plants | D75: 2 | E75: 해국과 미역을 서식 공간에 맞추면? | F75: 해국은 땅·미역은 바다 | G75: 해국은 바다·미역은 땅 | H75: 둘 다 동도 등대 안에서만 | I75: 1 | J75: 독도 땅에는 해국·섬기린초·땅채송화 같은 식물이 자라요. 바닷속 생물과 땅 위 식물을 함께 살펴보면 독도의 생명이 더 잘 보여요. | K75: 독도 땅에는 해국·섬기린초·땅채송화 같은 식물이 자라요. 바닷속 생물과 땅 위 식물을 함께 살펴보면 독도의 생명이 더 잘 보여요. | L75: 고른 보기 ‘해국은 바다·미역은 땅’와 달라요. 이 문항의 정답은 ‘해국은 땅·미역은 바다’입니다. 독도 땅에는 해국·섬기린초·땅채송화 같은 식물이 자라요. 바닷속 생물과 땅 위 식물을 함께 살펴보면 독도의 생명이 더 잘 보여요. | M75: 고른 보기 ‘둘 다 동도 등대 안에서만’와 달라요. 이 문항의 정답은 ‘해국은 땅·미역은 바다’입니다. 독도 땅에는 해국·섬기린초·땅채송화 같은 식물이 자라요. 바닷속 생물과 땅 위 식물을 함께 살펴보면 독도의 생명이 더 잘 보여요. | O75: https://dokdo.mofa.go.kr/kor/introduce/nature.jsp | P75: =LEN(E75)+MAX(LEN(F75),LEN(G75),LEN(H75)) -> 33 | Q75: 출처 기반 자체 검토 / 독립 승인 전
A76: 910075 | B76: 4 | C76: dk-coastal-plants | D76: 3 | E76: 자료의 두 목록을 연결한 바른 설명은? | F76: 독도 식물은 모두 미역 종류다 | G76: 독도에는 땅 위 식물이 없다 | H76: 독도에는 육상 식물과 해조류가 있다 | I76: 3 | J76: 독도 땅에는 해국·섬기린초·땅채송화 같은 식물이 자라요. 바닷속 생물과 땅 위 식물을 함께 살펴보면 독도의 생명이 더 잘 보여요. | K76: 고른 보기 ‘독도 식물은 모두 미역 종류다’와 달라요. 이 문항의 정답은 ‘독도에는 육상 식물과 해조류가 있다’입니다. 독도 땅에는 해국·섬기린초·땅채송화 같은 식물이 자라요. 바닷속 생물과 땅 위 식물을 함께 살펴보면 독도의 생명이 더 잘 보여요. | L76: 고른 보기 ‘독도에는 땅 위 식물이 없다’와 달라요. 이 문항의 정답은 ‘독도에는 육상 식물과 해조류가 있다’입니다. 독도 땅에는 해국·섬기린초·땅채송화 같은 식물이 자라요. 바닷속 생물과 땅 위 식물을 함께 살펴보면 독도의 생명이 더 잘 보여요. | M76: 독도 땅에는 해국·섬기린초·땅채송화 같은 식물이 자라요. 바닷속 생물과 땅 위 식물을 함께 살펴보면 독도의 생명이 더 잘 보여요. | N76: 외교부 식물 목록에는 해국·섬기린초·땅채송화가, 해양생물 목록에는 미역·다시마·김이 소개됩니다. 목록에 없다는 이유만으로 부재를 단정하지 않습니다. | O76: https://dokdo.mofa.go.kr/kor/introduce/nature.jsp | P76: =LEN(E76)+MAX(LEN(F76),LEN(G76),LEN(H76)) -> 40 | Q76: 출처 기반 자체 검토 / 독립 승인 전
A77: 910076 | B77: 4 | C77: dk-coastal-plants | D77: 4 | E77: 짧은 목록에 없는 식물은 독도에 없다고 해도 될까요? | F77: 사진에 꽃이 있으면 모든 종이 있다는 뜻이다 | G77: 전체 조사 목록과 조사 시기를 더 확인한다 | H77: 소개된 몇 종이 전부라는 뜻이다 | I77: 2 | J77: 독도 땅에는 해국·섬기린초·땅채송화 같은 식물이 자라요. 바닷속 생물과 땅 위 식물을 함께 살펴보면 독도의 생명이 더 잘 보여요. | K77: 고른 보기 ‘사진에 꽃이 있으면 모든 종이 있다는 뜻이다’와 달라요. 이 문항의 정답은 ‘전체 조사 목록과 조사 시기를 더 확인한다’입니다. 독도 땅에는 해국·섬기린초·땅채송화 같은 식물이 자라요. 바닷속 생물과 땅 위 식물을 함께 살펴보면 독도의 생명이 더 잘 보여요. | L77: 독도 땅에는 해국·섬기린초·땅채송화 같은 식물이 자라요. 바닷속 생물과 땅 위 식물을 함께 살펴보면 독도의 생명이 더 잘 보여요. | M77: 고른 보기 ‘소개된 몇 종이 전부라는 뜻이다’와 달라요. 이 문항의 정답은 ‘전체 조사 목록과 조사 시기를 더 확인한다’입니다. 독도 땅에는 해국·섬기린초·땅채송화 같은 식물이 자라요. 바닷속 생물과 땅 위 식물을 함께 살펴보면 독도의 생명이 더 잘 보여요. | N77: 외교부 식물 목록에는 해국·섬기린초·땅채송화가, 해양생물 목록에는 미역·다시마·김이 소개됩니다. 목록에 없다는 이유만으로 부재를 단정하지 않습니다. | O77: https://dokdo.mofa.go.kr/kor/introduce/nature.jsp | P77: =LEN(E77)+MAX(LEN(F77),LEN(G77),LEN(H77)) -> 53 | Q77: 출처 기반 자체 검토 / 독립 승인 전
A78: 910077 | B78: 4 | C78: dk-reserve-scope | D78: 1 | E78: 독도에서 보호할 대상으로 알맞은 것은? | F78: 새·식물·바위 지형 | G78: 등대 색깔만 | H78: 배 이름만 | I78: 1 | J78: 독도를 보호하는 이유에는 바닷새뿐 아니라 식물·바다 생물·화산 지형의 가치도 있어요. | K78: 독도를 보호하는 이유에는 바닷새뿐 아니라 식물·바다 생물·화산 지형의 가치도 있어요. | L78: 고른 보기 ‘등대 색깔만’와 달라요. 이 문항의 정답은 ‘새·식물·바위 지형’입니다. 독도를 보호하는 이유에는 바닷새뿐 아니라 식물·바다 생물·화산 지형의 가치도 있어요. | M78: 고른 보기 ‘배 이름만’와 달라요. 이 문항의 정답은 ‘새·식물·바위 지형’입니다. 독도를 보호하는 이유에는 바닷새뿐 아니라 식물·바다 생물·화산 지형의 가치도 있어요. | O78: https://www.heritage.go.kr/heri/cul/culSelectDetail.do?VdkVgwKey=16%2C03360000%2C37&pageNo=1_1_2_0 | P78: =LEN(E78)+MAX(LEN(F78),LEN(G78),LEN(H78)) -> 31 | Q78: 출처 기반 자체 검토 / 독립 승인 전
A79: 910078 | B79: 4 | C79: dk-reserve-scope | D79: 2 | E79: 독도 보호를 바닷새만으로 설명하면? | F79: 바다에는 생물이 없게 돼요 | G79: 두 섬의 이름이 같아져요 | H79: 식물과 지질의 가치도 빠져요 | I79: 3 | J79: 독도를 보호하는 이유에는 바닷새뿐 아니라 식물·바다 생물·화산 지형의 가치도 있어요. | K79: 고른 보기 ‘바다에는 생물이 없게 돼요’와 달라요. 이 문항의 정답은 ‘식물과 지질의 가치도 빠져요’입니다. 독도를 보호하는 이유에는 바닷새뿐 아니라 식물·바다 생물·화산 지형의 가치도 있어요. | L79: 고른 보기 ‘두 섬의 이름이 같아져요’와 달라요. 이 문항의 정답은 ‘식물과 지질의 가치도 빠져요’입니다. 독도를 보호하는 이유에는 바닷새뿐 아니라 식물·바다 생물·화산 지형의 가치도 있어요. | M79: 독도를 보호하는 이유에는 바닷새뿐 아니라 식물·바다 생물·화산 지형의 가치도 있어요. | O79: https://www.heritage.go.kr/heri/cul/culSelectDetail.do?VdkVgwKey=16%2C03360000%2C37&pageNo=1_1_2_0 | P79: =LEN(E79)+MAX(LEN(F79),LEN(G79),LEN(H79)) -> 34 | Q79: 출처 기반 자체 검토 / 독립 승인 전
A80: 910079 | B80: 4 | C80: dk-reserve-scope | D80: 3 | E80: 천연보호구역의 설명을 가장 잘 묶은 것은? | F80: 하루에 보인 새의 수만 | G80: 번식지·식생·해양생물·화산 지형 | H80: 항구의 크기와 입장료 | I80: 2 | J80: 독도를 보호하는 이유에는 바닷새뿐 아니라 식물·바다 생물·화산 지형의 가치도 있어요. | K80: 고른 보기 ‘하루에 보인 새의 수만’와 달라요. 이 문항의 정답은 ‘번식지·식생·해양생물·화산 지형’입니다. 독도를 보호하는 이유에는 바닷새뿐 아니라 식물·바다 생물·화산 지형의 가치도 있어요. | L80: 독도를 보호하는 이유에는 바닷새뿐 아니라 식물·바다 생물·화산 지형의 가치도 있어요. | M80: 고른 보기 ‘항구의 크기와 입장료’와 달라요. 이 문항의 정답은 ‘번식지·식생·해양생물·화산 지형’입니다. 독도를 보호하는 이유에는 바닷새뿐 아니라 식물·바다 생물·화산 지형의 가치도 있어요. | N80: 국가유산 설명은 바닷새 번식지의 가치와 함께 화산섬의 지질, 독특한 식물, 주변 해양생물을 들어 독도 천연보호구역의 의미를 설명합니다. | O80: https://www.heritage.go.kr/heri/cul/culSelectDetail.do?VdkVgwKey=16%2C03360000%2C37&pageNo=1_1_2_0 | P80: =LEN(E80)+MAX(LEN(F80),LEN(G80),LEN(H80)) -> 40 | Q80: 출처 기반 자체 검토 / 독립 승인 전
A81: 910080 | B81: 4 | C81: dk-reserve-scope | D81: 4 | E81: 독도의 보호 가치를 방문객 수만으로 평가한다면? | F81: 자료에 제시된 생태·지질 가치를 반영하지 못한다 | G81: 방문객이 적으면 지질 가치도 반드시 없다 | H81: 방문객 수가 곧 번식하는 새의 수다 | I81: 1 | J81: 독도를 보호하는 이유에는 바닷새뿐 아니라 식물·바다 생물·화산 지형의 가치도 있어요. | K81: 독도를 보호하는 이유에는 바닷새뿐 아니라 식물·바다 생물·화산 지형의 가치도 있어요. | L81: 고른 보기 ‘방문객이 적으면 지질 가치도 반드시 없다’와 달라요. 이 문항의 정답은 ‘자료에 제시된 생태·지질 가치를 반영하지 못한다’입니다. 독도를 보호하는 이유에는 바닷새뿐 아니라 식물·바다 생물·화산 지형의 가치도 있어요. | M81: 고른 보기 ‘방문객 수가 곧 번식하는 새의 수다’와 달라요. 이 문항의 정답은 ‘자료에 제시된 생태·지질 가치를 반영하지 못한다’입니다. 독도를 보호하는 이유에는 바닷새뿐 아니라 식물·바다 생물·화산 지형의 가치도 있어요. | N81: 국가유산 설명은 바닷새 번식지의 가치와 함께 화산섬의 지질, 독특한 식물, 주변 해양생물을 들어 독도 천연보호구역의 의미를 설명합니다. | O81: https://www.heritage.go.kr/heri/cul/culSelectDetail.do?VdkVgwKey=16%2C03360000%2C37&pageNo=1_1_2_0 | P81: =LEN(E81)+MAX(LEN(F81),LEN(G81),LEN(H81)) -> 52 | Q81: 출처 기반 자체 검토 / 독립 승인 전
A82: 910081 | B82: 5 | C82: dk-sea-forest | D82: 1 | E82: 독도 바다숲을 이루는 생물의 예는? | F82: 해국과 땅채송화 | G82: 괭이갈매기와 슴새 | H82: 감태와 대황 | I82: 3 | J82: 독도 바닷속에는 감태와 대황 같은 해조류가 자라 바다숲을 이루어요. 바위틈에도 여러 생물이 살아요. | K82: 고른 보기 ‘해국과 땅채송화’와 달라요. 이 문항의 정답은 ‘감태와 대황’입니다. 독도 바닷속에는 감태와 대황 같은 해조류가 자라 바다숲을 이루어요. 바위틈에도 여러 생물이 살아요. | L82: 고른 보기 ‘괭이갈매기와 슴새’와 달라요. 이 문항의 정답은 ‘감태와 대황’입니다. 독도 바닷속에는 감태와 대황 같은 해조류가 자라 바다숲을 이루어요. 바위틈에도 여러 생물이 살아요. | M82: 독도 바닷속에는 감태와 대황 같은 해조류가 자라 바다숲을 이루어요. 바위틈에도 여러 생물이 살아요. | O82: https://www.dokdo.re.kr/home/cms/cmsCont.do?cntnts_sn=87 | P82: =LEN(E82)+MAX(LEN(F82),LEN(G82),LEN(H82)) -> 28 | Q82: 출처 기반 자체 검토 / 독립 승인 전
A83: 910082 | B83: 5 | C83: dk-sea-forest | D83: 2 | E83: 독도 바위틈과 연결되는 생물은? | F83: 육상 나무만 | G83: 따개비와 홍합 | H83: 등대 주변 사람만 | I83: 2 | J83: 독도 바닷속에는 감태와 대황 같은 해조류가 자라 바다숲을 이루어요. 바위틈에도 여러 생물이 살아요. | K83: 고른 보기 ‘육상 나무만’와 달라요. 이 문항의 정답은 ‘따개비와 홍합’입니다. 독도 바닷속에는 감태와 대황 같은 해조류가 자라 바다숲을 이루어요. 바위틈에도 여러 생물이 살아요. | L83: 독도 바닷속에는 감태와 대황 같은 해조류가 자라 바다숲을 이루어요. 바위틈에도 여러 생물이 살아요. | M83: 고른 보기 ‘등대 주변 사람만’와 달라요. 이 문항의 정답은 ‘따개비와 홍합’입니다. 독도 바닷속에는 감태와 대황 같은 해조류가 자라 바다숲을 이루어요. 바위틈에도 여러 생물이 살아요. | O83: https://www.dokdo.re.kr/home/cms/cmsCont.do?cntnts_sn=87 | P83: =LEN(E83)+MAX(LEN(F83),LEN(G83),LEN(H83)) -> 26 | Q83: 출처 기반 자체 검토 / 독립 승인 전
A84: 910083 | B84: 5 | C84: dk-sea-forest | D84: 3 | E84: 자료가 독도의 바다숲과 함께 소개한 공간은? | F84: 여러 생물이 사는 바위틈 | G84: 생물이 전혀 없는 모든 해저 | H84: 울릉도의 논과 밭 | I84: 1 | J84: 독도 바닷속에는 감태와 대황 같은 해조류가 자라 바다숲을 이루어요. 바위틈에도 여러 생물이 살아요. | K84: 독도 바닷속에는 감태와 대황 같은 해조류가 자라 바다숲을 이루어요. 바위틈에도 여러 생물이 살아요. | L84: 고른 보기 ‘생물이 전혀 없는 모든 해저’와 달라요. 이 문항의 정답은 ‘여러 생물이 사는 바위틈’입니다. 독도 바닷속에는 감태와 대황 같은 해조류가 자라 바다숲을 이루어요. 바위틈에도 여러 생물이 살아요. | M84: 고른 보기 ‘울릉도의 논과 밭’와 달라요. 이 문항의 정답은 ‘여러 생물이 사는 바위틈’입니다. 독도 바닷속에는 감태와 대황 같은 해조류가 자라 바다숲을 이루어요. 바위틈에도 여러 생물이 살아요. | N84: 한국해양과학기술원은 독도 암반생태계의 감태·대황 해조숲과 바위틈의 따개비·홍합·게·고둥 등을 소개합니다. | O84: https://www.dokdo.re.kr/home/cms/cmsCont.do?cntnts_sn=87 | P84: =LEN(E84)+MAX(LEN(F84),LEN(G84),LEN(H84)) -> 39 | Q84: 출처 기반 자체 검토 / 독립 승인 전
A85: 910084 | B85: 5 | C85: dk-sea-forest | D85: 4 | E85: 독도 바다숲을 미역 한 종류로만 설명하면? | F85: 미역이라는 이름 자체의 의미 | G85: 두 섬의 최고 높이만 | H85: 자료에 제시된 해조류와 서식 공간의 다양성 | I85: 3 | J85: 독도 바닷속에는 감태와 대황 같은 해조류가 자라 바다숲을 이루어요. 바위틈에도 여러 생물이 살아요. | K85: 고른 보기 ‘미역이라는 이름 자체의 의미’와 달라요. 이 문항의 정답은 ‘자료에 제시된 해조류와 서식 공간의 다양성’입니다. 독도 바닷속에는 감태와 대황 같은 해조류가 자라 바다숲을 이루어요. 바위틈에도 여러 생물이 살아요. | L85: 고른 보기 ‘두 섬의 최고 높이만’와 달라요. 이 문항의 정답은 ‘자료에 제시된 해조류와 서식 공간의 다양성’입니다. 독도 바닷속에는 감태와 대황 같은 해조류가 자라 바다숲을 이루어요. 바위틈에도 여러 생물이 살아요. | M85: 독도 바닷속에는 감태와 대황 같은 해조류가 자라 바다숲을 이루어요. 바위틈에도 여러 생물이 살아요. | N85: 한국해양과학기술원은 독도 암반생태계의 감태·대황 해조숲과 바위틈의 따개비·홍합·게·고둥 등을 소개합니다. | O85: https://www.dokdo.re.kr/home/cms/cmsCont.do?cntnts_sn=87 | P85: =LEN(E85)+MAX(LEN(F85),LEN(G85),LEN(H85)) -> 46 | Q85: 출처 기반 자체 검토 / 독립 승인 전
A86: 910085 | B86: 5 | C86: dk-water-mixing | D86: 1 | E86: 독도 주변에서 함께 만나는 흐름은? | F86: 모래로 된 길 두 개 | G86: 따뜻한 흐름과 찬 흐름 | H86: 민물 강 두 개만 | I86: 2 | J86: 독도 주변에서는 따뜻한 흐름과 찬 흐름이 만나고 물이 섞여요. 물의 움직임은 생물이 쓰는 영양분의 이동에도 영향을 줘요. | K86: 고른 보기 ‘모래로 된 길 두 개’와 달라요. 이 문항의 정답은 ‘따뜻한 흐름과 찬 흐름’입니다. 독도 주변에서는 따뜻한 흐름과 찬 흐름이 만나고 물이 섞여요. 물의 움직임은 생물이 쓰는 영양분의 이동에도 영향을 줘요. | L86: 독도 주변에서는 따뜻한 흐름과 찬 흐름이 만나고 물이 섞여요. 물의 움직임은 생물이 쓰는 영양분의 이동에도 영향을 줘요. | M86: 고른 보기 ‘민물 강 두 개만’와 달라요. 이 문항의 정답은 ‘따뜻한 흐름과 찬 흐름’입니다. 독도 주변에서는 따뜻한 흐름과 찬 흐름이 만나고 물이 섞여요. 물의 움직임은 생물이 쓰는 영양분의 이동에도 영향을 줘요. | O86: https://www.dokdo.re.kr/home/cms/cmsCont.do?cntnts_sn=82 | P86: =LEN(E86)+MAX(LEN(F86),LEN(G86),LEN(H86)) -> 31 | Q86: 출처 기반 자체 검토 / 독립 승인 전
A87: 910086 | B87: 5 | C87: dk-water-mixing | D87: 2 | E87: 바닷물이 위아래로 섞이면 옮겨질 수 있는 것은? | F87: 아래쪽의 영양염 | G87: 섬의 이름 | H87: 등대의 주소 | I87: 1 | J87: 독도 주변에서는 따뜻한 흐름과 찬 흐름이 만나고 물이 섞여요. 물의 움직임은 생물이 쓰는 영양분의 이동에도 영향을 줘요. | K87: 독도 주변에서는 따뜻한 흐름과 찬 흐름이 만나고 물이 섞여요. 물의 움직임은 생물이 쓰는 영양분의 이동에도 영향을 줘요. | L87: 고른 보기 ‘섬의 이름’와 달라요. 이 문항의 정답은 ‘아래쪽의 영양염’입니다. 독도 주변에서는 따뜻한 흐름과 찬 흐름이 만나고 물이 섞여요. 물의 움직임은 생물이 쓰는 영양분의 이동에도 영향을 줘요. | M87: 고른 보기 ‘등대의 주소’와 달라요. 이 문항의 정답은 ‘아래쪽의 영양염’입니다. 독도 주변에서는 따뜻한 흐름과 찬 흐름이 만나고 물이 섞여요. 물의 움직임은 생물이 쓰는 영양분의 이동에도 영향을 줘요. | O87: https://www.dokdo.re.kr/home/cms/cmsCont.do?cntnts_sn=82 | P87: =LEN(E87)+MAX(LEN(F87),LEN(G87),LEN(H87)) -> 34 | Q87: 출처 기반 자체 검토 / 독립 승인 전
A88: 910087 | B88: 5 | C88: dk-water-mixing | D88: 3 | E88: 자료의 섬효과 과정과 맞는 연결은? | F88: 등대 점등→해조류 이름 변화 | G88: 표층 물 정지→모든 생물 증가 | H88: 수층 혼합→상층 영양염 공급 | I88: 3 | J88: 독도 주변에서는 따뜻한 흐름과 찬 흐름이 만나고 물이 섞여요. 물의 움직임은 생물이 쓰는 영양분의 이동에도 영향을 줘요. | K88: 고른 보기 ‘등대 점등→해조류 이름 변화’와 달라요. 이 문항의 정답은 ‘수층 혼합→상층 영양염 공급’입니다. 독도 주변에서는 따뜻한 흐름과 찬 흐름이 만나고 물이 섞여요. 물의 움직임은 생물이 쓰는 영양분의 이동에도 영향을 줘요. | L88: 고른 보기 ‘표층 물 정지→모든 생물 증가’와 달라요. 이 문항의 정답은 ‘수층 혼합→상층 영양염 공급’입니다. 독도 주변에서는 따뜻한 흐름과 찬 흐름이 만나고 물이 섞여요. 물의 움직임은 생물이 쓰는 영양분의 이동에도 영향을 줘요. | M88: 독도 주변에서는 따뜻한 흐름과 찬 흐름이 만나고 물이 섞여요. 물의 움직임은 생물이 쓰는 영양분의 이동에도 영향을 줘요. | N88: 섬효과 설명: 바람과 섬 지형은 수층 혼합에 영향을 줍니다. 이 과정에서 아래쪽 영양염이 빛이 드는 상층으로 공급될 수 있습니다. | O88: https://www.dokdo.re.kr/home/cms/cmsCont.do?cntnts_sn=82 | P88: =LEN(E88)+MAX(LEN(F88),LEN(G88),LEN(H88)) -> 35 | Q88: 출처 기반 자체 검토 / 독립 승인 전
A89: 910088 | B89: 5 | C89: dk-water-mixing | D89: 4 | E89: 섬효과가 있으니 독도 바다는 항상 같다고 하면? | F89: 영양염은 물의 움직임과 전혀 무관하다 | G89: 계절·바람·해류에 따른 변화도 살펴야 한다 | H89: 섬 주변이면 모든 날에 같은 혼합이 생긴다 | I89: 2 | J89: 독도 주변에서는 따뜻한 흐름과 찬 흐름이 만나고 물이 섞여요. 물의 움직임은 생물이 쓰는 영양분의 이동에도 영향을 줘요. | K89: 고른 보기 ‘영양염은 물의 움직임과 전혀 무관하다’와 달라요. 이 문항의 정답은 ‘계절·바람·해류에 따른 변화도 살펴야 한다’입니다. 독도 주변에서는 따뜻한 흐름과 찬 흐름이 만나고 물이 섞여요. 물의 움직임은 생물이 쓰는 영양분의 이동에도 영향을 줘요. | L89: 독도 주변에서는 따뜻한 흐름과 찬 흐름이 만나고 물이 섞여요. 물의 움직임은 생물이 쓰는 영양분의 이동에도 영향을 줘요. | M89: 고른 보기 ‘섬 주변이면 모든 날에 같은 혼합이 생긴다’와 달라요. 이 문항의 정답은 ‘계절·바람·해류에 따른 변화도 살펴야 한다’입니다. 독도 주변에서는 따뜻한 흐름과 찬 흐름이 만나고 물이 섞여요. 물의 움직임은 생물이 쓰는 영양분의 이동에도 영향을 줘요. | N89: 섬효과 설명: 바람과 섬 지형은 수층 혼합에 영향을 줍니다. 이 과정에서 아래쪽 영양염이 빛이 드는 상층으로 공급될 수 있습니다. | O89: https://www.dokdo.re.kr/home/cms/cmsCont.do?cntnts_sn=82 | P89: =LEN(E89)+MAX(LEN(F89),LEN(G89),LEN(H89)) -> 49 | Q89: 출처 기반 자체 검토 / 독립 승인 전
A90: 910089 | B90: 5 | C90: dk-food-links | D90: 1 | E90: 독도 바다 먹이 관계의 작은 바탕 생물은? | F90: 식물플랑크톤 | G90: 서도의 바위 자체 | H90: 등대의 전등 | I90: 1 | J90: 작은 식물플랑크톤은 독도 바다 먹이 관계의 바탕이 되어요. 이를 먹는 동물플랑크톤과 어린 물고기로 연결될 수 있어요. | K90: 작은 식물플랑크톤은 독도 바다 먹이 관계의 바탕이 되어요. 이를 먹는 동물플랑크톤과 어린 물고기로 연결될 수 있어요. | L90: 고른 보기 ‘서도의 바위 자체’와 달라요. 이 문항의 정답은 ‘식물플랑크톤’입니다. 작은 식물플랑크톤은 독도 바다 먹이 관계의 바탕이 되어요. 이를 먹는 동물플랑크톤과 어린 물고기로 연결될 수 있어요. | M90: 고른 보기 ‘등대의 전등’와 달라요. 이 문항의 정답은 ‘식물플랑크톤’입니다. 작은 식물플랑크톤은 독도 바다 먹이 관계의 바탕이 되어요. 이를 먹는 동물플랑크톤과 어린 물고기로 연결될 수 있어요. | O90: https://www.dokdo.re.kr/home/cms/cmsCont.do?cntnts_sn=82 | P90: =LEN(E90)+MAX(LEN(F90),LEN(G90),LEN(H90)) -> 32 | Q90: 출처 기반 자체 검토 / 독립 승인 전
A91: 910090 | B91: 5 | C91: dk-food-links | D91: 2 | E91: 식물플랑크톤 증가와 연결될 수 있는 것은? | F91: 독도 면적이 두 배로 증가 | G91: 서도와 동도가 한 이름이 됨 | H91: 이를 먹는 생물의 먹이 증가 | I91: 3 | J91: 작은 식물플랑크톤은 독도 바다 먹이 관계의 바탕이 되어요. 이를 먹는 동물플랑크톤과 어린 물고기로 연결될 수 있어요. | K91: 고른 보기 ‘독도 면적이 두 배로 증가’와 달라요. 이 문항의 정답은 ‘이를 먹는 생물의 먹이 증가’입니다. 작은 식물플랑크톤은 독도 바다 먹이 관계의 바탕이 되어요. 이를 먹는 동물플랑크톤과 어린 물고기로 연결될 수 있어요. | L91: 고른 보기 ‘서도와 동도가 한 이름이 됨’와 달라요. 이 문항의 정답은 ‘이를 먹는 생물의 먹이 증가’입니다. 작은 식물플랑크톤은 독도 바다 먹이 관계의 바탕이 되어요. 이를 먹는 동물플랑크톤과 어린 물고기로 연결될 수 있어요. | M91: 작은 식물플랑크톤은 독도 바다 먹이 관계의 바탕이 되어요. 이를 먹는 동물플랑크톤과 어린 물고기로 연결될 수 있어요. | O91: https://www.dokdo.re.kr/home/cms/cmsCont.do?cntnts_sn=82 | P91: =LEN(E91)+MAX(LEN(F91),LEN(G91),LEN(H91)) -> 38 | Q91: 출처 기반 자체 검토 / 독립 승인 전
A92: 910091 | B92: 5 | C92: dk-food-links | D92: 3 | E92: 자료의 순서에서 식물플랑크톤 다음 연결은? | F92: 울도군의 행정구역 | G92: 동물플랑크톤의 먹이 | H92: 독도등대의 전력 | I92: 2 | J92: 작은 식물플랑크톤은 독도 바다 먹이 관계의 바탕이 되어요. 이를 먹는 동물플랑크톤과 어린 물고기로 연결될 수 있어요. | K92: 고른 보기 ‘울도군의 행정구역’와 달라요. 이 문항의 정답은 ‘동물플랑크톤의 먹이’입니다. 작은 식물플랑크톤은 독도 바다 먹이 관계의 바탕이 되어요. 이를 먹는 동물플랑크톤과 어린 물고기로 연결될 수 있어요. | L92: 작은 식물플랑크톤은 독도 바다 먹이 관계의 바탕이 되어요. 이를 먹는 동물플랑크톤과 어린 물고기로 연결될 수 있어요. | M92: 고른 보기 ‘독도등대의 전력’와 달라요. 이 문항의 정답은 ‘동물플랑크톤의 먹이’입니다. 작은 식물플랑크톤은 독도 바다 먹이 관계의 바탕이 되어요. 이를 먹는 동물플랑크톤과 어린 물고기로 연결될 수 있어요. | N92: 연구 설명의 연결: 영양염 공급→식물플랑크톤 성장→동물플랑크톤의 먹이→어린 물고기의 먹이. 성육장 기능에 기여할 것으로 기대된다고 설명합니다. | O92: https://www.dokdo.re.kr/home/cms/cmsCont.do?cntnts_sn=82 | P92: =LEN(E92)+MAX(LEN(F92),LEN(G92),LEN(H92)) -> 33 | Q92: 출처 기반 자체 검토 / 독립 승인 전
A93: 910092 | B93: 5 | C93: dk-food-links | D93: 4 | E93: ‘성육장에 기여할 것으로 기대’의 바른 요약은? | F93: 기여 가능성으로 설명하며 조건을 남긴다 | G93: 모든 물고기 수가 이미 두 배가 됐다고 한다 | H93: 가능성이라는 이유로 관찰 자료도 전부 버린다 | I93: 1 | J93: 작은 식물플랑크톤은 독도 바다 먹이 관계의 바탕이 되어요. 이를 먹는 동물플랑크톤과 어린 물고기로 연결될 수 있어요. | K93: 작은 식물플랑크톤은 독도 바다 먹이 관계의 바탕이 되어요. 이를 먹는 동물플랑크톤과 어린 물고기로 연결될 수 있어요. | L93: 고른 보기 ‘모든 물고기 수가 이미 두 배가 됐다고 한다’와 달라요. 이 문항의 정답은 ‘기여 가능성으로 설명하며 조건을 남긴다’입니다. 작은 식물플랑크톤은 독도 바다 먹이 관계의 바탕이 되어요. 이를 먹는 동물플랑크톤과 어린 물고기로 연결될 수 있어요. | M93: 고른 보기 ‘가능성이라는 이유로 관찰 자료도 전부 버린다’와 달라요. 이 문항의 정답은 ‘기여 가능성으로 설명하며 조건을 남긴다’입니다. 작은 식물플랑크톤은 독도 바다 먹이 관계의 바탕이 되어요. 이를 먹는 동물플랑크톤과 어린 물고기로 연결될 수 있어요. | N93: 연구 설명의 연결: 영양염 공급→식물플랑크톤 성장→동물플랑크톤의 먹이→어린 물고기의 먹이. 성육장 기능에 기여할 것으로 기대된다고 설명합니다. | O93: https://www.dokdo.re.kr/home/cms/cmsCont.do?cntnts_sn=82 | P93: =LEN(E93)+MAX(LEN(F93),LEN(G93),LEN(H93)) -> 50 | Q93: 출처 기반 자체 검토 / 독립 승인 전
A94: 910093 | B94: 5 | C94: dk-gangchi-history | D94: 1 | E94: 옛 독도 바다에 살았던 동물은? | F94: 민물 돌고래 | G94: 사막여우 | H94: 강치 | I94: 3 | J94: 독도에는 강치가 살았어요. 연구는 지나치게 많이 잡은 일이 강치 감소와 멸종에 큰 영향을 주었음을 설명해요. | K94: 고른 보기 ‘민물 돌고래’와 달라요. 이 문항의 정답은 ‘강치’입니다. 독도에는 강치가 살았어요. 연구는 지나치게 많이 잡은 일이 강치 감소와 멸종에 큰 영향을 주었음을 설명해요. | L94: 고른 보기 ‘사막여우’와 달라요. 이 문항의 정답은 ‘강치’입니다. 독도에는 강치가 살았어요. 연구는 지나치게 많이 잡은 일이 강치 감소와 멸종에 큰 영향을 주었음을 설명해요. | M94: 독도에는 강치가 살았어요. 연구는 지나치게 많이 잡은 일이 강치 감소와 멸종에 큰 영향을 주었음을 설명해요. | O94: https://www.mof.go.kr/doc/ko/selectDoc.do?bbsSeq=10&docSeq=45126&menuSeq=971 https://www.mdpi.com/2077-1312/10/2/271 | P94: =LEN(E94)+MAX(LEN(F94),LEN(G94),LEN(H94)) -> 23 | Q94: 출처 기반 자체 검토 / 독립 승인 전
A95: 910094 | B95: 5 | C95: dk-gangchi-history | D95: 2 | E95: 연구가 강치 감소와 연결한 사람의 행동은? | F95: 옛 문서 정리 | G95: 지나친 포획 | H95: 섬 높이 측량 | I95: 2 | J95: 독도에는 강치가 살았어요. 연구는 지나치게 많이 잡은 일이 강치 감소와 멸종에 큰 영향을 주었음을 설명해요. | K95: 고른 보기 ‘옛 문서 정리’와 달라요. 이 문항의 정답은 ‘지나친 포획’입니다. 독도에는 강치가 살았어요. 연구는 지나치게 많이 잡은 일이 강치 감소와 멸종에 큰 영향을 주었음을 설명해요. | L95: 독도에는 강치가 살았어요. 연구는 지나치게 많이 잡은 일이 강치 감소와 멸종에 큰 영향을 주었음을 설명해요. | M95: 고른 보기 ‘섬 높이 측량’와 달라요. 이 문항의 정답은 ‘지나친 포획’입니다. 독도에는 강치가 살았어요. 연구는 지나치게 많이 잡은 일이 강치 감소와 멸종에 큰 영향을 주었음을 설명해요. | O95: https://www.mof.go.kr/doc/ko/selectDoc.do?bbsSeq=10&docSeq=45126&menuSeq=971 https://www.mdpi.com/2077-1312/10/2/271 | P95: =LEN(E95)+MAX(LEN(F95),LEN(G95),LEN(H95)) -> 30 | Q95: 출처 기반 자체 검토 / 독립 승인 전
A96: 910095 | B96: 5 | C96: dk-gangchi-history | D96: 3 | E96: 자료가 강치의 과거 개체 수를 살핀 방법은? | F96: 포획 기록과 개체군 모델 | G96: 현재 모든 강치를 직접 세기 | H96: 앱에 그린 동물 수 세기 | I96: 1 | J96: 독도에는 강치가 살았어요. 연구는 지나치게 많이 잡은 일이 강치 감소와 멸종에 큰 영향을 주었음을 설명해요. | K96: 독도에는 강치가 살았어요. 연구는 지나치게 많이 잡은 일이 강치 감소와 멸종에 큰 영향을 주었음을 설명해요. | L96: 고른 보기 ‘현재 모든 강치를 직접 세기’와 달라요. 이 문항의 정답은 ‘포획 기록과 개체군 모델’입니다. 독도에는 강치가 살았어요. 연구는 지나치게 많이 잡은 일이 강치 감소와 멸종에 큰 영향을 주었음을 설명해요. | M96: 고른 보기 ‘앱에 그린 동물 수 세기’와 달라요. 이 문항의 정답은 ‘포획 기록과 개체군 모델’입니다. 독도에는 강치가 살았어요. 연구는 지나치게 많이 잡은 일이 강치 감소와 멸종에 큰 영향을 주었음을 설명해요. | N96: 2022년 연구는 과거 포획 기록과 개체군 모델을 이용해 남획의 영향을 살폈습니다. 이 문항은 현재 동물 수를 외우는 문제가 아니라 독도 강치의 역사를 이해하는 문제입니다. | O96: https://www.mof.go.kr/doc/ko/selectDoc.do?bbsSeq=10&docSeq=45126&menuSeq=971 https://www.mdpi.com/2077-1312/10/2/271 | P96: =LEN(E96)+MAX(LEN(F96),LEN(G96),LEN(H96)) -> 39 | Q96: 출처 기반 자체 검토 / 독립 승인 전
A97: 910096 | B97: 5 | C97: dk-gangchi-history | D97: 4 | E97: 연구를 ‘남획 외 요인은 전부 불가능’이라 요약하면? | F97: 남획 연구이므로 모든 요인을 이미 검증했다 | G97: 과거 연구에는 어떤 결론도 있을 수 없다 | H97: 모델의 가정과 검토하지 않은 요인을 넘어선다 | I97: 3 | J97: 독도에는 강치가 살았어요. 연구는 지나치게 많이 잡은 일이 강치 감소와 멸종에 큰 영향을 주었음을 설명해요. | K97: 고른 보기 ‘남획 연구이므로 모든 요인을 이미 검증했다’와 달라요. 이 문항의 정답은 ‘모델의 가정과 검토하지 않은 요인을 넘어선다’입니다. 독도에는 강치가 살았어요. 연구는 지나치게 많이 잡은 일이 강치 감소와 멸종에 큰 영향을 주었음을 설명해요. | L97: 고른 보기 ‘과거 연구에는 어떤 결론도 있을 수 없다’와 달라요. 이 문항의 정답은 ‘모델의 가정과 검토하지 않은 요인을 넘어선다’입니다. 독도에는 강치가 살았어요. 연구는 지나치게 많이 잡은 일이 강치 감소와 멸종에 큰 영향을 주었음을 설명해요. | M97: 독도에는 강치가 살았어요. 연구는 지나치게 많이 잡은 일이 강치 감소와 멸종에 큰 영향을 주었음을 설명해요. | N97: 2022년 연구는 과거 포획 기록과 개체군 모델을 이용해 남획의 영향을 살폈습니다. 이 문항은 현재 동물 수를 외우는 문제가 아니라 독도 강치의 역사를 이해하는 문제입니다. | O97: https://www.mof.go.kr/doc/ko/selectDoc.do?bbsSeq=10&docSeq=45126&menuSeq=971 https://www.mdpi.com/2077-1312/10/2/271 | P97: =LEN(E97)+MAX(LEN(F97),LEN(G97),LEN(H97)) -> 53 | Q97: 출처 기반 자체 검토 / 독립 승인 전
A98: 910097 | B98: 5 | C98: dk-model-evidence | D98: 1 | E98: 옛 강치 수를 알아볼 때 쓸 자료는? | F98: 등대의 색 이름만 | G98: 남아 있는 포획 기록 | H98: 오늘의 배 시간표만 | I98: 2 | J98: 강치의 옛 개체 수는 남아 있는 기록으로 추정해요. 연구 모델의 수치와 당시 직접 센 수치는 구별해야 해요. | K98: 고른 보기 ‘등대의 색 이름만’와 달라요. 이 문항의 정답은 ‘남아 있는 포획 기록’입니다. 강치의 옛 개체 수는 남아 있는 기록으로 추정해요. 연구 모델의 수치와 당시 직접 센 수치는 구별해야 해요. | L98: 강치의 옛 개체 수는 남아 있는 기록으로 추정해요. 연구 모델의 수치와 당시 직접 센 수치는 구별해야 해요. | M98: 고른 보기 ‘오늘의 배 시간표만’와 달라요. 이 문항의 정답은 ‘남아 있는 포획 기록’입니다. 강치의 옛 개체 수는 남아 있는 기록으로 추정해요. 연구 모델의 수치와 당시 직접 센 수치는 구별해야 해요. | O98: https://www.mdpi.com/2077-1312/10/2/271 | P98: =LEN(E98)+MAX(LEN(F98),LEN(G98),LEN(H98)) -> 31 | Q98: 출처 기반 자체 검토 / 독립 승인 전
A99: 910098 | B99: 5 | C99: dk-model-evidence | D99: 2 | E99: 연구 모델로 구한 강치 수는 무엇일까요? | F99: 기록과 가정으로 구한 추정값 | G99: 그날 모든 개체를 직접 센 값 | H99: 해안선의 정확한 길이 | I99: 1 | J99: 강치의 옛 개체 수는 남아 있는 기록으로 추정해요. 연구 모델의 수치와 당시 직접 센 수치는 구별해야 해요. | K99: 강치의 옛 개체 수는 남아 있는 기록으로 추정해요. 연구 모델의 수치와 당시 직접 센 수치는 구별해야 해요. | L99: 고른 보기 ‘그날 모든 개체를 직접 센 값’와 달라요. 이 문항의 정답은 ‘기록과 가정으로 구한 추정값’입니다. 강치의 옛 개체 수는 남아 있는 기록으로 추정해요. 연구 모델의 수치와 당시 직접 센 수치는 구별해야 해요. | M99: 고른 보기 ‘해안선의 정확한 길이’와 달라요. 이 문항의 정답은 ‘기록과 가정으로 구한 추정값’입니다. 강치의 옛 개체 수는 남아 있는 기록으로 추정해요. 연구 모델의 수치와 당시 직접 센 수치는 구별해야 해요. | O99: https://www.mdpi.com/2077-1312/10/2/271 | P99: =LEN(E99)+MAX(LEN(F99),LEN(G99),LEN(H99)) -> 38 | Q99: 출처 기반 자체 검토 / 독립 승인 전
A100: 910099 | B100: 5 | C100: dk-model-evidence | D100: 3 | E100: 자료가 밝히는 연구의 한계는? | F100: 포획 기록을 전혀 사용하지 않음 | G100: 현대 선박의 길이만 조사함 | H100: 생태 정보 부족과 모델 가정 | I100: 3 | J100: 강치의 옛 개체 수는 남아 있는 기록으로 추정해요. 연구 모델의 수치와 당시 직접 센 수치는 구별해야 해요. | K100: 고른 보기 ‘포획 기록을 전혀 사용하지 않음’와 달라요. 이 문항의 정답은 ‘생태 정보 부족과 모델 가정’입니다. 강치의 옛 개체 수는 남아 있는 기록으로 추정해요. 연구 모델의 수치와 당시 직접 센 수치는 구별해야 해요. | L100: 고른 보기 ‘현대 선박의 길이만 조사함’와 달라요. 이 문항의 정답은 ‘생태 정보 부족과 모델 가정’입니다. 강치의 옛 개체 수는 남아 있는 기록으로 추정해요. 연구 모델의 수치와 당시 직접 센 수치는 구별해야 해요. | M100: 강치의 옛 개체 수는 남아 있는 기록으로 추정해요. 연구 모델의 수치와 당시 직접 센 수치는 구별해야 해요. | N100: Lee 외(2022)는 포획 기록과 개체군 모형으로 1900~1951년의 독도 강치 개체 수를 재구성했습니다. 논문은 생태 정보 부족과 모델 가정을 한계로 밝힙니다. | O100: https://www.mdpi.com/2077-1312/10/2/271 | P100: =LEN(E100)+MAX(LEN(F100),LEN(G100),LEN(H100)) -> 33 | Q100: 출처 기반 자체 검토 / 독립 승인 전
...

Sheet 문항_EN
A1: 문항 ID | B1: 단원 | C1: 개념 묶음 | D1: 인지단계 | E1: 질문 | F1: 보기 1 | G1: 보기 2 | H1: 보기 3 | I1: 정답 번호 | J1: 사실·해설 | K1: 오답 해설 1 | L1: 오답 해설 2 | M1: 오답 해설 3 | N1: 판단 자료 | O1: 출처 URL | P1: 질문+최장보기 글자수 | Q1: 검토 상태
A2: 910001 | B2: 1 | C2: dk-composition | D2: 1 | E2: Which are Dokdo’s two main islands? | F2: Jejudo and Seodo | G2: Dongdo and Seodo | H2: Ulleungdo and Dongdo | I2: 2 | J2: Dokdo consists of Dongdo, Seodo and smaller surrounding rocky islets. | K2: The selected option, “Jejudo and Seodo”, does not fit. The answer is “Dongdo and Seodo”. Dokdo consists of Dongdo, Seodo and smaller surrounding rocky islets. | L2: Dokdo consists of Dongdo, Seodo and smaller surrounding rocky islets. | M2: The selected option, “Ulleungdo and Dongdo”, does not fit. The answer is “Dongdo and Seodo”. Dokdo consists of Dongdo, Seodo and smaller surrounding rocky islets. | O2: https://dokdo.mofa.go.kr/kor/introduce/location.jsp | P2: =LEN(E2)+MAX(LEN(F2),LEN(G2),LEN(H2)) -> 55 | Q2: 출처 기반 자체 검토 / 독립 승인 전
A3: 910002 | B3: 1 | C3: dk-composition | D3: 2 | E3: What is missing if only the two main islands are drawn? | F3: The surrounding smaller islets | G3: The locations of the two main islands | H3: Seodo itself | I3: 1 | J3: Dokdo consists of Dongdo, Seodo and smaller surrounding rocky islets. | K3: Dokdo consists of Dongdo, Seodo and smaller surrounding rocky islets. | L3: The selected option, “The locations of the two main islands”, does not fit. The answer is “The surrounding smaller islets”. Dokdo consists of Dongdo, Seodo and smaller surrounding rocky islets. | M3: The selected option, “Seodo itself”, does not fit. The answer is “The surrounding smaller islets”. Dokdo consists of Dongdo, Seodo and smaller surrounding rocky islets. | O3: https://dokdo.mofa.go.kr/kor/introduce/location.jsp | P3: =LEN(E3)+MAX(LEN(F3),LEN(G3),LEN(H3)) -> 92 | Q3: 출처 기반 자체 검토 / 독립 승인 전
A4: 910003 | B4: 1 | C4: dk-composition | D4: 3 | E4: What does the number 89 count in the source? | F4: All islands including Dongdo and Seodo | G4: Peaks within Dongdo | H4: Associated islets counted separately from the two main islands | I4: 3 | J4: Dokdo consists of Dongdo, Seodo and smaller surrounding rocky islets. | K4: The selected option, “All islands including Dongdo and Seodo”, does not fit. The answer is “Associated islets counted separately from the two main islands”. Dokdo consists of Dongdo, Seodo and smaller surrounding rocky islets. | L4: The selected option, “Peaks within Dongdo”, does not fit. The answer is “Associated islets counted separately from the two main islands”. Dokdo consists of Dongdo, Seodo and smaller surrounding rocky islets. | M4: Dokdo consists of Dongdo, Seodo and smaller surrounding rocky islets. | N4: MOFA describes Dokdo as the two main islands Dongdo and Seodo, plus 89 associated islets. | O4: https://dokdo.mofa.go.kr/kor/introduce/location.jsp | P4: =LEN(E4)+MAX(LEN(F4),LEN(G4),LEN(H4)) -> 106 | Q4: 출처 기반 자체 검토 / 독립 승인 전
A5: 910004 | B5: 1 | C5: dk-composition | D5: 4 | E5: How should “Dokdo consists of only two islands” be revised? | F5: Describe all 89 as main islands | G5: Distinguish the main islands from associated islets | H5: Exclude all smaller islets from Dokdo | I5: 2 | J5: Dokdo consists of Dongdo, Seodo and smaller surrounding rocky islets. Naming the principal islands is not a complete description of the group. | K5: The selected option, “Describe all 89 as main islands”, does not fit. The answer is “Distinguish the main islands from associated islets”. Dokdo consists of Dongdo, Seodo and smaller surrounding rocky islets. Naming the principal islands is not a complete description of the group. | L5: Dokdo consists of Dongdo, Seodo and smaller surrounding rocky islets. Naming the principal islands is not a complete description of the group. | M5: The selected option, “Exclude all smaller islets from Dokdo”, does not fit. The answer is “Distinguish the main islands from associated islets”. Dokdo consists of Dongdo, Seodo and smaller surrounding rocky islets. Naming the principal islands is not a complete description of the group. | N5: MOFA describes Dokdo as the two main islands Dongdo and Seodo, plus 89 associated islets. | O5: https://dokdo.mofa.go.kr/kor/introduce/location.jsp | P5: =LEN(E5)+MAX(LEN(F5),LEN(G5),LEN(H5)) -> 110 | Q5: 출처 기반 자체 검토 / 독립 승인 전
A6: 910005 | B6: 1 | C6: dk-relative-location | D6: 1 | E6: In which direction is Dokdo from Ulleungdo? | F6: Southeast | G6: Northwest | H6: Southwest | I6: 1 | J6: Dokdo lies about 87.4 km southeast of Ulleungdo. | K6: Dokdo lies about 87.4 km southeast of Ulleungdo. | L6: The selected option, “Northwest”, does not fit. The answer is “Southeast”. Dokdo lies about 87.4 km southeast of Ulleungdo. | M6: The selected option, “Southwest”, does not fit. The answer is “Southeast”. Dokdo lies about 87.4 km southeast of Ulleungdo. | O6: https://dokdo.mofa.go.kr/kor/introduce/location.jsp | P6: =LEN(E6)+MAX(LEN(F6),LEN(G6),LEN(H6)) -> 52 | Q6: 출처 기반 자체 검토 / 독립 승인 전
A7: 910006 | B7: 1 | C7: dk-relative-location | D7: 2 | E7: How are Ulleungdo and Dokdo related geographically? | F7: Names for two sides of one island | G7: Both are within Dongdo | H7: Separate islands with sea between them | I7: 3 | J7: Dokdo lies about 87.4 km southeast of Ulleungdo. | K7: The selected option, “Names for two sides of one island”, does not fit. The answer is “Separate islands with sea between them”. Dokdo lies about 87.4 km southeast of Ulleungdo. | L7: The selected option, “Both are within Dongdo”, does not fit. The answer is “Separate islands with sea between them”. Dokdo lies about 87.4 km southeast of Ulleungdo. | M7: Dokdo lies about 87.4 km southeast of Ulleungdo. | O7: https://dokdo.mofa.go.kr/kor/introduce/location.jsp | P7: =LEN(E7)+MAX(LEN(F7),LEN(G7),LEN(H7)) -> 89 | Q7: 출처 기반 자체 검토 / 독립 승인 전
A8: 910007 | B8: 1 | C8: dk-relative-location | D8: 3 | E8: Which place is closer to Dokdo in the supplied data? | F8: Both are equally far away | G8: Ulleungdo | H8: The Oki Islands | I8: 2 | J8: Dokdo lies about 87.4 km southeast of Ulleungdo. 87.4 km is shorter than 157.5 km. | K8: The selected option, “Both are equally far away”, does not fit. The answer is “Ulleungdo”. Dokdo lies about 87.4 km southeast of Ulleungdo. 87.4 km is shorter than 157.5 km. | L8: Dokdo lies about 87.4 km southeast of Ulleungdo. 87.4 km is shorter than 157.5 km. | M8: The selected option, “The Oki Islands”, does not fit. The answer is “Ulleungdo”. Dokdo lies about 87.4 km southeast of Ulleungdo. 87.4 km is shorter than 157.5 km. | N8: Distances from Dokdo: Ulleungdo 87.4 km; Japan’s Oki Islands 157.5 km. Both measurements start at Dokdo. | O8: https://dokdo.mofa.go.kr/kor/introduce/location.jsp | P8: =LEN(E8)+MAX(LEN(F8),LEN(G8),LEN(H8)) -> 77 | Q8: 출처 기반 자체 검토 / 독립 승인 전
A9: 910008 | B9: 1 | C9: dk-relative-location | D9: 4 | E9: Which claim is supported by this distance table alone? | F9: Ulleungdo is closer to Dokdo than Oki is | G9: Distance alone determines all territorial history | H9: Ulleungdo and Dokdo are connected by land | I9: 1 | J9: Dokdo lies about 87.4 km southeast of Ulleungdo. A distance comparison is distinct from assessing historical and legal evidence. | K9: Dokdo lies about 87.4 km southeast of Ulleungdo. A distance comparison is distinct from assessing historical and legal evidence. | L9: The selected option, “Distance alone determines all territorial history”, does not fit. The answer is “Ulleungdo is closer to Dokdo than Oki is”. Dokdo lies about 87.4 km southeast of Ulleungdo. A distance comparison is distinct from assessing historical and legal evidence. | M9: The selected option, “Ulleungdo and Dokdo are connected by land”, does not fit. The answer is “Ulleungdo is closer to Dokdo than Oki is”. Dokdo lies about 87.4 km southeast of Ulleungdo. A distance comparison is distinct from assessing historical and legal evidence. | N9: Distances from Dokdo: Ulleungdo 87.4 km; Japan’s Oki Islands 157.5 km. Both measurements start at Dokdo. | O9: https://dokdo.mofa.go.kr/kor/introduce/location.jsp | P9: =LEN(E9)+MAX(LEN(F9),LEN(G9),LEN(H9)) -> 103 | Q9: 출처 기반 자체 검토 / 독립 승인 전
A10: 910009 | B10: 1 | C10: dk-orientation | D10: 1 | E10: What is Dokdo’s eastern main island called? | F10: Seodo | G10: Ulleungdo | H10: Dongdo | I10: 3 | J10: Seodo is the western main island and Dongdo the eastern one. Rotating a map does not change geographic directions. | K10: The selected option, “Seodo”, does not fit. The answer is “Dongdo”. Seodo is the western main island and Dongdo the eastern one. Rotating a map does not change geographic directions. | L10: The selected option, “Ulleungdo”, does not fit. The answer is “Dongdo”. Seodo is the western main island and Dongdo the eastern one. Rotating a map does not change geographic directions. | M10: Seodo is the western main island and Dongdo the eastern one. Rotating a map does not change geographic directions. | O10: https://dokdo.mofa.go.kr/kor/introduce/location.jsp | P10: =LEN(E10)+MAX(LEN(F10),LEN(G10),LEN(H10)) -> 52 | Q10: 출처 기반 자체 검토 / 독립 승인 전
A11: 910010 | B11: 1 | C11: dk-orientation | D11: 2 | E11: Which direction is linked to “seo” in Seodo? | F11: North | G11: West | H11: East | I11: 2 | J11: Seodo is the western main island and Dongdo the eastern one. Rotating a map does not change geographic directions. | K11: The selected option, “North”, does not fit. The answer is “West”. Seodo is the western main island and Dongdo the eastern one. Rotating a map does not change geographic directions. | L11: Seodo is the western main island and Dongdo the eastern one. Rotating a map does not change geographic directions. | M11: The selected option, “East”, does not fit. The answer is “West”. Seodo is the western main island and Dongdo the eastern one. Rotating a map does not change geographic directions. | O11: https://dokdo.mofa.go.kr/kor/introduce/location.jsp | P11: =LEN(E11)+MAX(LEN(F11),LEN(G11),LEN(H11)) -> 49 | Q11: 출처 기반 자체 검토 / 독립 승인 전
A12: 910011 | B12: 1 | C12: dk-orientation | D12: 3 | E12: On the supplied schematic, where is Dongdo relative to Seodo? | F12: To the right | G12: To the left | H12: At the same point | I12: 1 | J12: Seodo is the western main island and Dongdo the eastern one. Rotating a map does not change geographic directions. | K12: Seodo is the western main island and Dongdo the eastern one. Rotating a map does not change geographic directions. | L12: The selected option, “To the left”, does not fit. The answer is “To the right”. Seodo is the western main island and Dongdo the eastern one. Rotating a map does not change geographic directions. | M12: The selected option, “At the same point”, does not fit. The answer is “To the right”. Seodo is the western main island and Dongdo the eastern one. Rotating a map does not change geographic directions. | N12: Orientation diagram: north up, west left, east right. Seodo is on the left and Dongdo on the right. This schematic does not measure shorelines or distance. | O12: https://dokdo.mofa.go.kr/kor/introduce/location.jsp | P12: =LEN(E12)+MAX(LEN(F12),LEN(G12),LEN(H12)) -> 78 | Q12: 출처 기반 자체 검토 / 독립 승인 전
A13: 910012 | B13: 1 | C13: dk-orientation | D13: 4 | E13: What if a rotated map shows Dongdo on the left? | F13: Rename Dongdo as Seodo | G13: Conclude that the island physically moved | H13: Use the compass marker to determine east and west | I13: 3 | J13: Seodo is the western main island and Dongdo the eastern one. Rotating a map does not change geographic directions. Screen left and right need not correspond to geographic west and east. | K13: The selected option, “Rename Dongdo as Seodo”, does not fit. The answer is “Use the compass marker to determine east and west”. Seodo is the western main island and Dongdo the eastern one. Rotating a map does not change geographic directions. Screen left and right need not correspond to geographic west and east. | L13: The selected option, “Conclude that the island physically moved”, does not fit. The answer is “Use the compass marker to determine east and west”. Seodo is the western main island and Dongdo the eastern one. Rotating a map does not change geographic directions. Screen left and right need not correspond to geographic west and east. | M13: Seodo is the western main island and Dongdo the eastern one. Rotating a map does not change geographic directions. Screen left and right need not correspond to geographic west and east. | N13: Orientation diagram: north up, west left, east right. Seodo is on the left and Dongdo on the right. This schematic does not measure shorelines or distance. | O13: https://dokdo.mofa.go.kr/kor/introduce/location.jsp | P13: =LEN(E13)+MAX(LEN(F13),LEN(G13),LEN(H13)) -> 96 | Q13: 출처 기반 자체 검토 / 독립 승인 전
A14: 910013 | B14: 1 | C14: dk-visibility | D14: 1 | E14: What weather helps people see Dokdo from Ulleungdo? | F14: Rain obscuring the view | G14: A clear day | H14: Thick fog | I14: 2 | J14: Dokdo can be seen from Ulleungdo in clear weather. Fog or rain can obscure the view. | K14: The selected option, “Rain obscuring the view”, does not fit. The answer is “A clear day”. Dokdo can be seen from Ulleungdo in clear weather. Fog or rain can obscure the view. | L14: Dokdo can be seen from Ulleungdo in clear weather. Fog or rain can obscure the view. | M14: The selected option, “Thick fog”, does not fit. The answer is “A clear day”. Dokdo can be seen from Ulleungdo in clear weather. Fog or rain can obscure the view. | O14: https://dokdo.mofa.go.kr/kor/introduce/location.jsp https://dokdo.mofa.go.kr/kor/pds/part06_view02.jsp | P14: =LEN(E14)+MAX(LEN(F14),LEN(G14),LEN(H14)) -> 74 | Q14: 출처 기반 자체 검토 / 독립 승인 전
A15: 910014 | B15: 1 | C15: dk-visibility | D15: 2 | E15: What should be considered if Dokdo is not visible today? | F15: Weather conditions such as fog | G15: A change of island name | H15: An increase in Seodo’s area | I15: 1 | J15: Dokdo can be seen from Ulleungdo in clear weather. Fog or rain can obscure the view. | K15: Dokdo can be seen from Ulleungdo in clear weather. Fog or rain can obscure the view. | L15: The selected option, “A change of island name”, does not fit. The answer is “Weather conditions such as fog”. Dokdo can be seen from Ulleungdo in clear weather. Fog or rain can obscure the view. | M15: The selected option, “An increase in Seodo’s area”, does not fit. The answer is “Weather conditions such as fog”. Dokdo can be seen from Ulleungdo in clear weather. Fog or rain can obscure the view. | O15: https://dokdo.mofa.go.kr/kor/introduce/location.jsp https://dokdo.mofa.go.kr/kor/pds/part06_view02.jsp | P15: =LEN(E15)+MAX(LEN(F15),LEN(G15),LEN(H15)) -> 86 | Q15: 출처 기반 자체 검토 / 독립 승인 전
A16: 910015 | B16: 1 | C16: dk-visibility | D16: 3 | E16: What condition does the old passage place on visibility? | F16: Always, in all weather | G16: Only in winter | H16: When the weather is clear | I16: 3 | J16: Dokdo can be seen from Ulleungdo in clear weather. Fog or rain can obscure the view. | K16: The selected option, “Always, in all weather”, does not fit. The answer is “When the weather is clear”. Dokdo can be seen from Ulleungdo in clear weather. Fog or rain can obscure the view. | L16: The selected option, “Only in winter”, does not fit. The answer is “When the weather is clear”. Dokdo can be seen from Ulleungdo in clear weather. Fog or rain can obscure the view. | M16: Dokdo can be seen from Ulleungdo in clear weather. Fog or rain can obscure the view. | N16: The MOFA presentation of the geographical appendix to the Annals of Sejong says the islands Usan and Mureung can be seen in clear weather. | O16: https://dokdo.mofa.go.kr/kor/introduce/location.jsp https://dokdo.mofa.go.kr/kor/pds/part06_view02.jsp | P16: =LEN(E16)+MAX(LEN(F16),LEN(G16),LEN(H16)) -> 81 | Q16: 출처 기반 자체 검토 / 독립 승인 전
A17: 910016 | B17: 1 | C17: dk-visibility | D17: 4 | E17: Is “Dokdo is always visible from Ulleungdo” accurate? | F17: Weather never affects the visibility of nearby islands | G17: No; it omits the clear-weather condition | H17: Yes; the correct island names are sufficient | I17: 2 | J17: Dokdo can be seen from Ulleungdo in clear weather. Fog or rain can obscure the view. | K17: The selected option, “Weather never affects the visibility of nearby islands”, does not fit. The answer is “No; it omits the clear-weather condition”. Dokdo can be seen from Ulleungdo in clear weather. Fog or rain can obscure the view. | L17: Dokdo can be seen from Ulleungdo in clear weather. Fog or rain can obscure the view. | M17: The selected option, “Yes; the correct island names are sufficient”, does not fit. The answer is “No; it omits the clear-weather condition”. Dokdo can be seen from Ulleungdo in clear weather. Fog or rain can obscure the view. | N17: The MOFA presentation of the geographical appendix to the Annals of Sejong says the islands Usan and Mureung can be seen in clear weather. | O17: https://dokdo.mofa.go.kr/kor/introduce/location.jsp https://dokdo.mofa.go.kr/kor/pds/part06_view02.jsp | P17: =LEN(E17)+MAX(LEN(F17),LEN(G17),LEN(H17)) -> 107 | Q17: 출처 기반 자체 검토 / 독립 승인 전
A18: 910017 | B18: 1 | C18: dk-islet-count | D18: 1 | E18: Are the smaller rocky islets part of Dokdo? | F18: Yes, they are part of Dokdo | G18: No, only the main islands are Dokdo | H18: They all belong to Ulleungdo | I18: 1 | J18: Dokdo’s total land area includes the associated islets as well as Dongdo and Seodo. | K18: Dokdo’s total land area includes the associated islets as well as Dongdo and Seodo. | L18: The selected option, “No, only the main islands are Dokdo”, does not fit. The answer is “Yes, they are part of Dokdo”. Dokdo’s total land area includes the associated islets as well as Dongdo and Seodo. | M18: The selected option, “They all belong to Ulleungdo”, does not fit. The answer is “Yes, they are part of Dokdo”. Dokdo’s total land area includes the associated islets as well as Dongdo and Seodo. | O18: https://dokdo.mofa.go.kr/kor/introduce/location.jsp | P18: =LEN(E18)+MAX(LEN(F18),LEN(G18),LEN(H18)) -> 78 | Q18: 출처 기반 자체 검토 / 독립 승인 전
A19: 910018 | B19: 1 | C19: dk-islet-count | D19: 2 | E19: What must be included in Dokdo’s total land area? | F19: The elevations of the main islands | G19: The whole area of Ulleungdo | H19: The main islands and associated islets | I19: 3 | J19: Dokdo’s total land area includes the associated islets as well as Dongdo and Seodo. | K19: The selected option, “The elevations of the main islands”, does not fit. The answer is “The main islands and associated islets”. Dokdo’s total land area includes the associated islets as well as Dongdo and Seodo. | L19: The selected option, “The whole area of Ulleungdo”, does not fit. The answer is “The main islands and associated islets”. Dokdo’s total land area includes the associated islets as well as Dongdo and Seodo. | M19: Dokdo’s total land area includes the associated islets as well as Dongdo and Seodo. | O19: https://dokdo.mofa.go.kr/kor/introduce/location.jsp | P19: =LEN(E19)+MAX(LEN(F19),LEN(G19),LEN(H19)) -> 87 | Q19: 출처 기반 자체 검토 / 독립 승인 전
A20: 910019 | B20: 1 | C20: dk-islet-count | D20: 3 | E20: Why is the sum of the two main island areas below the total? | F20: Elevations were omitted from the area calculation | G20: Associated islets add land area | H20: The sea was counted twice | I20: 2 | J20: Dokdo’s total land area includes the associated islets as well as Dongdo and Seodo. | K20: The selected option, “Elevations were omitted from the area calculation”, does not fit. The answer is “Associated islets add land area”. Dokdo’s total land area includes the associated islets as well as Dongdo and Seodo. | L20: Dokdo’s total land area includes the associated islets as well as Dongdo and Seodo. | M20: The selected option, “The sea was counted twice”, does not fit. The answer is “Associated islets add land area”. Dokdo’s total land area includes the associated islets as well as Dongdo and Seodo. | N20: Areas: Dongdo 73,297 m²; Seodo 88,740 m²; Dokdo total 187,554 m². The total includes associated islets. | O20: https://dokdo.mofa.go.kr/kor/introduce/location.jsp | P20: =LEN(E20)+MAX(LEN(F20),LEN(G20),LEN(H20)) -> 109 | Q20: 출처 기반 자체 검토 / 독립 승인 전
A21: 910020 | B21: 1 | C21: dk-islet-count | D21: 4 | E21: What is wrong with using one photo’s rock count as the total? | F21: It may miss islets outside the frame | G21: None of the photographed rocks is part of Dokdo | H21: A photograph necessarily shows the whole group | I21: 1 | J21: Dokdo’s total land area includes the associated islets as well as Dongdo and Seodo. | K21: Dokdo’s total land area includes the associated islets as well as Dongdo and Seodo. | L21: The selected option, “None of the photographed rocks is part of Dokdo”, does not fit. The answer is “It may miss islets outside the frame”. Dokdo’s total land area includes the associated islets as well as Dongdo and Seodo. | M21: The selected option, “A photograph necessarily shows the whole group”, does not fit. The answer is “It may miss islets outside the frame”. Dokdo’s total land area includes the associated islets as well as Dongdo and Seodo. | N21: Areas: Dongdo 73,297 m²; Seodo 88,740 m²; Dokdo total 187,554 m². The total includes associated islets. | O21: https://dokdo.mofa.go.kr/kor/introduce/location.jsp | P21: =LEN(E21)+MAX(LEN(F21),LEN(G21),LEN(H21)) -> 108 | Q21: 출처 기반 자체 검토 / 독립 승인 전
A22: 910021 | B22: 2 | C22: dk-heights | D22: 1 | E22: Which main island is higher? | F22: Dongdo | G22: They are equally high | H22: Seodo | I22: 3 | J22: Seodo’s maximum elevation is 168.5 m; Dongdo’s is 98.6 m. Seodo is higher. | K22: The selected option, “Dongdo”, does not fit. The answer is “Seodo”. Seodo’s maximum elevation is 168.5 m; Dongdo’s is 98.6 m. Seodo is higher. | L22: The selected option, “They are equally high”, does not fit. The answer is “Seodo”. Seodo’s maximum elevation is 168.5 m; Dongdo’s is 98.6 m. Seodo is higher. | M22: Seodo’s maximum elevation is 168.5 m; Dongdo’s is 98.6 m. Seodo is higher. | O22: https://dokdo.mofa.go.kr/kor/introduce/location.jsp | P22: =LEN(E22)+MAX(LEN(F22),LEN(G22),LEN(H22)) -> 49 | Q22: 출처 기반 자체 검토 / 독립 승인 전
A23: 910022 | B23: 2 | C23: dk-heights | D23: 2 | E23: Which elevation pairing is correct? | F23: Both 168.5 m | G23: Seodo 168.5 m; Dongdo 98.6 m | H23: Seodo 98.6 m; Dongdo 168.5 m | I23: 2 | J23: Seodo’s maximum elevation is 168.5 m; Dongdo’s is 98.6 m. Seodo is higher. | K23: The selected option, “Both 168.5 m”, does not fit. The answer is “Seodo 168.5 m; Dongdo 98.6 m”. Seodo’s maximum elevation is 168.5 m; Dongdo’s is 98.6 m. Seodo is higher. | L23: Seodo’s maximum elevation is 168.5 m; Dongdo’s is 98.6 m. Seodo is higher. | M23: The selected option, “Seodo 98.6 m; Dongdo 168.5 m”, does not fit. The answer is “Seodo 168.5 m; Dongdo 98.6 m”. Seodo’s maximum elevation is 168.5 m; Dongdo’s is 98.6 m. Seodo is higher. | O23: https://dokdo.mofa.go.kr/kor/introduce/location.jsp | P23: =LEN(E23)+MAX(LEN(F23),LEN(G23),LEN(H23)) -> 63 | Q23: 출처 기반 자체 검토 / 독립 승인 전
A24: 910023 | B24: 2 | C24: dk-heights | D24: 3 | E24: What is the difference in the listed maximum elevations? | F24: 69.9 m | G24: 267.1 m | H24: 87.4 m | I24: 1 | J24: Seodo’s maximum elevation is 168.5 m; Dongdo’s is 98.6 m. Seodo is higher. 168.5 minus 98.6 is 69.9 m. This asks for a difference, not a sum. | K24: Seodo’s maximum elevation is 168.5 m; Dongdo’s is 98.6 m. Seodo is higher. 168.5 minus 98.6 is 69.9 m. This asks for a difference, not a sum. | L24: The selected option, “267.1 m”, does not fit. The answer is “69.9 m”. Seodo’s maximum elevation is 168.5 m; Dongdo’s is 98.6 m. Seodo is higher. 168.5 minus 98.6 is 69.9 m. This asks for a difference, not a sum. | M24: The selected option, “87.4 m”, does not fit. The answer is “69.9 m”. Seodo’s maximum elevation is 168.5 m; Dongdo’s is 98.6 m. Seodo is higher. 168.5 minus 98.6 is 69.9 m. This asks for a difference, not a sum. | N24: Elevations above sea level: Seodo 168.5 m; Dongdo 98.6 m. | O24: https://dokdo.mofa.go.kr/kor/introduce/location.jsp | P24: =LEN(E24)+MAX(LEN(F24),LEN(G24),LEN(H24)) -> 63 | Q24: 출처 기반 자체 검토 / 독립 승인 전
A25: 910024 | B25: 2 | C25: dk-heights | D25: 4 | E25: What if Dongdo looks larger in a photograph? | F25: Use image size alone to call Dongdo higher | G25: Assume actual elevation changes with each photo | H25: Consider perspective and measured elevation | I25: 3 | J25: Seodo’s maximum elevation is 168.5 m; Dongdo’s is 98.6 m. Seodo is higher. | K25: The selected option, “Use image size alone to call Dongdo higher”, does not fit. The answer is “Consider perspective and measured elevation”. Seodo’s maximum elevation is 168.5 m; Dongdo’s is 98.6 m. Seodo is higher. | L25: The selected option, “Assume actual elevation changes with each photo”, does not fit. The answer is “Consider perspective and measured elevation”. Seodo’s maximum elevation is 168.5 m; Dongdo’s is 98.6 m. Seodo is higher. | M25: Seodo’s maximum elevation is 168.5 m; Dongdo’s is 98.6 m. Seodo is higher. | N25: Elevations above sea level: Seodo 168.5 m; Dongdo 98.6 m. | O25: https://dokdo.mofa.go.kr/kor/introduce/location.jsp | P25: =LEN(E25)+MAX(LEN(F25),LEN(G25),LEN(H25)) -> 91 | Q25: 출처 기반 자체 검토 / 독립 승인 전
A26: 910025 | B26: 2 | C26: dk-area | D26: 1 | E26: Which main island has the larger land area? | F26: They have equal land areas | G26: Seodo | H26: Dongdo | I26: 2 | J26: Seodo has a larger land area than Dongdo. Elevation and area are different measurements. | K26: The selected option, “They have equal land areas”, does not fit. The answer is “Seodo”. Seodo has a larger land area than Dongdo. Elevation and area are different measurements. | L26: Seodo has a larger land area than Dongdo. Elevation and area are different measurements. | M26: The selected option, “Dongdo”, does not fit. The answer is “Seodo”. Seodo has a larger land area than Dongdo. Elevation and area are different measurements. | O26: https://dokdo.mofa.go.kr/kor/introduce/location.jsp | P26: =LEN(E26)+MAX(LEN(F26),LEN(G26),LEN(H26)) -> 69 | Q26: 출처 기반 자체 검토 / 독립 승인 전
A27: 910026 | B27: 2 | C27: dk-area | D27: 2 | E27: What does “Seodo has a larger area” compare? | F27: The extent of land | G27: Sea depth | H27: Lighthouse height | I27: 1 | J27: Seodo has a larger land area than Dongdo. Elevation and area are different measurements. | K27: Seodo has a larger land area than Dongdo. Elevation and area are different measurements. | L27: The selected option, “Sea depth”, does not fit. The answer is “The extent of land”. Seodo has a larger land area than Dongdo. Elevation and area are different measurements. | M27: The selected option, “Lighthouse height”, does not fit. The answer is “The extent of land”. Seodo has a larger land area than Dongdo. Elevation and area are different measurements. | O27: https://dokdo.mofa.go.kr/kor/introduce/location.jsp | P27: =LEN(E27)+MAX(LEN(F27),LEN(G27),LEN(H27)) -> 62 | Q27: 출처 기반 자체 검토 / 독립 승인 전
A28: 910027 | B28: 2 | C28: dk-area | D28: 3 | E28: Which values should be used to compare land area? | F28: 168.5 m and 98.6 m | G28: 87.4 km and 151 m | H28: 88,740 m² and 73,297 m² | I28: 3 | J28: Seodo has a larger land area than Dongdo. Elevation and area are different measurements. | K28: The selected option, “168.5 m and 98.6 m”, does not fit. The answer is “88,740 m² and 73,297 m²”. Seodo has a larger land area than Dongdo. Elevation and area are different measurements. | L28: The selected option, “87.4 km and 151 m”, does not fit. The answer is “88,740 m² and 73,297 m²”. Seodo has a larger land area than Dongdo. Elevation and area are different measurements. | M28: Seodo has a larger land area than Dongdo. Elevation and area are different measurements. | N28: Seodo area: 88,740 m²; Dongdo area: 73,297 m². Elevation uses metres; area uses square metres. | O28: https://dokdo.mofa.go.kr/kor/introduce/location.jsp | P28: =LEN(E28)+MAX(LEN(F28),LEN(G28),LEN(H28)) -> 72 | Q28: 출처 기반 자체 검토 / 독립 승인 전
A29: 910028 | B29: 2 | C29: dk-area | D29: 4 | E29: Evaluate “Seodo is higher, so it must have a larger area.” | F29: A higher island always has a smaller area | G29: Area must be checked with separate area data | H29: Correct, because adding heights produces area | I29: 2 | J29: Seodo has a larger land area than Dongdo. Elevation and area are different measurements. Both are greater for Seodo in this case, but elevation alone does not establish area. | K29: The selected option, “A higher island always has a smaller area”, does not fit. The answer is “Area must be checked with separate area data”. Seodo has a larger land area than Dongdo. Elevation and area are different measurements. Both are greater for Seodo in this case, but elevation alone does not establish area. | L29: Seodo has a larger land area than Dongdo. Elevation and area are different measurements. Both are greater for Seodo in this case, but elevation alone does not establish area. | M29: The selected option, “Correct, because adding heights produces area”, does not fit. The answer is “Area must be checked with separate area data”. Seodo has a larger land area than Dongdo. Elevation and area are different measurements. Both are greater for Seodo in this case, but elevation alone does not establish area. | N29: Seodo area: 88,740 m²; Dongdo area: 73,297 m². Elevation uses metres; area uses square metres. | O29: https://dokdo.mofa.go.kr/kor/introduce/location.jsp | P29: =LEN(E29)+MAX(LEN(F29),LEN(G29),LEN(H29)) -> 103 | Q29: 출처 기반 자체 검토 / 독립 승인 전
A30: 910029 | B30: 2 | C30: dk-shore-gap | D30: 1 | E30: What fills the gap between Dongdo and Seodo? | F30: Seawater | G30: An above-water land bridge | H30: A mountain on Ulleungdo | I30: 1 | J30: Dongdo and Seodo are separated by water, with about 151 m between their nearest shores. | K30: Dongdo and Seodo are separated by water, with about 151 m between their nearest shores. | L30: The selected option, “An above-water land bridge”, does not fit. The answer is “Seawater”. Dongdo and Seodo are separated by water, with about 151 m between their nearest shores. | M30: The selected option, “A mountain on Ulleungdo”, does not fit. The answer is “Seawater”. Dongdo and Seodo are separated by water, with about 151 m between their nearest shores. | O30: https://www.dokdo.re.kr/home/cms/cmsCont.do?cntnts_sn=66 | P30: =LEN(E30)+MAX(LEN(F30),LEN(G30),LEN(H30)) -> 70 | Q30: 출처 기반 자체 검토 / 독립 승인 전
A31: 910030 | B31: 2 | C31: dk-shore-gap | D31: 2 | E31: Which measurement is linked to 151 m? | F31: Seodo’s maximum elevation | G31: The distance from Ulleungdo to Dokdo | H31: The shortest shore-to-shore distance | I31: 3 | J31: Dongdo and Seodo are separated by water, with about 151 m between their nearest shores. | K31: The selected option, “Seodo’s maximum elevation”, does not fit. The answer is “The shortest shore-to-shore distance”. Dongdo and Seodo are separated by water, with about 151 m between their nearest shores. | L31: The selected option, “The distance from Ulleungdo to Dokdo”, does not fit. The answer is “The shortest shore-to-shore distance”. Dongdo and Seodo are separated by water, with about 151 m between their nearest shores. | M31: Dongdo and Seodo are separated by water, with about 151 m between their nearest shores. | O31: https://www.dokdo.re.kr/home/cms/cmsCont.do?cntnts_sn=66 | P31: =LEN(E31)+MAX(LEN(F31),LEN(G31),LEN(H31)) -> 73 | Q31: 출처 기반 자체 검토 / 독립 승인 전
A32: 910031 | B32: 2 | C32: dk-shore-gap | D32: 3 | E32: Which endpoints suit the 151 m annotation? | F32: The centres of Ulleungdo and Seodo | G32: The nearest points on the two shores | H32: The two summits | I32: 2 | J32: Dongdo and Seodo are separated by water, with about 151 m between their nearest shores. | K32: The selected option, “The centres of Ulleungdo and Seodo”, does not fit. The answer is “The nearest points on the two shores”. Dongdo and Seodo are separated by water, with about 151 m between their nearest shores. | L32: Dongdo and Seodo are separated by water, with about 151 m between their nearest shores. | M32: The selected option, “The two summits”, does not fit. The answer is “The nearest points on the two shores”. Dongdo and Seodo are separated by water, with about 151 m between their nearest shores. | N32: The 151 m figure describes the gap between the nearest shores, not between the summits or island centres. | O32: https://www.dokdo.re.kr/home/cms/cmsCont.do?cntnts_sn=66 | P32: =LEN(E32)+MAX(LEN(F32),LEN(G32),LEN(H32)) -> 78 | Q32: 출처 기반 자체 검토 / 독립 승인 전
A33: 910032 | B33: 2 | C33: dk-shore-gap | D33: 4 | E33: What if 151 m labels a line between the summits? | F33: Correct it: the endpoints differ from the source | G33: Any points on the same two islands are acceptable | H33: Remove it because 151 m is an area | I33: 1 | J33: Dongdo and Seodo are separated by water, with about 151 m between their nearest shores. Both the number and the endpoints must match the measurement. | K33: Dongdo and Seodo are separated by water, with about 151 m between their nearest shores. Both the number and the endpoints must match the measurement. | L33: The selected option, “Any points on the same two islands are acceptable”, does not fit. The answer is “Correct it: the endpoints differ from the source”. Dongdo and Seodo are separated by water, with about 151 m between their nearest shores. Both the number and the endpoints must match the measurement. | M33: The selected option, “Remove it because 151 m is an area”, does not fit. The answer is “Correct it: the endpoints differ from the source”. Dongdo and Seodo are separated by water, with about 151 m between their nearest shores. Both the number and the endpoints must match the measurement. | N33: The 151 m figure describes the gap between the nearest shores, not between the summits or island centres. | O33: https://www.dokdo.re.kr/home/cms/cmsCont.do?cntnts_sn=66 | P33: =LEN(E33)+MAX(LEN(F33),LEN(G33),LEN(H33)) -> 97 | Q33: 출처 기반 자체 검토 / 독립 승인 전
A34: 910033 | B34: 2 | C34: dk-terrain-contrast | D34: 1 | E34: Which island is especially steep and pointed? | F34: Dongdo | G34: Both islands are entirely flat | H34: Seodo | I34: 3 | J34: Seodo rises steeply, while Dongdo has a comparatively level upper area. | K34: The selected option, “Dongdo”, does not fit. The answer is “Seodo”. Seodo rises steeply, while Dongdo has a comparatively level upper area. | L34: The selected option, “Both islands are entirely flat”, does not fit. The answer is “Seodo”. Seodo rises steeply, while Dongdo has a comparatively level upper area. | M34: Seodo rises steeply, while Dongdo has a comparatively level upper area. | O34: https://www.heritage.go.kr/heri/cul/culSelectDetail.do?VdkVgwKey=16%2C03360000%2C37&pageNo=1_1_2_0 https://www.jbe.go.kr/dokdo/assets/sub/picture.html | P34: =LEN(E34)+MAX(LEN(F34),LEN(G34),LEN(H34)) -> 75 | Q34: 출처 기반 자체 검토 / 독립 승인 전
A35: 910034 | B35: 2 | C35: dk-terrain-contrast | D35: 2 | E35: Which description fits the upper part of Dongdo? | F35: An entirely sandy plain | G35: A comparatively level area | H35: Only peaks higher than Seodo | I35: 2 | J35: Seodo rises steeply, while Dongdo has a comparatively level upper area. | K35: The selected option, “An entirely sandy plain”, does not fit. The answer is “A comparatively level area”. Seodo rises steeply, while Dongdo has a comparatively level upper area. | L35: Seodo rises steeply, while Dongdo has a comparatively level upper area. | M35: The selected option, “Only peaks higher than Seodo”, does not fit. The answer is “A comparatively level area”. Seodo rises steeply, while Dongdo has a comparatively level upper area. | O35: https://www.heritage.go.kr/heri/cul/culSelectDetail.do?VdkVgwKey=16%2C03360000%2C37&pageNo=1_1_2_0 https://www.jbe.go.kr/dokdo/assets/sub/picture.html | P35: =LEN(E35)+MAX(LEN(F35),LEN(G35),LEN(H35)) -> 76 | Q35: 출처 기반 자체 검토 / 독립 승인 전
A36: 910035 | B36: 2 | C36: dk-terrain-contrast | D36: 3 | E36: Which comparison matches the supplied source? | F36: Seodo is steep; Dongdo’s upper area is relatively level | G36: Dongdo is higher and sharper than Seodo | H36: Both have the same shape and elevation | I36: 1 | J36: Seodo rises steeply, while Dongdo has a comparatively level upper area. | K36: Seodo rises steeply, while Dongdo has a comparatively level upper area. | L36: The selected option, “Dongdo is higher and sharper than Seodo”, does not fit. The answer is “Seodo is steep; Dongdo’s upper area is relatively level”. Seodo rises steeply, while Dongdo has a comparatively level upper area. | M36: The selected option, “Both have the same shape and elevation”, does not fit. The answer is “Seodo is steep; Dongdo’s upper area is relatively level”. Seodo rises steeply, while Dongdo has a comparatively level upper area. | N36: The heritage description and aerial photographs distinguish steep Seodo from Dongdo’s comparatively level upper area. Dongdo still has ridges and coastal cliffs. | O36: https://www.heritage.go.kr/heri/cul/culSelectDetail.do?VdkVgwKey=16%2C03360000%2C37&pageNo=1_1_2_0 https://www.jbe.go.kr/dokdo/assets/sub/picture.html | P36: =LEN(E36)+MAX(LEN(F36),LEN(G36),LEN(H36)) -> 100 | Q36: 출처 기반 자체 검토 / 독립 승인 전
A37: 910036 | B37: 2 | C37: dk-terrain-contrast | D37: 4 | E37: What is wrong with drawing Dongdo as a completely flat plate? | F37: Facilities prove a flat plate is accurate | G37: An island lower than Seodo cannot have cliffs | H37: It extends a relative upper-area feature to the whole island | I37: 3 | J37: Seodo rises steeply, while Dongdo has a comparatively level upper area. | K37: The selected option, “Facilities prove a flat plate is accurate”, does not fit. The answer is “It extends a relative upper-area feature to the whole island”. Seodo rises steeply, while Dongdo has a comparatively level upper area. | L37: The selected option, “An island lower than Seodo cannot have cliffs”, does not fit. The answer is “It extends a relative upper-area feature to the whole island”. Seodo rises steeply, while Dongdo has a comparatively level upper area. | M37: Seodo rises steeply, while Dongdo has a comparatively level upper area. | N37: The heritage description and aerial photographs distinguish steep Seodo from Dongdo’s comparatively level upper area. Dongdo still has ridges and coastal cliffs. | O37: https://www.heritage.go.kr/heri/cul/culSelectDetail.do?VdkVgwKey=16%2C03360000%2C37&pageNo=1_1_2_0 https://www.jbe.go.kr/dokdo/assets/sub/picture.html | P37: =LEN(E37)+MAX(LEN(F37),LEN(G37),LEN(H37)) -> 121 | Q37: 출처 기반 자체 검토 / 독립 승인 전
A38: 910037 | B38: 2 | C38: dk-above-below | D38: 1 | E38: Does Dokdo’s landform continue underwater? | F38: It rests on a boat | G38: Yes, it continues underwater | H38: No, it floats on the surface | I38: 2 | J38: The islands are exposed parts of a larger underwater volcanic structure. Their terrain continues below the sea. | K38: The selected option, “It rests on a boat”, does not fit. The answer is “Yes, it continues underwater”. The islands are exposed parts of a larger underwater volcanic structure. Their terrain continues below the sea. | L38: The islands are exposed parts of a larger underwater volcanic structure. Their terrain continues below the sea. | M38: The selected option, “No, it floats on the surface”, does not fit. The answer is “Yes, it continues underwater”. The islands are exposed parts of a larger underwater volcanic structure. Their terrain continues below the sea. | O38: https://www.dokdo.re.kr/home/cms/cmsCont.do?cntnts_sn=66 | P38: =LEN(E38)+MAX(LEN(F38),LEN(G38),LEN(H38)) -> 70 | Q38: 출처 기반 자체 검토 / 독립 승인 전
A39: 910038 | B39: 2 | C39: dk-above-below | D39: 2 | E39: What else is needed to understand the whole Dokdo volcano? | F39: Its underwater portion | G39: Only the lighthouse roof | H39: Only Dongdo’s buildings | I39: 1 | J39: The islands are exposed parts of a larger underwater volcanic structure. Their terrain continues below the sea. | K39: The islands are exposed parts of a larger underwater volcanic structure. Their terrain continues below the sea. | L39: The selected option, “Only the lighthouse roof”, does not fit. The answer is “Its underwater portion”. The islands are exposed parts of a larger underwater volcanic structure. Their terrain continues below the sea. | M39: The selected option, “Only Dongdo’s buildings”, does not fit. The answer is “Its underwater portion”. The islands are exposed parts of a larger underwater volcanic structure. Their terrain continues below the sea. | O39: https://www.dokdo.re.kr/home/cms/cmsCont.do?cntnts_sn=66 | P39: =LEN(E39)+MAX(LEN(F39),LEN(G39),LEN(H39)) -> 82 | Q39: 출처 기반 자체 검토 / 독립 승인 전
A40: 910039 | B40: 2 | C40: dk-above-below | D40: 3 | E40: Why can 168.5 m and about 2,300 m both be used? | F40: Seodo’s height changes drastically each day | G40: Both values measure land area | H40: They use sea level and the submarine base respectively | I40: 3 | J40: The islands are exposed parts of a larger underwater volcanic structure. Their terrain continues below the sea. | K40: The selected option, “Seodo’s height changes drastically each day”, does not fit. The answer is “They use sea level and the submarine base respectively”. The islands are exposed parts of a larger underwater volcanic structure. Their terrain continues below the sea. | L40: The selected option, “Both values measure land area”, does not fit. The answer is “They use sea level and the submarine base respectively”. The islands are exposed parts of a larger underwater volcanic structure. Their terrain continues below the sea. | M40: The islands are exposed parts of a larger underwater volcanic structure. Their terrain continues below the sea. | N40: Above-sea-level maxima: Seodo 168.5 m; Dongdo 98.6 m. The whole volcano rises about 2,300 m from its submarine base. The reference levels differ. | O40: https://www.dokdo.re.kr/home/cms/cmsCont.do?cntnts_sn=66 | P40: =LEN(E40)+MAX(LEN(F40),LEN(G40),LEN(H40)) -> 101 | Q40: 출처 기반 자체 검토 / 독립 승인 전
A41: 910040 | B41: 2 | C41: dk-above-below | D41: 4 | E41: How should “Dokdo rises 2,300 m above the sea” be corrected? | F41: Add 2,300 m to 168.5 m | G41: Specify that 2,300 m uses the submarine base | H41: Change Dongdo’s elevation to 2,300 m | I41: 2 | J41: The islands are exposed parts of a larger underwater volcanic structure. Their terrain continues below the sea. | K41: The selected option, “Add 2,300 m to 168.5 m”, does not fit. The answer is “Specify that 2,300 m uses the submarine base”. The islands are exposed parts of a larger underwater volcanic structure. Their terrain continues below the sea. | L41: The islands are exposed parts of a larger underwater volcanic structure. Their terrain continues below the sea. | M41: The selected option, “Change Dongdo’s elevation to 2,300 m”, does not fit. The answer is “Specify that 2,300 m uses the submarine base”. The islands are exposed parts of a larger underwater volcanic structure. Their terrain continues below the sea. | N41: Above-sea-level maxima: Seodo 168.5 m; Dongdo 98.6 m. The whole volcano rises about 2,300 m from its submarine base. The reference levels differ. | O41: https://www.dokdo.re.kr/home/cms/cmsCont.do?cntnts_sn=66 | P41: =LEN(E41)+MAX(LEN(F41),LEN(G41),LEN(H41)) -> 104 | Q41: 출처 기반 자체 검토 / 독립 승인 전
A42: 910041 | B42: 3 | C42: dk-volcano | D42: 1 | E42: Which activity is linked to Dokdo’s formation? | F42: Underwater volcanic activity | G42: Sand deposition at a river mouth | H42: Icebergs drifting at sea | I42: 1 | J42: Dokdo formed through underwater volcanic activity. Erupted material accumulated and hardened into rock. | K42: Dokdo formed through underwater volcanic activity. Erupted material accumulated and hardened into rock. | L42: The selected option, “Sand deposition at a river mouth”, does not fit. The answer is “Underwater volcanic activity”. Dokdo formed through underwater volcanic activity. Erupted material accumulated and hardened into rock. | M42: The selected option, “Icebergs drifting at sea”, does not fit. The answer is “Underwater volcanic activity”. Dokdo formed through underwater volcanic activity. Erupted material accumulated and hardened into rock. | O42: https://www.dokdo.re.kr/home/cms/cmsCont.do?cntnts_sn=66 | P42: =LEN(E42)+MAX(LEN(F42),LEN(G42),LEN(H42)) -> 78 | Q42: 출처 기반 자체 검토 / 독립 승인 전
A43: 910042 | B43: 3 | C43: dk-volcano | D43: 2 | E43: How is erupted material related to Dokdo’s rock? | F43: It was material produced by the lighthouse | G43: It is frozen seawater | H43: It accumulated and hardened into rock | I43: 3 | J43: Dokdo formed through underwater volcanic activity. Erupted material accumulated and hardened into rock. | K43: The selected option, “It was material produced by the lighthouse”, does not fit. The answer is “It accumulated and hardened into rock”. Dokdo formed through underwater volcanic activity. Erupted material accumulated and hardened into rock. | L43: The selected option, “It is frozen seawater”, does not fit. The answer is “It accumulated and hardened into rock”. Dokdo formed through underwater volcanic activity. Erupted material accumulated and hardened into rock. | M43: Dokdo formed through underwater volcanic activity. Erupted material accumulated and hardened into rock. | O43: https://www.dokdo.re.kr/home/cms/cmsCont.do?cntnts_sn=66 | P43: =LEN(E43)+MAX(LEN(F43),LEN(G43),LEN(H43)) -> 90 | Q43: 출처 기반 자체 검토 / 독립 승인 전
A44: 910043 | B44: 3 | C44: dk-volcano | D44: 3 | E44: What supports describing Dokdo as volcanic? | F44: The names of current facilities | G44: Submarine eruption and volcanic rock composition | H44: The size of vessels at the dock | I44: 2 | J44: Dokdo formed through underwater volcanic activity. Erupted material accumulated and hardened into rock. | K44: The selected option, “The names of current facilities”, does not fit. The answer is “Submarine eruption and volcanic rock composition”. Dokdo formed through underwater volcanic activity. Erupted material accumulated and hardened into rock. | L44: Dokdo formed through underwater volcanic activity. Erupted material accumulated and hardened into rock. | M44: The selected option, “The size of vessels at the dock”, does not fit. The answer is “Submarine eruption and volcanic rock composition”. Dokdo formed through underwater volcanic activity. Erupted material accumulated and hardened into rock. | N44: KIOST describes Dokdo as a volcanic structure formed by submarine eruptions, with rocks including trachyandesite and tuff. Focus on formation rather than memorising rock names. | O44: https://www.dokdo.re.kr/home/cms/cmsCont.do?cntnts_sn=66 | P44: =LEN(E44)+MAX(LEN(F44),LEN(G44),LEN(H44)) -> 91 | Q44: 출처 기반 자체 검토 / 독립 승인 전
A45: 910044 | B45: 3 | C45: dk-volcano | D45: 4 | E45: Does memorising rock names alone explain Dokdo’s formation? | F45: No; relate eruption, deposition and hardening | G45: Many names automatically prove the sequence | H45: Facility construction gives the volcanic sequence | I45: 1 | J45: Dokdo formed through underwater volcanic activity. Erupted material accumulated and hardened into rock. | K45: Dokdo formed through underwater volcanic activity. Erupted material accumulated and hardened into rock. | L45: The selected option, “Many names automatically prove the sequence”, does not fit. The answer is “No; relate eruption, deposition and hardening”. Dokdo formed through underwater volcanic activity. Erupted material accumulated and hardened into rock. | M45: The selected option, “Facility construction gives the volcanic sequence”, does not fit. The answer is “No; relate eruption, deposition and hardening”. Dokdo formed through underwater volcanic activity. Erupted material accumulated and hardened into rock. | N45: KIOST describes Dokdo as a volcanic structure formed by submarine eruptions, with rocks including trachyandesite and tuff. Focus on formation rather than memorising rock names. | O45: https://www.dokdo.re.kr/home/cms/cmsCont.do?cntnts_sn=66 | P45: =LEN(E45)+MAX(LEN(F45),LEN(G45),LEN(H45)) -> 108 | Q45: 출처 기반 자체 검토 / 독립 승인 전
A46: 910045 | B46: 3 | C46: dk-formation-time | D46: 1 | E46: How did Dokdo form? | F46: On the day the lighthouse was built | G46: At the moment the first boat arrived | H46: Over a long period | I46: 3 | J46: Dokdo formed and changed over a long period, growing underwater before emerging above the surface. | K46: The selected option, “On the day the lighthouse was built”, does not fit. The answer is “Over a long period”. Dokdo formed and changed over a long period, growing underwater before emerging above the surface. | L46: The selected option, “At the moment the first boat arrived”, does not fit. The answer is “Over a long period”. Dokdo formed and changed over a long period, growing underwater before emerging above the surface. | M46: Dokdo formed and changed over a long period, growing underwater before emerging above the surface. | O46: https://www.dokdo.re.kr/home/cms/cmsCont.do?cntnts_sn=66 | P46: =LEN(E46)+MAX(LEN(F46),LEN(G46),LEN(H46)) -> 55 | Q46: 출처 기반 자체 검토 / 독립 승인 전
A47: 910046 | B47: 3 | C47: dk-formation-time | D47: 2 | E47: Which sequence fits Dokdo’s formation? | F47: Dock construction → first rock formation | G47: Underwater growth → emergence | H47: Lighthouse construction → volcanism | I47: 2 | J47: Dokdo formed and changed over a long period, growing underwater before emerging above the surface. | K47: The selected option, “Dock construction → first rock formation”, does not fit. The answer is “Underwater growth → emergence”. Dokdo formed and changed over a long period, growing underwater before emerging above the surface. | L47: Dokdo formed and changed over a long period, growing underwater before emerging above the surface. | M47: The selected option, “Lighthouse construction → volcanism”, does not fit. The answer is “Underwater growth → emergence”. Dokdo formed and changed over a long period, growing underwater before emerging above the surface. | O47: https://www.dokdo.re.kr/home/cms/cmsCont.do?cntnts_sn=66 | P47: =LEN(E47)+MAX(LEN(F47),LEN(G47),LEN(H47)) -> 78 | Q47: 출처 기반 자체 검토 / 독립 승인 전
A48: 910047 | B48: 3 | C48: dk-formation-time | D48: 3 | E48: Which event came first in the supplied chronology? | F48: The start of submarine volcanism | G48: Emergence above the sea | H48: Installation of today’s lighthouse | I48: 1 | J48: Dokdo formed and changed over a long period, growing underwater before emerging above the surface. | K48: Dokdo formed and changed over a long period, growing underwater before emerging above the surface. | L48: The selected option, “Emergence above the sea”, does not fit. The answer is “The start of submarine volcanism”. Dokdo formed and changed over a long period, growing underwater before emerging above the surface. | M48: The selected option, “Installation of today’s lighthouse”, does not fit. The answer is “The start of submarine volcanism”. Dokdo formed and changed over a long period, growing underwater before emerging above the surface. | N48: Approximate chronology: underwater volcanic activity from about 4.6 million years ago, emergence from around 2.5 million years ago, followed by predominantly erosional change. Read the sequence rather than memorising dates. | O48: https://www.dokdo.re.kr/home/cms/cmsCont.do?cntnts_sn=66 | P48: =LEN(E48)+MAX(LEN(F48),LEN(G48),LEN(H48)) -> 84 | Q48: 출처 기반 자체 검토 / 독립 승인 전
A49: 910048 | B49: 3 | C49: dk-formation-time | D49: 4 | E49: Evaluate “Dokdo was completed in its current form 4.6 million years ago.” | F49: The starting form must equal the present form | G49: No volcanic structure existed before emergence | H49: It omits later erosion and change | I49: 3 | J49: Dokdo formed and changed over a long period, growing underwater before emerging above the surface. | K49: The selected option, “The starting form must equal the present form”, does not fit. The answer is “It omits later erosion and change”. Dokdo formed and changed over a long period, growing underwater before emerging above the surface. | L49: The selected option, “No volcanic structure existed before emergence”, does not fit. The answer is “It omits later erosion and change”. Dokdo formed and changed over a long period, growing underwater before emerging above the surface. | M49: Dokdo formed and changed over a long period, growing underwater before emerging above the surface. | N49: Approximate chronology: underwater volcanic activity from about 4.6 million years ago, emergence from around 2.5 million years ago, followed by predominantly erosional change. Read the sequence rather than memorising dates. | O49: https://www.dokdo.re.kr/home/cms/cmsCont.do?cntnts_sn=66 | P49: =LEN(E49)+MAX(LEN(F49),LEN(G49),LEN(H49)) -> 119 | Q49: 출처 기반 자체 검토 / 독립 승인 전
A50: 910049 | B50: 3 | C50: dk-wave-erosion | D50: 1 | E50: What erodes rock along Dokdo’s coast? | F50: Helipad markings | G50: Waves | H50: Lighthouse light | I50: 2 | J50: Waves erode Dokdo’s coastal rock and help form cliffs, caves and rock arches. | K50: The selected option, “Helipad markings”, does not fit. The answer is “Waves”. Waves erode Dokdo’s coastal rock and help form cliffs, caves and rock arches. | L50: Waves erode Dokdo’s coastal rock and help form cliffs, caves and rock arches. | M50: The selected option, “Lighthouse light”, does not fit. The answer is “Waves”. Waves erode Dokdo’s coastal rock and help form cliffs, caves and rock arches. | O50: https://www.dokdo.re.kr/home/cms/cmsCont.do?cntnts_sn=66 https://korean.visitkorea.or.kr/detail/ms_detail.do?cotid=0fe4eeb6-3f6a-48b1-ab75-c8d4ab6b43be | P50: =LEN(E50)+MAX(LEN(F50),LEN(G50),LEN(H50)) -> 53 | Q50: 출처 기반 자체 검토 / 독립 승인 전
A51: 910050 | B51: 3 | C51: dk-wave-erosion | D51: 2 | E51: Which process is linked to sea caves? | F51: Waves eroding rock | G51: Seawater freezing into piles | H51: Lighthouse beams accumulating | I51: 1 | J51: Waves erode Dokdo’s coastal rock and help form cliffs, caves and rock arches. | K51: Waves erode Dokdo’s coastal rock and help form cliffs, caves and rock arches. | L51: The selected option, “Seawater freezing into piles”, does not fit. The answer is “Waves eroding rock”. Waves erode Dokdo’s coastal rock and help form cliffs, caves and rock arches. | M51: The selected option, “Lighthouse beams accumulating”, does not fit. The answer is “Waves eroding rock”. Waves erode Dokdo’s coastal rock and help form cliffs, caves and rock arches. | O51: https://www.dokdo.re.kr/home/cms/cmsCont.do?cntnts_sn=66 https://korean.visitkorea.or.kr/detail/ms_detail.do?cotid=0fe4eeb6-3f6a-48b1-ab75-c8d4ab6b43be | P51: =LEN(E51)+MAX(LEN(F51),LEN(G51),LEN(H51)) -> 66 | Q51: 출처 기반 자체 검토 / 독립 승인 전
A52: 910051 | B52: 3 | C52: dk-wave-erosion | D52: 3 | E52: Which term describes a wave-eroded cliff? | F52: Sea cave | G52: Sea arch | H52: Sea cliff | I52: 3 | J52: Waves erode Dokdo’s coastal rock and help form cliffs, caves and rock arches. All three concern coastal landforms, but their structures differ. | K52: The selected option, “Sea cave”, does not fit. The answer is “Sea cliff”. Waves erode Dokdo’s coastal rock and help form cliffs, caves and rock arches. All three concern coastal landforms, but their structures differ. | L52: The selected option, “Sea arch”, does not fit. The answer is “Sea cliff”. Waves erode Dokdo’s coastal rock and help form cliffs, caves and rock arches. All three concern coastal landforms, but their structures differ. | M52: Waves erode Dokdo’s coastal rock and help form cliffs, caves and rock arches. All three concern coastal landforms, but their structures differ. | N52: A sea cliff, sea cave and sea arch are different coastal erosion features found on Dokdo. | O52: https://www.dokdo.re.kr/home/cms/cmsCont.do?cntnts_sn=66 https://korean.visitkorea.or.kr/detail/ms_detail.do?cotid=0fe4eeb6-3f6a-48b1-ab75-c8d4ab6b43be | P52: =LEN(E52)+MAX(LEN(F52),LEN(G52),LEN(H52)) -> 50 | Q52: 출처 기반 자체 검토 / 독립 승인 전
A53: 910052 | B53: 3 | C53: dk-wave-erosion | D53: 4 | E53: What is wrong with interpreting a rock arch as a built gate? | F53: Erosion does not occur at coasts | G53: It confuses resemblance with formation | H53: Anything gate-shaped is a building | I53: 2 | J53: Waves erode Dokdo’s coastal rock and help form cliffs, caves and rock arches. | K53: The selected option, “Erosion does not occur at coasts”, does not fit. The answer is “It confuses resemblance with formation”. Waves erode Dokdo’s coastal rock and help form cliffs, caves and rock arches. | L53: Waves erode Dokdo’s coastal rock and help form cliffs, caves and rock arches. | M53: The selected option, “Anything gate-shaped is a building”, does not fit. The answer is “It confuses resemblance with formation”. Waves erode Dokdo’s coastal rock and help form cliffs, caves and rock arches. | N53: A sea cliff, sea cave and sea arch are different coastal erosion features found on Dokdo. | O53: https://www.dokdo.re.kr/home/cms/cmsCont.do?cntnts_sn=66 https://korean.visitkorea.or.kr/detail/ms_detail.do?cotid=0fe4eeb6-3f6a-48b1-ab75-c8d4ab6b43be | P53: =LEN(E53)+MAX(LEN(F53),LEN(G53),LEN(H53)) -> 98 | Q53: 출처 기반 자체 검토 / 독립 승인 전
A54: 910053 | B54: 3 | C54: dk-weathering | D54: 1 | E54: What can happen to Dokdo’s rocks over time? | F54: They can change gradually | G54: No part can ever change | H54: Their form is determined only by lighthouse colour | I54: 1 | J54: Dokdo’s rocks weather and erode under exposure to wind and waves, making continued monitoring valuable. | K54: Dokdo’s rocks weather and erode under exposure to wind and waves, making continued monitoring valuable. | L54: The selected option, “No part can ever change”, does not fit. The answer is “They can change gradually”. Dokdo’s rocks weather and erode under exposure to wind and waves, making continued monitoring valuable. | M54: The selected option, “Their form is determined only by lighthouse colour”, does not fit. The answer is “They can change gradually”. Dokdo’s rocks weather and erode under exposure to wind and waves, making continued monitoring valuable. | O54: https://www.dokdo.re.kr/home/cms/cmsCont.do?cntnts_sn=66 | P54: =LEN(E54)+MAX(LEN(F54),LEN(G54),LEN(H54)) -> 93 | Q54: 출처 기반 자체 검토 / 독립 승인 전
A55: 910054 | B55: 3 | C55: dk-weathering | D55: 2 | E55: Why survey Dokdo over several years? | F55: To rename the islands yearly | G55: To force the rock count to increase | H55: To track coastal and rock changes | I55: 3 | J55: Dokdo’s rocks weather and erode under exposure to wind and waves, making continued monitoring valuable. | K55: The selected option, “To rename the islands yearly”, does not fit. The answer is “To track coastal and rock changes”. Dokdo’s rocks weather and erode under exposure to wind and waves, making continued monitoring valuable. | L55: The selected option, “To force the rock count to increase”, does not fit. The answer is “To track coastal and rock changes”. Dokdo’s rocks weather and erode under exposure to wind and waves, making continued monitoring valuable. | M55: Dokdo’s rocks weather and erode under exposure to wind and waves, making continued monitoring valuable. | O55: https://www.dokdo.re.kr/home/cms/cmsCont.do?cntnts_sn=66 | P55: =LEN(E55)+MAX(LEN(F55),LEN(G55),LEN(H55)) -> 71 | Q55: 출처 기반 자체 검토 / 독립 승인 전
A56: 910055 | B56: 3 | C56: dk-weathering | D56: 3 | E56: Which data best support a comparison of terrain change? | F56: A table listing only nicknames | G56: Repeated surveys with aligned references | H56: One undated drawing | I56: 2 | J56: Dokdo’s rocks weather and erode under exposure to wind and waves, making continued monitoring valuable. | K56: The selected option, “A table listing only nicknames”, does not fit. The answer is “Repeated surveys with aligned references”. Dokdo’s rocks weather and erode under exposure to wind and waves, making continued monitoring valuable. | L56: Dokdo’s rocks weather and erode under exposure to wind and waves, making continued monitoring valuable. | M56: The selected option, “One undated drawing”, does not fit. The answer is “Repeated surveys with aligned references”. Dokdo’s rocks weather and erode under exposure to wind and waves, making continued monitoring valuable. | N56: Dokdo terrain studies observe rockfall, soil loss and coastal change. Repeated surveys help when they use consistent references. | O56: https://www.dokdo.re.kr/home/cms/cmsCont.do?cntnts_sn=66 | P56: =LEN(E56)+MAX(LEN(F56),LEN(G56),LEN(H56)) -> 95 | Q56: 출처 기반 자체 검토 / 독립 승인 전
A57: 910056 | B57: 3 | C57: dk-weathering | D57: 4 | E57: Can every difference between two photos be called rockfall? | F57: Compare viewpoints and dates first | G57: Viewpoint is irrelevant for Dokdo photos | H57: Every shadow is rockfall | I57: 1 | J57: Dokdo’s rocks weather and erode under exposure to wind and waves, making continued monitoring valuable. | K57: Dokdo’s rocks weather and erode under exposure to wind and waves, making continued monitoring valuable. | L57: The selected option, “Viewpoint is irrelevant for Dokdo photos”, does not fit. The answer is “Compare viewpoints and dates first”. Dokdo’s rocks weather and erode under exposure to wind and waves, making continued monitoring valuable. | M57: The selected option, “Every shadow is rockfall”, does not fit. The answer is “Compare viewpoints and dates first”. Dokdo’s rocks weather and erode under exposure to wind and waves, making continued monitoring valuable. | N57: Dokdo terrain studies observe rockfall, soil loss and coastal change. Repeated surveys help when they use consistent references. | O57: https://www.dokdo.re.kr/home/cms/cmsCont.do?cntnts_sn=66 | P57: =LEN(E57)+MAX(LEN(F57),LEN(G57),LEN(H57)) -> 99 | Q57: 출처 기반 자체 검토 / 독립 승인 전
A58: 910057 | B58: 3 | C58: dk-mulgol | D58: 1 | E58: Which main island contains Mulgol? | F58: Dongdo | G58: Ulleungdo | H58: Seodo | I58: 3 | J58: Mulgol on Seodo contains dripping water and was used as a water source before desalination facilities. | K58: The selected option, “Dongdo”, does not fit. The answer is “Seodo”. Mulgol on Seodo contains dripping water and was used as a water source before desalination facilities. | L58: The selected option, “Ulleungdo”, does not fit. The answer is “Seodo”. Mulgol on Seodo contains dripping water and was used as a water source before desalination facilities. | M58: Mulgol on Seodo contains dripping water and was used as a water source before desalination facilities. | O58: https://www.dokdo.re.kr/home/cms/cmsCont.do?cntnts_sn=66 | P58: =LEN(E58)+MAX(LEN(F58),LEN(G58),LEN(H58)) -> 43 | Q58: 출처 기반 자체 검토 / 독립 승인 전
A59: 910058 | B59: 3 | C59: dk-mulgol | D59: 2 | E59: How was Mulgol linked to earlier life on Dokdo? | F59: A navigation lighthouse | G59: A place to obtain water | H59: A helipad | I59: 2 | J59: Mulgol on Seodo contains dripping water and was used as a water source before desalination facilities. | K59: The selected option, “A navigation lighthouse”, does not fit. The answer is “A place to obtain water”. Mulgol on Seodo contains dripping water and was used as a water source before desalination facilities. | L59: Mulgol on Seodo contains dripping water and was used as a water source before desalination facilities. | M59: The selected option, “A helipad”, does not fit. The answer is “A place to obtain water”. Mulgol on Seodo contains dripping water and was used as a water source before desalination facilities. | O59: https://www.dokdo.re.kr/home/cms/cmsCont.do?cntnts_sn=66 | P59: =LEN(E59)+MAX(LEN(F59),LEN(G59),LEN(H59)) -> 70 | Q59: 출처 기반 자체 검토 / 독립 승인 전
A60: 910059 | B60: 3 | C60: dk-mulgol | D60: 3 | E60: Which role of Mulgol is supported by the source? | F60: A water source before desalination facilities | G60: The sole present source of all water | H60: An airfield fuel store | I60: 1 | J60: Mulgol on Seodo contains dripping water and was used as a water source before desalination facilities. | K60: Mulgol on Seodo contains dripping water and was used as a water source before desalination facilities. | L60: The selected option, “The sole present source of all water”, does not fit. The answer is “A water source before desalination facilities”. Mulgol on Seodo contains dripping water and was used as a water source before desalination facilities. | M60: The selected option, “An airfield fuel store”, does not fit. The answer is “A water source before desalination facilities”. Mulgol on Seodo contains dripping water and was used as a water source before desalination facilities. | N60: KIOST describes Mulgol as a cave on Seodo’s northwestern coast whose dripping water was used before desalination facilities were installed. | O60: https://www.dokdo.re.kr/home/cms/cmsCont.do?cntnts_sn=66 | P60: =LEN(E60)+MAX(LEN(F60),LEN(G60),LEN(H60)) -> 93 | Q60: 출처 기반 자체 검토 / 독립 승인 전
A61: 910060 | B61: 3 | C61: dk-mulgol | D61: 4 | E61: Evaluate a claim that Mulgol is still the only water source. | F61: Past use proves present exclusivity | G61: Desalination has no relation to drinking water | H61: It extends a past role into the present and needs checking | I61: 3 | J61: Mulgol on Seodo contains dripping water and was used as a water source before desalination facilities. | K61: The selected option, “Past use proves present exclusivity”, does not fit. The answer is “It extends a past role into the present and needs checking”. Mulgol on Seodo contains dripping water and was used as a water source before desalination facilities. | L61: The selected option, “Desalination has no relation to drinking water”, does not fit. The answer is “It extends a past role into the present and needs checking”. Mulgol on Seodo contains dripping water and was used as a water source before desalination facilities. | M61: Mulgol on Seodo contains dripping water and was used as a water source before desalination facilities. | N61: KIOST describes Mulgol as a cave on Seodo’s northwestern coast whose dripping water was used before desalination facilities were installed. | O61: https://www.dokdo.re.kr/home/cms/cmsCont.do?cntnts_sn=66 | P61: =LEN(E61)+MAX(LEN(F61),LEN(G61),LEN(H61)) -> 118 | Q61: 출처 기반 자체 검토 / 독립 승인 전
A62: 910061 | B62: 4 | C62: dk-migratory-stopover | D62: 1 | E62: What role can Dokdo play for migrating birds? | F62: A freshwater lake | G62: A resting stopover | H62: An inland rice field | I62: 2 | J62: Dokdo is also a place where migrating birds can stop and rest. | K62: The selected option, “A freshwater lake”, does not fit. The answer is “A resting stopover”. Dokdo is also a place where migrating birds can stop and rest. | L62: Dokdo is also a place where migrating birds can stop and rest. | M62: The selected option, “An inland rice field”, does not fit. The answer is “A resting stopover”. Dokdo is also a place where migrating birds can stop and rest. | O62: https://dokdo.mofa.go.kr/kor/introduce/nature.jsp | P62: =LEN(E62)+MAX(LEN(F62),LEN(G62),LEN(H62)) -> 65 | Q62: 출처 기반 자체 검토 / 독립 승인 전
A63: 910062 | B63: 4 | C63: dk-migratory-stopover | D63: 2 | E63: What makes Dokdo a stopover? | F63: An island visited during a longer journey | G63: An island no bird ever leaves | H63: An island connected to the mainland by road | I63: 1 | J63: Dokdo is also a place where migrating birds can stop and rest. | K63: Dokdo is also a place where migrating birds can stop and rest. | L63: The selected option, “An island no bird ever leaves”, does not fit. The answer is “An island visited during a longer journey”. Dokdo is also a place where migrating birds can stop and rest. | M63: The selected option, “An island connected to the mainland by road”, does not fit. The answer is “An island visited during a longer journey”. Dokdo is also a place where migrating birds can stop and rest. | O63: https://dokdo.mofa.go.kr/kor/introduce/nature.jsp | P63: =LEN(E63)+MAX(LEN(F63),LEN(G63),LEN(H63)) -> 71 | Q63: 출처 기반 자체 검토 / 독립 승인 전
A64: 910063 | B64: 4 | C64: dk-migratory-stopover | D64: 3 | E64: What ecological value does the source describe? | F64: It is every migratory bird’s final destination | G64: Migrating birds feed only on Dokdo | H64: It provides a resting place during migration | I64: 3 | J64: Dokdo is also a place where migrating birds can stop and rest. | K64: The selected option, “It is every migratory bird’s final destination”, does not fit. The answer is “It provides a resting place during migration”. Dokdo is also a place where migrating birds can stop and rest. | L64: The selected option, “Migrating birds feed only on Dokdo”, does not fit. The answer is “It provides a resting place during migration”. Dokdo is also a place where migrating birds can stop and rest. | M64: Dokdo is also a place where migrating birds can stop and rest. | N64: MOFA describes Dokdo as a refuge and resting place along migratory routes. It does not say every bird stays for the same duration. | O64: https://dokdo.mofa.go.kr/kor/introduce/nature.jsp | P64: =LEN(E64)+MAX(LEN(F64),LEN(G64),LEN(H64)) -> 93 | Q64: 출처 기반 자체 검토 / 독립 승인 전
A65: 910064 | B65: 4 | C65: dk-migratory-stopover | D65: 4 | E65: Evaluate “Every bird visiting Dokdo breeds there.” | F65: A temporary visitor cannot be migratory | G65: It needs evidence distinguishing stopover from breeding | H65: The stopover description alone proves it | I65: 2 | J65: Dokdo is also a place where migrating birds can stop and rest. | K65: The selected option, “A temporary visitor cannot be migratory”, does not fit. The answer is “It needs evidence distinguishing stopover from breeding”. Dokdo is also a place where migrating birds can stop and rest. | L65: Dokdo is also a place where migrating birds can stop and rest. | M65: The selected option, “The stopover description alone proves it”, does not fit. The answer is “It needs evidence distinguishing stopover from breeding”. Dokdo is also a place where migrating birds can stop and rest. | N65: MOFA describes Dokdo as a refuge and resting place along migratory routes. It does not say every bird stays for the same duration. | O65: https://dokdo.mofa.go.kr/kor/introduce/nature.jsp | P65: =LEN(E65)+MAX(LEN(F65),LEN(G65),LEN(H65)) -> 105 | Q65: 출처 기반 자체 검토 / 독립 승인 전
A66: 910065 | B66: 4 | C66: dk-breeding-birds | D66: 1 | E66: Which is a seabird that breeds on Dokdo? | F66: Black-tailed gull | G66: Only the tree sparrow | H66: Only city pigeons | I66: 1 | J66: Seabirds including black-tailed gulls, storm petrels and streaked shearwaters breed on Dokdo. Breeding means producing and raising young. | K66: Seabirds including black-tailed gulls, storm petrels and streaked shearwaters breed on Dokdo. Breeding means producing and raising young. | L66: The selected option, “Only the tree sparrow”, does not fit. The answer is “Black-tailed gull”. Seabirds including black-tailed gulls, storm petrels and streaked shearwaters breed on Dokdo. Breeding means producing and raising young. | M66: The selected option, “Only city pigeons”, does not fit. The answer is “Black-tailed gull”. Seabirds including black-tailed gulls, storm petrels and streaked shearwaters breed on Dokdo. Breeding means producing and raising young. | O66: https://www.heritage.go.kr/heri/cul/culSelectDetail.do?VdkVgwKey=16%2C03360000%2C37&pageNo=1_1_2_0 | P66: =LEN(E66)+MAX(LEN(F66),LEN(G66),LEN(H66)) -> 61 | Q66: 출처 기반 자체 검토 / 독립 승인 전
A67: 910066 | B67: 4 | C67: dk-breeding-birds | D67: 2 | E67: What does it mean that Dokdo is a breeding area? | F67: A place birds only fly past | G67: A building displaying bird names | H67: A place to produce and raise young | I67: 3 | J67: Seabirds including black-tailed gulls, storm petrels and streaked shearwaters breed on Dokdo. Breeding means producing and raising young. | K67: The selected option, “A place birds only fly past”, does not fit. The answer is “A place to produce and raise young”. Seabirds including black-tailed gulls, storm petrels and streaked shearwaters breed on Dokdo. Breeding means producing and raising young. | L67: The selected option, “A building displaying bird names”, does not fit. The answer is “A place to produce and raise young”. Seabirds including black-tailed gulls, storm petrels and streaked shearwaters breed on Dokdo. Breeding means producing and raising young. | M67: Seabirds including black-tailed gulls, storm petrels and streaked shearwaters breed on Dokdo. Breeding means producing and raising young. | O67: https://www.heritage.go.kr/heri/cul/culSelectDetail.do?VdkVgwKey=16%2C03360000%2C37&pageNo=1_1_2_0 | P67: =LEN(E67)+MAX(LEN(F67),LEN(G67),LEN(H67)) -> 82 | Q67: 출처 기반 자체 검토 / 독립 승인 전
A68: 910067 | B68: 4 | C68: dk-breeding-birds | D68: 3 | E68: Which observation more directly indicates breeding? | F68: One photograph of an empty rock | G68: Nests and behaviour tending young | H68: One bird passing overhead | I68: 2 | J68: Seabirds including black-tailed gulls, storm petrels and streaked shearwaters breed on Dokdo. Breeding means producing and raising young. | K68: The selected option, “One photograph of an empty rock”, does not fit. The answer is “Nests and behaviour tending young”. Seabirds including black-tailed gulls, storm petrels and streaked shearwaters breed on Dokdo. Breeding means producing and raising young. | L68: Seabirds including black-tailed gulls, storm petrels and streaked shearwaters breed on Dokdo. Breeding means producing and raising young. | M68: The selected option, “One bird passing overhead”, does not fit. The answer is “Nests and behaviour tending young”. Seabirds including black-tailed gulls, storm petrels and streaked shearwaters breed on Dokdo. Breeding means producing and raising young. | N68: The heritage description identifies Dokdo as a breeding area for storm petrels, streaked shearwaters and black-tailed gulls. Breeding is more specific than a single sighting. | O68: https://www.heritage.go.kr/heri/cul/culSelectDetail.do?VdkVgwKey=16%2C03360000%2C37&pageNo=1_1_2_0 | P68: =LEN(E68)+MAX(LEN(F68),LEN(G68),LEN(H68)) -> 84 | Q68: 출처 기반 자체 검토 / 독립 승인 전
A69: 910068 | B69: 4 | C69: dk-breeding-birds | D69: 4 | E69: Can one photo of a passing bird establish a breeding site? | F69: Additional nesting or breeding evidence is needed | G69: Visible wings establish breeding | H69: A named species always breeds wherever it is seen | I69: 1 | J69: Seabirds including black-tailed gulls, storm petrels and streaked shearwaters breed on Dokdo. Breeding means producing and raising young. | K69: Seabirds including black-tailed gulls, storm petrels and streaked shearwaters breed on Dokdo. Breeding means producing and raising young. | L69: The selected option, “Visible wings establish breeding”, does not fit. The answer is “Additional nesting or breeding evidence is needed”. Seabirds including black-tailed gulls, storm petrels and streaked shearwaters breed on Dokdo. Breeding means producing and raising young. | M69: The selected option, “A named species always breeds wherever it is seen”, does not fit. The answer is “Additional nesting or breeding evidence is needed”. Seabirds including black-tailed gulls, storm petrels and streaked shearwaters breed on Dokdo. Breeding means producing and raising young. | N69: The heritage description identifies Dokdo as a breeding area for storm petrels, streaked shearwaters and black-tailed gulls. Breeding is more specific than a single sighting. | O69: https://www.heritage.go.kr/heri/cul/culSelectDetail.do?VdkVgwKey=16%2C03360000%2C37&pageNo=1_1_2_0 | P69: =LEN(E69)+MAX(LEN(F69),LEN(G69),LEN(H69)) -> 107 | Q69: 출처 기반 자체 검토 / 독립 승인 전
A70: 910069 | B70: 4 | C70: dk-birds-and-seaweed | D70: 1 | E70: Which is a seabird rather than a seaweed? | F70: Kelp | G70: Laver | H70: Black-tailed gull | I70: 3 | J70: Dokdo has both seabirds and seaweeds such as wakame. Similar-sounding Korean terms can refer to different organisms. | K70: The selected option, “Kelp”, does not fit. The answer is “Black-tailed gull”. Dokdo has both seabirds and seaweeds such as wakame. Similar-sounding Korean terms can refer to different organisms. | L70: The selected option, “Laver”, does not fit. The answer is “Black-tailed gull”. Dokdo has both seabirds and seaweeds such as wakame. Similar-sounding Korean terms can refer to different organisms. | M70: Dokdo has both seabirds and seaweeds such as wakame. Similar-sounding Korean terms can refer to different organisms. | O70: https://www.heritage.go.kr/heri/cul/culSelectDetail.do?VdkVgwKey=16%2C03360000%2C37&pageNo=1_1_2_0 https://dokdo.mofa.go.kr/kor/introduce/nature.jsp | P70: =LEN(E70)+MAX(LEN(F70),LEN(G70),LEN(H70)) -> 58 | Q70: 출처 기반 자체 검토 / 독립 승인 전
A71: 910070 | B71: 4 | C71: dk-birds-and-seaweed | D71: 2 | E71: Which classification is correct? | F71: Both are fish | G71: Gull = bird; wakame = seaweed | H71: Gull = seaweed; wakame = bird | I71: 2 | J71: Dokdo has both seabirds and seaweeds such as wakame. Similar-sounding Korean terms can refer to different organisms. | K71: The selected option, “Both are fish”, does not fit. The answer is “Gull = bird; wakame = seaweed”. Dokdo has both seabirds and seaweeds such as wakame. Similar-sounding Korean terms can refer to different organisms. | L71: Dokdo has both seabirds and seaweeds such as wakame. Similar-sounding Korean terms can refer to different organisms. | M71: The selected option, “Gull = seaweed; wakame = bird”, does not fit. The answer is “Gull = bird; wakame = seaweed”. Dokdo has both seabirds and seaweeds such as wakame. Similar-sounding Korean terms can refer to different organisms. | O71: https://www.heritage.go.kr/heri/cul/culSelectDetail.do?VdkVgwKey=16%2C03360000%2C37&pageNo=1_1_2_0 https://dokdo.mofa.go.kr/kor/introduce/nature.jsp | P71: =LEN(E71)+MAX(LEN(F71),LEN(G71),LEN(H71)) -> 61 | Q71: 출처 기반 자체 검토 / 독립 승인 전
A72: 910071 | B72: 4 | C72: dk-birds-and-seaweed | D72: 3 | E72: What does 海鳥類 refer to in the supplied source? | F72: Seabirds | G72: Seaweeds | H72: Coastal rocks | I72: 1 | J72: Dokdo has both seabirds and seaweeds such as wakame. Similar-sounding Korean terms can refer to different organisms. | K72: Dokdo has both seabirds and seaweeds such as wakame. Similar-sounding Korean terms can refer to different organisms. | L72: The selected option, “Seaweeds”, does not fit. The answer is “Seabirds”. Dokdo has both seabirds and seaweeds such as wakame. Similar-sounding Korean terms can refer to different organisms. | M72: The selected option, “Coastal rocks”, does not fit. The answer is “Seabirds”. Dokdo has both seabirds and seaweeds such as wakame. Similar-sounding Korean terms can refer to different organisms. | N72: In the heritage description, haejoryu written 海鳥類 means seabirds; 海藻類 means seaweeds. A black-tailed gull is a bird, while wakame is a seaweed. | O72: https://www.heritage.go.kr/heri/cul/culSelectDetail.do?VdkVgwKey=16%2C03360000%2C37&pageNo=1_1_2_0 https://dokdo.mofa.go.kr/kor/introduce/nature.jsp | P72: =LEN(E72)+MAX(LEN(F72),LEN(G72),LEN(H72)) -> 59 | Q72: 출처 기반 자체 검토 / 독립 승인 전
A73: 910072 | B73: 4 | C73: dk-birds-and-seaweed | D73: 4 | E73: What if the historic term is read only as a seaweed habitat? | F73: The same pronunciation means the same organisms | G73: Wakame’s presence makes the original meaning irrelevant | H73: Check the characters and context for seabirds | I73: 3 | J73: Dokdo has both seabirds and seaweeds such as wakame. Similar-sounding Korean terms can refer to different organisms. | K73: The selected option, “The same pronunciation means the same organisms”, does not fit. The answer is “Check the characters and context for seabirds”. Dokdo has both seabirds and seaweeds such as wakame. Similar-sounding Korean terms can refer to different organisms. | L73: The selected option, “Wakame’s presence makes the original meaning irrelevant”, does not fit. The answer is “Check the characters and context for seabirds”. Dokdo has both seabirds and seaweeds such as wakame. Similar-sounding Korean terms can refer to different organisms. | M73: Dokdo has both seabirds and seaweeds such as wakame. Similar-sounding Korean terms can refer to different organisms. | N73: In the heritage description, haejoryu written 海鳥類 means seabirds; 海藻類 means seaweeds. A black-tailed gull is a bird, while wakame is a seaweed. | O73: https://www.heritage.go.kr/heri/cul/culSelectDetail.do?VdkVgwKey=16%2C03360000%2C37&pageNo=1_1_2_0 https://dokdo.mofa.go.kr/kor/introduce/nature.jsp | P73: =LEN(E73)+MAX(LEN(F73),LEN(G73),LEN(H73)) -> 115 | Q73: 출처 기반 자체 검토 / 독립 승인 전
A74: 910073 | B74: 4 | C74: dk-coastal-plants | D74: 1 | E74: Which is an example of a land plant on Dokdo? | F74: Kelp | G74: Seaside daisy | H74: Wakame | I74: 2 | J74: Land plants recorded on Dokdo include seaside daisy, island stonecrop and rock stonecrop. Land and marine life together reveal its diversity. | K74: The selected option, “Kelp”, does not fit. The answer is “Seaside daisy”. Land plants recorded on Dokdo include seaside daisy, island stonecrop and rock stonecrop. Land and marine life together reveal its diversity. | L74: Land plants recorded on Dokdo include seaside daisy, island stonecrop and rock stonecrop. Land and marine life together reveal its diversity. | M74: The selected option, “Wakame”, does not fit. The answer is “Seaside daisy”. Land plants recorded on Dokdo include seaside daisy, island stonecrop and rock stonecrop. Land and marine life together reveal its diversity. | O74: https://dokdo.mofa.go.kr/kor/introduce/nature.jsp | P74: =LEN(E74)+MAX(LEN(F74),LEN(G74),LEN(H74)) -> 58 | Q74: 출처 기반 자체 검토 / 독립 승인 전
A75: 910074 | B75: 4 | C75: dk-coastal-plants | D75: 2 | E75: Which habitat pairing is appropriate? | F75: Daisy on land; wakame in the sea | G75: Daisy in the sea; wakame on land | H75: Both only inside the lighthouse | I75: 1 | J75: Land plants recorded on Dokdo include seaside daisy, island stonecrop and rock stonecrop. Land and marine life together reveal its diversity. | K75: Land plants recorded on Dokdo include seaside daisy, island stonecrop and rock stonecrop. Land and marine life together reveal its diversity. | L75: The selected option, “Daisy in the sea; wakame on land”, does not fit. The answer is “Daisy on land; wakame in the sea”. Land plants recorded on Dokdo include seaside daisy, island stonecrop and rock stonecrop. Land and marine life together reveal its diversity. | M75: The selected option, “Both only inside the lighthouse”, does not fit. The answer is “Daisy on land; wakame in the sea”. Land plants recorded on Dokdo include seaside daisy, island stonecrop and rock stonecrop. Land and marine life together reveal its diversity. | O75: https://dokdo.mofa.go.kr/kor/introduce/nature.jsp | P75: =LEN(E75)+MAX(LEN(F75),LEN(G75),LEN(H75)) -> 69 | Q75: 출처 기반 자체 검토 / 독립 승인 전
A76: 910075 | B76: 4 | C76: dk-coastal-plants | D76: 3 | E76: What do the two lists show together? | F76: All Dokdo plants are types of wakame | G76: Dokdo has no land plants | H76: Dokdo has terrestrial plants and seaweeds | I76: 3 | J76: Land plants recorded on Dokdo include seaside daisy, island stonecrop and rock stonecrop. Land and marine life together reveal its diversity. | K76: The selected option, “All Dokdo plants are types of wakame”, does not fit. The answer is “Dokdo has terrestrial plants and seaweeds”. Land plants recorded on Dokdo include seaside daisy, island stonecrop and rock stonecrop. Land and marine life together reveal its diversity. | L76: The selected option, “Dokdo has no land plants”, does not fit. The answer is “Dokdo has terrestrial plants and seaweeds”. Land plants recorded on Dokdo include seaside daisy, island stonecrop and rock stonecrop. Land and marine life together reveal its diversity. | M76: Land plants recorded on Dokdo include seaside daisy, island stonecrop and rock stonecrop. Land and marine life together reveal its diversity. | N76: MOFA lists terrestrial plants including seaside daisy and stonecrops, and marine seaweeds including wakame, kelp and laver. Absence from this short list does not prove absence from Dokdo. | O76: https://dokdo.mofa.go.kr/kor/introduce/nature.jsp | P76: =LEN(E76)+MAX(LEN(F76),LEN(G76),LEN(H76)) -> 77 | Q76: 출처 기반 자체 검토 / 독립 승인 전
A77: 910076 | B77: 4 | C77: dk-coastal-plants | D77: 4 | E77: Does omission from this short list establish absence? | F77: A flower photo implies every plant species is present | G77: Check a full survey and its date | H77: The few examples necessarily form a complete inventory | I77: 2 | J77: Land plants recorded on Dokdo include seaside daisy, island stonecrop and rock stonecrop. Land and marine life together reveal its diversity. | K77: The selected option, “A flower photo implies every plant species is present”, does not fit. The answer is “Check a full survey and its date”. Land plants recorded on Dokdo include seaside daisy, island stonecrop and rock stonecrop. Land and marine life together reveal its diversity. | L77: Land plants recorded on Dokdo include seaside daisy, island stonecrop and rock stonecrop. Land and marine life together reveal its diversity. | M77: The selected option, “The few examples necessarily form a complete inventory”, does not fit. The answer is “Check a full survey and its date”. Land plants recorded on Dokdo include seaside daisy, island stonecrop and rock stonecrop. Land and marine life together reveal its diversity. | N77: MOFA lists terrestrial plants including seaside daisy and stonecrops, and marine seaweeds including wakame, kelp and laver. Absence from this short list does not prove absence from Dokdo. | O77: https://dokdo.mofa.go.kr/kor/introduce/nature.jsp | P77: =LEN(E77)+MAX(LEN(F77),LEN(G77),LEN(H77)) -> 107 | Q77: 출처 기반 자체 검토 / 독립 승인 전
A78: 910077 | B78: 4 | C78: dk-reserve-scope | D78: 1 | E78: What is an appropriate conservation focus on Dokdo? | F78: Birds, plants and landforms | G78: Only the lighthouse colour | H78: Only vessel names | I78: 1 | J78: Dokdo’s conservation value includes seabirds, plants, marine organisms and volcanic geology. | K78: Dokdo’s conservation value includes seabirds, plants, marine organisms and volcanic geology. | L78: The selected option, “Only the lighthouse colour”, does not fit. The answer is “Birds, plants and landforms”. Dokdo’s conservation value includes seabirds, plants, marine organisms and volcanic geology. | M78: The selected option, “Only vessel names”, does not fit. The answer is “Birds, plants and landforms”. Dokdo’s conservation value includes seabirds, plants, marine organisms and volcanic geology. | O78: https://www.heritage.go.kr/heri/cul/culSelectDetail.do?VdkVgwKey=16%2C03360000%2C37&pageNo=1_1_2_0 | P78: =LEN(E78)+MAX(LEN(F78),LEN(G78),LEN(H78)) -> 78 | Q78: 출처 기반 자체 검토 / 독립 승인 전
A79: 910078 | B79: 4 | C79: dk-reserve-scope | D79: 2 | E79: What is missed by describing protection only in terms of seabirds? | F79: It means no organisms live in the sea | G79: It makes the island names identical | H79: Plant and geological value is missed | I79: 3 | J79: Dokdo’s conservation value includes seabirds, plants, marine organisms and volcanic geology. | K79: The selected option, “It means no organisms live in the sea”, does not fit. The answer is “Plant and geological value is missed”. Dokdo’s conservation value includes seabirds, plants, marine organisms and volcanic geology. | L79: The selected option, “It makes the island names identical”, does not fit. The answer is “Plant and geological value is missed”. Dokdo’s conservation value includes seabirds, plants, marine organisms and volcanic geology. | M79: Dokdo’s conservation value includes seabirds, plants, marine organisms and volcanic geology. | O79: https://www.heritage.go.kr/heri/cul/culSelectDetail.do?VdkVgwKey=16%2C03360000%2C37&pageNo=1_1_2_0 | P79: =LEN(E79)+MAX(LEN(F79),LEN(G79),LEN(H79)) -> 103 | Q79: 출처 기반 자체 검토 / 독립 승인 전
A80: 910079 | B80: 4 | C80: dk-reserve-scope | D80: 3 | E80: Which summary best covers the reserve’s stated value? | F80: Only one day’s bird count | G80: Breeding sites, vegetation, marine life and volcanic landforms | H80: Port size and admission fees | I80: 2 | J80: Dokdo’s conservation value includes seabirds, plants, marine organisms and volcanic geology. | K80: The selected option, “Only one day’s bird count”, does not fit. The answer is “Breeding sites, vegetation, marine life and volcanic landforms”. Dokdo’s conservation value includes seabirds, plants, marine organisms and volcanic geology. | L80: Dokdo’s conservation value includes seabirds, plants, marine organisms and volcanic geology. | M80: The selected option, “Port size and admission fees”, does not fit. The answer is “Breeding sites, vegetation, marine life and volcanic landforms”. Dokdo’s conservation value includes seabirds, plants, marine organisms and volcanic geology. | N80: The heritage account explains the Dokdo natural reserve in terms of seabird breeding, volcanic geology, distinctive plants and marine life. | O80: https://www.heritage.go.kr/heri/cul/culSelectDetail.do?VdkVgwKey=16%2C03360000%2C37&pageNo=1_1_2_0 | P80: =LEN(E80)+MAX(LEN(F80),LEN(G80),LEN(H80)) -> 115 | Q80: 출처 기반 자체 검토 / 독립 승인 전
A81: 910080 | B81: 4 | C81: dk-reserve-scope | D81: 4 | E81: What is wrong with judging its conservation value only by visitor numbers? | F81: It omits the ecological and geological values described | G81: Few visitors necessarily mean no geological value | H81: Visitor count equals breeding bird count | I81: 1 | J81: Dokdo’s conservation value includes seabirds, plants, marine organisms and volcanic geology. | K81: Dokdo’s conservation value includes seabirds, plants, marine organisms and volcanic geology. | L81: The selected option, “Few visitors necessarily mean no geological value”, does not fit. The answer is “It omits the ecological and geological values described”. Dokdo’s conservation value includes seabirds, plants, marine organisms and volcanic geology. | M81: The selected option, “Visitor count equals breeding bird count”, does not fit. The answer is “It omits the ecological and geological values described”. Dokdo’s conservation value includes seabirds, plants, marine organisms and volcanic geology. | N81: The heritage account explains the Dokdo natural reserve in terms of seabird breeding, volcanic geology, distinctive plants and marine life. | O81: https://www.heritage.go.kr/heri/cul/culSelectDetail.do?VdkVgwKey=16%2C03360000%2C37&pageNo=1_1_2_0 | P81: =LEN(E81)+MAX(LEN(F81),LEN(G81),LEN(H81)) -> 129 | Q81: 출처 기반 자체 검토 / 독립 승인 전
A82: 910081 | B82: 5 | C82: dk-sea-forest | D82: 1 | E82: Which organisms form underwater forests around Dokdo? | F82: Seaside daisy and rock stonecrop | G82: Gulls and shearwaters | H82: Ecklonia and Eisenia seaweeds | I82: 3 | J82: Seaweeds such as Ecklonia cava and Eisenia bicyclis form underwater forests around Dokdo. Rock crevices also support organisms. | K82: The selected option, “Seaside daisy and rock stonecrop”, does not fit. The answer is “Ecklonia and Eisenia seaweeds”. Seaweeds such as Ecklonia cava and Eisenia bicyclis form underwater forests around Dokdo. Rock crevices also support organisms. | L82: The selected option, “Gulls and shearwaters”, does not fit. The answer is “Ecklonia and Eisenia seaweeds”. Seaweeds such as Ecklonia cava and Eisenia bicyclis form underwater forests around Dokdo. Rock crevices also support organisms. | M82: Seaweeds such as Ecklonia cava and Eisenia bicyclis form underwater forests around Dokdo. Rock crevices also support organisms. | O82: https://www.dokdo.re.kr/home/cms/cmsCont.do?cntnts_sn=87 | P82: =LEN(E82)+MAX(LEN(F82),LEN(G82),LEN(H82)) -> 85 | Q82: 출처 기반 자체 검토 / 독립 승인 전
A83: 910082 | B83: 5 | C83: dk-sea-forest | D83: 2 | E83: Which organisms are linked to Dokdo’s rock crevices? | F83: Only terrestrial trees | G83: Barnacles and mussels | H83: Only people by the lighthouse | I83: 2 | J83: Seaweeds such as Ecklonia cava and Eisenia bicyclis form underwater forests around Dokdo. Rock crevices also support organisms. | K83: The selected option, “Only terrestrial trees”, does not fit. The answer is “Barnacles and mussels”. Seaweeds such as Ecklonia cava and Eisenia bicyclis form underwater forests around Dokdo. Rock crevices also support organisms. | L83: Seaweeds such as Ecklonia cava and Eisenia bicyclis form underwater forests around Dokdo. Rock crevices also support organisms. | M83: The selected option, “Only people by the lighthouse”, does not fit. The answer is “Barnacles and mussels”. Seaweeds such as Ecklonia cava and Eisenia bicyclis form underwater forests around Dokdo. Rock crevices also support organisms. | O83: https://www.dokdo.re.kr/home/cms/cmsCont.do?cntnts_sn=87 | P83: =LEN(E83)+MAX(LEN(F83),LEN(G83),LEN(H83)) -> 81 | Q83: 출처 기반 자체 검토 / 독립 승인 전
A84: 910083 | B84: 5 | C84: dk-sea-forest | D84: 3 | E84: What habitat does the source discuss alongside seaweed forests? | F84: Rock crevices supporting diverse organisms | G84: An entirely lifeless seabed | H84: Ulleungdo’s rice fields | I84: 1 | J84: Seaweeds such as Ecklonia cava and Eisenia bicyclis form underwater forests around Dokdo. Rock crevices also support organisms. | K84: Seaweeds such as Ecklonia cava and Eisenia bicyclis form underwater forests around Dokdo. Rock crevices also support organisms. | L84: The selected option, “An entirely lifeless seabed”, does not fit. The answer is “Rock crevices supporting diverse organisms”. Seaweeds such as Ecklonia cava and Eisenia bicyclis form underwater forests around Dokdo. Rock crevices also support organisms. | M84: The selected option, “Ulleungdo’s rice fields”, does not fit. The answer is “Rock crevices supporting diverse organisms”. Seaweeds such as Ecklonia cava and Eisenia bicyclis form underwater forests around Dokdo. Rock crevices also support organisms. | N84: KIOST describes Dokdo’s seaweed forests and organisms such as barnacles, mussels, crabs and snails in rocky habitats. | O84: https://www.dokdo.re.kr/home/cms/cmsCont.do?cntnts_sn=87 | P84: =LEN(E84)+MAX(LEN(F84),LEN(G84),LEN(H84)) -> 105 | Q84: 출처 기반 자체 검토 / 독립 승인 전
A85: 910084 | B85: 5 | C85: dk-sea-forest | D85: 4 | E85: What is lost by describing the forest as one kind of wakame? | F85: The meaning of the word wakame itself | G85: Only the maximum island elevations | H85: The diversity of seaweeds and habitats in the source | I85: 3 | J85: Seaweeds such as Ecklonia cava and Eisenia bicyclis form underwater forests around Dokdo. Rock crevices also support organisms. | K85: The selected option, “The meaning of the word wakame itself”, does not fit. The answer is “The diversity of seaweeds and habitats in the source”. Seaweeds such as Ecklonia cava and Eisenia bicyclis form underwater forests around Dokdo. Rock crevices also support organisms. | L85: The selected option, “Only the maximum island elevations”, does not fit. The answer is “The diversity of seaweeds and habitats in the source”. Seaweeds such as Ecklonia cava and Eisenia bicyclis form underwater forests around Dokdo. Rock crevices also support organisms. | M85: Seaweeds such as Ecklonia cava and Eisenia bicyclis form underwater forests around Dokdo. Rock crevices also support organisms. | N85: KIOST describes Dokdo’s seaweed forests and organisms such as barnacles, mussels, crabs and snails in rocky habitats. | O85: https://www.dokdo.re.kr/home/cms/cmsCont.do?cntnts_sn=87 | P85: =LEN(E85)+MAX(LEN(F85),LEN(G85),LEN(H85)) -> 112 | Q85: 출처 기반 자체 검토 / 독립 승인 전
A86: 910085 | B86: 5 | C86: dk-water-mixing | D86: 1 | E86: Which flows meet around Dokdo? | F86: Two sand roads | G86: Warm and cold currents | H86: Only two freshwater rivers | I86: 2 | J86: Warm and cold currents mix around Dokdo. Water movement also affects the supply of nutrients used by organisms. | K86: The selected option, “Two sand roads”, does not fit. The answer is “Warm and cold currents”. Warm and cold currents mix around Dokdo. Water movement also affects the supply of nutrients used by organisms. | L86: Warm and cold currents mix around Dokdo. Water movement also affects the supply of nutrients used by organisms. | M86: The selected option, “Only two freshwater rivers”, does not fit. The answer is “Warm and cold currents”. Warm and cold currents mix around Dokdo. Water movement also affects the supply of nutrients used by organisms. | O86: https://www.dokdo.re.kr/home/cms/cmsCont.do?cntnts_sn=82 | P86: =LEN(E86)+MAX(LEN(F86),LEN(G86),LEN(H86)) -> 56 | Q86: 출처 기반 자체 검토 / 독립 승인 전
A87: 910086 | B87: 5 | C87: dk-water-mixing | D87: 2 | E87: What can vertical water mixing transport? | F87: Nutrients from deeper water | G87: Island names | H87: The lighthouse address | I87: 1 | J87: Warm and cold currents mix around Dokdo. Water movement also affects the supply of nutrients used by organisms. | K87: Warm and cold currents mix around Dokdo. Water movement also affects the supply of nutrients used by organisms. | L87: The selected option, “Island names”, does not fit. The answer is “Nutrients from deeper water”. Warm and cold currents mix around Dokdo. Water movement also affects the supply of nutrients used by organisms. | M87: The selected option, “The lighthouse address”, does not fit. The answer is “Nutrients from deeper water”. Warm and cold currents mix around Dokdo. Water movement also affects the supply of nutrients used by organisms. | O87: https://www.dokdo.re.kr/home/cms/cmsCont.do?cntnts_sn=82 | P87: =LEN(E87)+MAX(LEN(F87),LEN(G87),LEN(H87)) -> 68 | Q87: 출처 기반 자체 검토 / 독립 승인 전
A88: 910087 | B88: 5 | C88: dk-water-mixing | D88: 3 | E88: Which sequence matches the island-effect explanation? | F88: Lighthouse lighting → renamed seaweeds | G88: Still surface water → increase in all life | H88: Water mixing → nutrients supplied above | I88: 3 | J88: Warm and cold currents mix around Dokdo. Water movement also affects the supply of nutrients used by organisms. | K88: The selected option, “Lighthouse lighting → renamed seaweeds”, does not fit. The answer is “Water mixing → nutrients supplied above”. Warm and cold currents mix around Dokdo. Water movement also affects the supply of nutrients used by organisms. | L88: The selected option, “Still surface water → increase in all life”, does not fit. The answer is “Water mixing → nutrients supplied above”. Warm and cold currents mix around Dokdo. Water movement also affects the supply of nutrients used by organisms. | M88: Warm and cold currents mix around Dokdo. Water movement also affects the supply of nutrients used by organisms. | N88: The island-effect account describes how wind and island topography influence water mixing, which can deliver nutrients from deeper water to the sunlit upper layer. | O88: https://www.dokdo.re.kr/home/cms/cmsCont.do?cntnts_sn=82 | P88: =LEN(E88)+MAX(LEN(F88),LEN(G88),LEN(H88)) -> 95 | Q88: 출처 기반 자체 검토 / 독립 승인 전
A89: 910088 | B89: 5 | C89: dk-water-mixing | D89: 4 | E89: Does the island effect mean conditions are always identical? | F89: Nutrients are unrelated to water movement | G89: Season, wind and current changes also matter | H89: Identical mixing occurs every day near an island | I89: 2 | J89: Warm and cold currents mix around Dokdo. Water movement also affects the supply of nutrients used by organisms. | K89: The selected option, “Nutrients are unrelated to water movement”, does not fit. The answer is “Season, wind and current changes also matter”. Warm and cold currents mix around Dokdo. Water movement also affects the supply of nutrients used by organisms. | L89: Warm and cold currents mix around Dokdo. Water movement also affects the supply of nutrients used by organisms. | M89: The selected option, “Identical mixing occurs every day near an island”, does not fit. The answer is “Season, wind and current changes also matter”. Warm and cold currents mix around Dokdo. Water movement also affects the supply of nutrients used by organisms. | N89: The island-effect account describes how wind and island topography influence water mixing, which can deliver nutrients from deeper water to the sunlit upper layer. | O89: https://www.dokdo.re.kr/home/cms/cmsCont.do?cntnts_sn=82 | P89: =LEN(E89)+MAX(LEN(F89),LEN(G89),LEN(H89)) -> 108 | Q89: 출처 기반 자체 검토 / 독립 승인 전
A90: 910089 | B90: 5 | C90: dk-food-links | D90: 1 | E90: Which tiny organisms help support the marine food web? | F90: Phytoplankton | G90: Seodo’s rock itself | H90: Lighthouse lamps | I90: 1 | J90: Phytoplankton support food relationships around Dokdo, including links to zooplankton and young fish. | K90: Phytoplankton support food relationships around Dokdo, including links to zooplankton and young fish. | L90: The selected option, “Seodo’s rock itself”, does not fit. The answer is “Phytoplankton”. Phytoplankton support food relationships around Dokdo, including links to zooplankton and young fish. | M90: The selected option, “Lighthouse lamps”, does not fit. The answer is “Phytoplankton”. Phytoplankton support food relationships around Dokdo, including links to zooplankton and young fish. | O90: https://www.dokdo.re.kr/home/cms/cmsCont.do?cntnts_sn=82 | P90: =LEN(E90)+MAX(LEN(F90),LEN(G90),LEN(H90)) -> 73 | Q90: 출처 기반 자체 검토 / 독립 승인 전
A91: 910090 | B91: 5 | C91: dk-food-links | D91: 2 | E91: What may follow an increase in phytoplankton? | F91: Dokdo’s area doubling | G91: The islands acquiring one name | H91: More food for organisms that eat them | I91: 3 | J91: Phytoplankton support food relationships around Dokdo, including links to zooplankton and young fish. | K91: The selected option, “Dokdo’s area doubling”, does not fit. The answer is “More food for organisms that eat them”. Phytoplankton support food relationships around Dokdo, including links to zooplankton and young fish. | L91: The selected option, “The islands acquiring one name”, does not fit. The answer is “More food for organisms that eat them”. Phytoplankton support food relationships around Dokdo, including links to zooplankton and young fish. | M91: Phytoplankton support food relationships around Dokdo, including links to zooplankton and young fish. | O91: https://www.dokdo.re.kr/home/cms/cmsCont.do?cntnts_sn=82 | P91: =LEN(E91)+MAX(LEN(F91),LEN(G91),LEN(H91)) -> 82 | Q91: 출처 기반 자체 검토 / 독립 승인 전
A92: 910091 | B92: 5 | C92: dk-food-links | D92: 3 | E92: Which comes next in the supplied food relationship? | F92: Uldo-gun’s administrative territory | G92: Food for zooplankton | H92: Electricity for the lighthouse | I92: 2 | J92: Phytoplankton support food relationships around Dokdo, including links to zooplankton and young fish. | K92: The selected option, “Uldo-gun’s administrative territory”, does not fit. The answer is “Food for zooplankton”. Phytoplankton support food relationships around Dokdo, including links to zooplankton and young fish. | L92: Phytoplankton support food relationships around Dokdo, including links to zooplankton and young fish. | M92: The selected option, “Electricity for the lighthouse”, does not fit. The answer is “Food for zooplankton”. Phytoplankton support food relationships around Dokdo, including links to zooplankton and young fish. | N92: The research account links nutrient supply, phytoplankton growth, zooplankton food and food for young fish. It describes a potential contribution to nursery functions. | O92: https://www.dokdo.re.kr/home/cms/cmsCont.do?cntnts_sn=82 | P92: =LEN(E92)+MAX(LEN(F92),LEN(G92),LEN(H92)) -> 86 | Q92: 출처 기반 자체 검토 / 독립 승인 전
A93: 910092 | B93: 5 | C93: dk-food-links | D93: 4 | E93: How should “expected to contribute to nursery functions” be summarised? | F93: Retain its status as an expected contribution | G93: Claim every fish population has already doubled | H93: Discard all observations because the conclusion is qualified | I93: 1 | J93: Phytoplankton support food relationships around Dokdo, including links to zooplankton and young fish. | K93: Phytoplankton support food relationships around Dokdo, including links to zooplankton and young fish. | L93: The selected option, “Claim every fish population has already doubled”, does not fit. The answer is “Retain its status as an expected contribution”. Phytoplankton support food relationships around Dokdo, including links to zooplankton and young fish. | M93: The selected option, “Discard all observations because the conclusion is qualified”, does not fit. The answer is “Retain its status as an expected contribution”. Phytoplankton support food relationships around Dokdo, including links to zooplankton and young fish. | N93: The research account links nutrient supply, phytoplankton growth, zooplankton food and food for young fish. It describes a potential contribution to nursery functions. | O93: https://www.dokdo.re.kr/home/cms/cmsCont.do?cntnts_sn=82 | P93: =LEN(E93)+MAX(LEN(F93),LEN(G93),LEN(H93)) -> 131 | Q93: 출처 기반 자체 검토 / 독립 승인 전
A94: 910093 | B94: 5 | C94: dk-gangchi-history | D94: 1 | E94: Which animal formerly lived around Dokdo? | F94: A freshwater river dolphin | G94: Fennec fox | H94: Japanese sea lion | I94: 3 | J94: Sea lions once lived on Dokdo. Research explains how excessive hunting contributed greatly to their decline and extinction. | K94: The selected option, “A freshwater river dolphin”, does not fit. The answer is “Japanese sea lion”. Sea lions once lived on Dokdo. Research explains how excessive hunting contributed greatly to their decline and extinction. | L94: The selected option, “Fennec fox”, does not fit. The answer is “Japanese sea lion”. Sea lions once lived on Dokdo. Research explains how excessive hunting contributed greatly to their decline and extinction. | M94: Sea lions once lived on Dokdo. Research explains how excessive hunting contributed greatly to their decline and extinction. | O94: https://www.mof.go.kr/doc/ko/selectDoc.do?bbsSeq=10&docSeq=45126&menuSeq=971 https://www.mdpi.com/2077-1312/10/2/271 | P94: =LEN(E94)+MAX(LEN(F94),LEN(G94),LEN(H94)) -> 67 | Q94: 출처 기반 자체 검토 / 독립 승인 전
A95: 910094 | B95: 5 | C95: dk-gangchi-history | D95: 2 | E95: Which human activity did the study link to sea lion decline? | F95: Cataloguing historical documents | G95: Excessive hunting | H95: Measuring island elevation | I95: 2 | J95: Sea lions once lived on Dokdo. Research explains how excessive hunting contributed greatly to their decline and extinction. | K95: The selected option, “Cataloguing historical documents”, does not fit. The answer is “Excessive hunting”. Sea lions once lived on Dokdo. Research explains how excessive hunting contributed greatly to their decline and extinction. | L95: Sea lions once lived on Dokdo. Research explains how excessive hunting contributed greatly to their decline and extinction. | M95: The selected option, “Measuring island elevation”, does not fit. The answer is “Excessive hunting”. Sea lions once lived on Dokdo. Research explains how excessive hunting contributed greatly to their decline and extinction. | O95: https://www.mof.go.kr/doc/ko/selectDoc.do?bbsSeq=10&docSeq=45126&menuSeq=971 https://www.mdpi.com/2077-1312/10/2/271 | P95: =LEN(E95)+MAX(LEN(F95),LEN(G95),LEN(H95)) -> 92 | Q95: 출처 기반 자체 검토 / 독립 승인 전
A96: 910095 | B96: 5 | C96: dk-gangchi-history | D96: 3 | E96: How did the study examine historical sea lion numbers? | F96: Capture records and a population model | G96: Counting all currently living animals | H96: Counting animals drawn in an app | I96: 1 | J96: Sea lions once lived on Dokdo. Research explains how excessive hunting contributed greatly to their decline and extinction. | K96: Sea lions once lived on Dokdo. Research explains how excessive hunting contributed greatly to their decline and extinction. | L96: The selected option, “Counting all currently living animals”, does not fit. The answer is “Capture records and a population model”. Sea lions once lived on Dokdo. Research explains how excessive hunting contributed greatly to their decline and extinction. | M96: The selected option, “Counting animals drawn in an app”, does not fit. The answer is “Capture records and a population model”. Sea lions once lived on Dokdo. Research explains how excessive hunting contributed greatly to their decline and extinction. | N96: A 2022 study examined hunting pressure using historical capture records and a population model. The focus is Dokdo sea lion history, not memorising present animal counts. | O96: https://www.mof.go.kr/doc/ko/selectDoc.do?bbsSeq=10&docSeq=45126&menuSeq=971 https://www.mdpi.com/2077-1312/10/2/271 | P96: =LEN(E96)+MAX(LEN(F96),LEN(G96),LEN(H96)) -> 92 | Q96: 출처 기반 자체 검토 / 독립 승인 전
A97: 910096 | B97: 5 | C97: dk-gangchi-history | D97: 4 | E97: Is “all factors other than hunting are impossible” an accurate summary? | F97: A hunting study necessarily tested every possible factor | G97: Historical research can never support a conclusion | H97: It exceeds the model’s assumptions and unexamined factors | I97: 3 | J97: Sea lions once lived on Dokdo. Research explains how excessive hunting contributed greatly to their decline and extinction. | K97: The selected option, “A hunting study necessarily tested every possible factor”, does not fit. The answer is “It exceeds the model’s assumptions and unexamined factors”. Sea lions once lived on Dokdo. Research explains how excessive hunting contributed greatly to their decline and extinction. | L97: The selected option, “Historical research can never support a conclusion”, does not fit. The answer is “It exceeds the model’s assumptions and unexamined factors”. Sea lions once lived on Dokdo. Research explains how excessive hunting contributed greatly to their decline and extinction. | M97: Sea lions once lived on Dokdo. Research explains how excessive hunting contributed greatly to their decline and extinction. | N97: A 2022 study examined hunting pressure using historical capture records and a population model. The focus is Dokdo sea lion history, not memorising present animal counts. | O97: https://www.mof.go.kr/doc/ko/selectDoc.do?bbsSeq=10&docSeq=45126&menuSeq=971 https://www.mdpi.com/2077-1312/10/2/271 | P97: =LEN(E97)+MAX(LEN(F97),LEN(G97),LEN(H97)) -> 128 | Q97: 출처 기반 자체 검토 / 독립 승인 전
A98: 910097 | B98: 5 | C98: dk-model-evidence | D98: 1 | E98: What can help investigate past sea lion numbers? | F98: Only lighthouse colour names | G98: Surviving capture records | H98: Only today’s ferry timetable | I98: 2 | J98: Historical sea lion populations can be estimated from surviving records. Modelled estimates must be distinguished from direct counts. | K98: The selected option, “Only lighthouse colour names”, does not fit. The answer is “Surviving capture records”. Historical sea lion populations can be estimated from surviving records. Modelled estimates must be distinguished from direct counts. | L98: Historical sea lion populations can be estimated from surviving records. Modelled estimates must be distinguished from direct counts. | M98: The selected option, “Only today’s ferry timetable”, does not fit. The answer is “Surviving capture records”. Historical sea lion populations can be estimated from surviving records. Modelled estimates must be distinguished from direct counts. | O98: https://www.mdpi.com/2077-1312/10/2/271 | P98: =LEN(E98)+MAX(LEN(F98),LEN(G98),LEN(H98)) -> 76 | Q98: 출처 기반 자체 검토 / 독립 승인 전
A99: 910098 | B99: 5 | C99: dk-model-evidence | D99: 2 | E99: What is a sea lion population value obtained from a model? | F99: An estimate based on records and assumptions | G99: A direct count of every animal on that day | H99: An exact coastline length | I99: 1 | J99: Historical sea lion populations can be estimated from surviving records. Modelled estimates must be distinguished from direct counts. | K99: Historical sea lion populations can be estimated from surviving records. Modelled estimates must be distinguished from direct counts. | L99: The selected option, “A direct count of every animal on that day”, does not fit. The answer is “An estimate based on records and assumptions”. Historical sea lion populations can be estimated from surviving records. Modelled estimates must be distinguished from direct counts. | M99: The selected option, “An exact coastline length”, does not fit. The answer is “An estimate based on records and assumptions”. Historical sea lion populations can be estimated from surviving records. Modelled estimates must be distinguished from direct counts. | O99: https://www.mdpi.com/2077-1312/10/2/271 | P99: =LEN(E99)+MAX(LEN(F99),LEN(G99),LEN(H99)) -> 102 | Q99: 출처 기반 자체 검토 / 독립 승인 전
A100: 910099 | B100: 5 | C100: dk-model-evidence | D100: 3 | E100: Which limitation is acknowledged in the source? | F100: No capture records were used | G100: Only modern vessel lengths were studied | H100: Limited ecological information and model assumptions | I100: 3 | J100: Historical sea lion populations can be estimated from surviving records. Modelled estimates must be distinguished from direct counts. | K100: The selected option, “No capture records were used”, does not fit. The answer is “Limited ecological information and model assumptions”. Historical sea lion populations can be estimated from surviving records. Modelled estimates must be distinguished from direct counts. | L100: The selected option, “Only modern vessel lengths were studied”, does not fit. The answer is “Limited ecological information and model assumptions”. Historical sea lion populations can be estimated from surviving records. Modelled estimates must be distinguished from direct counts. | M100: Historical sea lion populations can be estimated from surviving records. Modelled estimates must be distinguished from direct counts. | N100: Lee and colleagues (2022) reconstructed Dokdo sea lion populations for 1900–1951 using capture records and a population model. They acknowledge limited ecological information and modelling assumptions. | O100: https://www.mdpi.com/2077-1312/10/2/271 | P100: =LEN(E100)+MAX(LEN(F100),LEN(G100),LEN(H100)) -> 99 | Q100: 출처 기반 자체 검토 / 독립 승인 전
...

Sheet 연령경로
A1: 경로 | B1: L1 | C1: L2 | D1: L3 | E1: L4 | F1: 문항 수 | G1: 읽기 상한 | H1: 추천 시작 단원 | I1: 배정 문항 ID
A2: 초등 저학년 | B2: 42 | C2: 18 | D2: 0 | E2: 0 | F2: =SUM(B2:E2) -> 60 | G2: 48 | H2: 독도는 어디에 있을까 | I2: 910001, 910006, 910009, 910013, 910018, 910021, 910025, 910029, 910034, 910037, 910041, 910046, 910049, 910053, 910058, 910061, 910065, 910069, 910074, 910077, 910081, 910086, 910089, 910093, 910098, 910101, 910105, 910109, 910114, 910117, 910121, 910126, 910129, 910133, 910138, 910141, 910145, 910149, 910154, 910157, 910161, 910166, 910169, 910173, 910178, 910181, 910185, 910189, 910194, 910197, 910201, 910206, 910209, 910213, 910218, 910221, 910225, 910229, 910234, 910237
A3: 초등 중학년 | B3: 42 | C3: 18 | D3: 0 | E3: 0 | F3: =SUM(B3:E3) -> 60 | G3: 48 | H3: 동도와 서도 비교 | I3: 910001, 910006, 910009, 910013, 910018, 910021, 910025, 910029, 910034, 910037, 910041, 910046, 910049, 910053, 910058, 910061, 910065, 910069, 910074, 910077, 910081, 910086, 910089, 910093, 910098, 910101, 910105, 910109, 910114, 910117, 910121, 910126, 910129, 910133, 910138, 910141, 910145, 910149, 910154, 910157, 910161, 910166, 910169, 910173, 910178, 910181, 910185, 910189, 910194, 910197, 910201, 910206, 910209, 910213, 910218, 910221, 910225, 910229, 910234, 910237
A4: 초등 고학년 | B4: 30 | C4: 24 | D4: 6 | E4: 0 | F4: =SUM(B4:E4) -> 60 | G4: 60 | H4: 화산이 만든 독도 | I4: 910001, 910006, 910009, 910014, 910019, 910021, 910026, 910029, 910034, 910037, 910041, 910046, 910049, 910054, 910059, 910061, 910066, 910069, 910074, 910077, 910081, 910086, 910089, 910094, 910099, 910101, 910106, 910109, 910114, 910117, 910121, 910126, 910129, 910134, 910139, 910141, 910146, 910149, 910154, 910157, 910161, 910166, 910169, 910174, 910179, 910181, 910186, 910189, 910194, 910197, 910201, 910206, 910209, 910214, 910219, 910221, 910226, 910229, 910234, 910237
A5: 중학생 | B5: 15 | C5: 21 | D5: 18 | E5: 6 | F5: =SUM(B5:E5) -> 60 | G5: 80 | H5: 칙령 제41호 읽기 | I5: 910002, 910007, 910009, 910016, 910018, 910023, 910025, 910030, 910035, 910038, 910041, 910047, 910050, 910053, 910060, 910063, 910066, 910069, 910075, 910078, 910082, 910087, 910089, 910094, 910100, 910103, 910105, 910110, 910115, 910118, 910121, 910127, 910130, 910133, 910140, 910143, 910146, 910149, 910155, 910158, 910162, 910167, 910169, 910176, 910178, 910183, 910185, 910190, 910195, 910198, 910201, 910207, 910210, 910213, 910220, 910223, 910226, 910229, 910235, 910238
A6: 고등학생 | B6: 9 | C6: 15 | D6: 21 | E6: 15 | F6: =SUM(B6:E6) -> 60 | G6: 110 | H6: 1906년의 보고와 대응 | I6: 910003, 910008, 910010, 910013, 910019, 910024, 910026, 910031, 910033, 910040, 910043, 910046, 910051, 910056, 910058, 910063, 910065, 910072, 910074, 910079, 910083, 910088, 910090, 910093, 910099, 910104, 910106, 910111, 910113, 910120, 910123, 910126, 910131, 910136, 910138, 910143, 910145, 910152, 910154, 910159, 910163, 910168, 910170, 910173, 910179, 910184, 910186, 910191, 910193, 910200, 910203, 910206, 910211, 910216, 910218, 910223, 910225, 910232, 910234, 910239
A7: 성인 | B7: 6 | C7: 12 | D7: 18 | E7: 24 | F7: =SUM(B7:E7) -> 60 | G7: 160 | H7: 기록을 함께 읽기 | I7: 910004, 910007, 910010, 910016, 910019, 910021, 910028, 910030, 910035, 910040, 910044, 910047, 910050, 910056, 910059, 910061, 910068, 910070, 910075, 910080, 910084, 910087, 910090, 910096, 910099, 910101, 910108, 910110, 910115, 910120, 910124, 910127, 910130, 910136, 910139, 910141, 910148, 910150, 910155, 910160, 910164, 910167, 910170, 910176, 910179, 910181, 910188, 910190, 910195, 910200, 910204, 910207, 910210, 910216, 910219, 910221, 910228, 910230, 910235, 910240

Sheet 단원
A1: 단원 | B1: 제목 | C1: 분야 | D1: 배운 뒤 남는 한 문단 | E1: 개념 묶음 | F1: 출처
A2: 1 | B2: 독도는 어디에 있을까 | C2: 지리 | D2: 독도는 동도와 서도, 그리고 주변의 작은 바위섬들로 이루어져 있어요. 독도는 울릉도에서 동남쪽으로 약 87.4km 떨어져 있어요. 서도는 서쪽, 동도는 동쪽의 큰 섬이에요. 지도를 돌려도 실제 동쪽과 서쪽은 바뀌지 않아요. 울릉도에서는 맑은 날 독도를 볼 수 있어요. 안개나 비가 시야를 가리면 보이지 않을 수도 있어요. 독도 전체 면적에는 동도·서도뿐 아니라 부속 도서의 땅도 포함돼요. | E2: dk-composition dk-relative-location dk-orientation dk-visibility dk-islet-count | F2: https://dokdo.mofa.go.kr/kor/introduce/location.jsp https://dokdo.mofa.go.kr/kor/pds/part06_view02.jsp
A3: 2 | B3: 동도와 서도 비교 | C3: 지리 | D3: 서도의 최고 높이는 168.5m, 동도는 98.6m예요. 서도가 더 높아요. 서도는 동도보다 땅의 넓이도 넓어요. 높이와 면적은 서로 다른 값이에요. 동도와 서도는 바다로 떨어져 있어요. 가장 가까운 해안 사이 거리는 약 151m예요. 서도는 가파르게 솟은 모습이고, 동도는 정상 부근에 비교적 완만한 공간이 있어요. 독도는 큰 해저 화산체의 일부가 물 위에 드러난 모습이에요. 바닷속에도 지형이 이어져요. | E3: dk-heights dk-area dk-shore-gap dk-terrain-contrast dk-above-below | F3: https://www.dokdo.re.kr/home/cms/cmsCont.do?cntnts_sn=66 https://dokdo.mofa.go.kr/kor/introduce/location.jsp https://www.jbe.go.kr/dokdo/assets/sub/picture.html https://www.heritage.go.kr/heri/cul/culSelectDetail.do?VdkVgwKey=16%2C03360000%2C37&pageNo=1_1_2_0
A4: 3 | B4: 화산이 만든 독도 | C4: 지형 | D4: 독도는 바닷속 화산활동으로 만들어졌어요. 화산에서 나온 물질이 쌓이고 굳어 바위가 되었어요. 독도는 오랜 시간에 걸쳐 만들어지고 변했어요. 바닷속에서 자란 뒤 물 위로 드러났어요. 독도 해안의 파도는 바위를 깎아요. 해안 절벽·동굴·바위 아치 같은 지형이 생기는 데 영향을 주었어요. 독도 바위는 바람과 파도에 노출되어 조금씩 풍화되고 깎여요. 바위와 해안을 계속 살피는 연구가 필요해요. 서도의 물골에는 바위에서 떨어지는 물이 있어요. 담수화 시설이 생기기 전에는 식수원으로 쓰였어요. | E4: dk-volcano dk-formation-time dk-wave-erosion dk-weathering dk-mulgol | F4: https://korean.visitkorea.or.kr/detail/ms_detail.do?cotid=0fe4eeb6-3f6a-48b1-ab75-c8d4ab6b43be https://www.dokdo.re.kr/home/cms/cmsCont.do?cntnts_sn=66
A5: 4 | B5: 생명이 머무는 독도 | C5: 생태 | D5: 독도는 먼 길을 이동하는 새들이 쉬어 가는 곳이기도 해요. 독도에서는 괭이갈매기·바다제비·슴새 같은 바닷새가 번식해요. 번식은 새끼를 낳고 기르는 일이에요. 독도에는 바닷새도, 미역 같은 바닷말도 있어요. 비슷하게 들리는 말이라도 가리키는 생물은 다를 수 있어요. 독도 땅에는 해국·섬기린초·땅채송화 같은 식물이 자라요. 바닷속 생물과 땅 위 식물을 함께 살펴보면 독도의 생명이 더 잘 보여요. 독도를 보호하는 이유에는 바닷새뿐 아니라 식물·바다 생물·화산 지형의 가치도 있어요. | E5: dk-migratory-stopover dk-breeding-birds dk-birds-and-seaweed dk-coastal-plants dk-reserve-scope | F5: https://dokdo.mofa.go.kr/kor/introduce/nature.jsp https://www.heritage.go.kr/heri/cul/culSelectDetail.do?VdkVgwKey=16%2C03360000%2C37&pageNo=1_1_2_0
A6: 5 | B6: 독도 바다의 연결 | C6: 생태 | D6: 독도 바닷속에는 감태와 대황 같은 해조류가 자라 바다숲을 이루어요. 바위틈에도 여러 생물이 살아요. 독도 주변에서는 따뜻한 흐름과 찬 흐름이 만나고 물이 섞여요. 물의 움직임은 생물이 쓰는 영양분의 이동에도 영향을 줘요. 작은 식물플랑크톤은 독도 바다 먹이 관계의 바탕이 되어요. 이를 먹는 동물플랑크톤과 어린 물고기로 연결될 수 있어요. 독도에는 강치가 살았어요. 연구는 지나치게 많이 잡은 일이 강치 감소와 멸종에 큰 영향을 주었음을 설명해요. 강치의 옛 개체 수는 남아 있는 기록으로 추정해요. 연구 모델의 수치와 당시 직접 센 수치는 구별해야 해요. | E6: dk-sea-forest dk-water-mixing dk-food-links dk-gangchi-history dk-model-evidence | F6: https://www.dokdo.re.kr/home/cms/cmsCont.do?cntnts_sn=82 https://www.dokdo.re.kr/home/cms/cmsCont.do?cntnts_sn=87 https://www.mof.go.kr/doc/ko/selectDoc.do?bbsSeq=10&docSeq=45126&menuSeq=971 https://www.mdpi.com/2077-1312/10/2/271
A7: 6 | B7: 사람과 시설 | C7: 생활 | D7: 독도등대는 동도에 있어요. 등대는 바다를 지나는 배가 위치를 알아보는 데 도움을 주어요. 독도의 접안시설은 동도에 있어요. 배가 닿는 곳과 정상의 시설은 같은 장소가 아니에요. 서도에는 주민숙소가 있어요. 독도는 자연환경뿐 아니라 사람들의 생활과 관리 활동도 함께 살펴볼 곳이에요. 독도 생활에는 마실 물이 필요해요. 시설 안내에는 바닷물을 생활에 쓸 물로 바꾸는 담수시설이 나와요. 동도에는 선착장에서 위쪽 시설로 이어지는 길이 있어요. 사진에서 보이는 직선 거리와 실제 걷는 길의 길이는 다를 수 있어요. | E7: dk-lighthouse dk-dock dk-residence dk-freshwater dk-routes | F7: https://dokdo.mofa.go.kr/kor/introduce/facility.jsp https://www.dokdo.re.kr/home/cms/cmsCont.do?cntnts_sn=66 https://www.jbe.go.kr/dokdo/assets/sub/picture.html https://dokdo.mofa.go.kr/kor/introduce/residence.jsp
A8: 7 | B8: 옛 기록의 두 섬 | C8: 역사 | D8: 『세종실록』 지리지는 조선의 여러 지역을 설명한 기록이에요. 외교부는 이 기록의 우산·무릉을 독도·울릉도와 연결해 소개해요. 조선의 지리지는 나라가 지역을 어떻게 알고 기록했는지 살펴보는 자료예요. 옛 기록의 설명과 오늘의 관찰은 구분해 읽어요. 안용복과 박어둔은 1693년 울릉도에서 어업을 하다가 일본으로 끌려갔어요. 이 사건은 울릉도 관련 교섭의 계기가 되었어요. 안용복의 1696년 활동은 조선의 기록과 일본 오키섬의 조사 기록을 함께 대조하며 살펴볼 수 있어요. 1696년에는 1월 울릉도 도해금지령, 5월 안용복의 일본 도해가 연표에 나와요. 같은 해에도 사건의 순서를 살펴봐야 해요. | E8: dk-sejong-record dk-official-geography dk-an-1693 dk-an-records dk-an-chronology | F8: https://dokdo.mofa.go.kr/kor/include/print_faq.jsp?class_faq=q5 https://dokdo.mofa.go.kr/kor/pds/part06_view02.jsp https://dokdo.mofa.go.kr/m/kor/dokdo/reason_list.jsp
A9: 8 | B9: 칙령 제41호 읽기 | C9: 역사 | D9: 대한제국 칙령 제41호는 1900년에 울릉도를 울도로 이름 바꾸고 행정 체계를 정한 문서예요. 칙령 제41호는 도감을 군수로 바꾸도록 했어요. 군수는 군의 행정을 맡는 관리예요. 칙령 제41호 제2조에는 울릉전도·죽도·석도를 관할한다는 내용이 있어요. 원문의 지명과 현대의 해석을 구분하며 읽어요. 칙령 제41호의 날짜는 1900년 10월 25일이고, 관보 게재 날짜는 10월 27일이에요. 문서의 날짜와 공표된 기록의 날짜를 구분해요. 행정 개편은 제안·칙령·관보 게재의 과정으로 살펴볼 수 있어요. 청의서는 안건을 올린 문서예요. | E9: dk-decree-name dk-county-head dk-territory dk-gazette-date dk-proposal-order | F9: https://dokdo.mofa.go.kr/kor/pds/part02_view02.jsp https://dokdo.mofa.go.kr/kor/pds/part02_view03.jsp https://dokdo.mofa.go.kr/kor/pds/part02_view01.jsp
A10: 9 | B10: 1906년의 보고와 대응 | C10: 역사 | D10: 심흥택은 울도군수였어요. 1906년 독도와 관련해 들은 상황을 상부에 보고했어요. 심흥택의 보고에는 독도를 자기 군에 속한 섬으로 표현한 내용이 있어요. 이 표현은 당시 관리의 인식을 보여줘요. 심흥택 보고에는 일본 관리에게 들은 주장도 들어 있어요. 남의 말을 보고한 것과 그 주장에 동의한 것은 달라요. 1906년 지령 제3호는 일본의 주장을 받아들이지 않고 상황을 더 조사해 보고하도록 했어요. 1900년의 칙령과 1906년의 보고·지령은 서로 다른 때의 행정 기록이에요. 연표에 놓으면 관리와 대응의 흐름을 살펴볼 수 있어요. | E10: dk-shim-role dk-county-affiliation dk-reported-speech dk-order-response dk-1900-1906 | F10: https://dokdo.mofa.go.kr/kor/pds/part02_view02.jsp https://dokdo.mofa.go.kr/kor/pds/part02_view05.jsp https://dokdo.mofa.go.kr/kor/pds/part02_view04.jsp https://dokdo.mofa.go.kr/m/kor/dokdo/reason_list.jsp
A11: 10 | B11: 바위와 물길 살펴보기 | C11: 지형 | D11: 동도의 천장굴은 섬 안쪽으로 움푹 들어간 통 모양 지형이에요. 바다 쪽 벽에 있는 작은 구멍과는 다르게 보아야 해요. 독립문바위는 바위에 문처럼 열린 아치 모양이 있어서 붙은 이름이에요. 사람이 지은 문은 아니에요. 숫돌바위는 동도 선착장 가까이에서 볼 수 있어요. 칼을 가는 숫돌과 비슷한 바위 성질에서 이름이 왔어요. 큰가제바위와 작은가제바위의 ‘가제’는 강치를 부르던 현지 말과 연결돼요. 지명에는 생물과 사람의 기억이 남기도 해요. 탕건봉은 선비들이 쓰던 탕건을 닮은 모습에서 이름이 붙었어요. 독도 지명에는 바위의 모양을 담은 이름이 많아요. | E11: dk-cheonjang dk-dongnim-arch dk-sutdol dk-gaje-name dk-tanggeon | F11: https://www.dokdo.re.kr/home/cms/cmsCont.do?cntnts_sn=65 https://www.heritage.go.kr/heri/cul/culSelectDetail.do?VdkVgwKey=16%2C03360000%2C37&pageNo=1_1_2_0 https://korean.visitkorea.or.kr/detail/ms_detail.do?cotid=603167d6-1056-43c1-8a3d-c8640dd25938
A12: 11 | B12: 기록을 함께 읽기 | C12: 역사 | D12: 태정관지령은 1877년 일본의 행정 문서예요. 어떤 기관이 무엇을 검토하고 답했는지 확인하며 읽어야 해요. 옛 일본 기록에서 다케시마가 울릉도를 가리킨 경우가 있어요. 같은 이름도 시기와 자료에 따라 가리키는 섬을 확인해야 해요. 태정관 관련 자료는 문서와 함께 첨부 지도를 대조해 섬 이름을 살펴봐요. 지도에 적힌 이름과 위치 관계를 함께 읽는 것이 중요해요. 칙령은 제도를 정하고, 보고서는 상황을 알리며, 지령은 처리 방향을 지시해요. 독도 관련 기록도 역할이 다르므로 함께 구분해 읽어요. 독도 관련 사료를 읽을 때는 옛 문서 자체와 오늘의 설명을 구분해요. 해설을 이용하되 누가 어떻게 해석했는지 밝혀야 해요. | E12: dk-dajokan-type dk-historic-name-context dk-map-and-document dk-record-types dk-authority-and-interpretation | F12: https://dokdo.mofa.go.kr/kor/pds/part05_view03.jsp https://dokdo.mofa.go.kr/kor/include/print_faq.jsp?class_faq=q7 https://dokdo.mofa.go.kr/kor/pds/part02_view02.jsp https://dokdo.mofa.go.kr/kor/pds/part02_view05.jsp https://dokdo.mofa.go.kr/kor/pds/part06_view02.jsp https://dokdo.mofa.go.kr/kor/pds/part02_view04.jsp https://dokdo.mofa.go.kr/m/kor/dokdo/reason_list.jsp
A13: 12 | B13: 나의 독도 해설 | C13: 종합 | D13: 독도로 가는 배가 있어도 날씨나 선박 사정에 따라 섬에 내리지 못할 수 있어요. 방문 전에는 최신 안내를 확인해야 해요. 독도는 바다의 영향을 받는 해양성 기후예요. 안개와 구름도 자주 나타나 실제 보이는 모습은 날마다 다를 수 있어요. 독도의 주소는 경상북도 울릉군 울릉읍에 속해요. 동도와 서도에는 서로 다른 도로명 주소가 있어요. 독도 천연보호구역과 방문객에게 열린 관람 구역은 같지 않아요. 일부를 관람할 수 있다고 섬 전체에 들어갈 수 있는 것은 아니에요. 독도는 화산이 만든 섬이자 생명이 머무는 곳이고, 사람들의 생활과 역사 기록이 남은 곳이에요. 서로 다른 자료를 연결하면 더 잘 설명할 수 있어요. | E13: dk-weather-access dk-maritime-climate dk-admin-address dk-visiting-scope dk-whole-dokdo | F13: https://www.mof.go.kr/doc/ko/selectDoc.do?bbsSeq=27&docSeq=20937&menuSeq=929 https://dokdo.mofa.go.kr/kor/pds/part02_view02.jsp https://www.dokdo.re.kr/home/cms/cmsCont.do?cntnts_sn=66 https://dokdo.mofa.go.kr/kor/introduce/location.jsp https://dokdo.mofa.go.kr/kor/introduce/nature.jsp https://www.heritage.go.kr/heri/cul/culSelectDetail.do?VdkVgwKey=16%2C03360000%2C37&pageNo=1_1_2_0 https://dokdo.mofa.go.kr/kor/introduce/residence.jsp

Sheet 출처
A1: 키 | B1: 기관·자료 | C1: 확인 위치 | D1: URL | E1: 확인일
A2: location | B2: 외교부 · 독도의 구성 및 위치 | C2: 두 큰 섬·부속 도서 / 높이·면적 / 울릉도·오키섬 거리 | D2: https://dokdo.mofa.go.kr/kor/introduce/location.jsp | E2: 2026-09-11
A3: geology | B3: 한국해양과학기술원 · 독도 지형 및 지질 | C3: 해저 화산의 형성 / 해안 침식 지형 / 물골 / 지형 변화 | D3: https://www.dokdo.re.kr/home/cms/cmsCont.do?cntnts_sn=66 | E3: 2026-09-11
A4: nature | B4: 외교부 · 독도의 자연환경 | C4: 독도 식물·조류·해양생물 / 철새 이동경로의 휴식처 | D4: https://dokdo.mofa.go.kr/kor/introduce/nature.jsp | E4: 2026-09-11
A5: forest | B5: 한국해양과학기술원 · 독도 암반생태계 | C5: 감태·대황 해조숲 / 바위틈 생물 / 장기 관찰 | D5: https://www.dokdo.re.kr/home/cms/cmsCont.do?cntnts_sn=87 | E5: 2026-09-11
A6: mix | B6: 한국해양과학기술원 · 독도의 해양환경 | C6: 수괴 혼합·영양염·식물플랑크톤과 조사 자료 | D6: https://www.dokdo.re.kr/home/cms/cmsCont.do?cntnts_sn=78 | E6: 2026-09-11
A7: facility | B7: 외교부 · 독도 주요시설물 | C7: 서도 주민숙소 / 동도 접안시설·등대·경비대 / 담수시설 | D7: https://dokdo.mofa.go.kr/kor/introduce/facility.jsp | E7: 2026-09-11
A8: visit | B8: 외교부 · 주민 및 입도 안내 | C8: 입도 유의사항·동도 선착장 관람 / 2026년 7월 기준 표기. 실제 방문 전 최신 안내 확인 | D8: https://dokdo.mofa.go.kr/kor/introduce/residence.jsp | E8: 2026-09-11
A9: sejong | B9: 외교부 자료실 · 세종실록 지리지(1454) | C9: 우산·무릉과 맑은 날의 가시성; 괄호 안 현대 지명은 외교부 해석 | D9: https://dokdo.mofa.go.kr/kor/pds/part06_view02.jsp | E9: 2026-09-11
A10: an | B10: 외교부 · 안용복의 활동과 기록 | C10: 1693년과 1696년 / 숙종실록과 오키섬 조사 기록 | D10: https://dokdo.mofa.go.kr/kor/include/print_faq.jsp?class_faq=q5 | E10: 2026-09-11
A11: timeline | B11: 외교부 · 독도 연표 | C11: 1694 수토 / 1696년 1월 금지령·5월 도일 / 1900·1905·1906 순서 | D11: https://dokdo.mofa.go.kr/m/kor/dokdo/reason_list.jsp | E11: 2026-09-11
A12: decree | B12: 외교부 자료실 · 대한제국 칙령 제41호 | C12: 1900.10.25 / 제1조 울도·군수 / 제2조 울릉전도·죽도·석도 | D12: https://dokdo.mofa.go.kr/kor/pds/part02_view02.jsp | E12: 2026-09-11
... A28: address | B28: 해양수산부 · 독도의 주소와 위치 | C28: 동도·서도의 도로명 주소와 위치; 2018년 등록 자료, 2026-09-11 대조 | D28: https://www.mof.go.kr/doc/ko/selectDoc.do?bbsSeq=27&docSeq=20937&menuSeq=929 | E28: 2026-09-11
