Workbook

Sheet 요약
A1: 독도 코리아 스쿨 · 질문 전수 수정 1.2
A2: 실제 출제 240문항의 한국어·영어 쌍 / 원래 1,513문항은 미재작성 보관 / 독립 교육 검수 전
A5: 수정 문항 쌍 | B5: =COUNTA('문항240'!A2:A241) -> 240
A6: 보기별 해설 쌍 | B6: =COUNTA('보기해설711'!A2:A712) -> 711
A7: 자료가 필요한 문항 | B7: =COUNTIF('자료와출처'!C2:C241,1) -> 121
A8: 출처 항목 | B8: =COUNTA('출처30'!A2:A31) -> 30
A9: 읽기 길이 검토 항목 | B9: =COUNTA('읽기점검'!A2:A6) -> 5
A12: 실제 인지단계 | B12: 문항 수 | C12: 비율
A13: L1 알아보기 | B13: =COUNTIF('문항240'!E2:E241,1) -> 69 | C13: =B13/$B$5 -> 0.2875
A14: L2 이어보기 | B14: =COUNTIF('문항240'!E2:E241,2) -> 52 | C14: =B14/$B$5 -> 0.21666667
A15: L3 자료읽기 | B15: =COUNTIF('문항240'!E2:E241,3) -> 104 | C15: =B15/$B$5 -> 0.43333333
A16: L4 따져보기 | B16: =COUNTIF('문항240'!E2:E241,4) -> 15 | C16: =B16/$B$5 -> 0.0625
A18: 학습 경로 | B18: L1 | C18: L2 | D18: L3 | E18: L4 | F18: 문항 수
A19: early | B19: 45 | C19: 15 | D19: 0 | E19: 0 | F19: =SUM(B19:E19) -> 60
A20: primary | B20: 26 | C20: 34 | D20: 0 | E20: 0 | F20: =SUM(B20:E20) -> 60
A21: upper | B21: 33 | C21: 21 | D21: 6 | E21: 0 | F21: =SUM(B21:E21) -> 60
A22: middle | B22: 17 | C22: 19 | D22: 22 | E22: 2 | F22: =SUM(B22:E22) -> 60
A23: high | B23: 11 | C23: 13 | D23: 34 | E23: 2 | F23: =SUM(B23:E23) -> 60
A24: adult | B24: 7 | C24: 12 | D24: 36 | E24: 5 | F24: =SUM(B24:E24) -> 60
A26: 난이도 1~4와 인지단계 L1~L4는 다릅니다. 네 번째 변형이라고 자동으로 L4를 부여하지 않았습니다.
A28: 질문·보기·해설·자료·원문 URL을 모두 수록했습니다. 원문 작성기관과 현대 공개기관이 다를 때 출처 시트에서 구분합니다.
A30: 이 파일은 검토용입니다. 사용자 기록·지도·서버를 수정하지 않습니다. 5건의 길이 참고 기준 초과는 읽기점검 시트에 그대로 남겼습니다.

Sheet 문항240
A1: ID | B1: old ID | C1: 단원 | D1: 난이도 | E1: 실제 인지단계 | F1: 질문 | G1: A | H1: B | I1: C | J1: D | K1: 정답 번호 | L1: 정답 이유 | M1: 남길 한 문장 | N1: familyId | O1: 출처 | P1: 질문+최장보기 글자수
A2: 920001 | B2: 910001 | C2: 독도는 어디에 있을까 | D2: 1 | E2: 1 | F2: 독도를 이루는 두 큰 섬의 이름은 무엇인가요? | G2: 동도와 서도 | H2: 울릉도와 동도 | I2: 제주도와 서도 | J2: 울릉도와 제주도 | K2: 1 | L2: 동도와 서도가 독도의 두 큰 섬이에요. 둘레에는 작은 바위섬들도 있어요. | M2: 독도는 동도·서도라는 두 큰 섬과 주변 바위섬들로 이루어져요. | N2: dk-composition | O2: 대한민국 외교부 · 독도의 구성 및 위치 https://dokdo.mofa.go.kr/kor/introduce/location.jsp | P2: =LEN(F2)+MAX(LEN(G2),LEN(H2),LEN(I2),LEN(J2)) -> 33
A3: 920002 | B3: 910002 | C3: 독도는 어디에 있을까 | D3: 2 | E3: 2 | F3: 독도의 두 큰 섬 주위에는 어떤 땅이 더 있나요? | G3: 작은 바위섬들 | H3: 울릉도 본섬 | I3: 일본의 오키섬 | K3: 1 | L3: 독도에는 동도·서도뿐 아니라 둘레의 작은 바위섬들도 포함돼요. | M3: 독도는 동도·서도라는 두 큰 섬과 주변 바위섬들로 이루어져요. | N3: dk-composition | O3: 대한민국 외교부 · 독도의 구성 및 위치 https://dokdo.mofa.go.kr/kor/introduce/location.jsp | P3: =LEN(F3)+MAX(LEN(G3),LEN(H3),LEN(I3),LEN(J3)) -> 34
A4: 920003 | B4: 910003 | C4: 독도는 어디에 있을까 | D4: 3 | E4: 3 | F4: 독도 안내판에 두 큰 섬만 그렸다면 어떤 땅을 추가해야 하나요? | G4: 울릉도 전체 | H4: 주변의 부속 바위섬 | I4: 일본 오키섬 전체 | K4: 2 | L4: 자료는 두 큰 섬과 주변 부속 도서를 함께 독도의 구성으로 설명해요. | M4: 독도는 동도·서도라는 두 큰 섬과 주변 바위섬들로 이루어져요. | N4: dk-composition | O4: 대한민국 외교부 · 독도의 구성 및 위치 https://dokdo.mofa.go.kr/kor/introduce/location.jsp | P4: =LEN(F4)+MAX(LEN(G4),LEN(H4),LEN(I4),LEN(J4)) -> 45
A5: 920004 | B5: 910004 | C5: 독도는 어디에 있을까 | D5: 4 | E5: 4 | F5: 독도를 ‘동도 한 섬의 이름’이라고 쓴 문장을 어떻게 고쳐야 하나요? | G5: 동도와 울릉도를 아우르는 이름이다 | H5: 서도 한 섬만 가리키는 이름이다 | I5: 동도·서도와 주변 바위섬을 아우르는 이름이다 | K5: 3 | L5: 동도는 독도의 일부예요. 독도라는 이름은 서도와 부속 도서도 아울러요. | M5: 독도는 동도·서도라는 두 큰 섬과 주변 바위섬들로 이루어져요. | N5: dk-composition | O5: 대한민국 외교부 · 독도의 구성 및 위치 https://dokdo.mofa.go.kr/kor/introduce/location.jsp | P5: =LEN(F5)+MAX(LEN(G5),LEN(H5),LEN(I5),LEN(J5)) -> 62
A6: 920005 | B6: 910005 | C6: 독도는 어디에 있을까 | D6: 1 | E6: 1 | F6: 독도는 울릉도에서 어느 방향에 있나요? | G6: 동북쪽 | H6: 동남쪽 | I6: 서남쪽 | J6: 서북쪽 | K6: 2 | L6: 울릉도에서 동쪽이면서 남쪽인 방향으로 가면 독도가 있어요. | M6: 독도는 울릉도에서 동남쪽으로 약 87.4km 떨어져 있어요. | N6: dk-relative-location | O6: 대한민국 해양수산부 · 독도의 주소와 위치 https://www.mof.go.kr/doc/ko/selectDoc.do?bbsSeq=27&docSeq=20937&menuSeq=929 대한민국 외교부 · 독도의 구성 및 위치 https://dokdo.mofa.go.kr/kor/introduce/location.jsp | P6: =LEN(F6)+MAX(LEN(G6),LEN(H6),LEN(I6),LEN(J6)) -> 24
A7: 920006 | B7: 910006 | C7: 독도는 어디에 있을까 | D7: 2 | E7: 1 | F7: 울릉도와 독도 사이의 거리는 약 얼마인가요? | G7: 157.5km | H7: 8.74km | I7: 87.4km | J7: 874km | K7: 3 | L7: 87.4km가 울릉도와 독도 사이 거리예요. | M7: 독도는 울릉도에서 동남쪽으로 약 87.4km 떨어져 있어요. | N7: dk-relative-location | O7: 대한민국 해양수산부 · 독도의 주소와 위치 https://www.mof.go.kr/doc/ko/selectDoc.do?bbsSeq=27&docSeq=20937&menuSeq=929 대한민국 외교부 · 독도의 구성 및 위치 https://dokdo.mofa.go.kr/kor/introduce/location.jsp | P7: =LEN(F7)+MAX(LEN(G7),LEN(H7),LEN(I7),LEN(J7)) -> 31
A8: 920007 | B8: 910007 | C8: 독도는 어디에 있을까 | D8: 3 | E8: 3 | F8: 거리표에서 독도에 더 가까운 곳은 어디인가요? | G8: 울릉도 | H8: 일본 오키섬 | K8: 1 | L8: 87.4km가 157.5km보다 짧으므로 울릉도가 더 가까워요. | M8: 독도는 울릉도에서 동남쪽으로 약 87.4km 떨어져 있어요. | N8: dk-relative-location | O8: 대한민국 해양수산부 · 독도의 주소와 위치 https://www.mof.go.kr/doc/ko/selectDoc.do?bbsSeq=27&docSeq=20937&menuSeq=929 대한민국 외교부 · 독도의 구성 및 위치 https://dokdo.mofa.go.kr/kor/introduce/location.jsp | P8: =LEN(F8)+MAX(LEN(G8),LEN(H8),LEN(I8),LEN(J8)) -> 31
A9: 920008 | B9: 910008 | C9: 독도는 어디에 있을까 | D9: 4 | E9: 3 | F9: 독도에서 울릉도까지는 오키섬까지보다 몇 km 더 가까운가요? | G9: 244.9km | H9: 87.4km | I9: 157.5km | J9: 70.1km | K9: 4 | L9: 두 거리를 빼면 157.5−87.4=70.1km예요. 울릉도가 그만큼 더 가까워요. | M9: 독도는 울릉도에서 동남쪽으로 약 87.4km 떨어져 있어요. | N9: dk-relative-location | O9: 대한민국 해양수산부 · 독도의 주소와 위치 https://www.mof.go.kr/doc/ko/selectDoc.do?bbsSeq=27&docSeq=20937&menuSeq=929 대한민국 외교부 · 독도의 구성 및 위치 https://dokdo.mofa.go.kr/kor/introduce/location.jsp | P9: =LEN(F9)+MAX(LEN(G9),LEN(H9),LEN(I9),LEN(J9)) -> 40
A10: 920009 | B10: 910009 | C10: 독도는 어디에 있을까 | D10: 1 | E10: 1 | F10: 독도의 동쪽에 있는 큰 섬은 무엇인가요? | G10: 서도 | H10: 동도 | K10: 2 | L10: 동도의 ‘동’은 동쪽을 뜻해요. 서도보다 동쪽에 있는 큰 섬이에요. | M10: 동도는 동쪽의 큰 섬이고, 서도는 서쪽의 큰 섬이에요. | N10: dk-orientation | O10: 대한민국 외교부 · 독도의 구성 및 위치 https://dokdo.mofa.go.kr/kor/introduce/location.jsp | P10: =LEN(F10)+MAX(LEN(G10),LEN(H10),LEN(I10),LEN(J10)) -> 24
A11: 920010 | B11: 910010 | C11: 독도는 어디에 있을까 | D11: 2 | E11: 2 | F11: 독도의 서쪽 큰 섬을 지도에 표시하려면 어떤 이름을 쓰나요? | G11: 서도 | H11: 동도 | K11: 1 | L11: 서쪽 큰 섬은 서도이고, 동쪽 큰 섬은 동도예요. | M11: 동도는 동쪽의 큰 섬이고, 서도는 서쪽의 큰 섬이에요. | N11: dk-orientation | O11: 대한민국 외교부 · 독도의 구성 및 위치 https://dokdo.mofa.go.kr/kor/introduce/location.jsp | P11: =LEN(F11)+MAX(LEN(G11),LEN(H11),LEN(I11),LEN(J11)) -> 35
A12: 920011 | B12: 910011 | C12: 독도는 어디에 있을까 | D12: 3 | E12: 3 | F12: 위치표에서 A에 넣을 섬 이름은 무엇인가요? | G12: 동도 | H12: 서도 | K12: 2 | L12: A는 서쪽 자리에 있으므로 서도예요. 오른쪽 동도와 짝을 이루어요. | M12: 동도는 동쪽의 큰 섬이고, 서도는 서쪽의 큰 섬이에요. | N12: dk-orientation | O12: 대한민국 외교부 · 독도의 구성 및 위치 https://dokdo.mofa.go.kr/kor/introduce/location.jsp | P12: =LEN(F12)+MAX(LEN(G12),LEN(H12),LEN(I12),LEN(J12)) -> 26
A13: 920012 | B13: 910012 | C13: 독도는 어디에 있을까 | D13: 4 | E13: 3 | F13: 동쪽 화살표가 왼쪽을 가리키는 위치표에서 동도는 어느 쪽에 놓이나요? | G13: 왼쪽 | H13: 오른쪽 | K13: 1 | L13: 이 위치표에서는 동쪽이 왼쪽이에요. 동쪽 섬인 동도도 왼쪽에 놓여요. | M13: 동도는 동쪽의 큰 섬이고, 서도는 서쪽의 큰 섬이에요. | N13: dk-orientation | O13: 대한민국 외교부 · 독도의 구성 및 위치 https://dokdo.mofa.go.kr/kor/introduce/location.jsp | P13: =LEN(F13)+MAX(LEN(G13),LEN(H13),LEN(I13),LEN(J13)) -> 41
A14: 920013 | B14: 910013 | C14: 독도는 어디에 있을까 | D14: 1 | E14: 1 | F14: 울릉도에서 독도를 보기 좋은 날씨는 무엇인가요? | G14: 맑고 시야가 트인 날 | H14: 짙은 안개가 낀 날 | I14: 앞이 흐릴 만큼 비가 오는 날 | K14: 1 | L14: 맑고 시야가 트여야 멀리 있는 독도를 볼 수 있어요. | M14: 울릉도에서는 날씨가 맑고 시야가 좋을 때 독도를 볼 수 있어요. | N14: dk-visibility | O14: 대한민국 외교부 자료실 · 세종실록 지리지(1454) https://dokdo.mofa.go.kr/kor/pds/part06_view02.jsp 대한민국 외교부 · 독도의 구성 및 위치 https://dokdo.mofa.go.kr/kor/introduce/location.jsp | P14: =LEN(F14)+MAX(LEN(G14),LEN(H14),LEN(I14),LEN(J14)) -> 42
A15: 920014 | B15: 910014 | C15: 독도는 어디에 있을까 | D15: 2 | E15: 2 | F15: 울릉도에서 먼 독도를 보려면 어떤 대기 조건이 필요한가요? | G15: 짙은 안개가 바다를 덮음 | H15: 안개가 적고 시야가 맑음 | I15: 비가 강하게 내려 시야가 흐림 | K15: 2 | L15: 멀리 있는 섬을 보려면 시야를 가리는 안개 등이 적어야 해요. | M15: 울릉도에서는 날씨가 맑고 시야가 좋을 때 독도를 볼 수 있어요. | N15: dk-visibility | O15: 대한민국 외교부 자료실 · 세종실록 지리지(1454) https://dokdo.mofa.go.kr/kor/pds/part06_view02.jsp 대한민국 외교부 · 독도의 구성 및 위치 https://dokdo.mofa.go.kr/kor/introduce/location.jsp | P15: =LEN(F15)+MAX(LEN(G15),LEN(H15),LEN(I15),LEN(J15)) -> 48
A16: 920015 | B16: 910015 | C16: 독도는 어디에 있을까 | D16: 3 | E16: 3 | F16: 세종실록 지리지는 두 섬이 보이는 날씨를 어떻게 설명하나요? | G16: 짙은 안개가 낄 때 | H16: 계절에 상관없이 모든 날 | I16: 날씨가 맑을 때 | K16: 3 | L16: 역문은 날씨가 맑으면 바라볼 수 있다고 설명해요. | M16: 울릉도에서는 날씨가 맑고 시야가 좋을 때 독도를 볼 수 있어요. | N16: dk-visibility | O16: 대한민국 외교부 자료실 · 세종실록 지리지(1454) https://dokdo.mofa.go.kr/kor/pds/part06_view02.jsp 대한민국 외교부 · 독도의 구성 및 위치 https://dokdo.mofa.go.kr/kor/introduce/location.jsp | P16: =LEN(F16)+MAX(LEN(G16),LEN(H16),LEN(I16),LEN(J16)) -> 46
A17: 920016 | B17: 910016 | C17: 독도는 어디에 있을까 | D17: 4 | E17: 3 | F17: 두 관찰일 중 울릉도에서 독도를 보기 더 좋은 날은 언제인가요? | G17: B일 | H17: A일 | K17: 2 | L17: A일은 시야가 맑아 멀리 있는 독도를 바라보기에 더 적합해요. | M17: 울릉도에서는 날씨가 맑고 시야가 좋을 때 독도를 볼 수 있어요. | N17: dk-visibility | O17: 대한민국 외교부 자료실 · 세종실록 지리지(1454) https://dokdo.mofa.go.kr/kor/pds/part06_view02.jsp 대한민국 외교부 · 독도의 구성 및 위치 https://dokdo.mofa.go.kr/kor/introduce/location.jsp | P17: =LEN(F17)+MAX(LEN(G17),LEN(H17),LEN(I17),LEN(J17)) -> 37
A18: 920017 | B18: 910017 | C18: 독도는 어디에 있을까 | D18: 1 | E18: 1 | F18: 독도의 부속 도서 89개를 셀 때 따로 구분하는 두 큰 섬은 무엇인가요? | G18: 동도와 서도 | H18: 울릉도와 독도 | I18: 동도와 울릉도 | K18: 1 | L18: 부속 도서 89개에 동도와 서도 두 큰 섬을 따로 더해 구성해요. | M18: 독도의 부속 도서 89개는 동도와 서도를 뺀 작은 섬들의 수예요. | N18: dk-islet-count | O18: 대한민국 외교부 · 독도의 구성 및 위치 https://dokdo.mofa.go.kr/kor/introduce/location.jsp 대한민국 한국해양과학기술원 · 독도 위치 및 규모 https://www.dokdo.re.kr/home/cms/cmsCont.do?cntnts_sn=64 | P18: =LEN(F18)+MAX(LEN(G18),LEN(H18),LEN(I18),LEN(J18)) -> 47
A19: 920018 | B19: 910018 | C19: 독도는 어디에 있을까 | D19: 2 | E19: 2 | F19: 동도·서도와 부속 도서 89개를 합하면 몇 개인가요? | G19: 91개 | H19: 89개 | I19: 90개 | J19: 93개 | K19: 1 | L19: 두 큰 섬 2개와 부속 도서 89개를 더하면 91개예요. | M19: 독도의 부속 도서 89개는 동도와 서도를 뺀 작은 섬들의 수예요. | N19: dk-islet-count | O19: 대한민국 외교부 · 독도의 구성 및 위치 https://dokdo.mofa.go.kr/kor/introduce/location.jsp 대한민국 한국해양과학기술원 · 독도 위치 및 규모 https://www.dokdo.re.kr/home/cms/cmsCont.do?cntnts_sn=64 | P19: =LEN(F19)+MAX(LEN(G19),LEN(H19),LEN(I19),LEN(J19)) -> 32
A20: 920019 | B20: 910019 | C20: 독도는 어디에 있을까 | D20: 3 | E20: 3 | F20: 면적표에서 부속 도서 전체의 넓이는 얼마인가요? | G20: 73,297㎡ | H20: 25,517㎡ | I20: 88,740㎡ | J20: 187,554㎡ | K20: 2 | L20: 부속 도서 행의 값이 25,517㎡예요. 전체 면적이나 큰 섬 하나의 면적과 구분해요. | M20: 독도의 부속 도서 89개는 동도와 서도를 뺀 작은 섬들의 수예요. | N20: dk-islet-count | O20: 대한민국 외교부 · 독도의 구성 및 위치 https://dokdo.mofa.go.kr/kor/introduce/location.jsp 대한민국 한국해양과학기술원 · 독도 위치 및 규모 https://www.dokdo.re.kr/home/cms/cmsCont.do?cntnts_sn=64 | P20: =LEN(F20)+MAX(LEN(G20),LEN(H20),LEN(I20),LEN(J20)) -> 34
A21: 920020 | B21: 910020 | C21: 독도는 어디에 있을까 | D21: 4 | E21: 3 | F21: 독도 전체 면적을 동도와 서도 면적만 더해 계산하면 무엇이 빠지나요? | G21: 두 섬 사이 바다 25,517㎡ | H21: 부속 도서 25,517㎡ | I21: 울릉도 25,517㎡ | K21: 2 | L21: 187,554−73,297−88,740=25,517㎡예요. 빠진 값은 부속 도서의 땅 면적이에요. | M21: 독도의 부속 도서 89개는 동도와 서도를 뺀 작은 섬들의 수예요. | N21: dk-islet-count | O21: 대한민국 외교부 · 독도의 구성 및 위치 https://dokdo.mofa.go.kr/kor/introduce/location.jsp 대한민국 한국해양과학기술원 · 독도 위치 및 규모 https://www.dokdo.re.kr/home/cms/cmsCont.do?cntnts_sn=64 | P21: =LEN(F21)+MAX(LEN(G21),LEN(H21),LEN(I21),LEN(J21)) -> 55
A22: 920021 | B22: 910021 | C22: 동도와 서도 비교 | D22: 1 | E22: 1 | F22: 독도의 두 큰 섬 중 더 높은 섬은 무엇인가요? | G22: 서도 | H22: 동도 | K22: 1 | L22: 서도의 최고 높이는 168.5m로 동도의 98.6m보다 높아요. | M22: 독도에서 더 높은 큰 섬은 서도예요. 서도는 168.5m, 동도는 98.6m예요. | N22: dk-heights | O22: 대한민국 외교부 · 독도의 구성 및 위치 https://dokdo.mofa.go.kr/kor/introduce/location.jsp 대한민국 한국해양과학기술원 · 독도 위치 및 규모 https://www.dokdo.re.kr/home/cms/cmsCont.do?cntnts_sn=64 | P22: =LEN(F22)+MAX(LEN(G22),LEN(H22),LEN(I22),LEN(J22)) -> 28
A23: 920022 | B23: 910022 | C23: 동도와 서도 비교 | D23: 2 | E23: 2 | F23: 독도에서 최고 높이가 98.6m인 큰 섬은 무엇인가요? | G23: 서도 | H23: 동도 | K23: 2 | L23: 98.6m는 동도의 최고 높이예요. 서도의 값과 구분해요. | M23: 독도에서 더 높은 큰 섬은 서도예요. 서도는 168.5m, 동도는 98.6m예요. | N23: dk-heights | O23: 대한민국 외교부 · 독도의 구성 및 위치 https://dokdo.mofa.go.kr/kor/introduce/location.jsp 대한민국 한국해양과학기술원 · 독도 위치 및 규모 https://www.dokdo.re.kr/home/cms/cmsCont.do?cntnts_sn=64 | P23: =LEN(F23)+MAX(LEN(G23),LEN(H23),LEN(I23),LEN(J23)) -> 32
A24: 920023 | B24: 910023 | C24: 동도와 서도 비교 | D24: 3 | E24: 3 | F24: 높이표에 따르면 서도는 동도보다 몇 m 더 높은가요? | G24: 267.1m | H24: 98.6m | I24: 69.9m | J24: 151m | K24: 3 | L24: 168.5−98.6=69.9m예요. 두 최고 높이를 같은 단위로 빼요. | M24: 독도에서 더 높은 큰 섬은 서도예요. 서도는 168.5m, 동도는 98.6m예요. | N24: dk-heights | O24: 대한민국 외교부 · 독도의 구성 및 위치 https://dokdo.mofa.go.kr/kor/introduce/location.jsp 대한민국 한국해양과학기술원 · 독도 위치 및 규모 https://www.dokdo.re.kr/home/cms/cmsCont.do?cntnts_sn=64 | P24: =LEN(F24)+MAX(LEN(G24),LEN(H24),LEN(I24),LEN(J24)) -> 35
A25: 920024 | B25: 910024 | C25: 동도와 서도 비교 | D25: 4 | E25: 3 | F25: 표의 높이를 기준으로 100m보다 높은 곳이 있는 섬은 어디인가요? | G25: 동도만 | H25: 두 섬 모두 | I25: 어느 섬도 없음 | J25: 서도만 | K25: 4 | L25: 서도는 168.5m까지 올라가지만 동도의 최고점은 98.6m예요. 동도에 100m 지점을 표시하면 최고 높이를 넘어요. | M25: 독도에서 더 높은 큰 섬은 서도예요. 서도는 168.5m, 동도는 98.6m예요. | N25: dk-heights | O25: 대한민국 외교부 · 독도의 구성 및 위치 https://dokdo.mofa.go.kr/kor/introduce/location.jsp 대한민국 한국해양과학기술원 · 독도 위치 및 규모 https://www.dokdo.re.kr/home/cms/cmsCont.do?cntnts_sn=64 | P25: =LEN(F25)+MAX(LEN(G25),LEN(H25),LEN(I25),LEN(J25)) -> 45
A26: 920025 | B26: 910025 | C26: 동도와 서도 비교 | D26: 1 | E26: 1 | F26: 독도의 두 큰 섬 중 땅의 넓이가 더 넓은 섬은 무엇인가요? | G26: 서도 | H26: 동도 | K26: 1 | L26: 서도는 88,740㎡, 동도는 73,297㎡이므로 서도가 더 넓어요. | M26: 서도는 동도보다 면적이 넓지만, 해안선의 둘레는 동도가 더 길어요. | N26: dk-area | O26: 대한민국 외교부 · 독도의 구성 및 위치 https://dokdo.mofa.go.kr/kor/introduce/location.jsp 대한민국 한국해양과학기술원 · 독도 위치 및 규모 https://www.dokdo.re.kr/home/cms/cmsCont.do?cntnts_sn=64 | P26: =LEN(F26)+MAX(LEN(G26),LEN(H26),LEN(I26),LEN(J26)) -> 35
A27: 920026 | B27: 910026 | C27: 동도와 서도 비교 | D27: 2 | E27: 2 | F27: 독도 면적표의 ㎡는 무엇을 나타내는 단위인가요? | G27: 봉우리의 높이 | H27: 해안선을 따라 잰 길이 | I27: 땅의 넓이 | K27: 3 | L27: 제곱미터는 넓이를 나타내요. 섬의 높이를 나타내는 미터와 달라요. | M27: 서도는 동도보다 면적이 넓지만, 해안선의 둘레는 동도가 더 길어요. | N27: dk-area | O27: 대한민국 외교부 · 독도의 구성 및 위치 https://dokdo.mofa.go.kr/kor/introduce/location.jsp 대한민국 한국해양과학기술원 · 독도 위치 및 규모 https://www.dokdo.re.kr/home/cms/cmsCont.do?cntnts_sn=64 | P27: =LEN(F27)+MAX(LEN(G27),LEN(H27),LEN(I27),LEN(J27)) -> 38
A28: 920027 | B28: 910027 | C28: 동도와 서도 비교 | D28: 3 | E28: 3 | F28: 표에서 해안선의 둘레가 더 긴 큰 섬은 어디인가요? | G28: 서도 | H28: 동도 | K28: 2 | L28: 동도 둘레는 2.8km, 서도는 2.6km예요. 둘레를 비교하면 동도가 더 길어요. | M28: 서도는 동도보다 면적이 넓지만, 해안선의 둘레는 동도가 더 길어요. | N28: dk-area | O28: 대한민국 외교부 · 독도의 구성 및 위치 https://dokdo.mofa.go.kr/kor/introduce/location.jsp 대한민국 한국해양과학기술원 · 독도 위치 및 규모 https://www.dokdo.re.kr/home/cms/cmsCont.do?cntnts_sn=64 | P28: =LEN(F28)+MAX(LEN(G28),LEN(H28),LEN(I28),LEN(J28)) -> 30
A29: 920028 | B29: 910028 | C29: 동도와 서도 비교 | D29: 4 | E29: 3 | F29: 표에 맞게 서도와 동도의 면적·둘레를 함께 비교한 것은 무엇인가요? | G29: 서도는 더 넓고, 동도는 둘레가 더 길다 | H29: 서도가 더 넓으므로 둘레도 더 길다 | I29: 동도가 더 넓고 둘레도 더 길다 | K29: 1 | L29: 넓이와 둘레는 서로 다른 값이에요. 표에서는 두 항목에서 더 큰 섬이 서로 달라요. | M29: 서도는 동도보다 면적이 넓지만, 해안선의 둘레는 동도가 더 길어요. | N29: dk-area | O29: 대한민국 외교부 · 독도의 구성 및 위치 https://dokdo.mofa.go.kr/kor/introduce/location.jsp 대한민국 한국해양과학기술원 · 독도 위치 및 규모 https://www.dokdo.re.kr/home/cms/cmsCont.do?cntnts_sn=64 | P29: =LEN(F29)+MAX(LEN(G29),LEN(H29),LEN(I29),LEN(J29)) -> 59
A30: 920029 | B30: 910029 | C30: 동도와 서도 비교 | D30: 1 | E30: 1 | F30: 동도와 서도는 무엇을 사이에 두고 떨어져 있나요? | G30: 육지 도로 | H30: 바다 | I30: 강 | K30: 2 | L30: 두 섬의 물 위 육지는 바다를 사이에 두고 떨어져 있어요. | M30: 동도와 서도의 가장 가까운 해안 사이 거리는 약 151m예요. | N30: dk-shore-gap | O30: 대한민국 한국해양과학기술원 · 독도 지형 및 지질 https://www.dokdo.re.kr/home/cms/cmsCont.do?cntnts_sn=66 대한민국 국가유산청 · 독도 천연보호구역 https://www.heritage.go.kr/heri/cul/culSelectDetail.do?VdkVgwKey=16%2C03360000%2C37&pageNo=1_1_2_0 | P30: =LEN(F30)+MAX(LEN(G30),LEN(H30),LEN(I30),LEN(J30)) -> 32
A31: 920030 | B31: 910030 | C31: 동도와 서도 비교 | D31: 2 | E31: 2 | F31: 동도와 서도의 가장 가까운 해안 사이 거리는 약 얼마인가요? | G31: 151m | H31: 87.4km | I31: 98.6m | J31: 168.5m | K31: 1 | L31: 약 151m는 두 큰 섬의 가장 가까운 해안 사이 간격이에요. | M31: 동도와 서도의 가장 가까운 해안 사이 거리는 약 151m예요. | N31: dk-shore-gap | O31: 대한민국 한국해양과학기술원 · 독도 지형 및 지질 https://www.dokdo.re.kr/home/cms/cmsCont.do?cntnts_sn=66 대한민국 국가유산청 · 독도 천연보호구역 https://www.heritage.go.kr/heri/cul/culSelectDetail.do?VdkVgwKey=16%2C03360000%2C37&pageNo=1_1_2_0 | P31: =LEN(F31)+MAX(LEN(G31),LEN(H31),LEN(I31),LEN(J31)) -> 39
A32: 920031 | B32: 910031 | C32: 동도와 서도 비교 | D32: 3 | E32: 3 | F32: 151m라는 간격을 지도에 표시할 때 양 끝은 어디에 두어야 하나요? | G32: 두 섬의 정상 | H32: 등대와 주민숙소 | I32: 서로 가장 가까운 두 해안 | K32: 3 | L32: 151m는 가장 가까운 해안 사이 거리이므로 그 두 지점을 연결해요. | M32: 동도와 서도의 가장 가까운 해안 사이 거리는 약 151m예요. | N32: dk-shore-gap | O32: 대한민국 한국해양과학기술원 · 독도 지형 및 지질 https://www.dokdo.re.kr/home/cms/cmsCont.do?cntnts_sn=66 대한민국 국가유산청 · 독도 천연보호구역 https://www.heritage.go.kr/heri/cul/culSelectDetail.do?VdkVgwKey=16%2C03360000%2C37&pageNo=1_1_2_0 | P32: =LEN(F32)+MAX(LEN(G32),LEN(H32),LEN(I32),LEN(J32)) -> 52
A33: 920032 | B33: 910032 | C33: 동도와 서도 비교 | D33: 4 | E33: 3 | F33: 축척이 1cm당 50m인 지도에서 151m 간격은 약 몇 cm인가요? | G33: 7,550cm | H33: 3.02cm | I33: 151cm | J33: 0.302cm | K33: 2 | L33: 151÷50=3.02cm예요. 실제 간격을 1cm가 나타내는 거리로 나누어요. | M33: 동도와 서도의 가장 가까운 해안 사이 거리는 약 151m예요. | N33: dk-shore-gap | O33: 대한민국 한국해양과학기술원 · 독도 지형 및 지질 https://www.dokdo.re.kr/home/cms/cmsCont.do?cntnts_sn=66 대한민국 국가유산청 · 독도 천연보호구역 https://www.heritage.go.kr/heri/cul/culSelectDetail.do?VdkVgwKey=16%2C03360000%2C37&pageNo=1_1_2_0 | P33: =LEN(F33)+MAX(LEN(G33),LEN(H33),LEN(I33),LEN(J33)) -> 45
A34: 920033 | B34: 910033 | C34: 동도와 서도 비교 | D34: 1 | E34: 1 | F34: 독도에서 가파른 봉우리가 두드러지는 큰 섬은 무엇인가요? | G34: 서도 | H34: 동도 | K34: 1 | L34: 서도는 높고 가파르게 솟은 봉우리의 모습이 두드러져요. | M34: 서도는 가파르게 솟고, 동도는 정상 부근에 비교적 평탄한 공간이 있어요. | N34: dk-terrain-contrast | O34: 대한민국 국가유산청 · 독도 천연보호구역 https://www.heritage.go.kr/heri/cul/culSelectDetail.do?VdkVgwKey=16%2C03360000%2C37&pageNo=1_1_2_0 대한민국 전북교육청 · 독도 사진 자료 https://www.jbe.go.kr/dokdo/assets/sub/picture.html | P34: =LEN(F34)+MAX(LEN(G34),LEN(H34),LEN(I34),LEN(J34)) -> 33
A35: 920034 | B35: 910034 | C35: 동도와 서도 비교 | D35: 2 | E35: 2 | F35: 독도의 헬기장 등 시설이 자리한 비교적 평탄한 상부는 어느 섬에 있나요? | G35: 서도 | H35: 동도 | K35: 2 | L35: 동도 상부의 비교적 평탄한 곳에는 헬기장과 여러 시설이 있어요. | M35: 서도는 가파르게 솟고, 동도는 정상 부근에 비교적 평탄한 공간이 있어요. | N35: dk-terrain-contrast | O35: 대한민국 국가유산청 · 독도 천연보호구역 https://www.heritage.go.kr/heri/cul/culSelectDetail.do?VdkVgwKey=16%2C03360000%2C37&pageNo=1_1_2_0 대한민국 전북교육청 · 독도 사진 자료 https://www.jbe.go.kr/dokdo/assets/sub/picture.html | P35: =LEN(F35)+MAX(LEN(G35),LEN(H35),LEN(I35),LEN(J35)) -> 42
A36: 920035 | B36: 910035 | C36: 동도와 서도 비교 | D36: 3 | E36: 3 | F36: 지형 설명 A는 동도와 서도 중 어느 섬인가요? | G36: 동도 | H36: 서도 | K36: 1 | L36: A는 정상 부근이 비교적 평탄하고 시설이 있는 섬이므로 동도예요. | M36: 서도는 가파르게 솟고, 동도는 정상 부근에 비교적 평탄한 공간이 있어요. | N36: dk-terrain-contrast | O36: 대한민국 국가유산청 · 독도 천연보호구역 https://www.heritage.go.kr/heri/cul/culSelectDetail.do?VdkVgwKey=16%2C03360000%2C37&pageNo=1_1_2_0 대한민국 전북교육청 · 독도 사진 자료 https://www.jbe.go.kr/dokdo/assets/sub/picture.html | P36: =LEN(F36)+MAX(LEN(G36),LEN(H36),LEN(I36),LEN(J36)) -> 28
A37: 920036 | B37: 910036 | C37: 동도와 서도 비교 | D37: 4 | E37: 4 | F37: 독도 모형에서 동도를 서도와 똑같은 뾰족한 산으로 만들었다면 무엇을 고쳐야 하나요? | G37: 동도 상부의 비교적 평탄한 공간을 살린다 | H37: 동도를 서도보다 더 높게 만든다 | I37: 동도의 해안 절벽을 모두 없앤다 | K37: 1 | L37: 두 섬의 차이를 보여주려면 동도의 낮은 상부 공간과 주변 절벽을 함께 표현해야 해요. | M37: 서도는 가파르게 솟고, 동도는 정상 부근에 비교적 평탄한 공간이 있어요. | N37: dk-terrain-contrast | O37: 대한민국 국가유산청 · 독도 천연보호구역 https://www.heritage.go.kr/heri/cul/culSelectDetail.do?VdkVgwKey=16%2C03360000%2C37&pageNo=1_1_2_0 대한민국 전북교육청 · 독도 사진 자료 https://www.jbe.go.kr/dokdo/assets/sub/picture.html | P37: =LEN(F37)+MAX(LEN(G37),LEN(H37),LEN(I37),LEN(J37)) -> 68
A38: 920037 | B38: 910037 | C38: 동도와 서도 비교 | D38: 1 | E38: 1 | F38: 동도와 서도 아래 바닷속에도 독도의 지형이 이어지나요? | G38: 해수면에서 끝나요 | H38: 바닷속으로 이어져요 | K38: 2 | L38: 동도·서도는 해저 화산체의 일부가 물 위로 드러난 모습이에요. | M38: 동도·서도는 큰 해저 화산체에서 바다 위로 드러난 일부예요. | N38: dk-above-below | O38: 대한민국 한국해양과학기술원 · 독도 지형 및 지질 https://www.dokdo.re.kr/home/cms/cmsCont.do?cntnts_sn=66 | P38: =LEN(F38)+MAX(LEN(G38),LEN(H38),LEN(I38),LEN(J38)) -> 40
A39: 920038 | B39: 910038 | C39: 동도와 서도 비교 | D39: 2 | E39: 2 | F39: 독도의 두 큰 섬은 무엇의 일부가 바다 위로 드러난 것인가요? | G39: 강이 쌓은 삼각주 | H39: 해저 화산체 | I39: 산호가 쌓인 산호섬 | K39: 2 | L39: 바닷속 화산활동으로 자란 화산체의 윗부분이 바다 위에서 보여요. | M39: 동도·서도는 큰 해저 화산체에서 바다 위로 드러난 일부예요. | N39: dk-above-below | O39: 대한민국 한국해양과학기술원 · 독도 지형 및 지질 https://www.dokdo.re.kr/home/cms/cmsCont.do?cntnts_sn=66 | P39: =LEN(F39)+MAX(LEN(G39),LEN(H39),LEN(I39),LEN(J39)) -> 44
A40: 920039 | B40: 910039 | C40: 동도와 서도 비교 | D40: 3 | E40: 3 | F40: 독도 설명의 약 2,300m는 어디서부터 잰 규모인가요? | G40: 해수면부터 서도 정상까지 | H40: 해수면부터 동도 정상까지 | I40: 바닷속 화산체의 기저부부터 | K40: 3 | L40: 약 2,300m는 해저 기저부부터 화산체 전체를 본 높이예요. | M40: 동도·서도는 큰 해저 화산체에서 바다 위로 드러난 일부예요. | N40: dk-above-below | O40: 대한민국 한국해양과학기술원 · 독도 지형 및 지질 https://www.dokdo.re.kr/home/cms/cmsCont.do?cntnts_sn=66 | P40: =LEN(F40)+MAX(LEN(G40),LEN(H40),LEN(I40),LEN(J40)) -> 45
A41: 920040 | B41: 910040 | C41: 동도와 서도 비교 | D41: 4 | E41: 3 | F41: 168.5m와 약 2,300m를 함께 독도의 높이라고 쓰는 까닭은 무엇인가요? | G41: 높이를 재기 시작한 기준이 달라서 | H41: 168.5m는 동도, 2,300m는 서도 높이라서 | I41: 같은 시작점에서 잰 값의 단위만 달라서 | K41: 1 | L41: 168.5m는 해수면부터, 약 2,300m는 해저 기저부부터 설명한 높이예요. | M41: 동도·서도는 큰 해저 화산체에서 바다 위로 드러난 일부예요. | N41: dk-above-below | O41: 대한민국 한국해양과학기술원 · 독도 지형 및 지질 https://www.dokdo.re.kr/home/cms/cmsCont.do?cntnts_sn=66 | P41: =LEN(F41)+MAX(LEN(G41),LEN(H41),LEN(I41),LEN(J41)) -> 70
A42: 920041 | B42: 910041 | C42: 화산이 만든 독도 | D42: 1 | E42: 1 | F42: 독도를 처음 만든 자연 현상은 무엇인가요? | G42: 강물의 모래 퇴적 | H42: 산호의 성장 | I42: 바닷속 화산활동 | J42: 빙하의 퇴적 | K42: 3 | L42: 바닷속에서 분출된 화산 물질이 쌓이며 독도 화산체가 만들어졌어요. | M42: 독도는 바닷속 화산활동으로 분출된 물질이 쌓여 만들어졌어요. | N42: dk-volcano | O42: 대한민국 한국해양과학기술원 · 독도 지형 및 지질 https://www.dokdo.re.kr/home/cms/cmsCont.do?cntnts_sn=66 | P42: =LEN(F42)+MAX(LEN(G42),LEN(H42),LEN(I42),LEN(J42)) -> 32
A43: 920042 | B43: 910042 | C43: 화산이 만든 독도 | D43: 2 | E43: 1 | F43: 독도의 화산활동이 시작된 곳은 어디인가요? | G43: 육지 강의 하구 | H43: 바닷속 | I43: 해안 모래사장 | K43: 2 | L43: 독도 화산체는 바닷속에서 자라 나중에 일부가 수면 위로 드러났어요. | M43: 독도는 바닷속 화산활동으로 분출된 물질이 쌓여 만들어졌어요. | N43: dk-volcano | O43: 대한민국 한국해양과학기술원 · 독도 지형 및 지질 https://www.dokdo.re.kr/home/cms/cmsCont.do?cntnts_sn=66 | P43: =LEN(F43)+MAX(LEN(G43),LEN(H43),LEN(I43),LEN(J43)) -> 31
A44: 920043 | B44: 910043 | C44: 화산이 만든 독도 | D44: 3 | E44: 3 | F44: 독도의 형성 과정을 순서대로 놓으면 무엇인가요? | G44: 수면 위 출현 → 해저 분출 → 물질이 쌓임 | H44: 물질이 쌓임 → 수면 위 출현 → 첫 해저 분출 | I44: 해저 분출 → 물질이 쌓임 → 일부가 수면 위로 드러남 | K44: 3 | L44: 분출된 물질이 쌓여 화산체가 커진 뒤 일부가 물 위로 드러났어요. | M44: 독도는 바닷속 화산활동으로 분출된 물질이 쌓여 만들어졌어요. | N44: dk-volcano | O44: 대한민국 한국해양과학기술원 · 독도 지형 및 지질 https://www.dokdo.re.kr/home/cms/cmsCont.do?cntnts_sn=66 | P44: =LEN(F44)+MAX(LEN(G44),LEN(H44),LEN(I44),LEN(J44)) -> 56
A45: 920044 | B45: 910044 | C45: 화산이 만든 독도 | D45: 4 | E45: 3 | F45: 독도 해안이 파도에 깎인다는 사실과 화산 기원을 함께 설명한 것은 무엇인가요? | G45: 화산이 섬을 만들고, 이후 파도가 해안을 깎았다 | H45: 파도가 화산 물질을 처음 분출시켰다 | I45: 화산으로 생긴 뒤 해안은 변하지 않았다 | K45: 1 | L45: 처음 만들어진 원인과 이후 모양이 변한 원인은 다를 수 있어요. 독도에는 두 과정이 이어졌어요. | M45: 독도는 바닷속 화산활동으로 분출된 물질이 쌓여 만들어졌어요. | N45: dk-volcano | O45: 대한민국 한국해양과학기술원 · 독도 지형 및 지질 https://www.dokdo.re.kr/home/cms/cmsCont.do?cntnts_sn=66 | P45: =LEN(F45)+MAX(LEN(G45),LEN(H45),LEN(I45),LEN(J45)) -> 69
A46: 920045 | B46: 910045 | C46: 화산이 만든 독도 | D46: 1 | E46: 1 | F46: 독도는 먼저 어디에서 자란 뒤 물 위로 드러났나요? | G46: 울릉도 육지 위 | H46: 동해 바닷속 | I46: 한반도 강 하구 | K46: 2 | L46: 독도는 바닷속 화산체가 자라 일부가 물 위로 드러난 섬이에요. | M46: 독도는 해저에서 자란 뒤 수면 위로 드러났고, 오랜 시간 침식되며 모습이 달라졌어요. | N46: dk-formation-time | O46: 대한민국 한국해양과학기술원 · 독도 지형 및 지질 https://www.dokdo.re.kr/home/cms/cmsCont.do?cntnts_sn=66 | P46: =LEN(F46)+MAX(LEN(G46),LEN(H46),LEN(I46),LEN(J46)) -> 36
A47: 920046 | B47: 910046 | C47: 화산이 만든 독도 | D47: 2 | E47: 2 | F47: 독도가 생긴 뒤 해안을 깎아 온 작용은 무엇인가요? | G47: 산호가 섬을 덮는 성장 | H47: 강 하구에 모래가 쌓이는 퇴적 | I47: 파도 등에 의한 침식 | K47: 3 | L47: 바다 위로 나온 뒤에도 파도에 깎이면서 독도의 해안 모양이 변했어요. | M47: 독도는 해저에서 자란 뒤 수면 위로 드러났고, 오랜 시간 침식되며 모습이 달라졌어요. | N47: dk-formation-time | O47: 대한민국 한국해양과학기술원 · 독도 지형 및 지질 https://www.dokdo.re.kr/home/cms/cmsCont.do?cntnts_sn=66 | P47: =LEN(F47)+MAX(LEN(G47),LEN(H47),LEN(I47),LEN(J47)) -> 44
A48: 920047 | B48: 910047 | C48: 화산이 만든 독도 | D48: 3 | E48: 3 | F48: 제시된 독도 형성 연표에서 먼저 일어난 일은 무엇인가요? | G48: 해저 화산활동 시작 | H48: 수면 위로 드러남 | K48: 1 | L48: 약 460만 년 전이 약 250만 년 전보다 더 오래전이에요. | M48: 독도는 해저에서 자란 뒤 수면 위로 드러났고, 오랜 시간 침식되며 모습이 달라졌어요. | N48: dk-formation-time | O48: 대한민국 한국해양과학기술원 · 독도 지형 및 지질 https://www.dokdo.re.kr/home/cms/cmsCont.do?cntnts_sn=66 | P48: =LEN(F48)+MAX(LEN(G48),LEN(H48),LEN(I48),LEN(J48)) -> 41
A49: 920048 | B49: 910048 | C49: 화산이 만든 독도 | D49: 4 | E49: 3 | F49: 형성 연표에서 460만 년 전과 250만 년 전의 차이는 약 몇 년인가요? | G49: 710만 년 | H49: 21만 년 | I49: 250만 년 | J49: 210만 년 | K49: 4 | L49: 460만−250만=210만 년이에요. 자료의 대략적인 시점끼리 계산한 차이예요. | M49: 독도는 해저에서 자란 뒤 수면 위로 드러났고, 오랜 시간 침식되며 모습이 달라졌어요. | N49: dk-formation-time | O49: 대한민국 한국해양과학기술원 · 독도 지형 및 지질 https://www.dokdo.re.kr/home/cms/cmsCont.do?cntnts_sn=66 | P49: =LEN(F49)+MAX(LEN(G49),LEN(H49),LEN(I49),LEN(J49)) -> 47
A50: 920049 | B50: 910049 | C50: 화산이 만든 독도 | D50: 1 | E50: 1 | F50: 독도 해안의 바위를 깎는 바닷물의 움직임은 무엇인가요? | G50: 파도 | H50: 강의 흐름 | I50: 빙하의 이동 | K50: 1 | L50: 파도가 해안에 부딪치며 바위를 깎는 작용을 해요. | M50: 파도는 독도 해안의 바위를 깎아 절벽·동굴·아치 같은 지형을 만드는 데 영향을 주어요. | N50: dk-wave-erosion | O50: 대한민국 한국해양과학기술원 · 독도 지형 및 지질 https://www.dokdo.re.kr/home/cms/cmsCont.do?cntnts_sn=66 대한민국 한국관광공사 · 독립문바위 https://korean.visitkorea.or.kr/detail/ms_detail.do?cotid=0fe4eeb6-3f6a-48b1-ab75-c8d4ab6b43be | P50: =LEN(F50)+MAX(LEN(G50),LEN(H50),LEN(I50),LEN(J50)) -> 36
A51: 920050 | B51: 910050 | C51: 화산이 만든 독도 | D51: 2 | E51: 2 | F51: 독도 해안의 바위가 파도에 깎이는 작용을 무엇이라고 하나요? | G51: 퇴적 | H51: 해식 | I51: 분출 | K51: 2 | L51: 해식은 바다의 파도 등이 해안 지형을 깎는 작용이에요. | M51: 파도는 독도 해안의 바위를 깎아 절벽·동굴·아치 같은 지형을 만드는 데 영향을 주어요. | N51: dk-wave-erosion | O51: 대한민국 한국해양과학기술원 · 독도 지형 및 지질 https://www.dokdo.re.kr/home/cms/cmsCont.do?cntnts_sn=66 대한민국 한국관광공사 · 독립문바위 https://korean.visitkorea.or.kr/detail/ms_detail.do?cotid=0fe4eeb6-3f6a-48b1-ab75-c8d4ab6b43be | P51: =LEN(F51)+MAX(LEN(G51),LEN(H51),LEN(I51),LEN(J51)) -> 35
A52: 920051 | B52: 910051 | C52: 화산이 만든 독도 | D52: 3 | E52: 3 | F52: 설명된 독립문바위의 아치 구멍을 만드는 데 영향을 준 작용은 무엇인가요? | G52: 강이 실어 온 모래가 쌓이는 작용 | H52: 산호가 고리 모양으로 자라는 작용 | I52: 해안 바위가 파도에 깎이는 작용 | K52: 3 | L52: 바위가 깎여 통로가 생긴 해식아치이므로 파도의 침식과 연결돼요. | M52: 파도는 독도 해안의 바위를 깎아 절벽·동굴·아치 같은 지형을 만드는 데 영향을 주어요. | N52: dk-wave-erosion | O52: 대한민국 한국해양과학기술원 · 독도 지형 및 지질 https://www.dokdo.re.kr/home/cms/cmsCont.do?cntnts_sn=66 대한민국 한국관광공사 · 독립문바위 https://korean.visitkorea.or.kr/detail/ms_detail.do?cotid=0fe4eeb6-3f6a-48b1-ab75-c8d4ab6b43be | P52: =LEN(F52)+MAX(LEN(G52),LEN(H52),LEN(I52),LEN(J52)) -> 58
A53: 920052 | B53: 910052 | C53: 화산이 만든 독도 | D53: 4 | E53: 3 | F53: 독도 바위를 관찰해 해식 지형으로 분류할 수 있는 설명은 무엇인가요? | G53: 바닷가 암벽의 약한 부분이 깎여 구멍이 생겼다 | H53: 해저에서 분출물이 쌓여 화산체가 커졌다 | I53: 모래가 물 밑에 가라앉아 새 층을 이루었다 | K53: 1 | L53: 해안 바위가 깎인 과정이므로 해식 지형의 설명에 맞아요. | M53: 파도는 독도 해안의 바위를 깎아 절벽·동굴·아치 같은 지형을 만드는 데 영향을 주어요. | N53: dk-wave-erosion | O53: 대한민국 한국해양과학기술원 · 독도 지형 및 지질 https://www.dokdo.re.kr/home/cms/cmsCont.do?cntnts_sn=66 대한민국 한국관광공사 · 독립문바위 https://korean.visitkorea.or.kr/detail/ms_detail.do?cotid=0fe4eeb6-3f6a-48b1-ab75-c8d4ab6b43be | P53: =LEN(F53)+MAX(LEN(G53),LEN(H53),LEN(I53),LEN(J53)) -> 63
A54: 920053 | B54: 910053 | C54: 화산이 만든 독도 | D54: 1 | E54: 1 | F54: 독도의 바위가 바람과 추위 등에 오래 노출되어 약해지는 과정을 무엇이라고 하나요? | G54: 분출 | H54: 풍화 | I54: 퇴적 | K54: 2 | L54: 풍화는 바위가 주변 환경의 영향을 받아 약해지거나 부서지는 과정이에요. | M54: 독도의 바위는 풍화로 약해지고 침식으로 깎이며, 이런 변화가 해안 모습을 바꿔요. | N54: dk-weathering | O54: 대한민국 한국해양과학기술원 · 독도 지형 및 지질 https://www.dokdo.re.kr/home/cms/cmsCont.do?cntnts_sn=66 | P54: =LEN(F54)+MAX(LEN(G54),LEN(H54),LEN(I54),LEN(J54)) -> 47
A55: 920054 | B55: 910054 | C55: 화산이 만든 독도 | D55: 2 | E55: 2 | F55: 독도 해안에서 깎인 바위 조각이 다른 곳에 쌓이는 과정은 무엇인가요? | G55: 분출 | H55: 풍화 | I55: 퇴적 | K55: 3 | L55: 옮겨진 조각이 쌓이는 단계는 퇴적이에요. 깎여 나오는 침식과 구분해요. | M55: 독도의 바위는 풍화로 약해지고 침식으로 깎이며, 이런 변화가 해안 모습을 바꿔요. | N55: dk-weathering | O55: 대한민국 한국해양과학기술원 · 독도 지형 및 지질 https://www.dokdo.re.kr/home/cms/cmsCont.do?cntnts_sn=66 | P55: =LEN(F55)+MAX(LEN(G55),LEN(H55),LEN(I55),LEN(J55)) -> 40
A56: 920055 | B56: 910055 | C56: 화산이 만든 독도 | D56: 3 | E56: 3 | F56: 독도 바위가 약해진 뒤 파도에 깎였다는 설명의 과정 순서는 무엇인가요? | G56: 풍화 → 침식 | H56: 퇴적 → 풍화 | I56: 분출 → 퇴적 | K56: 1 | L56: 먼저 바위가 약해지는 풍화가 있고, 이어 파도에 깎이는 침식이 있어요. | M56: 독도의 바위는 풍화로 약해지고 침식으로 깎이며, 이런 변화가 해안 모습을 바꿔요. | N56: dk-weathering | O56: 대한민국 한국해양과학기술원 · 독도 지형 및 지질 https://www.dokdo.re.kr/home/cms/cmsCont.do?cntnts_sn=66 | P56: =LEN(F56)+MAX(LEN(G56),LEN(H56),LEN(I56),LEN(J56)) -> 46
A57: 920056 | B57: 910056 | C57: 화산이 만든 독도 | D57: 4 | E57: 4 | F57: 독도 해안선의 변화를 비교하려면 어느 자료 묶음이 적합한가요? | G57: 서도 전체 사진과 동도 한 바위의 확대 사진 | H57: 같은 해안 구간을 같은 축척으로 나타낸 두 시기의 자료 | I57: 동도 높이표와 울릉도 기온표 | K57: 2 | L57: 장소와 축척을 맞추어야 해안이 달라진 부분을 비교할 수 있어요. | M57: 독도의 바위는 풍화로 약해지고 침식으로 깎이며, 이런 변화가 해안 모습을 바꿔요. | N57: dk-weathering | O57: 대한민국 한국해양과학기술원 · 독도 지형 및 지질 https://www.dokdo.re.kr/home/cms/cmsCont.do?cntnts_sn=66 | P57: =LEN(F57)+MAX(LEN(G57),LEN(H57),LEN(I57),LEN(J57)) -> 64
A58: 920057 | B58: 910057 | C58: 화산이 만든 독도 | D58: 1 | E58: 1 | F58: 독도의 물골은 어느 큰 섬에 있나요? | G58: 동도 | H58: 서도 | K58: 2 | L58: 물골은 서도 해안에 있는 물이 모이는 곳이에요. | M58: 서도의 물골은 바위에서 물이 떨어지는 곳으로, 담수화 시설 이전에 식수원으로 쓰였어요. | N58: dk-mulgol | O58: 대한민국 한국해양과학기술원 · 독도 지형 및 지질 https://www.dokdo.re.kr/home/cms/cmsCont.do?cntnts_sn=66 대한민국 외교부 · 독도 주요시설물 https://dokdo.mofa.go.kr/kor/introduce/facility.jsp | P58: =LEN(F58)+MAX(LEN(G58),LEN(H58),LEN(I58),LEN(J58)) -> 22
A59: 920058 | B59: 910058 | C59: 화산이 만든 독도 | D59: 2 | E59: 2 | F59: 담수화 시설이 생기기 전, 독도의 물골은 주로 무엇에 쓰였나요? | G59: 배가 닿는 곳 | H59: 헬기가 내리는 곳 | I59: 마실 물을 얻는 곳 | K59: 3 | L59: 물골 바위에서 떨어지는 물을 식수원으로 이용했어요. | M59: 서도의 물골은 바위에서 물이 떨어지는 곳으로, 담수화 시설 이전에 식수원으로 쓰였어요. | N59: dk-mulgol | O59: 대한민국 한국해양과학기술원 · 독도 지형 및 지질 https://www.dokdo.re.kr/home/cms/cmsCont.do?cntnts_sn=66 대한민국 외교부 · 독도 주요시설물 https://dokdo.mofa.go.kr/kor/introduce/facility.jsp | P59: =LEN(F59)+MAX(LEN(G59),LEN(H59),LEN(I59),LEN(J59)) -> 45
A60: 920059 | B60: 910059 | C60: 화산이 만든 독도 | D60: 3 | E60: 3 | F60: 설명의 빈칸에 들어갈 지명은 무엇인가요? | G60: 물골 | H60: 천장굴 | I60: 독립문바위 | K60: 1 | L60: 서도에서 물을 얻던 장소라는 설명이 물골과 맞아요. | M60: 서도의 물골은 바위에서 물이 떨어지는 곳으로, 담수화 시설 이전에 식수원으로 쓰였어요. | N60: dk-mulgol | O60: 대한민국 한국해양과학기술원 · 독도 지형 및 지질 https://www.dokdo.re.kr/home/cms/cmsCont.do?cntnts_sn=66 대한민국 외교부 · 독도 주요시설물 https://dokdo.mofa.go.kr/kor/introduce/facility.jsp | P60: =LEN(F60)+MAX(LEN(G60),LEN(H60),LEN(I60),LEN(J60)) -> 27
A61: 920060 | B61: 910060 | C61: 화산이 만든 독도 | D61: 4 | E61: 3 | F61: 물골과 담수화 시설의 물 공급 방식을 바르게 짝지은 것은 무엇인가요? | G61: 물골: 바닷물을 끓이는 기계 / 담수화: 바위에서 떨어지는 물 | H61: 물골: 바위에서 떨어지는 물 / 담수화: 바닷물의 소금을 줄임 | I61: 둘 다 같은 바위틈에서 물을 모음 | K61: 2 | L61: 자연적으로 떨어지는 물을 모으는 방식과 바닷물을 처리하는 방식이 달라요. | M61: 서도의 물골은 바위에서 물이 떨어지는 곳으로, 담수화 시설 이전에 식수원으로 쓰였어요. | N61: dk-mulgol | O61: 대한민국 한국해양과학기술원 · 독도 지형 및 지질 https://www.dokdo.re.kr/home/cms/cmsCont.do?cntnts_sn=66 대한민국 외교부 · 독도 주요시설물 https://dokdo.mofa.go.kr/kor/introduce/facility.jsp | P61: =LEN(F61)+MAX(LEN(G61),LEN(H61),LEN(I61),LEN(J61)) -> 72
A62: 920061 | B62: 910061 | C62: 생명이 머무는 독도 | D62: 1 | E62: 1 | F62: 먼 거리를 이동하는 철새에게 독도는 어떤 곳인가요? | G62: 겨울에만 머무는 곳 | H62: 모든 새가 평생 머무는 곳 | I62: 이동 중 쉬어 가는 곳 | K62: 3 | L62: 바다를 건너는 철새는 독도에서 잠시 쉬었다가 이동을 이어갈 수 있어요. | M62: 독도는 먼 거리를 이동하는 철새가 쉬어 가는 중간 기착지예요. | N62: dk-migratory-stopover | O62: 대한민국 외교부 · 독도의 자연환경 https://dokdo.mofa.go.kr/kor/introduce/nature.jsp | P62: =LEN(F62)+MAX(LEN(G62),LEN(H62),LEN(I62),LEN(J62)) -> 42
A63: 920062 | B63: 910062 | C63: 생명이 머무는 독도 | D63: 2 | E63: 2 | F63: 철새가 이동하다 독도처럼 잠시 들러 쉬는 곳을 무엇이라고 하나요? | G63: 중간 기착지 | H63: 번식지 | I63: 월동지 | K63: 1 | L63: 이동 중 잠시 들르는 휴식 장소를 중간 기착지라고 해요. | M63: 독도는 먼 거리를 이동하는 철새가 쉬어 가는 중간 기착지예요. | N63: dk-migratory-stopover | O63: 대한민국 외교부 · 독도의 자연환경 https://dokdo.mofa.go.kr/kor/introduce/nature.jsp | P63: =LEN(F63)+MAX(LEN(G63),LEN(H63),LEN(I63),LEN(J63)) -> 42
A64: 920063 | B64: 910063 | C64: 생명이 머무는 독도 | D64: 3 | E64: 3 | F64: 이동 경로가 ‘출발지 → 독도에서 휴식 → 목적지’라면 독도의 역할은 무엇인가요? | G64: 출발지 | H64: 중간 기착지 | I64: 최종 목적지 | K64: 2 | L64: 출발지와 목적지 사이에서 쉬었으므로 중간 기착지에 해당해요. | M64: 독도는 먼 거리를 이동하는 철새가 쉬어 가는 중간 기착지예요. | N64: dk-migratory-stopover | O64: 대한민국 외교부 · 독도의 자연환경 https://dokdo.mofa.go.kr/kor/introduce/nature.jsp | P64: =LEN(F64)+MAX(LEN(G64),LEN(H64),LEN(I64),LEN(J64)) -> 51
A65: 920064 | B65: 910064 | C65: 생명이 머무는 독도 | D65: 4 | E65: 3 | F65: 독도의 두 새 관찰에서 ‘중간 기착’에 해당하는 것은 무엇인가요? | G65: A: 이동 중 잠시 쉬고 다른 곳으로 떠남 | H65: B: 둥지에서 알을 품고 새끼를 기름 | K65: 1 | L65: 긴 이동을 이어가기 전 쉬는 행동이 중간 기착에 해당해요. | M65: 독도는 먼 거리를 이동하는 철새가 쉬어 가는 중간 기착지예요. | N65: dk-migratory-stopover | O65: 대한민국 외교부 · 독도의 자연환경 https://dokdo.mofa.go.kr/kor/introduce/nature.jsp | P65: =LEN(F65)+MAX(LEN(G65),LEN(H65),LEN(I65),LEN(J65)) -> 59
A66: 920065 | B66: 910065 | C66: 생명이 머무는 독도 | D66: 1 | E66: 1 | F66: 독도에서 번식하는 바닷새는 어느 것인가요? | G66: 황제펭귄 | H66: 타조 | I66: 괭이갈매기 | K66: 3 | L66: 괭이갈매기는 독도의 대표적인 번식 바닷새로 소개돼요. | M66: 괭이갈매기·바다제비·슴새는 독도에서 번식하는 바닷새로 소개돼요. | N66: dk-breeding-birds | O66: 대한민국 국가유산청 · 독도 천연보호구역 https://www.heritage.go.kr/heri/cul/culSelectDetail.do?VdkVgwKey=16%2C03360000%2C37&pageNo=1_1_2_0 대한민국 외교부 · 독도의 자연환경 https://dokdo.mofa.go.kr/kor/introduce/nature.jsp | P66: =LEN(F66)+MAX(LEN(G66),LEN(H66),LEN(I66),LEN(J66)) -> 28
A67: 920066 | B67: 910066 | C67: 생명이 머무는 독도 | D67: 2 | E67: 2 | F67: 괭이갈매기가 독도에서 번식한다는 뜻은 무엇인가요? | G67: 알을 낳고 새끼를 기른다 | H67: 잠시 쉬었다가 떠나기만 한다 | I67: 먹이만 찾고 떠난다 | K67: 1 | L67: 번식은 새끼를 낳거나 알에서 부화시켜 다음 세대를 이어가는 일이에요. | M67: 괭이갈매기·바다제비·슴새는 독도에서 번식하는 바닷새로 소개돼요. | N67: dk-breeding-birds | O67: 대한민국 국가유산청 · 독도 천연보호구역 https://www.heritage.go.kr/heri/cul/culSelectDetail.do?VdkVgwKey=16%2C03360000%2C37&pageNo=1_1_2_0 대한민국 외교부 · 독도의 자연환경 https://dokdo.mofa.go.kr/kor/introduce/nature.jsp | P67: =LEN(F67)+MAX(LEN(G67),LEN(H67),LEN(I67),LEN(J67)) -> 42
A68: 920067 | B68: 910067 | C68: 생명이 머무는 독도 | D68: 3 | E68: 3 | F68: 독도에서 번식한다고 소개된 새만 모은 것은 무엇인가요? | G68: 괭이갈매기·황제펭귄·슴새 | H68: 괭이갈매기·바다제비·슴새 | I68: 바다제비·슴새·타조 | K68: 2 | L68: 자료에서 번식 조류로 제시한 세 종류가 모두 들어 있어요. | M68: 괭이갈매기·바다제비·슴새는 독도에서 번식하는 바닷새로 소개돼요. | N68: dk-breeding-birds | O68: 대한민국 국가유산청 · 독도 천연보호구역 https://www.heritage.go.kr/heri/cul/culSelectDetail.do?VdkVgwKey=16%2C03360000%2C37&pageNo=1_1_2_0 대한민국 외교부 · 독도의 자연환경 https://dokdo.mofa.go.kr/kor/introduce/nature.jsp | P68: =LEN(F68)+MAX(LEN(G68),LEN(H68),LEN(I68),LEN(J68)) -> 43
A69: 920068 | B69: 910068 | C69: 생명이 머무는 독도 | D69: 4 | E69: 3 | F69: 독도의 ‘번식지’ 기능을 보여 주는 관찰은 무엇인가요? | G69: 철새가 바위에서 쉬고 곧 떠난다 | H69: 새가 섬 위를 지나가며 날아간다 | I69: 괭이갈매기가 둥지의 새끼에게 먹이를 준다 | K69: 3 | L69: 둥지에서 새끼를 기르는 행동이므로 번식지를 이용하는 모습이에요. | M69: 괭이갈매기·바다제비·슴새는 독도에서 번식하는 바닷새로 소개돼요. | N69: dk-breeding-birds | O69: 대한민국 국가유산청 · 독도 천연보호구역 https://www.heritage.go.kr/heri/cul/culSelectDetail.do?VdkVgwKey=16%2C03360000%2C37&pageNo=1_1_2_0 대한민국 외교부 · 독도의 자연환경 https://dokdo.mofa.go.kr/kor/introduce/nature.jsp | P69: =LEN(F69)+MAX(LEN(G69),LEN(H69),LEN(I69),LEN(J69)) -> 52
A70: 920069 | B70: 910069 | C70: 생명이 머무는 독도 | D70: 1 | E70: 1 | F70: 독도 바닷속에서 자라는 바닷말은 어느 것인가요? | G70: 미역 | H70: 슴새 | I70: 해국 | K70: 1 | L70: 미역은 독도 주변 바다에서 소개하는 바닷말 가운데 하나예요. | M70: 독도에는 하늘을 나는 바닷새와 바닷속에 자라는 바닷말이 함께 있어요. | N70: dk-birds-and-seaweed | O70: 대한민국 외교부 · 독도의 자연환경 https://dokdo.mofa.go.kr/kor/introduce/nature.jsp 대한민국 국가유산청 · 독도 천연보호구역 https://www.heritage.go.kr/heri/cul/culSelectDetail.do?VdkVgwKey=16%2C03360000%2C37&pageNo=1_1_2_0 | P70: =LEN(F70)+MAX(LEN(G70),LEN(H70),LEN(I70),LEN(J70)) -> 28
A71: 920070 | B71: 910070 | C71: 생명이 머무는 독도 | D71: 2 | E71: 2 | F71: 독도의 괭이갈매기와 미역을 종류별로 짝지으면 무엇인가요? | G71: 바닷말 / 바닷새 | H71: 바닷새 / 바닷말 | I71: 바닷새 / 바닷새 | K71: 2 | L71: 괭이갈매기는 새이고 미역은 바닷속에서 자라는 해조류예요. | M71: 독도에는 하늘을 나는 바닷새와 바닷속에 자라는 바닷말이 함께 있어요. | N71: dk-birds-and-seaweed | O71: 대한민국 외교부 · 독도의 자연환경 https://dokdo.mofa.go.kr/kor/introduce/nature.jsp 대한민국 국가유산청 · 독도 천연보호구역 https://www.heritage.go.kr/heri/cul/culSelectDetail.do?VdkVgwKey=16%2C03360000%2C37&pageNo=1_1_2_0 | P71: =LEN(F71)+MAX(LEN(G71),LEN(H71),LEN(I71),LEN(J71)) -> 40
A72: 920071 | B72: 910071 | C72: 생명이 머무는 독도 | D72: 3 | E72: 3 | F72: ‘독도는 해조류(海鳥類)의 번식지’에서 해조류는 무엇을 뜻하나요? | G72: 바닷말 | H72: 바다 물고기 | I72: 바닷새 | K72: 3 | L72: 새 조(鳥)가 쓰였으므로 바닷새라는 뜻이에요. | M72: 독도에는 하늘을 나는 바닷새와 바닷속에 자라는 바닷말이 함께 있어요. | N72: dk-birds-and-seaweed | O72: 대한민국 외교부 · 독도의 자연환경 https://dokdo.mofa.go.kr/kor/introduce/nature.jsp 대한민국 국가유산청 · 독도 천연보호구역 https://www.heritage.go.kr/heri/cul/culSelectDetail.do?VdkVgwKey=16%2C03360000%2C37&pageNo=1_1_2_0 | P72: =LEN(F72)+MAX(LEN(G72),LEN(H72),LEN(I72),LEN(J72)) -> 42
A73: 920072 | B73: 910072 | C73: 생명이 머무는 독도 | D73: 4 | E73: 3 | F73: 독도 생물 목록을 ‘바닷말’로만 묶으면 어느 조합인가요? | G73: 미역·다시마 | H73: 미역·슴새 | I73: 괭이갈매기·바다제비 | K73: 1 | L73: 두 종류 모두 독도 자연환경 안내에 나온 바닷말이에요. | M73: 독도에는 하늘을 나는 바닷새와 바닷속에 자라는 바닷말이 함께 있어요. | N73: dk-birds-and-seaweed | O73: 대한민국 외교부 · 독도의 자연환경 https://dokdo.mofa.go.kr/kor/introduce/nature.jsp 대한민국 국가유산청 · 독도 천연보호구역 https://www.heritage.go.kr/heri/cul/culSelectDetail.do?VdkVgwKey=16%2C03360000%2C37&pageNo=1_1_2_0 | P73: =LEN(F73)+MAX(LEN(G73),LEN(H73),LEN(I73),LEN(J73)) -> 41
A74: 920073 | B74: 910073 | C74: 생명이 머무는 독도 | D74: 1 | E74: 1 | F74: 독도 땅에 자라는 꽃식물은 어느 것인가요? | G74: 미역 | H74: 해국 | I74: 다시마 | K74: 2 | L74: 해국은 독도 식물 목록에 소개되는 땅 위 식물이에요. | M74: 독도 땅에는 해국·섬기린초·땅채송화 같은 식물이 자라요. | N74: dk-coastal-plants | O74: 대한민국 외교부 · 독도의 자연환경 https://dokdo.mofa.go.kr/kor/introduce/nature.jsp | P74: =LEN(F74)+MAX(LEN(G74),LEN(H74),LEN(I74),LEN(J74)) -> 26
A75: 920074 | B75: 910074 | C75: 생명이 머무는 독도 | D75: 2 | E75: 2 | F75: 독도에서 해국과 섬기린초를 함께 조사한다면 무엇을 조사하는 것인가요? | G75: 번식하는 바닷새 | H75: 바닷속 물고기 | I75: 땅 위 식물 | K75: 3 | L75: 해국과 섬기린초는 독도 땅에 자라는 식물이에요. | M75: 독도 땅에는 해국·섬기린초·땅채송화 같은 식물이 자라요. | N75: dk-coastal-plants | O75: 대한민국 외교부 · 독도의 자연환경 https://dokdo.mofa.go.kr/kor/introduce/nature.jsp | P75: =LEN(F75)+MAX(LEN(G75),LEN(H75),LEN(I75),LEN(J75)) -> 46
A76: 920075 | B76: 910075 | C76: 생명이 머무는 독도 | D76: 3 | E76: 3 | F76: 제시된 독도 목록에서 육상 식물끼리 묶인 것은 무엇인가요? | G76: 섬기린초·땅채송화 | H76: 섬기린초·미역 | I76: 미역·다시마 | K76: 1 | L76: 두 식물은 육상 식물 목록에 있어요. | M76: 독도 땅에는 해국·섬기린초·땅채송화 같은 식물이 자라요. | N76: dk-coastal-plants | O76: 대한민국 외교부 · 독도의 자연환경 https://dokdo.mofa.go.kr/kor/introduce/nature.jsp | P76: =LEN(F76)+MAX(LEN(G76),LEN(H76),LEN(I76),LEN(J76)) -> 41
A77: 920076 | B77: 910076 | C77: 생명이 머무는 독도 | D77: 4 | E77: 3 | F77: 독도 식물 조사에서 미역만 기록했다면 추가해야 할 조사 대상은 무엇인가요? | G77: 다시마 등 바닷말만 | H77: 해국·섬기린초 등 땅 위 식물 | I77: 괭이갈매기 등 바닷새 | K77: 2 | L77: 미역만으로는 독도 땅의 식물을 조사한 것이 아니므로 육상 식물을 더 살펴야 해요. | M77: 독도 땅에는 해국·섬기린초·땅채송화 같은 식물이 자라요. | N77: dk-coastal-plants | O77: 대한민국 외교부 · 독도의 자연환경 https://dokdo.mofa.go.kr/kor/introduce/nature.jsp | P77: =LEN(F77)+MAX(LEN(G77),LEN(H77),LEN(I77),LEN(J77)) -> 57
... A101: 920100 | B101: 910100 | C101: 독도 바다의 연결 | D101: 4 | E101: 4 | F101: 강치 연구의 번식 가정이 달라졌을 때 다시 해야 할 일은 무엇인가요? | G101: 기존 계산값을 직접 관찰값으로 바꾸어 표시 | H101: 바뀐 가정으로 계산해 결과가 얼마나 달라지는지 비교 | I101: 포획 기록의 숫자를 결과에 맞게 바꾸기 | K101: 2 | L101: 모형 결과가 가정에 얼마나 의존하는지 확인하는 방법이에요. | M101: 과거 강치 개체 수의 모형 추정값은 당시 현장에서 전부 센 값과 구분해야 해요. | N101: dk-model-evidence | O101: 국제 학술지 JMSE · Lee 외 강치 개체군 연구(2022) https://www.mdpi.com/2077-1312/10/2/271 대한민국 해양수산부 · 독도 강치 연구 발표(2022) https://www.mof.go.kr/doc/ko/selectDoc.do?bbsSeq=10&docSeq=45126&menuSeq=971 | P101: =LEN(F101)+MAX(LEN(G101),LEN(H101),LEN(I101),LEN(J101)) -> 66
A102: 920101 | B102: 910101 | C102: 사람과 시설 | D102: 1 | E102: 1 | F102: 독도등대는 어느 큰 섬에 있나요? | G102: 서도 | H102: 동도 | K102: 2 | L102: 등대는 동도에 있어요. 서도에는 주민숙소가 있어요. | M102: 독도등대는 동도에 있으며, 배가 바다에서 위치를 알아보는 데 도움을 주어요. | N102: dk-lighthouse | O102: 대한민국 외교부 · 독도 주요시설물 https://dokdo.mofa.go.kr/kor/introduce/facility.jsp | P102: =LEN(F102)+MAX(LEN(G102),LEN(H102),LEN(I102),LEN(J102)) -> 20
A103: 920102 | B103: 910102 | C103: 사람과 시설 | D103: 2 | E103: 2 | F103: 독도등대가 바다를 지나는 배에 주는 도움은 무엇인가요? | G103: 배가 닿을 접안 공간을 제공한다 | H103: 바닷물을 마실 물로 바꾼다 | I103: 빛으로 위치를 알아보게 한다 | K103: 3 | L103: 등대의 빛은 배가 바다에서 위치를 파악하는 항해 표지가 돼요. | M103: 독도등대는 동도에 있으며, 배가 바다에서 위치를 알아보는 데 도움을 주어요. | N103: dk-lighthouse | O103: 대한민국 외교부 · 독도 주요시설물 https://dokdo.mofa.go.kr/kor/introduce/facility.jsp | P103: =LEN(F103)+MAX(LEN(G103),LEN(H103),LEN(I103),LEN(J103)) -> 47
A104: 920103 | B104: 910103 | C104: 사람과 시설 | D104: 3 | E104: 3 | F104: 동도에서 빛을 이용해 항해를 돕는 시설의 이름은 무엇인가요? | G104: 독도등대 | H104: 접안시설 | I104: 담수화 시설 | K104: 1 | L104: 위치와 기능을 함께 읽으면 동도의 독도등대를 찾을 수 있어요. | M104: 독도등대는 동도에 있으며, 배가 바다에서 위치를 알아보는 데 도움을 주어요. | N104: dk-lighthouse | O104: 대한민국 외교부 · 독도 주요시설물 https://dokdo.mofa.go.kr/kor/introduce/facility.jsp | P104: =LEN(F104)+MAX(LEN(G104),LEN(H104),LEN(I104),LEN(J104)) -> 39
A105: 920104 | B105: 910104 | C105: 사람과 시설 | D105: 4 | E105: 3 | F105: 독도에서 배의 위치 파악과 섬에 닿는 일을 각각 돕는 시설은 무엇인가요? | G105: 접안시설 → 등대 | H105: 등대 → 접안시설 | I105: 담수시설 → 주민숙소 | K105: 2 | L105: 등대는 항해 중 위치를 알아보게 하고, 접안시설은 실제로 배가 닿게 해요. | M105: 독도등대는 동도에 있으며, 배가 바다에서 위치를 알아보는 데 도움을 주어요. | N105: dk-lighthouse | O105: 대한민국 외교부 · 독도 주요시설물 https://dokdo.mofa.go.kr/kor/introduce/facility.jsp | P105: =LEN(F105)+MAX(LEN(G105),LEN(H105),LEN(I105),LEN(J105)) -> 51
A106: 920105 | B106: 910105 | C106: 사람과 시설 | D106: 1 | E106: 1 | F106: 일반 탐방객이 배에서 내리는 독도 선착장은 어느 큰 섬에 있나요? | G106: 동도 | H106: 서도 | K106: 1 | L106: 입도 안내에서 일반 탐방객의 관람 공간은 동도 선착장으로 안내해요. | M106: 독도의 주요 접안시설은 동도에 있으며 배가 섬에 닿는 공간이에요. | N106: dk-dock | O106: 대한민국 외교부 · 독도 주요시설물 https://dokdo.mofa.go.kr/kor/introduce/facility.jsp 대한민국 외교부 · 주민 및 입도 안내 https://dokdo.mofa.go.kr/kor/introduce/residence.jsp | P106: =LEN(F106)+MAX(LEN(G106),LEN(H106),LEN(I106),LEN(J106)) -> 38
A107: 920106 | B107: 910106 | C107: 사람과 시설 | D107: 2 | E107: 2 | F107: 독도의 ‘접안시설’은 무엇을 하는 곳인가요? | G107: 헬기가 착륙하는 곳 | H107: 밤에 빛으로 위치를 알리는 곳 | I107: 배가 섬에 닿고 사람이 내리는 곳 | K107: 3 | L107: 접안은 배를 육지나 시설에 대는 일이에요. | M107: 독도의 주요 접안시설은 동도에 있으며 배가 섬에 닿는 공간이에요. | N107: dk-dock | O107: 대한민국 외교부 · 독도 주요시설물 https://dokdo.mofa.go.kr/kor/introduce/facility.jsp 대한민국 외교부 · 주민 및 입도 안내 https://dokdo.mofa.go.kr/kor/introduce/residence.jsp | P107: =LEN(F107)+MAX(LEN(G107),LEN(H107),LEN(I107),LEN(J107)) -> 42
A108: 920107 | B108: 910107 | C108: 사람과 시설 | D108: 3 | E108: 3 | F108: 시설 안내에서 길이 80m로 소개된 동도 시설은 무엇인가요? | G108: 접안시설 | H108: 등대 | I108: 주민숙소 | K108: 1 | L108: 자료의 80m는 동도 접안시설 길이에 붙어 있어요. | M108: 독도의 주요 접안시설은 동도에 있으며 배가 섬에 닿는 공간이에요. | N108: dk-dock | O108: 대한민국 외교부 · 독도 주요시설물 https://dokdo.mofa.go.kr/kor/introduce/facility.jsp 대한민국 외교부 · 주민 및 입도 안내 https://dokdo.mofa.go.kr/kor/introduce/residence.jsp | P108: =LEN(F108)+MAX(LEN(G108),LEN(H108),LEN(I108),LEN(J108)) -> 37
A109: 920108 | B109: 910108 | C109: 사람과 시설 | D109: 4 | E109: 3 | F109: ‘80m 접안시설’과 ‘두 섬 사이 151m’의 측정 대상은 어떻게 다른가요? | G109: 둘 다 동도에서 서도까지 가는 거리 | H109: 80m는 시설 길이, 151m는 가장 가까운 해안 사이 거리 | I109: 80m는 동도 높이, 151m는 서도 높이 | K109: 2 | L109: 서로 다른 대상을 잰 값이므로 같은 길이라고 생각하거나 연결해서 더하지 않아요. | M109: 독도의 주요 접안시설은 동도에 있으며 배가 섬에 닿는 공간이에요. | N109: dk-dock | O109: 대한민국 외교부 · 독도 주요시설물 https://dokdo.mofa.go.kr/kor/introduce/facility.jsp 대한민국 외교부 · 주민 및 입도 안내 https://dokdo.mofa.go.kr/kor/introduce/residence.jsp | P109: =LEN(F109)+MAX(LEN(G109),LEN(H109),LEN(I109),LEN(J109)) -> 76
A110: 920109 | B110: 910109 | C110: 사람과 시설 | D110: 1 | E110: 1 | F110: 독도 주민숙소는 어느 큰 섬에 있나요? | G110: 동도 | H110: 서도 | K110: 2 | L110: 주민숙소는 서도에 있는 생활 시설이에요. | M110: 독도의 주민숙소는 서도에 있어요. | N110: dk-residence | O110: 대한민국 외교부 · 독도 주요시설물 https://dokdo.mofa.go.kr/kor/introduce/facility.jsp 대한민국 해양수산부 · 독도의 주소와 위치 https://www.mof.go.kr/doc/ko/selectDoc.do?bbsSeq=27&docSeq=20937&menuSeq=929 | P110: =LEN(F110)+MAX(LEN(G110),LEN(H110),LEN(I110),LEN(J110)) -> 23
A111: 920110 | B111: 910110 | C111: 사람과 시설 | D111: 2 | E111: 2 | F111: 서도 주민숙소의 주된 기능은 무엇인가요? | G111: 배의 위치를 알리는 항해 표지 | H111: 헬기 착륙 공간 | I111: 사람이 머무는 생활 공간 | K111: 3 | L111: 이름 그대로 독도에서 사람이 생활하는 공간으로 소개돼요. | M111: 독도의 주민숙소는 서도에 있어요. | N111: dk-residence | O111: 대한민국 외교부 · 독도 주요시설물 https://dokdo.mofa.go.kr/kor/introduce/facility.jsp 대한민국 해양수산부 · 독도의 주소와 위치 https://www.mof.go.kr/doc/ko/selectDoc.do?bbsSeq=27&docSeq=20937&menuSeq=929 | P111: =LEN(F111)+MAX(LEN(G111),LEN(H111),LEN(I111),LEN(J111)) -> 38
A112: 920111 | B112: 910111 | C112: 사람과 시설 | D112: 3 | E112: 3 | F112: 시설 목록에서 서도에 속하는 항목은 무엇인가요? | G112: 주민숙소 | H112: 독도등대 | I112: 독도경비대 | K112: 1 | L112: 목록에서 주민숙소의 섬이 서도로 표시돼요. | M112: 독도의 주민숙소는 서도에 있어요. | N112: dk-residence | O112: 대한민국 외교부 · 독도 주요시설물 https://dokdo.mofa.go.kr/kor/introduce/facility.jsp 대한민국 해양수산부 · 독도의 주소와 위치 https://www.mof.go.kr/doc/ko/selectDoc.do?bbsSeq=27&docSeq=20937&menuSeq=929 | P112: =LEN(F112)+MAX(LEN(G112),LEN(H112),LEN(I112),LEN(J112)) -> 31
A113: 920112 | B113: 910112 | C113: 사람과 시설 | D113: 4 | E113: 4 | F113: ‘독도의 생활 시설은 모두 동도에 있다’는 설명을 고칠 근거는 무엇인가요? | G113: 등대가 동도에 있다 | H113: 주민숙소가 서도에 있다 | I113: 접안시설이 동도에 있다 | K113: 2 | L113: 서도 생활 시설의 구체적인 사례가 있으므로 ‘모두 동도’라는 설명은 틀려요. | M113: 독도의 주민숙소는 서도에 있어요. | N113: dk-residence | O113: 대한민국 외교부 · 독도 주요시설물 https://dokdo.mofa.go.kr/kor/introduce/facility.jsp 대한민국 해양수산부 · 독도의 주소와 위치 https://www.mof.go.kr/doc/ko/selectDoc.do?bbsSeq=27&docSeq=20937&menuSeq=929 | P113: =LEN(F113)+MAX(LEN(G113),LEN(H113),LEN(I113),LEN(J113)) -> 53
A114: 920113 | B114: 910113 | C114: 사람과 시설 | D114: 1 | E114: 1 | F114: 독도에서 바닷물을 생활에 쓸 물로 바꾸는 시설은 무엇인가요? | G114: 등대 | H114: 접안시설 | I114: 담수화 시설 | K114: 3 | L114: 담수화는 바닷물의 소금을 줄이는 처리예요. | M114: 담수화 시설은 바닷물의 소금을 줄여 생활에 쓸 물을 만들어요. | N114: dk-freshwater | O114: 대한민국 외교부 · 독도 주요시설물 https://dokdo.mofa.go.kr/kor/introduce/facility.jsp 대한민국 한국해양과학기술원 · 독도 지형 및 지질 https://www.dokdo.re.kr/home/cms/cmsCont.do?cntnts_sn=66 | P114: =LEN(F114)+MAX(LEN(G114),LEN(H114),LEN(I114),LEN(J114)) -> 39
A115: 920114 | B115: 910114 | C115: 사람과 시설 | D115: 2 | E115: 2 | F115: 바닷물을 담수화할 때 주로 줄이려는 성분은 무엇인가요? | G115: 소금 | H115: 물 자체 | I115: 모래만 | K115: 1 | L115: 바닷물에 녹아 있는 소금을 줄여 생활에 쓸 담수를 얻어요. | M115: 담수화 시설은 바닷물의 소금을 줄여 생활에 쓸 물을 만들어요. | N115: dk-freshwater | O115: 대한민국 외교부 · 독도 주요시설물 https://dokdo.mofa.go.kr/kor/introduce/facility.jsp 대한민국 한국해양과학기술원 · 독도 지형 및 지질 https://www.dokdo.re.kr/home/cms/cmsCont.do?cntnts_sn=66 | P115: =LEN(F115)+MAX(LEN(G115),LEN(H115),LEN(I115),LEN(J115)) -> 34
A116: 920115 | B116: 910115 | C116: 사람과 시설 | D116: 3 | E116: 3 | F116: 독도의 물 공급에서 자연 식수원과 처리 시설을 바르게 짝지은 것은 무엇인가요? | G116: 담수화 시설 — 물골 | H116: 물골 — 담수화 시설 | I116: 등대 — 접안시설 | K116: 2 | L116: 물골은 자연적으로 떨어지는 물을 얻던 곳이고 담수화 시설은 바닷물을 처리해요. | M116: 담수화 시설은 바닷물의 소금을 줄여 생활에 쓸 물을 만들어요. | N116: dk-freshwater | O116: 대한민국 외교부 · 독도 주요시설물 https://dokdo.mofa.go.kr/kor/introduce/facility.jsp 대한민국 한국해양과학기술원 · 독도 지형 및 지질 https://www.dokdo.re.kr/home/cms/cmsCont.do?cntnts_sn=66 | P116: =LEN(F116)+MAX(LEN(G116),LEN(H116),LEN(I116),LEN(J116)) -> 54
A117: 920116 | B117: 910116 | C117: 사람과 시설 | D117: 4 | E117: 3 | F117: 바닷물에서 모래만 걸렀다면 독도 생활용 담수를 만든 것인가요? | G117: 네, 맑아 보이면 소금도 모두 사라져요 | H117: 네, 물을 차갑게 만들면 모두 담수가 돼요 | I117: 아니요, 녹아 있는 소금도 줄여야 해요 | K117: 3 | L117: 눈에 보이는 모래와 물속에 녹아 있는 염분은 다르므로 모래 제거만으로 담수화가 되지 않아요. | M117: 담수화 시설은 바닷물의 소금을 줄여 생활에 쓸 물을 만들어요. | N117: dk-freshwater | O117: 대한민국 외교부 · 독도 주요시설물 https://dokdo.mofa.go.kr/kor/introduce/facility.jsp 대한민국 한국해양과학기술원 · 독도 지형 및 지질 https://www.dokdo.re.kr/home/cms/cmsCont.do?cntnts_sn=66 | P117: =LEN(F117)+MAX(LEN(G117),LEN(H117),LEN(I117),LEN(J117)) -> 57
A118: 920117 | B118: 910117 | C118: 사람과 시설 | D118: 1 | E118: 1 | F118: 동도 선착장에서 위쪽 시설로 걸어갈 때 이용하는 길은 무엇인가요? | G118: 계단과 길 | H118: 화물 운반 케이블 | I118: 배가 다니는 항로 | K118: 1 | L118: 동도 선착장에서 위쪽 시설로는 계단과 길을 따라 걸어 올라가요. | M118: 동도 선착장과 상부 시설은 다른 장소이며 길과 운반 시설로 연결돼요. | N118: dk-routes | O118: 대한민국 외교부 · 독도 주요시설물 https://dokdo.mofa.go.kr/kor/introduce/facility.jsp 대한민국 전북교육청 · 독도 사진 자료 https://www.jbe.go.kr/dokdo/assets/sub/picture.html | P118: =LEN(F118)+MAX(LEN(G118),LEN(H118),LEN(I118),LEN(J118)) -> 45
A119: 920118 | B119: 910118 | C119: 사람과 시설 | D119: 2 | E119: 2 | F119: 동도 경사면의 계단은 선착장과 어느 곳을 연결하나요? | G119: 서도 주민숙소 | H119: 위쪽의 관리 시설 | I119: 울릉도 항구 | K119: 2 | L119: 동도는 높낮이가 있어 선착장에서 상부 시설까지 올라가는 길이 필요해요. | M119: 동도 선착장과 상부 시설은 다른 장소이며 길과 운반 시설로 연결돼요. | N119: dk-routes | O119: 대한민국 외교부 · 독도 주요시설물 https://dokdo.mofa.go.kr/kor/introduce/facility.jsp 대한민국 전북교육청 · 독도 사진 자료 https://www.jbe.go.kr/dokdo/assets/sub/picture.html | P119: =LEN(F119)+MAX(LEN(G119),LEN(H119),LEN(I119),LEN(J119)) -> 38
A120: 920119 | B120: 910119 | C120: 사람과 시설 | D120: 3 | E120: 3 | F120: 동도 선착장과 경비대 사이 시설로 안내된 것은 무엇인가요? | G120: 철도 | H120: 서도까지의 교량 | I120: 케이블카 | K120: 3 | L120: 주요 시설 안내에는 선착장과 경비대 사이 케이블카가 나와요. | M120: 동도 선착장과 상부 시설은 다른 장소이며 길과 운반 시설로 연결돼요. | N120: dk-routes | O120: 대한민국 외교부 · 독도 주요시설물 https://dokdo.mofa.go.kr/kor/introduce/facility.jsp 대한민국 전북교육청 · 독도 사진 자료 https://www.jbe.go.kr/dokdo/assets/sub/picture.html | P120: =LEN(F120)+MAX(LEN(G120),LEN(H120),LEN(I120),LEN(J120)) -> 40
A121: 920120 | B121: 910120 | C121: 사람과 시설 | D121: 4 | E121: 3 | F121: 동도 선착장부터 정상 시설까지 실제 이동 거리를 알아보려면 무엇을 재야 하나요? | G121: 계단과 굽은 길을 따라 잰 거리 | H121: 사진 위 두 점의 직선만 | I121: 동도 전체 해안선 길이 | K121: 1 | L121: 실제 이동은 길을 따라가므로 출발점과 끝점을 잇는 직선만 재면 부족해요. | M121: 동도 선착장과 상부 시설은 다른 장소이며 길과 운반 시설로 연결돼요. | N121: dk-routes | O121: 대한민국 외교부 · 독도 주요시설물 https://dokdo.mofa.go.kr/kor/introduce/facility.jsp 대한민국 전북교육청 · 독도 사진 자료 https://www.jbe.go.kr/dokdo/assets/sub/picture.html | P121: =LEN(F121)+MAX(LEN(G121),LEN(H121),LEN(I121),LEN(J121)) -> 61
A122: 920121 | B122: 910121 | C122: 옛 기록의 두 섬 | D122: 1 | E122: 1 | F122: 우산·무릉 두 섬을 기록한 조선의 지리 기록은 무엇인가요? | G122: 대한제국 칙령 제41호 | H122: 『세종실록』 지리지 | I122: 일본 태정관지령 | K122: 2 | L122: 이 기록은 조선의 지역 정보를 설명하며 우산·무릉 두 섬을 적고 있어요. | M122: 『세종실록』 지리지의 우산·무릉은 대한민국 외교부 해설에서 독도·울릉도로 풀이돼요. | N122: dk-sejong-record | O122: 대한민국 외교부 자료실 · 세종실록 지리지(1454) https://dokdo.mofa.go.kr/kor/pds/part06_view02.jsp | P122: =LEN(F122)+MAX(LEN(G122),LEN(H122),LEN(I122),LEN(J122)) -> 44
... A138: 920137 | B138: 910137 | C138: 옛 기록의 두 섬 | D138: 1 | E138: 1 | F138: 1696년 일본 에도 막부의 울릉도 도해금지령은 어느 달에 내려졌나요? | G138: 5월 | H138: 10월 | I138: 1월 | K138: 3 | L138: 연표에는 울릉도 도해금지령이 1696년 1월에 나와요. | M138: 1696년 1월 울릉도 도해금지령이 먼저이고, 안용복의 5월 일본 도해는 그 뒤예요. | N138: dk-an-chronology | O138: 대한민국 외교부 · 독도 연표 https://dokdo.mofa.go.kr/m/kor/dokdo/reason_list.jsp 대한민국 외교부 · 울릉도 도해금지령(1696) https://dokdo.mofa.go.kr/kor/pds/part05_view06.jsp | P138: =LEN(F138)+MAX(LEN(G138),LEN(H138),LEN(I138),LEN(J138)) -> 42
...

Sheet 보기해설711
A1: ID | B1: choice ID | C1: 보기 | D1: 정답 여부 | E1: 보기별 해설 | F1: English choice | G1: English feedback
A2: 920001 | B2: a | C2: 동도와 서도 | D2: 1 | E2: 동도와 서도가 독도의 두 큰 섬이에요. 둘레에는 작은 바위섬들도 있어요. | F2: Dongdo and Seodo | G2: Dongdo and Seodo are the two main islands, surrounded by smaller islets.
A3: 920001 | B3: b | C3: 울릉도와 동도 | D3: 0 | E3: 동도는 맞지만 울릉도는 독도에서 떨어진 별개의 섬이에요. 다른 큰 섬은 서도예요. | F3: Ulleungdo and Dongdo | G3: Dongdo belongs to Dokdo, but Ulleungdo is a separate island. The other main island is Seodo.
A4: 920001 | B4: c | C4: 제주도와 서도 | D4: 0 | E4: 서도는 맞지만 제주도는 독도를 이루는 섬이 아니에요. 서도와 짝을 이루는 큰 섬은 동도예요. | F4: Jejudo and Seodo | G4: Seodo belongs to Dokdo, but Jejudo does not. Its other main island is Dongdo.
A5: 920001 | B5: d | C5: 울릉도와 제주도 | D5: 0 | E5: 울릉도와 제주도는 모두 독도와 별개의 섬이에요. 독도의 두 큰 섬은 동도와 서도예요. | F5: Ulleungdo and Jejudo | G5: Both are separate from Dokdo. Dokdo’s main islands are Dongdo and Seodo.
A6: 920002 | B6: a | C6: 작은 바위섬들 | D6: 1 | E6: 독도에는 동도·서도뿐 아니라 둘레의 작은 바위섬들도 포함돼요. | F6: Smaller rocky islets | G6: Dokdo includes the surrounding rocky islets as well as Dongdo and Seodo.
A7: 920002 | B7: b | C7: 울릉도 본섬 | D7: 0 | E7: 울릉도는 독도 주변의 부속 바위섬이 아니라 별개의 섬이에요. | F7: The main island of Ulleungdo | G7: Ulleungdo is a separate island, not one of Dokdo’s associated islets.
A8: 920002 | B8: c | C8: 일본의 오키섬 | D8: 0 | E8: 오키섬은 독도의 부속 섬이 아니라 일본에 있는 별개의 섬들이에요. | F8: Japan’s Oki Islands | G8: The Oki Islands are in Japan and are not part of Dokdo.
A9: 920003 | B9: b | C9: 울릉도 전체 | D9: 0 | E9: 울릉도는 독도 구성 목록에 들어 있지 않아요. 주변 부속 바위섬을 더해야 해요. | F9: All of Ulleungdo | G9: Ulleungdo is not part of the listed land area. The missing land is the associated islets.
A10: 920003 | B10: a | C10: 주변의 부속 바위섬 | D10: 1 | E10: 자료는 두 큰 섬과 주변 부속 도서를 함께 독도의 구성으로 설명해요. | F10: The surrounding associated islets | G10: The description includes the associated islets as well as the two main islands.
A11: 920003 | B11: c | C11: 일본 오키섬 전체 | D11: 0 | E11: 오키섬은 독도를 이루는 섬이 아니므로 이 구성도에 더하지 않아요. | F11: All of Japan’s Oki Islands | G11: The Oki Islands do not form part of Dokdo.
A12: 920004 | B12: b | C12: 동도와 울릉도를 아우르는 이름이다 | D12: 0 | E12: 울릉도는 독도와 별개의 섬이므로 구성에 넣으면 안 돼요. | F12: It names Dongdo and Ulleungdo | G12: Ulleungdo is separate and should not be added to Dokdo’s composition.
A13: 920004 | B13: c | C13: 서도 한 섬만 가리키는 이름이다 | D13: 0 | E13: 서도만으로 바꾸어도 여전히 동도와 주변 바위섬을 빠뜨려요. | F13: It names Seodo alone | G13: Changing the answer to Seodo alone still omits Dongdo and the smaller islets.
... A712: 920240 | B712: a | C712: 두 큰 섬과 부속 도서가 있고, 해저 화산활동으로 형성되었다 | D712: 1 | E712: 구성과 형성 원인이 모두 자료와 맞아요. | F712: It has two main islands and associated islets and formed through submarine volcanism | G712: Both the composition and origin match the sources.

Sheet 자료와출처
A1: ID | B1: 질문 | C1: 자료 필수 | D1: 먼저 알아둘 배경 | E1: 문항에 보이는 자료 | F1: 자료 범위·해석 표시 | G1: 근거 위치 | H1: 출처
A2: 920001 | B2: 독도를 이루는 두 큰 섬의 이름은 무엇인가요? | C2: 0 | G2: location: 두 큰 섬·부속 도서 / 높이·면적 / 울릉도·오키섬 거리 | H2: 대한민국 외교부 · 독도의 구성 및 위치 https://dokdo.mofa.go.kr/kor/introduce/location.jsp
A3: 920002 | B3: 독도의 두 큰 섬 주위에는 어떤 땅이 더 있나요? | C3: 0 | G3: location: 두 큰 섬·부속 도서 / 높이·면적 / 울릉도·오키섬 거리 | H3: 대한민국 외교부 · 독도의 구성 및 위치 https://dokdo.mofa.go.kr/kor/introduce/location.jsp
A4: 920003 | B4: 독도 안내판에 두 큰 섬만 그렸다면 어떤 땅을 추가해야 하나요? | C4: 1 | E4: 독도의 구성: 동도 + 서도 + 주변 부속 도서 89개. 부속 도서는 두 큰 섬 주변의 작은 섬들이에요. | G4: location: 두 큰 섬·부속 도서 / 높이·면적 / 울릉도·오키섬 거리 | H4: 대한민국 외교부 · 독도의 구성 및 위치 https://dokdo.mofa.go.kr/kor/introduce/location.jsp
A5: 920004 | B5: 독도를 ‘동도 한 섬의 이름’이라고 쓴 문장을 어떻게 고쳐야 하나요? | C5: 1 | E5: 구성 자료에는 동도·서도와 89개 부속 도서가 모두 독도에 포함된다고 나와 있어요. | G5: location: 두 큰 섬·부속 도서 / 높이·면적 / 울릉도·오키섬 거리 | H5: 대한민국 외교부 · 독도의 구성 및 위치 https://dokdo.mofa.go.kr/kor/introduce/location.jsp
A6: 920005 | B6: 독도는 울릉도에서 어느 방향에 있나요? | C6: 0 | G6: address: 동도·서도의 도로명 주소와 위치; 2018년 등록 자료, 2026-09-11 대조 location: 두 큰 섬·부속 도서 / 높이·면적 / 울릉도·오키섬 거리 | H6: 대한민국 해양수산부 · 독도의 주소와 위치 https://www.mof.go.kr/doc/ko/selectDoc.do?bbsSeq=27&docSeq=20937&menuSeq=929 대한민국 외교부 · 독도의 구성 및 위치 https://dokdo.mofa.go.kr/kor/introduce/location.jsp
A7: 920006 | B7: 울릉도와 독도 사이의 거리는 약 얼마인가요? | C7: 0 | G7: address: 동도·서도의 도로명 주소와 위치; 2018년 등록 자료, 2026-09-11 대조 location: 두 큰 섬·부속 도서 / 높이·면적 / 울릉도·오키섬 거리 | H7: 대한민국 해양수산부 · 독도의 주소와 위치 https://www.mof.go.kr/doc/ko/selectDoc.do?bbsSeq=27&docSeq=20937&menuSeq=929 대한민국 외교부 · 독도의 구성 및 위치 https://dokdo.mofa.go.kr/kor/introduce/location.jsp
A8: 920007 | B8: 거리표에서 독도에 더 가까운 곳은 어디인가요? | C8: 1 | E8: 독도에서 울릉도: 87.4km 독도에서 일본 오키섬: 157.5km | G8: address: 동도·서도의 도로명 주소와 위치; 2018년 등록 자료, 2026-09-11 대조 location: 두 큰 섬·부속 도서 / 높이·면적 / 울릉도·오키섬 거리 | H8: 대한민국 해양수산부 · 독도의 주소와 위치 https://www.mof.go.kr/doc/ko/selectDoc.do?bbsSeq=27&docSeq=20937&menuSeq=929 대한민국 외교부 · 독도의 구성 및 위치 https://dokdo.mofa.go.kr/kor/introduce/location.jsp
A9: 920008 | B9: 독도에서 울릉도까지는 오키섬까지보다 몇 km 더 가까운가요? | C9: 1 | E9: 독도–울릉도 87.4km, 독도–일본 오키섬 157.5km. 이 수치로 거리의 차이를 계산하세요. | G9: address: 동도·서도의 도로명 주소와 위치; 2018년 등록 자료, 2026-09-11 대조 location: 두 큰 섬·부속 도서 / 높이·면적 / 울릉도·오키섬 거리 | H9: 대한민국 해양수산부 · 독도의 주소와 위치 https://www.mof.go.kr/doc/ko/selectDoc.do?bbsSeq=27&docSeq=20937&menuSeq=929 대한민국 외교부 · 독도의 구성 및 위치 https://dokdo.mofa.go.kr/kor/introduce/location.jsp
A10: 920009 | B10: 독도의 동쪽에 있는 큰 섬은 무엇인가요? | C10: 0 | F10: 방향을 단순화한 위치 관계이며 두 섬의 실제 해안선을 그린 지도가 아니에요. | G10: location: 두 큰 섬·부속 도서 / 높이·면적 / 울릉도·오키섬 거리 | H10: 대한민국 외교부 · 독도의 구성 및 위치 https://dokdo.mofa.go.kr/kor/introduce/location.jsp
A11: 920010 | B11: 독도의 서쪽 큰 섬을 지도에 표시하려면 어떤 이름을 쓰나요? | C11: 0 | F11: 방향을 단순화한 위치 관계이며 두 섬의 실제 해안선을 그린 지도가 아니에요. | G11: location: 두 큰 섬·부속 도서 / 높이·면적 / 울릉도·오키섬 거리 | H11: 대한민국 외교부 · 독도의 구성 및 위치 https://dokdo.mofa.go.kr/kor/introduce/location.jsp
A12: 920011 | B12: 위치표에서 A에 넣을 섬 이름은 무엇인가요? | C12: 1 | E12: 서쪽 ← [ A ] ··· [ 동도 ] → 동쪽 동도와 서도의 방향 관계만 간단히 나타냈어요. | F12: 방향을 단순화한 위치 관계이며 두 섬의 실제 해안선을 그린 지도가 아니에요. | G12: location: 두 큰 섬·부속 도서 / 높이·면적 / 울릉도·오키섬 거리 | H12: 대한민국 외교부 · 독도의 구성 및 위치 https://dokdo.mofa.go.kr/kor/introduce/location.jsp
A13: 920012 | B13: 동쪽 화살표가 왼쪽을 가리키는 위치표에서 동도는 어느 쪽에 놓이나요? | C13: 1 | E13: 동쪽 ← [ A ] ··· [ B ] → 서쪽 동도는 동쪽 섬, 서도는 서쪽 섬이에요. 글자 방향이 아니라 화살표를 따라 읽으세요. | F13: 방향을 단순화한 위치 관계이며 두 섬의 실제 해안선을 그린 지도가 아니에요. | G13: location: 두 큰 섬·부속 도서 / 높이·면적 / 울릉도·오키섬 거리 | H13: 대한민국 외교부 · 독도의 구성 및 위치 https://dokdo.mofa.go.kr/kor/introduce/location.jsp
A14: 920013 | B14: 울릉도에서 독도를 보기 좋은 날씨는 무엇인가요? | C14: 0 | G14: sejong: 우산·무릉과 맑은 날의 가시성; 괄호 안 현대 지명은 외교부 해석 location: 두 큰 섬·부속 도서 / 높이·면적 / 울릉도·오키섬 거리 | H14: 대한민국 외교부 자료실 · 세종실록 지리지(1454) https://dokdo.mofa.go.kr/kor/pds/part06_view02.jsp 대한민국 외교부 · 독도의 구성 및 위치 https://dokdo.mofa.go.kr/kor/introduce/location.jsp
A15: 920014 | B15: 울릉도에서 먼 독도를 보려면 어떤 대기 조건이 필요한가요? | C15: 0 | G15: sejong: 우산·무릉과 맑은 날의 가시성; 괄호 안 현대 지명은 외교부 해석 location: 두 큰 섬·부속 도서 / 높이·면적 / 울릉도·오키섬 거리 | H15: 대한민국 외교부 자료실 · 세종실록 지리지(1454) https://dokdo.mofa.go.kr/kor/pds/part06_view02.jsp 대한민국 외교부 · 독도의 구성 및 위치 https://dokdo.mofa.go.kr/kor/introduce/location.jsp
A16: 920015 | B16: 세종실록 지리지는 두 섬이 보이는 날씨를 어떻게 설명하나요? | C16: 1 | E16: 1454년 『세종실록』 지리지의 역문 요약: 우산과 무릉 두 섬은 멀리 떨어져 있지 않아 날씨가 맑으면 바라볼 수 있다. 우산·무릉은 아래 출처의 해설에서 독도·울릉도로 풀이해요. | G16: sejong: 우산·무릉과 맑은 날의 가시성; 괄호 안 현대 지명은 외교부 해석 location: 두 큰 섬·부속 도서 / 높이·면적 / 울릉도·오키섬 거리 | H16: 대한민국 외교부 자료실 · 세종실록 지리지(1454) https://dokdo.mofa.go.kr/kor/pds/part06_view02.jsp 대한민국 외교부 · 독도의 구성 및 위치 https://dokdo.mofa.go.kr/kor/introduce/location.jsp
A17: 920016 | B17: 두 관찰일 중 울릉도에서 독도를 보기 더 좋은 날은 언제인가요? | C17: 1 | E17: 관찰 계획을 위한 예시: A일은 안개 없이 시야가 맑다. B일은 짙은 안개로 먼 바다가 보이지 않는다. 같은 울릉도 관찰 지점에서 볼 예정이다. | G17: sejong: 우산·무릉과 맑은 날의 가시성; 괄호 안 현대 지명은 외교부 해석 location: 두 큰 섬·부속 도서 / 높이·면적 / 울릉도·오키섬 거리 | H17: 대한민국 외교부 자료실 · 세종실록 지리지(1454) https://dokdo.mofa.go.kr/kor/pds/part06_view02.jsp 대한민국 외교부 · 독도의 구성 및 위치 https://dokdo.mofa.go.kr/kor/introduce/location.jsp
A18: 920017 | B18: 독도의 부속 도서 89개를 셀 때 따로 구분하는 두 큰 섬은 무엇인가요? | C18: 0 | G18: location: 두 큰 섬·부속 도서 / 높이·면적 / 울릉도·오키섬 거리 size: 동도 73,297㎡ / 서도 88,740㎡ / 부속 도서 25,517㎡ / 전체 187,554㎡ | H18: 대한민국 외교부 · 독도의 구성 및 위치 https://dokdo.mofa.go.kr/kor/introduce/location.jsp 대한민국 한국해양과학기술원 · 독도 위치 및 규모 https://www.dokdo.re.kr/home/cms/cmsCont.do?cntnts_sn=64
A19: 920018 | B19: 동도·서도와 부속 도서 89개를 합하면 몇 개인가요? | C19: 0 | G19: location: 두 큰 섬·부속 도서 / 높이·면적 / 울릉도·오키섬 거리 size: 동도 73,297㎡ / 서도 88,740㎡ / 부속 도서 25,517㎡ / 전체 187,554㎡ | H19: 대한민국 외교부 · 독도의 구성 및 위치 https://dokdo.mofa.go.kr/kor/introduce/location.jsp 대한민국 한국해양과학기술원 · 독도 위치 및 규모 https://www.dokdo.re.kr/home/cms/cmsCont.do?cntnts_sn=64
A20: 920019 | B20: 면적표에서 부속 도서 전체의 넓이는 얼마인가요? | C20: 1 | E20: 동도 73,297㎡ 서도 88,740㎡ 부속 도서 89개 25,517㎡ 합계 187,554㎡ | G20: location: 두 큰 섬·부속 도서 / 높이·면적 / 울릉도·오키섬 거리 size: 동도 73,297㎡ / 서도 88,740㎡ / 부속 도서 25,517㎡ / 전체 187,554㎡ | H20: 대한민국 외교부 · 독도의 구성 및 위치 https://dokdo.mofa.go.kr/kor/introduce/location.jsp 대한민국 한국해양과학기술원 · 독도 위치 및 규모 https://www.dokdo.re.kr/home/cms/cmsCont.do?cntnts_sn=64
A21: 920020 | B21: 독도 전체 면적을 동도와 서도 면적만 더해 계산하면 무엇이 빠지나요? | C21: 1 | E21: 독도 전체 땅 면적 187,554㎡ / 동도 73,297㎡ / 서도 88,740㎡. 부속 도서도 독도를 이루는 땅이에요. | G21: location: 두 큰 섬·부속 도서 / 높이·면적 / 울릉도·오키섬 거리 size: 동도 73,297㎡ / 서도 88,740㎡ / 부속 도서 25,517㎡ / 전체 187,554㎡ | H21: 대한민국 외교부 · 독도의 구성 및 위치 https://dokdo.mofa.go.kr/kor/introduce/location.jsp 대한민국 한국해양과학기술원 · 독도 위치 및 규모 https://www.dokdo.re.kr/home/cms/cmsCont.do?cntnts_sn=64
A22: 920021 | B22: 독도의 두 큰 섬 중 더 높은 섬은 무엇인가요? | C22: 0 | G22: location: 두 큰 섬·부속 도서 / 높이·면적 / 울릉도·오키섬 거리 size: 동도 73,297㎡ / 서도 88,740㎡ / 부속 도서 25,517㎡ / 전체 187,554㎡ | H22: 대한민국 외교부 · 독도의 구성 및 위치 https://dokdo.mofa.go.kr/kor/introduce/location.jsp 대한민국 한국해양과학기술원 · 독도 위치 및 규모 https://www.dokdo.re.kr/home/cms/cmsCont.do?cntnts_sn=64
A23: 920022 | B23: 독도에서 최고 높이가 98.6m인 큰 섬은 무엇인가요? | C23: 0 | G23: location: 두 큰 섬·부속 도서 / 높이·면적 / 울릉도·오키섬 거리 size: 동도 73,297㎡ / 서도 88,740㎡ / 부속 도서 25,517㎡ / 전체 187,554㎡ | H23: 대한민국 외교부 · 독도의 구성 및 위치 https://dokdo.mofa.go.kr/kor/introduce/location.jsp 대한민국 한국해양과학기술원 · 독도 위치 및 규모 https://www.dokdo.re.kr/home/cms/cmsCont.do?cntnts_sn=64
A24: 920023 | B24: 높이표에 따르면 서도는 동도보다 몇 m 더 높은가요? | C24: 1 | E24: 서도 최고 높이 168.5m 동도 최고 높이 98.6m 두 값은 해수면을 기준으로 한 높이예요. | G24: location: 두 큰 섬·부속 도서 / 높이·면적 / 울릉도·오키섬 거리 size: 동도 73,297㎡ / 서도 88,740㎡ / 부속 도서 25,517㎡ / 전체 187,554㎡ | H24: 대한민국 외교부 · 독도의 구성 및 위치 https://dokdo.mofa.go.kr/kor/introduce/location.jsp 대한민국 한국해양과학기술원 · 독도 위치 및 규모 https://www.dokdo.re.kr/home/cms/cmsCont.do?cntnts_sn=64
A25: 920024 | B25: 표의 높이를 기준으로 100m보다 높은 곳이 있는 섬은 어디인가요? | C25: 1 | E25: 서도 168.5m / 동도 98.6m. 지형도의 100m 높이선을 넣을 수 있는 섬을 판단하려고 해요. | G25: location: 두 큰 섬·부속 도서 / 높이·면적 / 울릉도·오키섬 거리 size: 동도 73,297㎡ / 서도 88,740㎡ / 부속 도서 25,517㎡ / 전체 187,554㎡ | H25: 대한민국 외교부 · 독도의 구성 및 위치 https://dokdo.mofa.go.kr/kor/introduce/location.jsp 대한민국 한국해양과학기술원 · 독도 위치 및 규모 https://www.dokdo.re.kr/home/cms/cmsCont.do?cntnts_sn=64
A26: 920025 | B26: 독도의 두 큰 섬 중 땅의 넓이가 더 넓은 섬은 무엇인가요? | C26: 0 | G26: location: 두 큰 섬·부속 도서 / 높이·면적 / 울릉도·오키섬 거리 size: 동도 73,297㎡ / 서도 88,740㎡ / 부속 도서 25,517㎡ / 전체 187,554㎡ | H26: 대한민국 외교부 · 독도의 구성 및 위치 https://dokdo.mofa.go.kr/kor/introduce/location.jsp 대한민국 한국해양과학기술원 · 독도 위치 및 규모 https://www.dokdo.re.kr/home/cms/cmsCont.do?cntnts_sn=64
A27: 920026 | B27: 독도 면적표의 ㎡는 무엇을 나타내는 단위인가요? | C27: 1 | E27: 서도: 88,740㎡ / 동도: 73,297㎡ | G27: location: 두 큰 섬·부속 도서 / 높이·면적 / 울릉도·오키섬 거리 size: 동도 73,297㎡ / 서도 88,740㎡ / 부속 도서 25,517㎡ / 전체 187,554㎡ | H27: 대한민국 외교부 · 독도의 구성 및 위치 https://dokdo.mofa.go.kr/kor/introduce/location.jsp 대한민국 한국해양과학기술원 · 독도 위치 및 규모 https://www.dokdo.re.kr/home/cms/cmsCont.do?cntnts_sn=64
A28: 920027 | B28: 표에서 해안선의 둘레가 더 긴 큰 섬은 어디인가요? | C28: 1 | E28: 동도: 면적 73,297㎡, 둘레 2.8km 서도: 면적 88,740㎡, 둘레 2.6km | G28: location: 두 큰 섬·부속 도서 / 높이·면적 / 울릉도·오키섬 거리 size: 동도 73,297㎡ / 서도 88,740㎡ / 부속 도서 25,517㎡ / 전체 187,554㎡ | H28: 대한민국 외교부 · 독도의 구성 및 위치 https://dokdo.mofa.go.kr/kor/introduce/location.jsp 대한민국 한국해양과학기술원 · 독도 위치 및 규모 https://www.dokdo.re.kr/home/cms/cmsCont.do?cntnts_sn=64
A29: 920028 | B29: 표에 맞게 서도와 동도의 면적·둘레를 함께 비교한 것은 무엇인가요? | C29: 1 | E29: 동도 73,297㎡ / 둘레 2.8km 서도 88,740㎡ / 둘레 2.6km 면적은 땅의 넓이, 둘레는 해안선을 따라 잰 길이예요. | G29: location: 두 큰 섬·부속 도서 / 높이·면적 / 울릉도·오키섬 거리 size: 동도 73,297㎡ / 서도 88,740㎡ / 부속 도서 25,517㎡ / 전체 187,554㎡ | H29: 대한민국 외교부 · 독도의 구성 및 위치 https://dokdo.mofa.go.kr/kor/introduce/location.jsp 대한민국 한국해양과학기술원 · 독도 위치 및 규모 https://www.dokdo.re.kr/home/cms/cmsCont.do?cntnts_sn=64
A30: 920029 | B30: 동도와 서도는 무엇을 사이에 두고 떨어져 있나요? | C30: 0 | F30: 해안 사이의 간격이지 두 정상 사이 거리나 걷는 길의 길이가 아니에요. | G30: geology: 해저 화산의 형성 / 해안 침식 지형 / 물골 / 지형 변화 reserve: 해안지형·조류 번식지·식생 보호; 지정 날짜를 묻는 문항은 제외 | H30: 대한민국 한국해양과학기술원 · 독도 지형 및 지질 https://www.dokdo.re.kr/home/cms/cmsCont.do?cntnts_sn=66 대한민국 국가유산청 · 독도 천연보호구역 https://www.heritage.go.kr/heri/cul/culSelectDetail.do?VdkVgwKey=16%2C03360000%2C37&pageNo=1_1_2_0
A31: 920030 | B31: 동도와 서도의 가장 가까운 해안 사이 거리는 약 얼마인가요? | C31: 0 | F31: 해안 사이의 간격이지 두 정상 사이 거리나 걷는 길의 길이가 아니에요. | G31: geology: 해저 화산의 형성 / 해안 침식 지형 / 물골 / 지형 변화 reserve: 해안지형·조류 번식지·식생 보호; 지정 날짜를 묻는 문항은 제외 | H31: 대한민국 한국해양과학기술원 · 독도 지형 및 지질 https://www.dokdo.re.kr/home/cms/cmsCont.do?cntnts_sn=66 대한민국 국가유산청 · 독도 천연보호구역 https://www.heritage.go.kr/heri/cul/culSelectDetail.do?VdkVgwKey=16%2C03360000%2C37&pageNo=1_1_2_0
A32: 920031 | B32: 151m라는 간격을 지도에 표시할 때 양 끝은 어디에 두어야 하나요? | C32: 1 | E32: 거리 설명: 동도와 서도가 가장 가까이 마주한 해안 사이의 간격은 약 151m이다. | F32: 해안 사이의 간격이지 두 정상 사이 거리나 걷는 길의 길이가 아니에요. | G32: geology: 해저 화산의 형성 / 해안 침식 지형 / 물골 / 지형 변화 reserve: 해안지형·조류 번식지·식생 보호; 지정 날짜를 묻는 문항은 제외 | H32: 대한민국 한국해양과학기술원 · 독도 지형 및 지질 https://www.dokdo.re.kr/home/cms/cmsCont.do?cntnts_sn=66 대한민국 국가유산청 · 독도 천연보호구역 https://www.heritage.go.kr/heri/cul/culSelectDetail.do?VdkVgwKey=16%2C03360000%2C37&pageNo=1_1_2_0
A33: 920032 | B33: 축척이 1cm당 50m인 지도에서 151m 간격은 약 몇 cm인가요? | C33: 1 | E33: 실제 해안 간격: 약 151m 학습용 지도 축척: 1cm가 실제 50m를 나타냄 이 축척은 계산 연습을 위해 정한 값이에요. | F33: 해안 사이의 간격이지 두 정상 사이 거리나 걷는 길의 길이가 아니에요. | G33: geology: 해저 화산의 형성 / 해안 침식 지형 / 물골 / 지형 변화 reserve: 해안지형·조류 번식지·식생 보호; 지정 날짜를 묻는 문항은 제외 | H33: 대한민국 한국해양과학기술원 · 독도 지형 및 지질 https://www.dokdo.re.kr/home/cms/cmsCont.do?cntnts_sn=66 대한민국 국가유산청 · 독도 천연보호구역 https://www.heritage.go.kr/heri/cul/culSelectDetail.do?VdkVgwKey=16%2C03360000%2C37&pageNo=1_1_2_0
A34: 920033 | B34: 독도에서 가파른 봉우리가 두드러지는 큰 섬은 무엇인가요? | C34: 0 | G34: reserve: 해안지형·조류 번식지·식생 보호; 지정 날짜를 묻는 문항은 제외 photos: 두 섬·선착장·등대로 가는 길·바위의 사진 설명; 사진 파일은 재배포하지 않음 | H34: 대한민국 국가유산청 · 독도 천연보호구역 https://www.heritage.go.kr/heri/cul/culSelectDetail.do?VdkVgwKey=16%2C03360000%2C37&pageNo=1_1_2_0 대한민국 전북교육청 · 독도 사진 자료 https://www.jbe.go.kr/dokdo/assets/sub/picture.html
A35: 920034 | B35: 독도의 헬기장 등 시설이 자리한 비교적 평탄한 상부는 어느 섬에 있나요? | C35: 0 | G35: reserve: 해안지형·조류 번식지·식생 보호; 지정 날짜를 묻는 문항은 제외 photos: 두 섬·선착장·등대로 가는 길·바위의 사진 설명; 사진 파일은 재배포하지 않음 | H35: 대한민국 국가유산청 · 독도 천연보호구역 https://www.heritage.go.kr/heri/cul/culSelectDetail.do?VdkVgwKey=16%2C03360000%2C37&pageNo=1_1_2_0 대한민국 전북교육청 · 독도 사진 자료 https://www.jbe.go.kr/dokdo/assets/sub/picture.html
A36: 920035 | B36: 지형 설명 A는 동도와 서도 중 어느 섬인가요? | C36: 1 | E36: A: 해안에는 절벽이 있고, 정상 부근은 비교적 평탄하여 헬기장과 시설이 있다. B: 높고 가파른 봉우리가 두드러진다. | G36: reserve: 해안지형·조류 번식지·식생 보호; 지정 날짜를 묻는 문항은 제외 photos: 두 섬·선착장·등대로 가는 길·바위의 사진 설명; 사진 파일은 재배포하지 않음 | H36: 대한민국 국가유산청 · 독도 천연보호구역 https://www.heritage.go.kr/heri/cul/culSelectDetail.do?VdkVgwKey=16%2C03360000%2C37&pageNo=1_1_2_0 대한민국 전북교육청 · 독도 사진 자료 https://www.jbe.go.kr/dokdo/assets/sub/picture.html
A37: 920036 | B37: 독도 모형에서 동도를 서도와 똑같은 뾰족한 산으로 만들었다면 무엇을 고쳐야 하나요? | C37: 1 | E37: 지형 자료: 서도 168.5m, 가파른 봉우리 / 동도 98.6m, 해안 절벽과 비교적 평탄한 정상 부근. 수정할 모형: 두 섬을 높이만 다른 똑같은 뾰족한 산으로 만듦. | G37: reserve: 해안지형·조류 번식지·식생 보호; 지정 날짜를 묻는 문항은 제외 photos: 두 섬·선착장·등대로 가는 길·바위의 사진 설명; 사진 파일은 재배포하지 않음 | H37: 대한민국 국가유산청 · 독도 천연보호구역 https://www.heritage.go.kr/heri/cul/culSelectDetail.do?VdkVgwKey=16%2C03360000%2C37&pageNo=1_1_2_0 대한민국 전북교육청 · 독도 사진 자료 https://www.jbe.go.kr/dokdo/assets/sub/picture.html
A38: 920037 | B38: 동도와 서도 아래 바닷속에도 독도의 지형이 이어지나요? | C38: 0 | G38: geology: 해저 화산의 형성 / 해안 침식 지형 / 물골 / 지형 변화 | H38: 대한민국 한국해양과학기술원 · 독도 지형 및 지질 https://www.dokdo.re.kr/home/cms/cmsCont.do?cntnts_sn=66
A39: 920038 | B39: 독도의 두 큰 섬은 무엇의 일부가 바다 위로 드러난 것인가요? | C39: 0 | G39: geology: 해저 화산의 형성 / 해안 침식 지형 / 물골 / 지형 변화 | H39: 대한민국 한국해양과학기술원 · 독도 지형 및 지질 https://www.dokdo.re.kr/home/cms/cmsCont.do?cntnts_sn=66
A40: 920039 | B40: 독도 설명의 약 2,300m는 어디서부터 잰 규모인가요? | C40: 1 | E40: 서도의 해발 높이: 168.5m. 독도 화산체의 전체 높이: 해저 기저부부터 약 2,300m. 높이를 비교할 때 출발 기준을 확인하세요. | G40: geology: 해저 화산의 형성 / 해안 침식 지형 / 물골 / 지형 변화 | H40: 대한민국 한국해양과학기술원 · 독도 지형 및 지질 https://www.dokdo.re.kr/home/cms/cmsCont.do?cntnts_sn=66
A41: 920040 | B41: 168.5m와 약 2,300m를 함께 독도의 높이라고 쓰는 까닭은 무엇인가요? | C41: 1 | E41: 해수면 → 서도 정상: 168.5m 해저 화산체 기저부 → 화산체 상부: 약 2,300m | G41: geology: 해저 화산의 형성 / 해안 침식 지형 / 물골 / 지형 변화 | H41: 대한민국 한국해양과학기술원 · 독도 지형 및 지질 https://www.dokdo.re.kr/home/cms/cmsCont.do?cntnts_sn=66
A42: 920041 | B42: 독도를 처음 만든 자연 현상은 무엇인가요? | C42: 0 | G42: geology: 해저 화산의 형성 / 해안 침식 지형 / 물골 / 지형 변화 | H42: 대한민국 한국해양과학기술원 · 독도 지형 및 지질 https://www.dokdo.re.kr/home/cms/cmsCont.do?cntnts_sn=66
A43: 920042 | B43: 독도의 화산활동이 시작된 곳은 어디인가요? | C43: 0 | G43: geology: 해저 화산의 형성 / 해안 침식 지형 / 물골 / 지형 변화 | H43: 대한민국 한국해양과학기술원 · 독도 지형 및 지질 https://www.dokdo.re.kr/home/cms/cmsCont.do?cntnts_sn=66
A44: 920043 | B44: 독도의 형성 과정을 순서대로 놓으면 무엇인가요? | C44: 1 | E44: 해저에서 화산 물질이 분출했다. 분출물이 쌓여 화산체가 자랐다. 화산체 일부가 바다 위로 드러났다. | G44: geology: 해저 화산의 형성 / 해안 침식 지형 / 물골 / 지형 변화 | H44: 대한민국 한국해양과학기술원 · 독도 지형 및 지질 https://www.dokdo.re.kr/home/cms/cmsCont.do?cntnts_sn=66
A45: 920044 | B45: 독도 해안이 파도에 깎인다는 사실과 화산 기원을 함께 설명한 것은 무엇인가요? | C45: 1 | E45: 독도는 해저 화산활동으로 만들어졌다. 수면 위로 드러난 뒤 침식이 우세해져, 처음 드러났던 화산체의 일부가 남은 것으로 설명된다. | G45: geology: 해저 화산의 형성 / 해안 침식 지형 / 물골 / 지형 변화 | H45: 대한민국 한국해양과학기술원 · 독도 지형 및 지질 https://www.dokdo.re.kr/home/cms/cmsCont.do?cntnts_sn=66
A46: 920045 | B46: 독도는 먼저 어디에서 자란 뒤 물 위로 드러났나요? | C46: 0 | F46: 형성 시기는 연구 자료의 대략적인 추정값이며 정확한 하루를 뜻하지 않아요. | G46: geology: 해저 화산의 형성 / 해안 침식 지형 / 물골 / 지형 변화 | H46: 대한민국 한국해양과학기술원 · 독도 지형 및 지질 https://www.dokdo.re.kr/home/cms/cmsCont.do?cntnts_sn=66
A47: 920046 | B47: 독도가 생긴 뒤 해안을 깎아 온 작용은 무엇인가요? | C47: 0 | F47: 형성 시기는 연구 자료의 대략적인 추정값이며 정확한 하루를 뜻하지 않아요. | G47: geology: 해저 화산의 형성 / 해안 침식 지형 / 물골 / 지형 변화 | H47: 대한민국 한국해양과학기술원 · 독도 지형 및 지질 https://www.dokdo.re.kr/home/cms/cmsCont.do?cntnts_sn=66
A48: 920047 | B48: 제시된 독도 형성 연표에서 먼저 일어난 일은 무엇인가요? | C48: 1 | E48: 형성 자료 요약: 최소 약 460만 년 전 해저 화산활동으로 형성되기 시작했고, 약 250만 년 전부터 수면 위로 드러났다. | F48: 형성 시기는 연구 자료의 대략적인 추정값이며 정확한 하루를 뜻하지 않아요. | G48: geology: 해저 화산의 형성 / 해안 침식 지형 / 물골 / 지형 변화 | H48: 대한민국 한국해양과학기술원 · 독도 지형 및 지질 https://www.dokdo.re.kr/home/cms/cmsCont.do?cntnts_sn=66
A49: 920048 | B49: 형성 연표에서 460만 년 전과 250만 년 전의 차이는 약 몇 년인가요? | C49: 1 | E49: 계산에 사용할 대략적인 시점: 해저 화산활동 460만 년 전 / 수면 위 출현 250만 년 전. 실제 형성은 오랜 과정이며 이 계산이 정확한 형성 기간을 확정하지는 않아요. | F49: 형성 시기는 연구 자료의 대략적인 추정값이며 정확한 하루를 뜻하지 않아요. | G49: geology: 해저 화산의 형성 / 해안 침식 지형 / 물골 / 지형 변화 | H49: 대한민국 한국해양과학기술원 · 독도 지형 및 지질 https://www.dokdo.re.kr/home/cms/cmsCont.do?cntnts_sn=66
A50: 920049 | B50: 독도 해안의 바위를 깎는 바닷물의 움직임은 무엇인가요? | C50: 0 | G50: geology: 해저 화산의 형성 / 해안 침식 지형 / 물골 / 지형 변화 arch: 동도 해식아치의 형태와 형성 | H50: 대한민국 한국해양과학기술원 · 독도 지형 및 지질 https://www.dokdo.re.kr/home/cms/cmsCont.do?cntnts_sn=66 대한민국 한국관광공사 · 독립문바위 https://korean.visitkorea.or.kr/detail/ms_detail.do?cotid=0fe4eeb6-3f6a-48b1-ab75-c8d4ab6b43be
A51: 920050 | B51: 독도 해안의 바위가 파도에 깎이는 작용을 무엇이라고 하나요? | C51: 0 | G51: geology: 해저 화산의 형성 / 해안 침식 지형 / 물골 / 지형 변화 arch: 동도 해식아치의 형태와 형성 | H51: 대한민국 한국해양과학기술원 · 독도 지형 및 지질 https://www.dokdo.re.kr/home/cms/cmsCont.do?cntnts_sn=66 대한민국 한국관광공사 · 독립문바위 https://korean.visitkorea.or.kr/detail/ms_detail.do?cotid=0fe4eeb6-3f6a-48b1-ab75-c8d4ab6b43be
A52: 920051 | B52: 설명된 독립문바위의 아치 구멍을 만드는 데 영향을 준 작용은 무엇인가요? | C52: 1 | E52: 독립문바위는 동도에 있는 해식아치예요. 해식아치는 해안의 바위가 깎여 아치 모양으로 남은 지형이에요. | G52: geology: 해저 화산의 형성 / 해안 침식 지형 / 물골 / 지형 변화 arch: 동도 해식아치의 형태와 형성 | H52: 대한민국 한국해양과학기술원 · 독도 지형 및 지질 https://www.dokdo.re.kr/home/cms/cmsCont.do?cntnts_sn=66 대한민국 한국관광공사 · 독립문바위 https://korean.visitkorea.or.kr/detail/ms_detail.do?cotid=0fe4eeb6-3f6a-48b1-ab75-c8d4ab6b43be
A53: 920052 | B53: 독도 바위를 관찰해 해식 지형으로 분류할 수 있는 설명은 무엇인가요? | C53: 1 | E53: 분류 기준: 해식은 파도 등에 의해 해안 바위가 깎이는 과정이다. 독도의 해식동굴·해식아치는 이 과정과 관련된다. | G53: geology: 해저 화산의 형성 / 해안 침식 지형 / 물골 / 지형 변화 arch: 동도 해식아치의 형태와 형성 | H53: 대한민국 한국해양과학기술원 · 독도 지형 및 지질 https://www.dokdo.re.kr/home/cms/cmsCont.do?cntnts_sn=66 대한민국 한국관광공사 · 독립문바위 https://korean.visitkorea.or.kr/detail/ms_detail.do?cotid=0fe4eeb6-3f6a-48b1-ab75-c8d4ab6b43be
A54: 920053 | B54: 독도의 바위가 바람과 추위 등에 오래 노출되어 약해지는 과정을 무엇이라고 하나요? | C54: 0 | G54: geology: 해저 화산의 형성 / 해안 침식 지형 / 물골 / 지형 변화 | H54: 대한민국 한국해양과학기술원 · 독도 지형 및 지질 https://www.dokdo.re.kr/home/cms/cmsCont.do?cntnts_sn=66
A55: 920054 | B55: 독도 해안에서 깎인 바위 조각이 다른 곳에 쌓이는 과정은 무엇인가요? | C55: 0 | G55: geology: 해저 화산의 형성 / 해안 침식 지형 / 물골 / 지형 변화 | H55: 대한민국 한국해양과학기술원 · 독도 지형 및 지질 https://www.dokdo.re.kr/home/cms/cmsCont.do?cntnts_sn=66
A56: 920055 | B56: 독도 바위가 약해진 뒤 파도에 깎였다는 설명의 과정 순서는 무엇인가요? | C56: 1 | E56: 관찰 예시: 독도 해안 바위에 틈이 커졌다. 약해진 부분을 파도가 깎아 바위 조각을 옮겼다. 실제 특정 날짜의 조사값이 아닌 과정 설명이에요. | G56: geology: 해저 화산의 형성 / 해안 침식 지형 / 물골 / 지형 변화 | H56: 대한민국 한국해양과학기술원 · 독도 지형 및 지질 https://www.dokdo.re.kr/home/cms/cmsCont.do?cntnts_sn=66
A57: 920056 | B57: 독도 해안선의 변화를 비교하려면 어느 자료 묶음이 적합한가요? | C57: 1 | E57: 독도 해안에서는 풍화·침식으로 작은 지형 변화가 생길 수 있어요. 조사에서는 같은 구간의 과거 모습과 새 측정 결과를 대조하려고 해요. | G57: geology: 해저 화산의 형성 / 해안 침식 지형 / 물골 / 지형 변화 | H57: 대한민국 한국해양과학기술원 · 독도 지형 및 지질 https://www.dokdo.re.kr/home/cms/cmsCont.do?cntnts_sn=66
A58: 920057 | B58: 독도의 물골은 어느 큰 섬에 있나요? | C58: 0 | G58: geology: 해저 화산의 형성 / 해안 침식 지형 / 물골 / 지형 변화 facility: 서도 주민숙소 / 동도 접안시설·등대·경비대 / 담수시설 | H58: 대한민국 한국해양과학기술원 · 독도 지형 및 지질 https://www.dokdo.re.kr/home/cms/cmsCont.do?cntnts_sn=66 대한민국 외교부 · 독도 주요시설물 https://dokdo.mofa.go.kr/kor/introduce/facility.jsp
A59: 920058 | B59: 담수화 시설이 생기기 전, 독도의 물골은 주로 무엇에 쓰였나요? | C59: 0 | G59: geology: 해저 화산의 형성 / 해안 침식 지형 / 물골 / 지형 변화 facility: 서도 주민숙소 / 동도 접안시설·등대·경비대 / 담수시설 | H59: 대한민국 한국해양과학기술원 · 독도 지형 및 지질 https://www.dokdo.re.kr/home/cms/cmsCont.do?cntnts_sn=66 대한민국 외교부 · 독도 주요시설물 https://dokdo.mofa.go.kr/kor/introduce/facility.jsp
A60: 920059 | B60: 설명의 빈칸에 들어갈 지명은 무엇인가요? | C60: 1 | E60: 서도의 [ ]에서는 바위에서 물이 조금씩 떨어진다. 바닷물을 담수로 바꾸는 시설이 설치되기 전 식수원으로 이용되었다. | G60: geology: 해저 화산의 형성 / 해안 침식 지형 / 물골 / 지형 변화 facility: 서도 주민숙소 / 동도 접안시설·등대·경비대 / 담수시설 | H60: 대한민국 한국해양과학기술원 · 독도 지형 및 지질 https://www.dokdo.re.kr/home/cms/cmsCont.do?cntnts_sn=66 대한민국 외교부 · 독도 주요시설물 https://dokdo.mofa.go.kr/kor/introduce/facility.jsp
A61: 920060 | B61: 물골과 담수화 시설의 물 공급 방식을 바르게 짝지은 것은 무엇인가요? | C61: 1 | E61: 물골: 서도 바위에서 물이 떨어져 과거 식수원으로 이용됨. 담수화 시설: 바닷물의 소금을 줄여 생활에 쓸 물을 만듦. | G61: geology: 해저 화산의 형성 / 해안 침식 지형 / 물골 / 지형 변화 facility: 서도 주민숙소 / 동도 접안시설·등대·경비대 / 담수시설 | H61: 대한민국 한국해양과학기술원 · 독도 지형 및 지질 https://www.dokdo.re.kr/home/cms/cmsCont.do?cntnts_sn=66 대한민국 외교부 · 독도 주요시설물 https://dokdo.mofa.go.kr/kor/introduce/facility.jsp
A62: 920061 | B62: 먼 거리를 이동하는 철새에게 독도는 어떤 곳인가요? | C62: 0 | G62: nature: 독도 식물·조류·해양생물 / 철새 이동경로의 휴식처 | H62: 대한민국 외교부 · 독도의 자연환경 https://dokdo.mofa.go.kr/kor/introduce/nature.jsp
A63: 920062 | B63: 철새가 이동하다 독도처럼 잠시 들러 쉬는 곳을 무엇이라고 하나요? | C63: 0 | G63: nature: 독도 식물·조류·해양생물 / 철새 이동경로의 휴식처 | H63: 대한민국 외교부 · 독도의 자연환경 https://dokdo.mofa.go.kr/kor/introduce/nature.jsp
A64: 920063 | B64: 이동 경로가 ‘출발지 → 독도에서 휴식 → 목적지’라면 독도의 역할은 무엇인가요? | C64: 1 | E64: 철새 이동을 나타낸 학습용 경로: 출발지 → 독도에서 잠시 휴식 → 목적지. 특정 새의 실제 추적 자료는 아니에요. | G64: nature: 독도 식물·조류·해양생물 / 철새 이동경로의 휴식처 | H64: 대한민국 외교부 · 독도의 자연환경 https://dokdo.mofa.go.kr/kor/introduce/nature.jsp
A65: 920064 | B65: 독도의 두 새 관찰에서 ‘중간 기착’에 해당하는 것은 무엇인가요? | C65: 1 | E65: 독도는 철새의 휴식처이면서 일부 바닷새의 번식지예요. 관찰 예시 A: 이동 중 쉬고 떠남. B: 둥지에서 새끼를 기름. | G65: nature: 독도 식물·조류·해양생물 / 철새 이동경로의 휴식처 | H65: 대한민국 외교부 · 독도의 자연환경 https://dokdo.mofa.go.kr/kor/introduce/nature.jsp
A66: 920065 | B66: 독도에서 번식하는 바닷새는 어느 것인가요? | C66: 0 | G66: reserve: 해안지형·조류 번식지·식생 보호; 지정 날짜를 묻는 문항은 제외 nature: 독도 식물·조류·해양생물 / 철새 이동경로의 휴식처 | H66: 대한민국 국가유산청 · 독도 천연보호구역 https://www.heritage.go.kr/heri/cul/culSelectDetail.do?VdkVgwKey=16%2C03360000%2C37&pageNo=1_1_2_0 대한민국 외교부 · 독도의 자연환경 https://dokdo.mofa.go.kr/kor/introduce/nature.jsp
A67: 920066 | B67: 괭이갈매기가 독도에서 번식한다는 뜻은 무엇인가요? | C67: 0 | G67: reserve: 해안지형·조류 번식지·식생 보호; 지정 날짜를 묻는 문항은 제외 nature: 독도 식물·조류·해양생물 / 철새 이동경로의 휴식처 | H67: 대한민국 국가유산청 · 독도 천연보호구역 https://www.heritage.go.kr/heri/cul/culSelectDetail.do?VdkVgwKey=16%2C03360000%2C37&pageNo=1_1_2_0 대한민국 외교부 · 독도의 자연환경 https://dokdo.mofa.go.kr/kor/introduce/nature.jsp
A68: 920067 | B68: 독도에서 번식한다고 소개된 새만 모은 것은 무엇인가요? | C68: 1 | E68: 독도 천연보호구역 안내의 번식 조류: 바다제비, 슴새, 괭이갈매기. | G68: reserve: 해안지형·조류 번식지·식생 보호; 지정 날짜를 묻는 문항은 제외 nature: 독도 식물·조류·해양생물 / 철새 이동경로의 휴식처 | H68: 대한민국 국가유산청 · 독도 천연보호구역 https://www.heritage.go.kr/heri/cul/culSelectDetail.do?VdkVgwKey=16%2C03360000%2C37&pageNo=1_1_2_0 대한민국 외교부 · 독도의 자연환경 https://dokdo.mofa.go.kr/kor/introduce/nature.jsp
A69: 920068 | B69: 독도의 ‘번식지’ 기능을 보여 주는 관찰은 무엇인가요? | C69: 1 | E69: 활동 구분: 번식은 알을 낳고 새끼를 기르는 일, 기착은 이동 중 잠시 들르는 일이에요. 아래 관찰은 구분 연습을 위한 예시예요. | G69: reserve: 해안지형·조류 번식지·식생 보호; 지정 날짜를 묻는 문항은 제외 nature: 독도 식물·조류·해양생물 / 철새 이동경로의 휴식처 | H69: 대한민국 국가유산청 · 독도 천연보호구역 https://www.heritage.go.kr/heri/cul/culSelectDetail.do?VdkVgwKey=16%2C03360000%2C37&pageNo=1_1_2_0 대한민국 외교부 · 독도의 자연환경 https://dokdo.mofa.go.kr/kor/introduce/nature.jsp
A70: 920069 | B70: 독도 바닷속에서 자라는 바닷말은 어느 것인가요? | C70: 0 | G70: nature: 독도 식물·조류·해양생물 / 철새 이동경로의 휴식처 reserve: 해안지형·조류 번식지·식생 보호; 지정 날짜를 묻는 문항은 제외 | H70: 대한민국 외교부 · 독도의 자연환경 https://dokdo.mofa.go.kr/kor/introduce/nature.jsp 대한민국 국가유산청 · 독도 천연보호구역 https://www.heritage.go.kr/heri/cul/culSelectDetail.do?VdkVgwKey=16%2C03360000%2C37&pageNo=1_1_2_0
A71: 920070 | B71: 독도의 괭이갈매기와 미역을 종류별로 짝지으면 무엇인가요? | C71: 0 | G71: nature: 독도 식물·조류·해양생물 / 철새 이동경로의 휴식처 reserve: 해안지형·조류 번식지·식생 보호; 지정 날짜를 묻는 문항은 제외 | H71: 대한민국 외교부 · 독도의 자연환경 https://dokdo.mofa.go.kr/kor/introduce/nature.jsp 대한민국 국가유산청 · 독도 천연보호구역 https://www.heritage.go.kr/heri/cul/culSelectDetail.do?VdkVgwKey=16%2C03360000%2C37&pageNo=1_1_2_0
A72: 920071 | B72: ‘독도는 해조류(海鳥類)의 번식지’에서 해조류는 무엇을 뜻하나요? | C72: 1 | E72: 말 풀이: 海는 바다, 鳥는 새, 藻는 바닷말을 뜻해요. 해조류(海鳥類)와 해조류(海藻類)는 소리가 같지만 뜻은 달라요. | G72: nature: 독도 식물·조류·해양생물 / 철새 이동경로의 휴식처 reserve: 해안지형·조류 번식지·식생 보호; 지정 날짜를 묻는 문항은 제외 | H72: 대한민국 외교부 · 독도의 자연환경 https://dokdo.mofa.go.kr/kor/introduce/nature.jsp 대한민국 국가유산청 · 독도 천연보호구역 https://www.heritage.go.kr/heri/cul/culSelectDetail.do?VdkVgwKey=16%2C03360000%2C37&pageNo=1_1_2_0
A73: 920072 | B73: 독도 생물 목록을 ‘바닷말’로만 묶으면 어느 조합인가요? | C73: 1 | E73: 독도 생물 목록: 바닷말 — 미역, 다시마 / 바닷새 — 괭이갈매기, 바다제비, 슴새. | G73: nature: 독도 식물·조류·해양생물 / 철새 이동경로의 휴식처 reserve: 해안지형·조류 번식지·식생 보호; 지정 날짜를 묻는 문항은 제외 | H73: 대한민국 외교부 · 독도의 자연환경 https://dokdo.mofa.go.kr/kor/introduce/nature.jsp 대한민국 국가유산청 · 독도 천연보호구역 https://www.heritage.go.kr/heri/cul/culSelectDetail.do?VdkVgwKey=16%2C03360000%2C37&pageNo=1_1_2_0
A74: 920073 | B74: 독도 땅에 자라는 꽃식물은 어느 것인가요? | C74: 0 | G74: nature: 독도 식물·조류·해양생물 / 철새 이동경로의 휴식처 | H74: 대한민국 외교부 · 독도의 자연환경 https://dokdo.mofa.go.kr/kor/introduce/nature.jsp
A75: 920074 | B75: 독도에서 해국과 섬기린초를 함께 조사한다면 무엇을 조사하는 것인가요? | C75: 0 | G75: nature: 독도 식물·조류·해양생물 / 철새 이동경로의 휴식처 | H75: 대한민국 외교부 · 독도의 자연환경 https://dokdo.mofa.go.kr/kor/introduce/nature.jsp
A76: 920075 | B76: 제시된 독도 목록에서 육상 식물끼리 묶인 것은 무엇인가요? | C76: 1 | E76: 독도 육상 식물: 해국, 섬기린초, 땅채송화. 독도 바닷말: 미역, 다시마. | G76: nature: 독도 식물·조류·해양생물 / 철새 이동경로의 휴식처 | H76: 대한민국 외교부 · 독도의 자연환경 https://dokdo.mofa.go.kr/kor/introduce/nature.jsp
A77: 920076 | B77: 독도 식물 조사에서 미역만 기록했다면 추가해야 할 조사 대상은 무엇인가요? | C77: 1 | E77: 조사 목표: 독도의 땅과 바다에 자라는 식물을 함께 살펴보기. 현재 기록에는 바닷말인 미역만 있어요. | G77: nature: 독도 식물·조류·해양생물 / 철새 이동경로의 휴식처 | H77: 대한민국 외교부 · 독도의 자연환경 https://dokdo.mofa.go.kr/kor/introduce/nature.jsp
A78: 920077 | B78: 독도에서 자연유산으로 함께 보호하는 대상은 무엇인가요? | C78: 0 | G78: reserve: 해안지형·조류 번식지·식생 보호; 지정 날짜를 묻는 문항은 제외 nature: 독도 식물·조류·해양생물 / 철새 이동경로의 휴식처 | H78: 대한민국 국가유산청 · 독도 천연보호구역 https://www.heritage.go.kr/heri/cul/culSelectDetail.do?VdkVgwKey=16%2C03360000%2C37&pageNo=1_1_2_0 대한민국 외교부 · 독도의 자연환경 https://dokdo.mofa.go.kr/kor/introduce/nature.jsp
A79: 920078 | B79: 독도 해안 절벽에 남아 있는 자연의 흔적은 무엇인가요? | C79: 0 | G79: reserve: 해안지형·조류 번식지·식생 보호; 지정 날짜를 묻는 문항은 제외 nature: 독도 식물·조류·해양생물 / 철새 이동경로의 휴식처 | H79: 대한민국 국가유산청 · 독도 천연보호구역 https://www.heritage.go.kr/heri/cul/culSelectDetail.do?VdkVgwKey=16%2C03360000%2C37&pageNo=1_1_2_0 대한민국 외교부 · 독도의 자연환경 https://dokdo.mofa.go.kr/kor/introduce/nature.jsp
A80: 920079 | B80: 독도 보호 계획에 ‘바닷새만 보호’라고 적으면 빠지는 대상은 무엇인가요? | C80: 1 | E80: 독도 천연보호구역 안내는 바닷새 번식지, 육상 식생, 화산 지질과 해안 지형 등의 가치를 함께 소개해요. | G80: reserve: 해안지형·조류 번식지·식생 보호; 지정 날짜를 묻는 문항은 제외 nature: 독도 식물·조류·해양생물 / 철새 이동경로의 휴식처 | H80: 대한민국 국가유산청 · 독도 천연보호구역 https://www.heritage.go.kr/heri/cul/culSelectDetail.do?VdkVgwKey=16%2C03360000%2C37&pageNo=1_1_2_0 대한민국 외교부 · 독도의 자연환경 https://dokdo.mofa.go.kr/kor/introduce/nature.jsp
A81: 920080 | B81: 독도 탐방 해설판에 보호 가치를 균형 있게 담은 구성은 무엇인가요? | C81: 1 | E81: 해설판의 목표는 독도가 왜 자연유산으로 보호되는지 알리는 것이에요. 보호구역 안내는 바닷새·식생·화산 지형을 근거로 소개해요. | G81: reserve: 해안지형·조류 번식지·식생 보호; 지정 날짜를 묻는 문항은 제외 nature: 독도 식물·조류·해양생물 / 철새 이동경로의 휴식처 | H81: 대한민국 국가유산청 · 독도 천연보호구역 https://www.heritage.go.kr/heri/cul/culSelectDetail.do?VdkVgwKey=16%2C03360000%2C37&pageNo=1_1_2_0 대한민국 외교부 · 독도의 자연환경 https://dokdo.mofa.go.kr/kor/introduce/nature.jsp
A82: 920081 | B82: 독도 바다숲을 이루는 큰 바닷말은 어느 것인가요? | C82: 0 | G82: forest: 감태·대황 해조숲 / 바위틈 생물 / 장기 관찰 | H82: 대한민국 한국해양과학기술원 · 독도 암반생태계 https://www.dokdo.re.kr/home/cms/cmsCont.do?cntnts_sn=87
A83: 920082 | B83: 감태와 대황이 많이 자라는 독도 바닷속 공간을 무엇이라고 부르나요? | C83: 0 | G83: forest: 감태·대황 해조숲 / 바위틈 생물 / 장기 관찰 | H83: 대한민국 한국해양과학기술원 · 독도 암반생태계 https://www.dokdo.re.kr/home/cms/cmsCont.do?cntnts_sn=87
A84: 920083 | B84: 자료에서 독도 바다숲을 만드는 생물끼리 짝지은 것은 무엇인가요? | C84: 1 | E84: 독도 암반생태계 안내: 감태와 대황이 바다숲을 이룬다. 홍합·거북손은 바위에 붙어 살며, 바위틈에는 게와 소라 등도 있다. | G84: forest: 감태·대황 해조숲 / 바위틈 생물 / 장기 관찰 | H84: 대한민국 한국해양과학기술원 · 독도 암반생태계 https://www.dokdo.re.kr/home/cms/cmsCont.do?cntnts_sn=87
A85: 920084 | B85: 독도 바다숲의 변화를 조사할 때 직접 비교해야 할 것은 무엇인가요? | C85: 1 | E85: 조사 목표: 독도에서 감태·대황이 이루는 바다숲의 범위가 시간에 따라 달라지는지 확인하기. | G85: forest: 감태·대황 해조숲 / 바위틈 생물 / 장기 관찰 | H85: 대한민국 한국해양과학기술원 · 독도 암반생태계 https://www.dokdo.re.kr/home/cms/cmsCont.do?cntnts_sn=87
A86: 920085 | B86: 독도 주변에서 함께 만나는 바닷물의 흐름은 무엇인가요? | C86: 0 | G86: effect: 난류·한류 혼합 / 영양염의 상층 공급 / 식물플랑크톤과 성육장 기능 | H86: 대한민국 한국해양과학기술원 · 독도 섬효과 https://www.dokdo.re.kr/home/cms/cmsCont.do?cntnts_sn=82
A87: 920086 | B87: 독도 주변의 깊은 물이 위로 섞이면 식물플랑크톤에 무엇을 공급할 수 있나요? | C87: 0 | D87: 식물플랑크톤은 햇빛과 영양분을 이용하는 작은 생물이에요. | G87: effect: 난류·한류 혼합 / 영양염의 상층 공급 / 식물플랑크톤과 성육장 기능 | H87: 대한민국 한국해양과학기술원 · 독도 섬효과 https://www.dokdo.re.kr/home/cms/cmsCont.do?cntnts_sn=82
A88: 920087 | B88: 독도 주변 바닷물 혼합과 영양분 공급의 순서는 무엇인가요? | C88: 1 | E88: 독도 섬효과 설명: 흐름과 바람의 영향으로 바닷물이 수직으로 섞이면 깊은 곳의 영양분이 위쪽에 공급될 수 있다. | G88: effect: 난류·한류 혼합 / 영양염의 상층 공급 / 식물플랑크톤과 성육장 기능 | H88: 대한민국 한국해양과학기술원 · 독도 섬효과 https://www.dokdo.re.kr/home/cms/cmsCont.do?cntnts_sn=82
A89: 920088 | B89: 독도 주변에서 물의 혼합이 줄면 가장 먼저 확인할 변화는 무엇인가요? | C89: 1 | E89: 검토할 연결: 수직 혼합 → 영양분의 상층 공급 → 식물플랑크톤 생장에 도움. 혼합이 줄었다고 생물 수가 반드시 즉시 감소한다고 단정하지 않아요. | G89: effect: 난류·한류 혼합 / 영양염의 상층 공급 / 식물플랑크톤과 성육장 기능 | H89: 대한민국 한국해양과학기술원 · 독도 섬효과 https://www.dokdo.re.kr/home/cms/cmsCont.do?cntnts_sn=82
A90: 920089 | B90: 독도 바다 먹이 관계의 바탕이 되는 작은 광합성 생물은 무엇인가요? | C90: 0 | G90: effect: 난류·한류 혼합 / 영양염의 상층 공급 / 식물플랑크톤과 성육장 기능 | H90: 대한민국 한국해양과학기술원 · 독도 섬효과 https://www.dokdo.re.kr/home/cms/cmsCont.do?cntnts_sn=82
A91: 920090 | B91: 독도 바다의 먹이 연결에서 식물플랑크톤을 먹는 것은 무엇인가요? | C91: 0 | D91: 간단한 먹이 연결: 식물플랑크톤 → 동물플랑크톤 → 어린 물고기. 화살표는 먹히는 쪽에서 먹는 쪽으로 향해요. | G91: effect: 난류·한류 혼합 / 영양염의 상층 공급 / 식물플랑크톤과 성육장 기능 | H91: 대한민국 한국해양과학기술원 · 독도 섬효과 https://www.dokdo.re.kr/home/cms/cmsCont.do?cntnts_sn=82
A92: 920091 | B92: 제시된 먹이 관계에서 동물플랑크톤을 먹는 생물은 무엇인가요? | C92: 1 | E92: 독도 바다의 단순화한 먹이 관계: 식물플랑크톤 → 동물플랑크톤 → 어린 물고기. 화살표는 ‘먹히는 생물에서 먹는 생물로’를 뜻해요. | G92: effect: 난류·한류 혼합 / 영양염의 상층 공급 / 식물플랑크톤과 성육장 기능 | H92: 대한민국 한국해양과학기술원 · 독도 섬효과 https://www.dokdo.re.kr/home/cms/cmsCont.do?cntnts_sn=82
A93: 920092 | B93: 독도 바다에서 어린 물고기의 먹이 공급을 살피려면 함께 조사할 생물은 무엇인가요? | C93: 1 | E93: 검토할 먹이 연결: 식물플랑크톤을 동물플랑크톤이 먹고, 일부 어린 물고기가 동물플랑크톤을 먹는다. 독도 바다 전체의 모든 먹이 관계를 나타낸 것은 아니에요. | G93: effect: 난류·한류 혼합 / 영양염의 상층 공급 / 식물플랑크톤과 성육장 기능 | H93: 대한민국 한국해양과학기술원 · 독도 섬효과 https://www.dokdo.re.kr/home/cms/cmsCont.do?cntnts_sn=82
A94: 920093 | B94: 과거 독도에 무리 지어 살았지만 사라진 바다 포유류는 무엇인가요? | C94: 0 | G94: gangchi: 포획 자료 기반 개체군 추정과 남획의 영향; 모델과 직접 관측 구분 gangchi-paper: Abstract 및 Discussion / 포획 압력·모델 가정과 환경 변화 미포함의 한계; CC BY 4.0 | H94: 대한민국 해양수산부 · 독도 강치 연구 발표(2022) https://www.mof.go.kr/doc/ko/selectDoc.do?bbsSeq=10&docSeq=45126&menuSeq=971 국제 학술지 JMSE · Lee 외 강치 개체군 연구(2022) https://www.mdpi.com/2077-1312/10/2/271
A95: 920094 | B95: 독도 강치를 크게 줄어들게 한 인간 활동은 무엇인가요? | C95: 0 | G95: gangchi: 포획 자료 기반 개체군 추정과 남획의 영향; 모델과 직접 관측 구분 gangchi-paper: Abstract 및 Discussion / 포획 압력·모델 가정과 환경 변화 미포함의 한계; CC BY 4.0 | H95: 대한민국 해양수산부 · 독도 강치 연구 발표(2022) https://www.mof.go.kr/doc/ko/selectDoc.do?bbsSeq=10&docSeq=45126&menuSeq=971 국제 학술지 JMSE · Lee 외 강치 개체군 연구(2022) https://www.mdpi.com/2077-1312/10/2/271
A96: 920095 | B96: 독도 강치 연구가 이용한 과거 인간 활동 기록은 무엇인가요? | C96: 1 | E96: 2022년 강치 연구는 남아 있는 포획 자료와 생물학적 가정을 이용해 과거 개체군 변화를 모의 계산했어요. | G96: gangchi: 포획 자료 기반 개체군 추정과 남획의 영향; 모델과 직접 관측 구분 gangchi-paper: Abstract 및 Discussion / 포획 압력·모델 가정과 환경 변화 미포함의 한계; CC BY 4.0 | H96: 대한민국 해양수산부 · 독도 강치 연구 발표(2022) https://www.mof.go.kr/doc/ko/selectDoc.do?bbsSeq=10&docSeq=45126&menuSeq=971 국제 학술지 JMSE · Lee 외 강치 개체군 연구(2022) https://www.mdpi.com/2077-1312/10/2/271
A97: 920096 | B97: 강치 모형에서 포획 압력이 커질 때 직접 늘어나는 항목은 무엇인가요? | C97: 1 | E97: 모형의 개체 수 변화: 출생으로 증가, 자연 사망과 포획으로 감소. 같은 번식 조건에서 포획 압력만 높여 본다. | G97: gangchi: 포획 자료 기반 개체군 추정과 남획의 영향; 모델과 직접 관측 구분 gangchi-paper: Abstract 및 Discussion / 포획 압력·모델 가정과 환경 변화 미포함의 한계; CC BY 4.0 | H97: 대한민국 해양수산부 · 독도 강치 연구 발표(2022) https://www.mof.go.kr/doc/ko/selectDoc.do?bbsSeq=10&docSeq=45126&menuSeq=971 국제 학술지 JMSE · Lee 외 강치 개체군 연구(2022) https://www.mdpi.com/2077-1312/10/2/271
A98: 920097 | B98: 옛 강치 기록으로 당시 개체 수를 계산한 값은 무엇이라고 하나요? | C98: 0 | G98: gangchi-paper: Abstract 및 Discussion / 포획 압력·모델 가정과 환경 변화 미포함의 한계; CC BY 4.0 gangchi: 포획 자료 기반 개체군 추정과 남획의 영향; 모델과 직접 관측 구분 | H98: 국제 학술지 JMSE · Lee 외 강치 개체군 연구(2022) https://www.mdpi.com/2077-1312/10/2/271 대한민국 해양수산부 · 독도 강치 연구 발표(2022) https://www.mof.go.kr/doc/ko/selectDoc.do?bbsSeq=10&docSeq=45126&menuSeq=971
A99: 920098 | B99: 독도 강치의 ‘포획 수’는 무엇을 센 값인가요? | C99: 0 | G99: gangchi-paper: Abstract 및 Discussion / 포획 압력·모델 가정과 환경 변화 미포함의 한계; CC BY 4.0 gangchi: 포획 자료 기반 개체군 추정과 남획의 영향; 모델과 직접 관측 구분 | H99: 국제 학술지 JMSE · Lee 외 강치 개체군 연구(2022) https://www.mdpi.com/2077-1312/10/2/271 대한민국 해양수산부 · 독도 강치 연구 발표(2022) https://www.mof.go.kr/doc/ko/selectDoc.do?bbsSeq=10&docSeq=45126&menuSeq=971
A100: 920099 | B100: ‘모형으로 계산한 강치 수’에 붙일 올바른 자료 표시는 무엇인가요? | C100: 1 | E100: 연구 방식: 과거 포획 기록을 넣고 번식과 사망에 관한 가정을 적용해 개체군을 계산했다. | G100: gangchi-paper: Abstract 및 Discussion / 포획 압력·모델 가정과 환경 변화 미포함의 한계; CC BY 4.0 gangchi: 포획 자료 기반 개체군 추정과 남획의 영향; 모델과 직접 관측 구분 | H100: 국제 학술지 JMSE · Lee 외 강치 개체군 연구(2022) https://www.mdpi.com/2077-1312/10/2/271 대한민국 해양수산부 · 독도 강치 연구 발표(2022) https://www.mof.go.kr/doc/ko/selectDoc.do?bbsSeq=10&docSeq=45126&menuSeq=971
...

Sheet 영어240
A1: ID | B1: Question | C1: A | D1: B | E1: C | F1: D | G1: Answer | H1: Why correct | I1: Takeaway | J1: Material / context | K1: Source
A2: 920001 | B2: What are the names of Dokdo’s two main islands? | C2: Dongdo and Seodo | D2: Ulleungdo and Dongdo | E2: Jejudo and Seodo | F2: Ulleungdo and Jejudo | G2: 1 | H2: Dongdo and Seodo are the two main islands, surrounded by smaller islets. | I2: Dokdo consists of Dongdo, Seodo and the smaller islets around them. | K2: 대한민국 외교부 · 독도의 구성 및 위치 https://dokdo.mofa.go.kr/kor/introduce/location.jsp
A3: 920002 | B3: What other land surrounds Dokdo’s two main islands? | C3: Smaller rocky islets | D3: The main island of Ulleungdo | E3: Japan’s Oki Islands | G3: 1 | H3: Dokdo includes the surrounding rocky islets as well as Dongdo and Seodo. | I3: Dokdo consists of Dongdo, Seodo and the smaller islets around them. | K3: 대한민국 외교부 · 독도의 구성 및 위치 https://dokdo.mofa.go.kr/kor/introduce/location.jsp
A4: 920003 | B4: What land should be added to a Dokdo sign that shows only its two main islands? | C4: All of Ulleungdo | D4: The surrounding associated islets | E4: All of Japan’s Oki Islands | G4: 2 | H4: The description includes the associated islets as well as the two main islands. | I4: Dokdo consists of Dongdo, Seodo and the smaller islets around them. | J4: Dokdo’s composition: Dongdo + Seodo + 89 associated islets. These are smaller islands around the two main islands. | K4: 대한민국 외교부 · 독도의 구성 및 위치 https://dokdo.mofa.go.kr/kor/introduce/location.jsp
A5: 920004 | B5: How should the statement “Dokdo is the name of Dongdo alone” be corrected? | C5: It names Dongdo and Ulleungdo | D5: It names Seodo alone | E5: It names Dongdo, Seodo and the surrounding islets | G5: 3 | H5: Dongdo is only part of Dokdo, which also includes Seodo and associated islets. | I5: Dokdo consists of Dongdo, Seodo and the smaller islets around them. | J5: The composition data includes Dongdo, Seodo and 89 associated islets within Dokdo. | K5: 대한민국 외교부 · 독도의 구성 및 위치 https://dokdo.mofa.go.kr/kor/introduce/location.jsp
A6: 920005 | B6: In which direction from Ulleungdo is Dokdo? | C6: Northeast | D6: Southeast | E6: Southwest | F6: Northwest | G6: 2 | H6: Dokdo is both east and south of Ulleungdo: southeast. | I6: Dokdo lies about 87.4 km southeast of Ulleungdo. | K6: 대한민국 해양수산부 · 독도의 주소와 위치 https://www.mof.go.kr/doc/ko/selectDoc.do?bbsSeq=27&docSeq=20937&menuSeq=929 대한민국 외교부 · 독도의 구성 및 위치 https://dokdo.mofa.go.kr/kor/introduce/location.jsp
A7: 920006 | B7: Approximately how far apart are Ulleungdo and Dokdo? | C7: 157.5 km | D7: 8.74 km | E7: 87.4 km | F7: 874 km | G7: 3 | H7: The distance between Ulleungdo and Dokdo is about 87.4 km. | I7: Dokdo lies about 87.4 km southeast of Ulleungdo. | K7: 대한민국 해양수산부 · 독도의 주소와 위치 https://www.mof.go.kr/doc/ko/selectDoc.do?bbsSeq=27&docSeq=20937&menuSeq=929 대한민국 외교부 · 독도의 구성 및 위치 https://dokdo.mofa.go.kr/kor/introduce/location.jsp
A8: 920007 | B8: Which place is nearer to Dokdo in the distance table? | C8: Ulleungdo | D8: Japan’s Oki Islands | G8: 1 | H8: 87.4 km is less than 157.5 km, so Ulleungdo is nearer. | I8: Dokdo lies about 87.4 km southeast of Ulleungdo. | J8: Dokdo to Ulleungdo: 87.4 km Dokdo to Japan’s Oki Islands: 157.5 km | K8: 대한민국 해양수산부 · 독도의 주소와 위치 https://www.mof.go.kr/doc/ko/selectDoc.do?bbsSeq=27&docSeq=20937&menuSeq=929 대한민국 외교부 · 독도의 구성 및 위치 https://dokdo.mofa.go.kr/kor/introduce/location.jsp
A9: 920008 | B9: How many kilometres nearer to Dokdo is Ulleungdo than the Oki Islands? | C9: 244.9 km | D9: 87.4 km | E9: 157.5 km | F9: 70.1 km | G9: 4 | H9: Subtracting gives 157.5 − 87.4 = 70.1 km, the difference in distance. | I9: Dokdo lies about 87.4 km southeast of Ulleungdo. | J9: Dokdo–Ulleungdo: 87.4 km. Dokdo–Japan’s Oki Islands: 157.5 km. Use these distances to calculate the difference. | K9: 대한민국 해양수산부 · 독도의 주소와 위치 https://www.mof.go.kr/doc/ko/selectDoc.do?bbsSeq=27&docSeq=20937&menuSeq=929 대한민국 외교부 · 독도의 구성 및 위치 https://dokdo.mofa.go.kr/kor/introduce/location.jsp
A10: 920009 | B10: Which main island is on Dokdo’s eastern side? | C10: Seodo | D10: Dongdo | G10: 2 | H10: “Dong” means east; Dongdo is the eastern main island. | I10: Dongdo is the eastern main island and Seodo is the western one. | J10: This simplifies their directional relationship; it is not a coastline map. | K10: 대한민국 외교부 · 독도의 구성 및 위치 https://dokdo.mofa.go.kr/kor/introduce/location.jsp
A11: 920010 | B11: What name labels Dokdo’s western main island? | C11: Seodo | D11: Dongdo | G11: 1 | H11: Seodo is the western island; Dongdo is the eastern one. | I11: Dongdo is the eastern main island and Seodo is the western one. | J11: This simplifies their directional relationship; it is not a coastline map. | K11: 대한민국 외교부 · 독도의 구성 및 위치 https://dokdo.mofa.go.kr/kor/introduce/location.jsp
A12: 920011 | B12: Which island name belongs at A in the position key? | C12: Dongdo | D12: Seodo | G12: 2 | H12: A occupies the western position, so it is Seodo. | I12: Dongdo is the eastern main island and Seodo is the western one. | J12: West ← [ A ] ··· [ Dongdo ] → East This key shows only the simplified east–west relationship. This simplifies their directional relationship; it is not a coastline map. | K12: 대한민국 외교부 · 독도의 구성 및 위치 https://dokdo.mofa.go.kr/kor/introduce/location.jsp
A13: 920012 | B13: On a position key with east pointing left, on which side is Dongdo placed? | C13: Left | D13: Right | G13: 1 | H13: East points left in this key, so the eastern island, Dongdo, is on the left. | I13: Dongdo is the eastern main island and Seodo is the western one. | J13: East ← [ A ] ··· [ B ] → West Dongdo is the eastern island and Seodo is the western island. Follow the arrows in this key. This simplifies their directional relationship; it is not a coastline map. | K13: 대한민국 외교부 · 독도의 구성 및 위치 https://dokdo.mofa.go.kr/kor/introduce/location.jsp
A14: 920013 | B14: What weather offers a good chance of seeing Dokdo from Ulleungdo? | C14: Clear weather with good visibility | D14: Dense fog | E14: Rain that obscures the view | G14: 1 | H14: Clear air allows a distant island such as Dokdo to be visible. | I14: Dokdo can be seen from Ulleungdo in clear weather with good visibility. | K14: 대한민국 외교부 자료실 · 세종실록 지리지(1454) https://dokdo.mofa.go.kr/kor/pds/part06_view02.jsp 대한민국 외교부 · 독도의 구성 및 위치 https://dokdo.mofa.go.kr/kor/introduce/location.jsp
A15: 920014 | B15: Which atmospheric condition helps observers see distant Dokdo from Ulleungdo? | C15: Dense fog over the sea | D15: Little fog and clear visibility | E15: Heavy rain reducing visibility | G15: 2 | H15: Distant viewing requires conditions with little obscuring fog. | I15: Dokdo can be seen from Ulleungdo in clear weather with good visibility. | K15: 대한민국 외교부 자료실 · 세종실록 지리지(1454) https://dokdo.mofa.go.kr/kor/pds/part06_view02.jsp 대한민국 외교부 · 독도의 구성 및 위치 https://dokdo.mofa.go.kr/kor/introduce/location.jsp
A16: 920015 | B16: What weather does the Sejong geographical record associate with seeing the two islands? | C16: When there is dense fog | D16: Every day regardless of conditions | E16: When the weather is clear | G16: 3 | H16: The translation says the islands can be seen when the weather is clear. | I16: Dokdo can be seen from Ulleungdo in clear weather with good visibility. | J16: Summary of the translated 1454 Sejong geographical record: Usan and Mureung are not far apart and can be seen in clear weather. The cited commentary identifies them as Dokdo and Ulleungdo. | K16: 대한민국 외교부 자료실 · 세종실록 지리지(1454) https://dokdo.mofa.go.kr/kor/pds/part06_view02.jsp 대한민국 외교부 · 독도의 구성 및 위치 https://dokdo.mofa.go.kr/kor/introduce/location.jsp
A17: 920016 | B17: Which of the two days is more suitable for viewing Dokdo from Ulleungdo? | C17: Day B | D17: Day A | G17: 2 | H17: Day A has clearer visibility for viewing the distant islands. | I17: Dokdo can be seen from Ulleungdo in clear weather with good visibility. | J17: Illustrative plan: day A has clear visibility without fog; on day B dense fog obscures the distant sea. Both observations would use the same point on Ulleungdo. | K17: 대한민국 외교부 자료실 · 세종실록 지리지(1454) https://dokdo.mofa.go.kr/kor/pds/part06_view02.jsp 대한민국 외교부 · 독도의 구성 및 위치 https://dokdo.mofa.go.kr/kor/introduce/location.jsp
A18: 920017 | B18: Which two main islands are counted separately from Dokdo’s 89 associated islets? | C18: Dongdo and Seodo | D18: Ulleungdo and Dokdo | E18: Dongdo and Ulleungdo | G18: 1 | H18: The 89 associated islets are in addition to Dongdo and Seodo. | I18: Dokdo’s 89 associated islets are counted separately from Dongdo and Seodo. | K18: 대한민국 외교부 · 독도의 구성 및 위치 https://dokdo.mofa.go.kr/kor/introduce/location.jsp 대한민국 한국해양과학기술원 · 독도 위치 및 규모 https://www.dokdo.re.kr/home/cms/cmsCont.do?cntnts_sn=64
A19: 920018 | B19: How many islands are there when Dongdo, Seodo and 89 associated islets are counted together? | C19: 91 | D19: 89 | E19: 90 | F19: 93 | G19: 1 | H19: Two main islands plus 89 associated islets equals 91. | I19: Dokdo’s 89 associated islets are counted separately from Dongdo and Seodo. | K19: 대한민국 외교부 · 독도의 구성 및 위치 https://dokdo.mofa.go.kr/kor/introduce/location.jsp 대한민국 한국해양과학기술원 · 독도 위치 및 규모 https://www.dokdo.re.kr/home/cms/cmsCont.do?cntnts_sn=64
A20: 920019 | B20: What is the combined area of the associated islets in the table? | C20: 73,297 m² | D20: 25,517 m² | E20: 88,740 m² | F20: 187,554 m² | G20: 2 | H20: The associated-islets row is 25,517 m², not the total or a main island’s area. | I20: Dokdo’s 89 associated islets are counted separately from Dongdo and Seodo. | J20: Dongdo: 73,297 m² Seodo: 88,740 m² 89 associated islets: 25,517 m² Total: 187,554 m² | K20: 대한민국 외교부 · 독도의 구성 및 위치 https://dokdo.mofa.go.kr/kor/introduce/location.jsp 대한민국 한국해양과학기술원 · 독도 위치 및 규모 https://www.dokdo.re.kr/home/cms/cmsCont.do?cntnts_sn=64
A21: 920020 | B21: What is left out when Dokdo’s total area is calculated using only Dongdo and Seodo? | C21: 25,517 m² of sea between the islands | D21: 25,517 m² of associated islets | E21: 25,517 m² of Ulleungdo | G21: 2 | H21: 187,554 − 73,297 − 88,740 = 25,517 m², the land area of the associated islets. | I21: Dokdo’s 89 associated islets are counted separately from Dongdo and Seodo. | J21: Dokdo total land area: 187,554 m²; Dongdo: 73,297 m²; Seodo: 88,740 m². Associated islets also contribute land area. | K21: 대한민국 외교부 · 독도의 구성 및 위치 https://dokdo.mofa.go.kr/kor/introduce/location.jsp 대한민국 한국해양과학기술원 · 독도 위치 및 규모 https://www.dokdo.re.kr/home/cms/cmsCont.do?cntnts_sn=64
A22: 920021 | B22: Which of Dokdo’s two main islands is higher? | C22: Seodo | D22: Dongdo | G22: 1 | H22: Seodo reaches 168.5 m, higher than Dongdo’s 98.6 m. | I22: Seodo is the higher main island: 168.5 m, compared with Dongdo’s 98.6 m. | K22: 대한민국 외교부 · 독도의 구성 및 위치 https://dokdo.mofa.go.kr/kor/introduce/location.jsp 대한민국 한국해양과학기술원 · 독도 위치 및 규모 https://www.dokdo.re.kr/home/cms/cmsCont.do?cntnts_sn=64
A23: 920022 | B23: Which main island of Dokdo reaches a maximum height of 98.6 m? | C23: Seodo | D23: Dongdo | G23: 2 | H23: 98.6 m is Dongdo’s maximum elevation. | I23: Seodo is the higher main island: 168.5 m, compared with Dongdo’s 98.6 m. | K23: 대한민국 외교부 · 독도의 구성 및 위치 https://dokdo.mofa.go.kr/kor/introduce/location.jsp 대한민국 한국해양과학기술원 · 독도 위치 및 규모 https://www.dokdo.re.kr/home/cms/cmsCont.do?cntnts_sn=64
A24: 920023 | B24: According to the height table, how many metres higher is Seodo than Dongdo? | C24: 267.1 m | D24: 98.6 m | E24: 69.9 m | F24: 151 m | G24: 3 | H24: Subtracting the two elevations gives 168.5 − 98.6 = 69.9 m. | I24: Seodo is the higher main island: 168.5 m, compared with Dongdo’s 98.6 m. | J24: Seodo maximum elevation: 168.5 m Dongdo maximum elevation: 98.6 m Both elevations are measured relative to sea level. | K24: 대한민국 외교부 · 독도의 구성 및 위치 https://dokdo.mofa.go.kr/kor/introduce/location.jsp 대한민국 한국해양과학기술원 · 독도 위치 및 규모 https://www.dokdo.re.kr/home/cms/cmsCont.do?cntnts_sn=64
A25: 920024 | B25: Which island has land above 100 m, based on the elevations in the table? | C25: Dongdo only | D25: Both islands | E25: Neither island | F25: Seodo only | G25: 4 | H25: Seodo reaches 168.5 m; Dongdo peaks at 98.6 m and therefore has no point at 100 m. | I25: Seodo is the higher main island: 168.5 m, compared with Dongdo’s 98.6 m. | J25: Seodo: 168.5 m; Dongdo: 98.6 m. Consider which island could have a 100 m contour. | K25: 대한민국 외교부 · 독도의 구성 및 위치 https://dokdo.mofa.go.kr/kor/introduce/location.jsp 대한민국 한국해양과학기술원 · 독도 위치 및 규모 https://www.dokdo.re.kr/home/cms/cmsCont.do?cntnts_sn=64
A26: 920025 | B26: Which of Dokdo’s main islands has the larger land area? | C26: Seodo | D26: Dongdo | G26: 1 | H26: Seodo’s 88,740 m² exceeds Dongdo’s 73,297 m². | I26: Seodo has the larger area, but Dongdo has the longer coastline. | K26: 대한민국 외교부 · 독도의 구성 및 위치 https://dokdo.mofa.go.kr/kor/introduce/location.jsp 대한민국 한국해양과학기술원 · 독도 위치 및 규모 https://www.dokdo.re.kr/home/cms/cmsCont.do?cntnts_sn=64
A27: 920026 | B27: What does m² measure in Dokdo’s area table? | C27: Peak elevation | D27: Length along the coastline | E27: Land area | G27: 3 | H27: Square metres measure area, unlike metres used for elevation. | I27: Seodo has the larger area, but Dongdo has the longer coastline. | J27: Seodo: 88,740 m² / Dongdo: 73,297 m² | K27: 대한민국 외교부 · 독도의 구성 및 위치 https://dokdo.mofa.go.kr/kor/introduce/location.jsp 대한민국 한국해양과학기술원 · 독도 위치 및 규모 https://www.dokdo.re.kr/home/cms/cmsCont.do?cntnts_sn=64
A28: 920027 | B28: Which main island has the longer coastline in the table? | C28: Seodo | D28: Dongdo | G28: 2 | H28: Dongdo’s 2.8 km coastline is longer than Seodo’s 2.6 km. | I28: Seodo has the larger area, but Dongdo has the longer coastline. | J28: Dongdo: area 73,297 m²; coastline 2.8 km Seodo: area 88,740 m²; coastline 2.6 km | K28: 대한민국 외교부 · 독도의 구성 및 위치 https://dokdo.mofa.go.kr/kor/introduce/location.jsp 대한민국 한국해양과학기술원 · 독도 위치 및 규모 https://www.dokdo.re.kr/home/cms/cmsCont.do?cntnts_sn=64
A29: 920028 | B29: Which comparison of both area and coastline agrees with the table? | C29: Seodo has more area; Dongdo has a longer coastline | D29: Seodo has more area and therefore a longer coastline | E29: Dongdo has both more area and a longer coastline | G29: 1 | H29: Area and coastline length are distinct quantities; different islands lead in each. | I29: Seodo has the larger area, but Dongdo has the longer coastline. | J29: Dongdo: 73,297 m² / coastline 2.8 km Seodo: 88,740 m² / coastline 2.6 km Area measures land extent; coastline length follows the shore. | K29: 대한민국 외교부 · 독도의 구성 및 위치 https://dokdo.mofa.go.kr/kor/introduce/location.jsp 대한민국 한국해양과학기술원 · 독도 위치 및 규모 https://www.dokdo.re.kr/home/cms/cmsCont.do?cntnts_sn=64
A30: 920029 | B30: What separates Dongdo and Seodo? | C30: A land road | D30: Sea | E30: A river | G30: 2 | H30: Their exposed land areas are separated by seawater. | I30: The nearest shores of Dongdo and Seodo are about 151 m apart. | J30: This is a shore-to-shore gap, not the peak-to-peak distance or a walking route. | K30: 대한민국 한국해양과학기술원 · 독도 지형 및 지질 https://www.dokdo.re.kr/home/cms/cmsCont.do?cntnts_sn=66 대한민국 국가유산청 · 독도 천연보호구역 https://www.heritage.go.kr/heri/cul/culSelectDetail.do?VdkVgwKey=16%2C03360000%2C37&pageNo=1_1_2_0
A31: 920030 | B31: Approximately how far apart are the nearest shores of Dongdo and Seodo? | C31: 151 m | D31: 87.4 km | E31: 98.6 m | F31: 168.5 m | G31: 1 | H31: About 151 m is the gap between the nearest shores of the main islands. | I31: The nearest shores of Dongdo and Seodo are about 151 m apart. | J31: This is a shore-to-shore gap, not the peak-to-peak distance or a walking route. | K31: 대한민국 한국해양과학기술원 · 독도 지형 및 지질 https://www.dokdo.re.kr/home/cms/cmsCont.do?cntnts_sn=66 대한민국 국가유산청 · 독도 천연보호구역 https://www.heritage.go.kr/heri/cul/culSelectDetail.do?VdkVgwKey=16%2C03360000%2C37&pageNo=1_1_2_0
A32: 920031 | B32: Where should the ends of a line marking the 151 m gap be placed? | C32: At the two peaks | D32: At the lighthouse and residence | E32: At the nearest points on the two shores | G32: 3 | H32: The measurement is shore-to-shore, so the line connects those nearest points. | I32: The nearest shores of Dongdo and Seodo are about 151 m apart. | J32: Distance definition: the nearest facing shores of Dongdo and Seodo are approximately 151 m apart. This is a shore-to-shore gap, not the peak-to-peak distance or a walking route. | K32: 대한민국 한국해양과학기술원 · 독도 지형 및 지질 https://www.dokdo.re.kr/home/cms/cmsCont.do?cntnts_sn=66 대한민국 국가유산청 · 독도 천연보호구역 https://www.heritage.go.kr/heri/cul/culSelectDetail.do?VdkVgwKey=16%2C03360000%2C37&pageNo=1_1_2_0
A33: 920032 | B33: On a map where 1 cm represents 50 m, how long is a 151 m gap? | C33: 7,550 cm | D33: 3.02 cm | E33: 151 cm | F33: 0.302 cm | G33: 2 | H33: 151 ÷ 50 = 3.02 cm. | I33: The nearest shores of Dongdo and Seodo are about 151 m apart. | J33: Actual shore gap: about 151 m Practice map scale: 1 cm represents 50 m The scale is chosen for this exercise. This is a shore-to-shore gap, not the peak-to-peak distance or a walking route. | K33: 대한민국 한국해양과학기술원 · 독도 지형 및 지질 https://www.dokdo.re.kr/home/cms/cmsCont.do?cntnts_sn=66 대한민국 국가유산청 · 독도 천연보호구역 https://www.heritage.go.kr/heri/cul/culSelectDetail.do?VdkVgwKey=16%2C03360000%2C37&pageNo=1_1_2_0
A34: 920033 | B34: Which main island of Dokdo is especially marked by a steep peak? | C34: Seodo | D34: Dongdo | G34: 1 | H34: Seodo is characterised by its higher, steeply rising peak. | I34: Seodo rises steeply; Dongdo has a comparatively level upper area. | K34: 대한민국 국가유산청 · 독도 천연보호구역 https://www.heritage.go.kr/heri/cul/culSelectDetail.do?VdkVgwKey=16%2C03360000%2C37&pageNo=1_1_2_0 대한민국 전북교육청 · 독도 사진 자료 https://www.jbe.go.kr/dokdo/assets/sub/picture.html
A35: 920034 | B35: Which island has the comparatively level upper area used by facilities such as the helipad? | C35: Seodo | D35: Dongdo | G35: 2 | H35: Dongdo’s relatively level upper area accommodates the helipad and other facilities. | I35: Seodo rises steeply; Dongdo has a comparatively level upper area. | K35: 대한민국 국가유산청 · 독도 천연보호구역 https://www.heritage.go.kr/heri/cul/culSelectDetail.do?VdkVgwKey=16%2C03360000%2C37&pageNo=1_1_2_0 대한민국 전북교육청 · 독도 사진 자료 https://www.jbe.go.kr/dokdo/assets/sub/picture.html
A36: 920035 | B36: Does terrain description A refer to Dongdo or Seodo? | C36: Dongdo | D36: Seodo | G36: 1 | H36: A describes the relatively level upper area with facilities on Dongdo. | I36: Seodo rises steeply; Dongdo has a comparatively level upper area. | J36: A: coastal cliffs, with a comparatively level upper area containing a helipad and facilities. B: a prominent high, steep peak. | K36: 대한민국 국가유산청 · 독도 천연보호구역 https://www.heritage.go.kr/heri/cul/culSelectDetail.do?VdkVgwKey=16%2C03360000%2C37&pageNo=1_1_2_0 대한민국 전북교육청 · 독도 사진 자료 https://www.jbe.go.kr/dokdo/assets/sub/picture.html
A37: 920036 | B37: What should be changed in a model that makes Dongdo as pointed as Seodo? | C37: Restore Dongdo’s comparatively level upper area | D37: Make Dongdo higher than Seodo | E37: Remove all of Dongdo’s coastal cliffs | G37: 1 | H37: Represent Dongdo’s comparatively level upper area as well as its coastal cliffs. | I37: Seodo rises steeply; Dongdo has a comparatively level upper area. | J37: Terrain data: Seodo 168.5 m with a steep peak; Dongdo 98.6 m with coastal cliffs and a comparatively level upper area. Model to revise: two identical pointed mountains differing only in height. | K37: 대한민국 국가유산청 · 독도 천연보호구역 https://www.heritage.go.kr/heri/cul/culSelectDetail.do?VdkVgwKey=16%2C03360000%2C37&pageNo=1_1_2_0 대한민국 전북교육청 · 독도 사진 자료 https://www.jbe.go.kr/dokdo/assets/sub/picture.html
A38: 920037 | B38: Does Dokdo’s terrain continue underwater below Dongdo and Seodo? | C38: It ends at sea level | D38: It continues underwater | G38: 2 | H38: Dongdo and Seodo are exposed parts of an underwater volcanic structure. | I38: Dongdo and Seodo are exposed parts of a much larger underwater volcanic structure. | K38: 대한민국 한국해양과학기술원 · 독도 지형 및 지질 https://www.dokdo.re.kr/home/cms/cmsCont.do?cntnts_sn=66
A39: 920038 | B39: The two main islands of Dokdo are exposed parts of what? | C39: A river delta | D39: An underwater volcanic structure | E39: A coral-built island | G39: 2 | H39: The exposed islands belong to a volcanic structure formed underwater. | I39: Dongdo and Seodo are exposed parts of a much larger underwater volcanic structure. | K39: 대한민국 한국해양과학기술원 · 독도 지형 및 지질 https://www.dokdo.re.kr/home/cms/cmsCont.do?cntnts_sn=66
A40: 920039 | B40: From where is the approximately 2,300 m height of Dokdo’s volcanic structure measured? | C40: From sea level to Seodo’s peak | D40: From sea level to Dongdo’s peak | E40: From the submarine base | G40: 3 | H40: About 2,300 m describes the entire structure from its submarine base. | I40: Dongdo and Seodo are exposed parts of a much larger underwater volcanic structure. | J40: Seodo’s elevation above sea level: 168.5 m. The full Dokdo volcanic structure: about 2,300 m from its submarine base. Note the different reference levels. | K40: 대한민국 한국해양과학기술원 · 독도 지형 및 지질 https://www.dokdo.re.kr/home/cms/cmsCont.do?cntnts_sn=66
A41: 920040 | B41: Why can 168.5 m and about 2,300 m both appear in descriptions of Dokdo’s height? | C41: The reference points for height differ | D41: 168.5 m is Dongdo and 2,300 m is Seodo | E41: Only the units differ for measurements from one reference | G41: 1 | H41: 168.5 m is relative to sea level; about 2,300 m is relative to the submarine base. | I41: Dongdo and Seodo are exposed parts of a much larger underwater volcanic structure. | J41: Sea level → Seodo’s peak: 168.5 m Submarine volcanic base → top of the structure: about 2,300 m | K41: 대한민국 한국해양과학기술원 · 독도 지형 및 지질 https://www.dokdo.re.kr/home/cms/cmsCont.do?cntnts_sn=66
A42: 920041 | B42: Which natural process originally formed Dokdo? | C42: Deposition of river sand | D42: Coral growth | E42: Underwater volcanic activity | F42: Glacial deposition | G42: 3 | H42: Erupted volcanic material accumulated to form the Dokdo volcanic structure. | I42: Dokdo formed from material erupted by underwater volcanic activity. | K42: 대한민국 한국해양과학기술원 · 독도 지형 및 지질 https://www.dokdo.re.kr/home/cms/cmsCont.do?cntnts_sn=66
A43: 920042 | B43: Where did the volcanic activity that formed Dokdo begin? | C43: At a river mouth on land | D43: Under the sea | E43: On a sandy beach | G43: 2 | H43: The structure grew underwater before part emerged above the surface. | I43: Dokdo formed from material erupted by underwater volcanic activity. | K43: 대한민국 한국해양과학기술원 · 독도 지형 및 지질 https://www.dokdo.re.kr/home/cms/cmsCont.do?cntnts_sn=66
A44: 920043 | B44: Which sequence describes Dokdo’s formation? | C44: Emergence → submarine eruption → accumulation | D44: Accumulation → emergence → first submarine eruption | E44: Submarine eruption → accumulation → emergence | G44: 3 | H44: Erupted material accumulated and built a structure that eventually emerged. | I44: Dokdo formed from material erupted by underwater volcanic activity. | J44: Volcanic material erupted underwater, accumulated into a growing structure, and eventually emerged above the sea. | K44: 대한민국 한국해양과학기술원 · 독도 지형 및 지질 https://www.dokdo.re.kr/home/cms/cmsCont.do?cntnts_sn=66
A45: 920044 | B45: Which account combines Dokdo’s volcanic origin with later wave erosion? | C45: Volcanism built the island; later waves eroded its coast | D45: Waves caused the original volcanic eruptions | E45: The coast stopped changing after volcanic formation | G45: 1 | H45: Formation and later reshaping are different processes, both relevant to Dokdo. | I45: Dokdo formed from material erupted by underwater volcanic activity. | J45: Dokdo originated through submarine volcanism. Erosion became dominant after emergence, leaving only part of the originally exposed structure. | K45: 대한민국 한국해양과학기술원 · 독도 지형 및 지질 https://www.dokdo.re.kr/home/cms/cmsCont.do?cntnts_sn=66
A46: 920045 | B46: Where did Dokdo grow before emerging above the water? | C46: On Ulleungdo’s land | D46: Beneath the East Sea | E46: At a river mouth on the Korean Peninsula | G46: 2 | H46: Dokdo is the exposed part of a structure that grew beneath the sea. | I46: Dokdo grew underwater, emerged, and was reshaped by erosion over a long period. | J46: Formation ages are approximate research estimates, not exact calendar dates. | K46: 대한민국 한국해양과학기술원 · 독도 지형 및 지질 https://www.dokdo.re.kr/home/cms/cmsCont.do?cntnts_sn=66
A47: 920046 | B47: What has eroded Dokdo’s coast since the islands formed? | C47: Coral growing over the islands | D47: Sand deposited at a river mouth | E47: Erosion by waves | G47: 3 | H47: Erosion, including wave action, reshaped the exposed coastline. | I47: Dokdo grew underwater, emerged, and was reshaped by erosion over a long period. | J47: Formation ages are approximate research estimates, not exact calendar dates. | K47: 대한민국 한국해양과학기술원 · 독도 지형 및 지질 https://www.dokdo.re.kr/home/cms/cmsCont.do?cntnts_sn=66
A48: 920047 | B48: Which event happened first in the Dokdo formation timeline? | C48: The beginning of submarine volcanic activity | D48: Emergence above the sea | G48: 1 | H48: About 4.6 million years ago is earlier than about 2.5 million years ago. | I48: Dokdo grew underwater, emerged, and was reshaped by erosion over a long period. | J48: Formation account: submarine volcanism began at least approximately 4.6 million years ago; emergence began around 2.5 million years ago. Formation ages are approximate research estimates, not exact calendar dates. | K48: 대한민국 한국해양과학기술원 · 독도 지형 및 지질 https://www.dokdo.re.kr/home/cms/cmsCont.do?cntnts_sn=66
A49: 920048 | B49: What is the approximate difference between 4.6 and 2.5 million years ago? | C49: 7.1 million years | D49: 210,000 years | E49: 2.5 million years | F49: 2.1 million years | G49: 4 | H49: 4.6 − 2.5 = 2.1 million years, using the supplied approximate dates. | I49: Dokdo grew underwater, emerged, and was reshaped by erosion over a long period. | J49: Approximate dates for calculation: submarine volcanic activity 4.6 million years ago; emergence 2.5 million years ago. This calculation does not establish an exact formation duration. Formation ages are approximate research estimates, not exact calendar dates. | K49: 대한민국 한국해양과학기술원 · 독도 지형 및 지질 https://www.dokdo.re.kr/home/cms/cmsCont.do?cntnts_sn=66
A50: 920049 | B50: What movement of seawater erodes Dokdo’s coastal rock? | C50: Waves | D50: River flow | E50: Glacial movement | G50: 1 | H50: Waves striking the shore contribute to erosion. | I50: Wave erosion helps shape Dokdo’s coastal cliffs, caves and arches. | K50: 대한민국 한국해양과학기술원 · 독도 지형 및 지질 https://www.dokdo.re.kr/home/cms/cmsCont.do?cntnts_sn=66 대한민국 한국관광공사 · 독립문바위 https://korean.visitkorea.or.kr/detail/ms_detail.do?cotid=0fe4eeb6-3f6a-48b1-ab75-c8d4ab6b43be
A51: 920050 | B51: What is the wearing away of Dokdo’s coastal rock by waves called? | C51: Deposition | D51: Marine erosion | E51: Eruption | G51: 2 | H51: Marine erosion is the wearing away of coastal material by the sea. | I51: Wave erosion helps shape Dokdo’s coastal cliffs, caves and arches. | K51: 대한민국 한국해양과학기술원 · 독도 지형 및 지질 https://www.dokdo.re.kr/home/cms/cmsCont.do?cntnts_sn=66 대한민국 한국관광공사 · 독립문바위 https://korean.visitkorea.or.kr/detail/ms_detail.do?cotid=0fe4eeb6-3f6a-48b1-ab75-c8d4ab6b43be
A52: 920051 | B52: Which process contributed to the arch opening in Dongnimmun Rock? | C52: Accumulation of sand carried by a river | D52: Coral growing into a ring | E52: Wave erosion of coastal rock | G52: 3 | H52: The rock is a sea arch formed through erosion of coastal rock. | I52: Wave erosion helps shape Dokdo’s coastal cliffs, caves and arches. | J52: Dongnimmun Rock is a sea arch on Dongdo. A sea arch is coastal rock eroded into an arch-shaped remnant. | K52: 대한민국 한국해양과학기술원 · 독도 지형 및 지질 https://www.dokdo.re.kr/home/cms/cmsCont.do?cntnts_sn=66 대한민국 한국관광공사 · 독립문바위 https://korean.visitkorea.or.kr/detail/ms_detail.do?cotid=0fe4eeb6-3f6a-48b1-ab75-c8d4ab6b43be
A53: 920052 | B53: Which description identifies a wave-eroded landform on Dokdo? | C53: Weak parts of coastal rock were eroded into an opening | D53: Erupted material accumulated into a larger submarine volcano | E53: Sand settled underwater to form a new layer | G53: 1 | H53: This describes coastal rock being worn away, consistent with marine erosion. | I53: Wave erosion helps shape Dokdo’s coastal cliffs, caves and arches. | J53: Classification: marine erosion wears away coastal rock. Dokdo’s sea caves and arches are associated with this process. | K53: 대한민국 한국해양과학기술원 · 독도 지형 및 지질 https://www.dokdo.re.kr/home/cms/cmsCont.do?cntnts_sn=66 대한민국 한국관광공사 · 독립문바위 https://korean.visitkorea.or.kr/detail/ms_detail.do?cotid=0fe4eeb6-3f6a-48b1-ab75-c8d4ab6b43be
A54: 920053 | B54: What is the process in which exposure weakens Dokdo’s rocks over time? | C54: Eruption | D54: Weathering | E54: Deposition | G54: 2 | H54: Weathering weakens or breaks down rock through environmental exposure. | I54: Weathering weakens Dokdo’s rock and erosion wears it away, reshaping the coast. | K54: 대한민국 한국해양과학기술원 · 독도 지형 및 지질 https://www.dokdo.re.kr/home/cms/cmsCont.do?cntnts_sn=66
A55: 920054 | B55: What process occurs when eroded fragments from Dokdo accumulate elsewhere? | C55: Eruption | D55: Weathering | E55: Deposition | G55: 3 | H55: The accumulation stage is deposition, distinct from removal by erosion. | I55: Weathering weakens Dokdo’s rock and erosion wears it away, reshaping the coast. | K55: 대한민국 한국해양과학기술원 · 독도 지형 및 지질 https://www.dokdo.re.kr/home/cms/cmsCont.do?cntnts_sn=66
A56: 920055 | B56: Which order matches rock weakening followed by removal by waves on Dokdo? | C56: Weathering → erosion | D56: Deposition → weathering | E56: Eruption → deposition | G56: 1 | H56: Weathering weakens the rock before erosion removes material. | I56: Weathering weakens Dokdo’s rock and erosion wears it away, reshaping the coast. | J56: Illustrative observation: cracks widened in Dokdo’s coastal rock, then waves removed material from the weakened section. This describes processes, not a dated field measurement. | K56: 대한민국 한국해양과학기술원 · 독도 지형 및 지질 https://www.dokdo.re.kr/home/cms/cmsCont.do?cntnts_sn=66
A57: 920056 | B57: Which pair of records is suitable for comparing change in Dokdo’s coastline? | C57: A whole-Seodo image and a close-up of one Dongdo rock | D57: Two dates of the same coastal section at the same scale | E57: Dongdo elevations and Ulleungdo temperatures | G57: 2 | H57: Matching location and scale allows a meaningful comparison of coastline change. | I57: Weathering weakens Dokdo’s rock and erosion wears it away, reshaping the coast. | J57: Weathering and erosion can produce small changes along Dokdo’s coast. A survey needs to compare past and newer observations of the same section. | K57: 대한민국 한국해양과학기술원 · 독도 지형 및 지질 https://www.dokdo.re.kr/home/cms/cmsCont.do?cntnts_sn=66
A58: 920057 | B58: On which main island of Dokdo is Mulgol? | C58: Dongdo | D58: Seodo | G58: 2 | H58: Mulgol is a water source on Seodo’s coast. | I58: Mulgol on Seodo supplies dripping water and was used as a drinking-water source before desalination facilities. | K58: 대한민국 한국해양과학기술원 · 독도 지형 및 지질 https://www.dokdo.re.kr/home/cms/cmsCont.do?cntnts_sn=66 대한민국 외교부 · 독도 주요시설물 https://dokdo.mofa.go.kr/kor/introduce/facility.jsp
A59: 920058 | B59: Before desalination facilities, what was Mulgol used for? | C59: A boat landing | D59: A helicopter landing | E59: A source of drinking water | G59: 3 | H59: Water dripping at Mulgol was used for drinking. | I59: Mulgol on Seodo supplies dripping water and was used as a drinking-water source before desalination facilities. | K59: 대한민국 한국해양과학기술원 · 독도 지형 및 지질 https://www.dokdo.re.kr/home/cms/cmsCont.do?cntnts_sn=66 대한민국 외교부 · 독도 주요시설물 https://dokdo.mofa.go.kr/kor/introduce/facility.jsp
A60: 920059 | B60: Which place name completes the description? | C60: Mulgol | D60: Cheonjang Cave | E60: Dongnimmun Rock | G60: 1 | H60: A historical water source on Seodo identifies Mulgol. | I60: Mulgol on Seodo supplies dripping water and was used as a drinking-water source before desalination facilities. | J60: At [ ] on Seodo, water drips from the rock. It was used for drinking before seawater-desalination equipment was installed. | K60: 대한민국 한국해양과학기술원 · 독도 지형 및 지질 https://www.dokdo.re.kr/home/cms/cmsCont.do?cntnts_sn=66 대한민국 외교부 · 독도 주요시설물 https://dokdo.mofa.go.kr/kor/introduce/facility.jsp
A61: 920060 | B61: Which pairing correctly describes water supply at Mulgol and at a desalination facility? | C61: Mulgol: a seawater boiler / desalination: dripping rock water | D61: Mulgol: dripping water / desalination: removing salt from seawater | E61: Both collect water from the same rock crevice | G61: 2 | H61: One collects naturally dripping water; the other processes seawater. | I61: Mulgol on Seodo supplies dripping water and was used as a drinking-water source before desalination facilities. | J61: Mulgol: dripping rock water on Seodo, historically used for drinking. Desalination: equipment that removes salt from seawater for use. | K61: 대한민국 한국해양과학기술원 · 독도 지형 및 지질 https://www.dokdo.re.kr/home/cms/cmsCont.do?cntnts_sn=66 대한민국 외교부 · 독도 주요시설물 https://dokdo.mofa.go.kr/kor/introduce/facility.jsp
A62: 920061 | B62: What does Dokdo provide for birds making long migrations? | C62: A place used only in winter | D62: A permanent home for every visiting bird | E62: A place to rest during migration | G62: 3 | H62: Migrating birds can pause on Dokdo before continuing their journeys. | I62: Dokdo is a stopover where migrating birds can rest. | K62: 대한민국 외교부 · 독도의 자연환경 https://dokdo.mofa.go.kr/kor/introduce/nature.jsp
A63: 920062 | B63: What is a place such as Dokdo where migrating birds pause called? | C63: A stopover site | D63: A breeding site | E63: A wintering site | G63: 1 | H63: A temporary resting place during a journey is a stopover. | I63: Dokdo is a stopover where migrating birds can rest. | K63: 대한민국 외교부 · 독도의 자연환경 https://dokdo.mofa.go.kr/kor/introduce/nature.jsp
A64: 920063 | B64: In the route “departure → rest on Dokdo → destination”, what role does Dokdo play? | C64: The departure site | D64: A stopover | E64: The final destination | G64: 2 | H64: The birds rest between departure and destination, making Dokdo a stopover. | I64: Dokdo is a stopover where migrating birds can rest. | J64: Illustrative migration route: departure → a short rest on Dokdo → destination. This is not a tracked route of an individual bird. | K64: 대한민국 외교부 · 독도의 자연환경 https://dokdo.mofa.go.kr/kor/introduce/nature.jsp
A65: 920064 | B65: Which of the two bird observations on Dokdo describes a stopover? | C65: A: resting briefly and then continuing elsewhere | D65: B: incubating eggs and raising chicks at a nest | G65: 1 | H65: Resting before continuing a longer journey is a stopover. | I65: Dokdo is a stopover where migrating birds can rest. | J65: Dokdo is a stopover and a breeding site for some seabirds. Illustrative observations: A rests during migration and leaves; B raises chicks at a nest. | K65: 대한민국 외교부 · 독도의 자연환경 https://dokdo.mofa.go.kr/kor/introduce/nature.jsp
A66: 920065 | B66: Which bird is recorded as breeding on Dokdo? | C66: Emperor penguin | D66: Ostrich | E66: Black-tailed gull | G66: 3 | H66: Black-tailed gulls are among the seabirds recorded as breeding on Dokdo. | I66: Black-tailed gulls, storm petrels and streaked shearwaters are recorded as breeding seabirds on Dokdo. | K66: 대한민국 국가유산청 · 독도 천연보호구역 https://www.heritage.go.kr/heri/cul/culSelectDetail.do?VdkVgwKey=16%2C03360000%2C37&pageNo=1_1_2_0 대한민국 외교부 · 독도의 자연환경 https://dokdo.mofa.go.kr/kor/introduce/nature.jsp
A67: 920066 | B67: What does it mean that black-tailed gulls breed on Dokdo? | C67: They lay eggs and raise chicks. | D67: They only stop to rest and leave. | E67: They only look for food and leave. | G67: 1 | H67: Breeding produces the next generation, including laying eggs and raising chicks. | I67: Black-tailed gulls, storm petrels and streaked shearwaters are recorded as breeding seabirds on Dokdo. | K67: 대한민국 국가유산청 · 독도 천연보호구역 https://www.heritage.go.kr/heri/cul/culSelectDetail.do?VdkVgwKey=16%2C03360000%2C37&pageNo=1_1_2_0 대한민국 외교부 · 독도의 자연환경 https://dokdo.mofa.go.kr/kor/introduce/nature.jsp
A68: 920067 | B68: Which set contains only birds listed as breeding on Dokdo? | C68: Black-tailed gulls, emperor penguins and streaked shearwaters | D68: Black-tailed gulls, storm petrels and streaked shearwaters | E68: Storm petrels, streaked shearwaters and ostriches | G68: 2 | H68: These are the three breeding-bird groups listed in the supplied account. | I68: Black-tailed gulls, storm petrels and streaked shearwaters are recorded as breeding seabirds on Dokdo. | J68: Breeding birds named in the Dokdo Natural Reserve account: storm petrels, streaked shearwaters and black-tailed gulls. | K68: 대한민국 국가유산청 · 독도 천연보호구역 https://www.heritage.go.kr/heri/cul/culSelectDetail.do?VdkVgwKey=16%2C03360000%2C37&pageNo=1_1_2_0 대한민국 외교부 · 독도의 자연환경 https://dokdo.mofa.go.kr/kor/introduce/nature.jsp
A69: 920068 | B69: Which observation demonstrates Dokdo’s function as a breeding site? | C69: A migrant rests on a rock and soon leaves | D69: A bird flies past above the islands | E69: A black-tailed gull feeds chicks at its nest | G69: 3 | H69: Raising chicks at a nest demonstrates use of a breeding site. | I69: Black-tailed gulls, storm petrels and streaked shearwaters are recorded as breeding seabirds on Dokdo. | J69: Breeding involves producing and raising young; a stopover is a temporary pause during migration. The observations below are illustrative examples. | K69: 대한민국 국가유산청 · 독도 천연보호구역 https://www.heritage.go.kr/heri/cul/culSelectDetail.do?VdkVgwKey=16%2C03360000%2C37&pageNo=1_1_2_0 대한민국 외교부 · 독도의 자연환경 https://dokdo.mofa.go.kr/kor/introduce/nature.jsp
A70: 920069 | B70: Which seaweed grows in the waters around Dokdo? | C70: Wakame | D70: Streaked shearwater | E70: Seaside daisy | G70: 1 | H70: Wakame is a seaweed listed for waters around Dokdo. | I70: Dokdo supports both seabirds and underwater seaweeds. | K70: 대한민국 외교부 · 독도의 자연환경 https://dokdo.mofa.go.kr/kor/introduce/nature.jsp 대한민국 국가유산청 · 독도 천연보호구역 https://www.heritage.go.kr/heri/cul/culSelectDetail.do?VdkVgwKey=16%2C03360000%2C37&pageNo=1_1_2_0
A71: 920070 | B71: How are Dokdo’s black-tailed gull and wakame classified? | C71: Seaweed / seabird | D71: Seabird / seaweed | E71: Seabird / seabird | G71: 2 | H71: The gull is a bird; wakame is a seaweed. | I71: Dokdo supports both seabirds and underwater seaweeds. | K71: 대한민국 외교부 · 독도의 자연환경 https://dokdo.mofa.go.kr/kor/introduce/nature.jsp 대한민국 국가유산청 · 독도 천연보호구역 https://www.heritage.go.kr/heri/cul/culSelectDetail.do?VdkVgwKey=16%2C03360000%2C37&pageNo=1_1_2_0
A72: 920071 | B72: In “Dokdo is a breeding site for 海鳥類”, what does 海鳥類 mean? | C72: Seaweeds | D72: Marine fish | E72: Seabirds | G72: 3 | H72: The character 鳥 means bird, so the term refers to seabirds. | I72: Dokdo supports both seabirds and underwater seaweeds. | J72: Word key: 海 means sea, 鳥 bird, and 藻 algae. In Korean, 海鳥類 and 海藻類 sound alike but refer to seabirds and seaweeds respectively. | K72: 대한민국 외교부 · 독도의 자연환경 https://dokdo.mofa.go.kr/kor/introduce/nature.jsp 대한민국 국가유산청 · 독도 천연보호구역 https://www.heritage.go.kr/heri/cul/culSelectDetail.do?VdkVgwKey=16%2C03360000%2C37&pageNo=1_1_2_0
A73: 920072 | B73: Which pair belongs entirely in the “seaweeds” category of Dokdo organisms? | C73: Wakame and kelp | D73: Wakame and streaked shearwater | E73: Black-tailed gull and storm petrel | G73: 1 | H73: Both are seaweeds listed in the Dokdo natural-environment account. | I73: Dokdo supports both seabirds and underwater seaweeds. | J73: Dokdo list: seaweeds — wakame, kelp; seabirds — black-tailed gulls, storm petrels, streaked shearwaters. | K73: 대한민국 외교부 · 독도의 자연환경 https://dokdo.mofa.go.kr/kor/introduce/nature.jsp 대한민국 국가유산청 · 독도 천연보호구역 https://www.heritage.go.kr/heri/cul/culSelectDetail.do?VdkVgwKey=16%2C03360000%2C37&pageNo=1_1_2_0
A74: 920073 | B74: Which flowering plant grows on Dokdo’s land? | C74: Wakame | D74: Seaside daisy | E74: Kelp | G74: 2 | H74: Seaside daisy is listed among Dokdo’s land plants. | I74: Plants on Dokdo include seaside daisy, island stonecrop and rock stonecrop. | K74: 대한민국 외교부 · 독도의 자연환경 https://dokdo.mofa.go.kr/kor/introduce/nature.jsp
A75: 920074 | B75: What would a survey of seaside daisy and island stonecrop on Dokdo investigate? | C75: Breeding seabirds | D75: Marine fish | E75: Land plants | G75: 3 | H75: Both are plants that grow on Dokdo’s land. | I75: Plants on Dokdo include seaside daisy, island stonecrop and rock stonecrop. | K75: 대한민국 외교부 · 독도의 자연환경 https://dokdo.mofa.go.kr/kor/introduce/nature.jsp
A76: 920075 | B76: Which pair consists of land plants in the supplied Dokdo list? | C76: Island stonecrop and rock stonecrop | D76: Island stonecrop and wakame | E76: Wakame and kelp | G76: 1 | H76: Both appear in the land-plant list. | I76: Plants on Dokdo include seaside daisy, island stonecrop and rock stonecrop. | J76: Dokdo land plants: seaside daisy, island stonecrop, rock stonecrop. Seaweeds: wakame and kelp. | K76: 대한민국 외교부 · 독도의 자연환경 https://dokdo.mofa.go.kr/kor/introduce/nature.jsp
A77: 920076 | B77: If a Dokdo plant survey records only wakame, what should be added to cover land plants? | C77: Only other seaweeds such as kelp | D77: Land plants such as seaside daisy and island stonecrop | E77: Seabirds such as black-tailed gulls | G77: 2 | H77: Wakame alone does not represent plants growing on the islands’ land. | I77: Plants on Dokdo include seaside daisy, island stonecrop and rock stonecrop. | J77: Survey goal: cover vegetation on both Dokdo’s land and in its waters. The current record contains only wakame, a seaweed. | K77: 대한민국 외교부 · 독도의 자연환경 https://dokdo.mofa.go.kr/kor/introduce/nature.jsp
A78: 920077 | B78: What is protected together as part of Dokdo’s natural heritage? | C78: Only buildings | D78: Only vessels and the dock | E78: Organisms and volcanic landforms | G78: 3 | H78: Conservation value includes plants, marine life and volcanic terrain as well as birds. | I78: Dokdo conservation includes breeding seabirds, plants and volcanic landforms. | K78: 대한민국 국가유산청 · 독도 천연보호구역 https://www.heritage.go.kr/heri/cul/culSelectDetail.do?VdkVgwKey=16%2C03360000%2C37&pageNo=1_1_2_0 대한민국 외교부 · 독도의 자연환경 https://dokdo.mofa.go.kr/kor/introduce/nature.jsp
A79: 920078 | B79: What natural processes are recorded in Dokdo’s coastal cliffs? | C79: Volcanic formation and erosion | D79: A valley carved by a glacier | E79: River-mouth sand deposition | G79: 1 | H79: Rock and cliff forms help reveal the island’s construction and erosion. | I79: Dokdo conservation includes breeding seabirds, plants and volcanic landforms. | K79: 대한민국 국가유산청 · 독도 천연보호구역 https://www.heritage.go.kr/heri/cul/culSelectDetail.do?VdkVgwKey=16%2C03360000%2C37&pageNo=1_1_2_0 대한민국 외교부 · 독도의 자연환경 https://dokdo.mofa.go.kr/kor/introduce/nature.jsp
A80: 920079 | B80: What would a Dokdo plan that protects “only seabirds” omit? | C80: Storm petrels and black-tailed gulls | D80: Land plants and volcanic landforms | E80: Seabird breeding | G80: 2 | H80: The supplied account identifies vegetation and landforms as valuable too. | I80: Dokdo conservation includes breeding seabirds, plants and volcanic landforms. | J80: The Dokdo Natural Reserve account describes breeding seabirds, land vegetation, volcanic geology and coastal landforms. | K80: 대한민국 국가유산청 · 독도 천연보호구역 https://www.heritage.go.kr/heri/cul/culSelectDetail.do?VdkVgwKey=16%2C03360000%2C37&pageNo=1_1_2_0 대한민국 외교부 · 독도의 자연환경 https://dokdo.mofa.go.kr/kor/introduce/nature.jsp
A81: 920080 | B81: Which interpretation-panel plan covers Dokdo’s conservation values most fully? | C81: Repeat only three seabird names | D81: Explain only facility addresses and ferry times | E81: Explain seabird breeding, land plants, volcanic and eroded terrain | G81: 3 | H81: This covers both biological and geological values identified in the account. | I81: Dokdo conservation includes breeding seabirds, plants and volcanic landforms. | J81: The panel aims to explain why Dokdo is conserved as natural heritage. The reserve account identifies birds, vegetation and volcanic landforms. | K81: 대한민국 국가유산청 · 독도 천연보호구역 https://www.heritage.go.kr/heri/cul/culSelectDetail.do?VdkVgwKey=16%2C03360000%2C37&pageNo=1_1_2_0 대한민국 외교부 · 독도의 자연환경 https://dokdo.mofa.go.kr/kor/introduce/nature.jsp
A82: 920081 | B82: Which large seaweed helps form underwater forests around Dokdo? | C82: Ecklonia cava | D82: Seaside daisy | E82: Island stonecrop | G82: 1 | H82: Ecklonia cava is described as a forest-forming seaweed in Dokdo’s rocky waters. | I82: Large seaweeds such as Ecklonia cava and Eisenia bicyclis form underwater forests around Dokdo. | K82: 대한민국 한국해양과학기술원 · 독도 암반생태계 https://www.dokdo.re.kr/home/cms/cmsCont.do?cntnts_sn=87
A83: 920082 | B83: What is an area where large seaweeds grow abundantly around Dokdo called? | C83: A tidal mudflat | D83: An underwater forest | E83: A coral reef | G83: 2 | H83: An underwater forest is an area of large, abundant seaweeds. | I83: Large seaweeds such as Ecklonia cava and Eisenia bicyclis form underwater forests around Dokdo. | K83: 대한민국 한국해양과학기술원 · 독도 암반생태계 https://www.dokdo.re.kr/home/cms/cmsCont.do?cntnts_sn=87
A84: 920083 | B84: Which pair forms underwater forests in the supplied Dokdo account? | C84: Mussels and stalked barnacles | D84: Crabs and turban snails | E84: Ecklonia cava and Eisenia bicyclis | G84: 3 | H84: Both are identified as large, forest-forming seaweeds. | I84: Large seaweeds such as Ecklonia cava and Eisenia bicyclis form underwater forests around Dokdo. | J84: Dokdo rocky-ecosystem account: large seaweeds form forests; mussels and barnacles attach to rock; crabs and snails also live in crevices. | K84: 대한민국 한국해양과학기술원 · 독도 암반생태계 https://www.dokdo.re.kr/home/cms/cmsCont.do?cntnts_sn=87
A85: 920084 | B85: What should be directly compared to monitor changes in Dokdo’s underwater forests? | C85: Coverage of the forest-forming seaweeds in the same area | D85: A single water-temperature reading from different sites | E85: Only the area of seaside-daisy colonies on land | G85: 1 | H85: This measures the target forest itself at the same location. | I85: Large seaweeds such as Ecklonia cava and Eisenia bicyclis form underwater forests around Dokdo. | J85: Survey goal: determine whether the coverage of Dokdo’s seaweed forests changes over time. | K85: 대한민국 한국해양과학기술원 · 독도 암반생태계 https://www.dokdo.re.kr/home/cms/cmsCont.do?cntnts_sn=87
A86: 920085 | B86: Which water flows meet around Dokdo? | C86: Only warm currents | D86: Warm and cold currents | E86: Only cold currents | G86: 2 | H86: Dokdo’s marine environment is influenced by meeting warm and cold currents. | I86: Warm and cold currents mix around Dokdo and influence nutrient transport. | K86: 대한민국 한국해양과학기술원 · 독도 섬효과 https://www.dokdo.re.kr/home/cms/cmsCont.do?cntnts_sn=82
A87: 920086 | B87: What can mixing of deeper water supply to phytoplankton around Dokdo? | C87: Sunlight | D87: Seabird eggs | E87: Nutrients | G87: 3 | H87: Upward nutrient transport can support phytoplankton growth. | I87: Warm and cold currents mix around Dokdo and influence nutrient transport. | J87: Phytoplankton are small organisms that use light and nutrients. | K87: 대한민국 한국해양과학기술원 · 독도 섬효과 https://www.dokdo.re.kr/home/cms/cmsCont.do?cntnts_sn=82
A88: 920087 | B88: Which sequence links water mixing and nutrient supply around Dokdo? | C88: Vertical mixing → deeper nutrients move into upper water | D88: Vertical mixing → complete removal of upper-water nutrients | E88: Vertical mixing → nutrient transport always stops | G88: 1 | H88: This follows the sequence of mixing and upward nutrient transport. | I88: Warm and cold currents mix around Dokdo and influence nutrient transport. | J88: Dokdo island-effect account: currents and wind can promote vertical mixing and supply deeper nutrients to upper waters. | K88: 대한민국 한국해양과학기술원 · 독도 섬효과 https://www.dokdo.re.kr/home/cms/cmsCont.do?cntnts_sn=82
A89: 920088 | B89: If vertical mixing around Dokdo decreases, what change should be checked first? | C89: Only total young-fish abundance | D89: Nutrient supply to upper waters | E89: Only seabird breeding numbers | G89: 2 | H89: In the supplied causal chain, nutrient transport is the immediate next step. | I89: Warm and cold currents mix around Dokdo and influence nutrient transport. | J89: Relationship to examine: vertical mixing → nutrient supply to upper waters → support for phytoplankton growth. Reduced mixing alone does not establish an immediate decline in organisms. | K89: 대한민국 한국해양과학기술원 · 독도 섬효과 https://www.dokdo.re.kr/home/cms/cmsCont.do?cntnts_sn=82
A90: 920089 | B90: Which small photosynthetic organisms support food links around Dokdo? | C90: Young fish | D90: Sea lions | E90: Phytoplankton | G90: 3 | H90: Phytoplankton use light and can become food for other organisms. | I90: Food links around Dokdo can connect phytoplankton, zooplankton and young fish. | K90: 대한민국 한국해양과학기술원 · 독도 섬효과 https://www.dokdo.re.kr/home/cms/cmsCont.do?cntnts_sn=82
A91: 920090 | B91: Which organisms consume phytoplankton in this Dokdo food link? | C91: Zooplankton | D91: Ecklonia cava | E91: Eisenia bicyclis | G91: 1 | H91: In this link, zooplankton eat phytoplankton and can feed young fish. | I91: Food links around Dokdo can connect phytoplankton, zooplankton and young fish. | J91: Simple food link: phytoplankton → zooplankton → young fish. Arrows run from food to consumer. | K91: 대한민국 한국해양과학기술원 · 독도 섬효과 https://www.dokdo.re.kr/home/cms/cmsCont.do?cntnts_sn=82
A92: 920091 | B92: Which organisms eat zooplankton in the supplied food chain? | C92: Phytoplankton | D92: Young fish | E92: Ecklonia cava | G92: 2 | H92: The arrow runs from zooplankton to young fish. | I92: Food links around Dokdo can connect phytoplankton, zooplankton and young fish. | J92: Simplified food link around Dokdo: phytoplankton → zooplankton → young fish. Arrows point from food organisms to their consumers. | K92: 대한민국 한국해양과학기술원 · 독도 섬효과 https://www.dokdo.re.kr/home/cms/cmsCont.do?cntnts_sn=82
A93: 920092 | B93: Which organisms should be surveyed to examine food supply for young fish around Dokdo? | C93: Only coastal seabird nest counts | D93: Only land-plant species on the islands | E93: Abundance of zooplankton used as food | G93: 3 | H93: This surveys the food directly consumed by the young fish in the given link. | I93: Food links around Dokdo can connect phytoplankton, zooplankton and young fish. | J93: Link for investigation: zooplankton consume phytoplankton, and some young fish consume zooplankton. This is not a complete web for all organisms around Dokdo. | K93: 대한민국 한국해양과학기술원 · 독도 섬효과 https://www.dokdo.re.kr/home/cms/cmsCont.do?cntnts_sn=82
A94: 920093 | B94: Which marine mammal once lived in groups on Dokdo but disappeared? | C94: Japanese sea lion | D94: Sea otter | E94: Seal | G94: 1 | H94: The Dokdo catch records and population study concern the extinct Japanese sea lion. | I94: Sea lions once lived on Dokdo, and excessive hunting contributed greatly to their decline and extinction. | K94: 대한민국 해양수산부 · 독도 강치 연구 발표(2022) https://www.mof.go.kr/doc/ko/selectDoc.do?bbsSeq=10&docSeq=45126&menuSeq=971 국제 학술지 JMSE · Lee 외 강치 개체군 연구(2022) https://www.mdpi.com/2077-1312/10/2/271
A95: 920094 | B95: Which human activity contributed greatly to Dokdo sea lions’ decline? | C95: Expansion of farmland on the islands | D95: Excessive hunting | E95: Seaweed harvesting alone | G95: 2 | H95: Research using catch records identifies heavy hunting pressure as a major cause. | I95: Sea lions once lived on Dokdo, and excessive hunting contributed greatly to their decline and extinction. | K95: 대한민국 해양수산부 · 독도 강치 연구 발표(2022) https://www.mof.go.kr/doc/ko/selectDoc.do?bbsSeq=10&docSeq=45126&menuSeq=971 국제 학술지 JMSE · Lee 외 강치 개체군 연구(2022) https://www.mdpi.com/2077-1312/10/2/271
A96: 920095 | B96: Which historical human-activity records were used in research on Dokdo sea lions? | C96: Only annual seabird nest counts | D96: Only present fish catches | E96: Historical annual sea lion catches | G96: 3 | H96: Catch information provides a model input for population change. | I96: Sea lions once lived on Dokdo, and excessive hunting contributed greatly to their decline and extinction. | J96: A 2022 study simulated historical sea lion population changes using surviving catch information and biological assumptions. | K96: 대한민국 해양수산부 · 독도 강치 연구 발표(2022) https://www.mof.go.kr/doc/ko/selectDoc.do?bbsSeq=10&docSeq=45126&menuSeq=971 국제 학술지 JMSE · Lee 외 강치 개체군 연구(2022) https://www.mdpi.com/2077-1312/10/2/271
A97: 920096 | B97: Which component increases directly when hunting pressure rises in a sea lion model? | C97: Losses from the population through catches | D97: The number of newborns | E97: The number actually observed in a past survey | G97: 1 | H97: Hunting directly adds catch losses, which must be compared with replacement through births. | I97: Sea lions once lived on Dokdo, and excessive hunting contributed greatly to their decline and extinction. | J97: Model balance: births increase the population; natural mortality and catches reduce it. Consider increasing hunting pressure while holding reproduction assumptions constant. | K97: 대한민국 해양수산부 · 독도 강치 연구 발표(2022) https://www.mof.go.kr/doc/ko/selectDoc.do?bbsSeq=10&docSeq=45126&menuSeq=971 국제 학술지 JMSE · Lee 외 강치 개체군 연구(2022) https://www.mdpi.com/2077-1312/10/2/271
A98: 920097 | B98: What is a historical sea lion population calculated from records called? | C98: A complete count made at that time | D98: An estimate | E98: A live population count today | G98: 2 | H98: A calculation from incomplete records and assumptions is an estimate, not a complete census. | I98: Modelled historical sea lion populations must be distinguished from complete field counts. | K98: 국제 학술지 JMSE · Lee 외 강치 개체군 연구(2022) https://www.mdpi.com/2077-1312/10/2/271 대한민국 해양수산부 · 독도 강치 연구 발표(2022) https://www.mof.go.kr/doc/ko/selectDoc.do?bbsSeq=10&docSeq=45126&menuSeq=971
A99: 920098 | B99: What does a historical Dokdo sea lion catch total count? | C99: Every sea lion alive at the time | D99: Sea lions born that year | E99: Sea lions caught by people | G99: 3 | H99: A catch total counts sea lions taken by people. It is not the whole population, which also includes uncaught animals. | I99: Modelled historical sea lion populations must be distinguished from complete field counts. | K99: 국제 학술지 JMSE · Lee 외 강치 개체군 연구(2022) https://www.mdpi.com/2077-1312/10/2/271 대한민국 해양수산부 · 독도 강치 연구 발표(2022) https://www.mof.go.kr/doc/ko/selectDoc.do?bbsSeq=10&docSeq=45126&menuSeq=971
A100: 920099 | B100: Which label correctly describes a modelled sea lion population? | C100: An estimate calculated from historical records and assumptions | D100: A full count made by researchers at the historical time | E100: The number of sea lions now living on Dokdo | G100: 1 | H100: This identifies the calculation and distinguishes it from observation. | I100: Modelled historical sea lion populations must be distinguished from complete field counts. | J100: Method: historical catch records were combined with assumptions about reproduction and mortality to calculate population change. | K100: 국제 학술지 JMSE · Lee 외 강치 개체군 연구(2022) https://www.mdpi.com/2077-1312/10/2/271 대한민국 해양수산부 · 독도 강치 연구 발표(2022) https://www.mof.go.kr/doc/ko/selectDoc.do?bbsSeq=10&docSeq=45126&menuSeq=971
...

Sheet 이전대조
A1: old ID | B1: new ID | C1: 이전 질문 | D1: 수정 질문 | E1: 기록 정책
A2: 910001 | B2: 920001 | C2: 독도의 두 큰 섬은? | D2: 독도를 이루는 두 큰 섬의 이름은 무엇인가요? | E2: 이전 ID는 회수하고 학습 기록·불빛은 보존. 새 문제의 정답·숙달로 자동 치환하지 않음.
A3: 910002 | B3: 920002 | C3: 동도·서도만 그리면 빠지는 것은? | D3: 독도의 두 큰 섬 주위에는 어떤 땅이 더 있나요? | E3: 이전 ID는 회수하고 학습 기록·불빛은 보존. 새 문제의 정답·숙달로 자동 치환하지 않음.
A4: 910003 | B4: 920003 | C4: 자료의 89개는 무엇을 센 수일까요? | D4: 독도 안내판에 두 큰 섬만 그렸다면 어떤 땅을 추가해야 하나요? | E4: 이전 ID는 회수하고 학습 기록·불빛은 보존. 새 문제의 정답·숙달로 자동 치환하지 않음.
A5: 910004 | B5: 920004 | C5: 독도를 ‘섬 두 개뿐’이라 소개한 글의 수정은? | D5: 독도를 ‘동도 한 섬의 이름’이라고 쓴 문장을 어떻게 고쳐야 하나요? | E5: 이전 ID는 회수하고 학습 기록·불빛은 보존. 새 문제의 정답·숙달로 자동 치환하지 않음.
A6: 910005 | B6: 920005 | C6: 울릉도에서 독도는 어느 방향일까요? | D6: 독도는 울릉도에서 어느 방향에 있나요? | E6: 이전 ID는 회수하고 학습 기록·불빛은 보존. 새 문제의 정답·숙달로 자동 치환하지 않음.
A7: 910006 | B7: 920006 | C7: 울릉도와 독도의 관계는? | D7: 울릉도와 독도 사이의 거리는 약 얼마인가요? | E7: 이전 ID는 회수하고 학습 기록·불빛은 보존. 새 문제의 정답·숙달로 자동 치환하지 않음.
A8: 910007 | B8: 920007 | C8: 주어진 거리에서 독도에 더 가까운 곳은? | D8: 거리표에서 독도에 더 가까운 곳은 어디인가요? | E8: 이전 ID는 회수하고 학습 기록·불빛은 보존. 새 문제의 정답·숙달로 자동 치환하지 않음.
A9: 910008 | B9: 920008 | C9: 이 거리 표만으로 뒷받침되는 말은? | D9: 독도에서 울릉도까지는 오키섬까지보다 몇 km 더 가까운가요? | E9: 이전 ID는 회수하고 학습 기록·불빛은 보존. 새 문제의 정답·숙달로 자동 치환하지 않음.
A10: 910009 | B10: 920009 | C10: 독도의 동쪽 큰 섬 이름은? | D10: 독도의 동쪽에 있는 큰 섬은 무엇인가요? | E10: 이전 ID는 회수하고 학습 기록·불빛은 보존. 새 문제의 정답·숙달로 자동 치환하지 않음.
A11: 910010 | B11: 920010 | C11: 서도 이름의 ‘서’와 연결되는 방향은? | D11: 독도의 서쪽 큰 섬을 지도에 표시하려면 어떤 이름을 쓰나요? | E11: 이전 ID는 회수하고 학습 기록·불빛은 보존. 새 문제의 정답·숙달로 자동 치환하지 않음.
A12: 910011 | B12: 920011 | C12: 주어진 방향도에서 동도는 서도의 어느 쪽인가요? | D12: 위치표에서 A에 넣을 섬 이름은 무엇인가요? | E12: 이전 ID는 회수하고 학습 기록·불빛은 보존. 새 문제의 정답·숙달로 자동 치환하지 않음.
A13: 910012 | B13: 920012 | C13: 지도를 돌려 동도가 왼쪽에 보이면? | D13: 동쪽 화살표가 왼쪽을 가리키는 위치표에서 동도는 어느 쪽에 놓이나요? | E13: 이전 ID는 회수하고 학습 기록·불빛은 보존. 새 문제의 정답·숙달로 자동 치환하지 않음.
... A241: 910240 | B241: 920240 | C241: 여러 자료로 독도를 설명할 때 지킬 기준은? | D241: 독도 소개문에 넣을 설명으로 사실에 맞는 것은 무엇인가요? | E241: 이전 ID는 회수하고 학습 기록·불빛은 보존. 새 문제의 정답·숙달로 자동 치환하지 않음.

Sheet 출처30
A1: source ID | B1: 국가·공개 기관 | C1: 원문 URL | D1: 근거 위치 | E1: 공개 국가 | F1: 확인 방식·한계 | G1: 출처 역할 | H1: originalCreator | I1: checked
A2: location | B2: 대한민국 외교부 · 독도의 구성 및 위치 | C2: https://dokdo.mofa.go.kr/kor/introduce/location.jsp | D2: 두 큰 섬·부속 도서 / 높이·면적 / 울릉도·오키섬 거리 | E2: 대한민국 | F2: official-page text or official indexed text | G2: 현재 공개된 기관 안내; 조사 시기·범위의 한계를 유지 | H2: "" | I2: 2026-09-12
A3: geology | B3: 대한민국 한국해양과학기술원 · 독도 지형 및 지질 | C3: https://www.dokdo.re.kr/home/cms/cmsCont.do?cntnts_sn=66 | D3: 해저 화산의 형성 / 해안 침식 지형 / 물골 / 지형 변화 | E3: 대한민국 | F3: official-indexed-text; live-page access limited | G3: 현재 공개된 기관 안내; 조사 시기·범위의 한계를 유지 | H3: "" | I3: 2026-09-12
A4: nature | B4: 대한민국 외교부 · 독도의 자연환경 | C4: https://dokdo.mofa.go.kr/kor/introduce/nature.jsp | D4: 독도 식물·조류·해양생물 / 철새 이동경로의 휴식처 | E4: 대한민국 | F4: official-page text or official indexed text | G4: 현재 공개된 기관 안내; 조사 시기·범위의 한계를 유지 | H4: "" | I4: 2026-09-12
A5: forest | B5: 대한민국 한국해양과학기술원 · 독도 암반생태계 | C5: https://www.dokdo.re.kr/home/cms/cmsCont.do?cntnts_sn=87 | D5: 감태·대황 해조숲 / 바위틈 생물 / 장기 관찰 | E5: 대한민국 | F5: official-indexed-text; live-page access limited | G5: 현재 공개된 기관 안내; 조사 시기·범위의 한계를 유지 | H5: "" | I5: 2026-09-12
A6: facility | B6: 대한민국 외교부 · 독도 주요시설물 | C6: https://dokdo.mofa.go.kr/kor/introduce/facility.jsp | D6: 서도 주민숙소 / 동도 접안시설·등대·경비대 / 담수시설 | E6: 대한민국 | F6: official-page text or official indexed text | G6: 현재 공개된 기관 안내; 조사 시기·범위의 한계를 유지 | H6: "" | I6: 2026-09-12
A7: visit | B7: 대한민국 외교부 · 주민 및 입도 안내 | C7: https://dokdo.mofa.go.kr/kor/introduce/residence.jsp | D7: 입도 유의사항·동도 선착장 관람 / 2026년 7월 기준 표기. 실제 방문 전 최신 안내 확인 | E7: 대한민국 | F7: official-page text or official indexed text | G7: 현재 공개된 기관 안내; 조사 시기·범위의 한계를 유지 | H7: "" | I7: 2026-09-12
A8: sejong | B8: 대한민국 외교부 자료실 · 세종실록 지리지(1454) | C8: https://dokdo.mofa.go.kr/kor/pds/part06_view02.jsp | D8: 우산·무릉과 맑은 날의 가시성; 괄호 안 현대 지명은 외교부 해석 | E8: 대한민국 | F8: official-page text or official indexed text | G8: 역사 원문·역문과 현대 대한민국 기관의 해설을 구분 | H8: {"ko": "조선 · 『세종실록』 지리지", "en": "Joseon · geographical appendix to the Annals of Sejong"} | I8: 2026-09-12
A9: an | B9: 대한민국 외교부 · 안용복의 활동과 기록 | C9: https://dokdo.mofa.go.kr/kor/include/print_faq.jsp?class_faq=q5 | D9: 1693년과 1696년 / 숙종실록과 오키섬 조사 기록 | E9: 대한민국 | F9: official-page text or official indexed text | G9: 현재 공개된 기관 안내; 조사 시기·범위의 한계를 유지 | H9: "" | I9: 2026-09-12
A10: timeline | B10: 대한민국 외교부 · 독도 연표 | C10: https://dokdo.mofa.go.kr/m/kor/dokdo/reason_list.jsp | D10: 1694 수토 / 1696년 1월 금지령·5월 도일 / 1900·1905·1906 순서 | E10: 대한민국 | F10: official-page text or official indexed text | G10: 현재 공개된 기관 안내; 조사 시기·범위의 한계를 유지 | H10: "" | I10: 2026-09-12
A11: decree | B11: 대한민국 외교부 자료실 · 대한제국 칙령 제41호 | C11: https://dokdo.mofa.go.kr/kor/pds/part02_view02.jsp | D11: 1900.10.25 / 제1조 울도·군수 / 제2조 울릉전도·죽도·석도 | E11: 대한민국 | F11: official-page text or official indexed text | G11: 역사 원문·역문과 현대 대한민국 기관의 해설을 구분 | H11: {"ko": "1900년 대한제국 · 고종 황제의 칙령", "en": "Korean Empire · imperial decree, 1900"} | I11: 2026-09-12
A12: gazette | B12: 대한민국 외교부 자료실 · 관보(1900.10.27) | C12: https://dokdo.mofa.go.kr/kor/pds/part02_view03.jsp | D12: 관보 게재 날짜와 칙령 날짜의 구분 | E12: 대한민국 | F12: official-page text or official indexed text | G12: 역사 원문·역문과 현대 대한민국 기관의 해설을 구분 | H12: {"ko": "1900년 대한제국 관보", "en": "Korean Empire government gazette, 1900"} | I12: 2026-09-12
... A31: size | B31: 대한민국 한국해양과학기술원 · 독도 위치 및 규모 | C31: https://www.dokdo.re.kr/home/cms/cmsCont.do?cntnts_sn=64 | D31: 동도 73,297㎡ / 서도 88,740㎡ / 부속 도서 25,517㎡ / 전체 187,554㎡ | E31: 대한민국 | F31: official-indexed-text; live-page access limited | G31: 현재 공개된 기관 안내; 조사 시기·범위의 한계를 유지 | H31: "" | I31: 2026-09-12

Sheet 읽기점검
A1: track | B1: ID | C1: 질문+최장보기 글자수 | D1: 권장 길이 | E1: 자료 포함 글자수 | F1: 검토 메모
A2: early | B2: 920201 | C2: 52 | D2: 48 | E2: 101 | F2: 질문에서 주체·시기·대상을 삭제하지 않음. 참고 상한 초과이며 실제 학습자 읽기 검토가 필요함. 글자수만으로 학년 적합성을 승인하지 않음.
A3: early | B3: 920234 | C3: 49 | D3: 48 | E3: 49 | F3: 질문에서 주체·시기·대상을 삭제하지 않음. 참고 상한 초과이며 실제 학습자 읽기 검토가 필요함. 글자수만으로 학년 적합성을 승인하지 않음.
A4: primary | B4: 920205 | C4: 57 | D4: 48 | E4: 57 | F4: 질문에서 주체·시기·대상을 삭제하지 않음. 참고 상한 초과이며 실제 학습자 읽기 검토가 필요함. 글자수만으로 학년 적합성을 승인하지 않음.
A5: primary | B5: 920222 | C5: 56 | D5: 48 | E5: 56 | F5: 질문에서 주체·시기·대상을 삭제하지 않음. 참고 상한 초과이며 실제 학습자 읽기 검토가 필요함. 글자수만으로 학년 적합성을 승인하지 않음.
A6: primary | B6: 920234 | C6: 49 | D6: 48 | E6: 49 | F6: 질문에서 주체·시기·대상을 삭제하지 않음. 참고 상한 초과이며 실제 학습자 읽기 검토가 필요함. 글자수만으로 학년 적합성을 승인하지 않음.

Sheet 문항정의
A1: 검수 항목 | B1: 수정 기준 | C1: 검토 메모
A2: 문제 정의 | B2: 독도에 관한 한 가지 사실·명칭·관계·판단을 분명하게 묻고, 정답의 이유와 독도 지식 하나를 남기는 질문 | C2: 앱 조작법과 일반 예절로 독도 수업을 대체하지 않음
A3: 질문 | B3: 무엇을 답할지 질문 안에 명시. 행동 주체·시기·대상을 필요한 만큼 포함 | C3: 출처 기관을 반복하는 머리말은 넣지 않음
A4: 보기 | B4: 같은 범주의 비교 가능한 보기 2~4개. 정답은 하나 | C4: 번호가 아니라 고유 choice ID에 피드백을 연결
A5: 해설 | B5: 각 보기마다 왜 맞거나 틀린지 직접 설명 | C5: 개념 공통 문장을 빈 해설의 대체재로 사용하지 않음
A6: 자료 | B6: 자료가 필요한 문항에는 난이도와 무관하게 표시 | C6: 존재하지 않는 지도나 사진을 본 것으로 가정하지 않음
A7: 국가와 사료 | B7: 원문 작성기관과 현재 번역·해설 공개기관을 구분 | C7: 대한민국 외교부 자료 / 역사 행위자는 일본 태정관·내무성·에도 막부 등
A8: 영유권 근거 | B8: 자료가 실제 뒷받침하는 의미를 정확히 전달 | C8: 1696년 문서의 명시적 목적지를 독도까지 임의 확장하지 않음. 태정관지령의 사료적 의미를 지우지 않음
A9: 전수 범위 | B9: 현재 출제 중인 240개를 새 ID로 교체 | C9: 원래 1,513개와 이전 48개는 보관·출제 제외. 이 숫자에 합산하지 않음
A10: 검증 한계 | B10: 작성자 자체 대조와 자동 반례 검증 | C10: 독립 교사·역사 전문가·어린이 실사용 검토 완료가 아님
A11: 편집 방법 | B11: 실행 원본은 tools/content/authored-questions.json | C11: 이 Excel은 열람·검토용이며 저장만으로 앱에 반영되지 않음
